Workbook

Sheet Outreach
A1: Company | R1: Contact — fill in | W1: Nearest pitch | Z1: Lead with (message) | AM1: Tracking — fill in
A2: # | B2: Priority | C2: Segment | D2: Area | E2: Company | F2: Name for messages | G2: Website | H2: Email | I2: Email type | J2: Email source | K2: Companies House no. | L2: Companies House | M2: Accounts | N2: Incorporated | O2: Registered address | P2: Postcode | Q2: In 933 research list? | R2: Contact first name | S2: Contact full name | T2: Job title | U2: Direct email | V2: Phone | W2: Nearest pitch | X2: Walk (min) | Y2: Other pitches ≤19 min | Z2: Lead with: pitch | AA2: Walk to it (min) | AB2: Pitch status | AC2: Open slots | AD2: Lead with: slot | AE2: Lead with: format | AF2: Price per player (£) | AG2: Lead-with line | AH2: Send to | AI2: Subject | AJ2: Email draft | AK2: Follow-up email (day 4) | AL2: Draft status | AM2: Owner | AN2: Channel | AO2: Contacted on | AP2: Follow-up sent on | AQ2: Replied | AR2: Call booked | AS2: Group created | AT2: First game booked | AU2: Second game booked | AV2: Objection (exact words) | AW2: Next step | AX2: Notes
A3: 1 | B3: 1 | C3: Law firm | D3: City of London | E3: Allen Overy Shearman Sterling LLP | F3: A&O Shearman | G3: https://www.aoshearman.com | H3: dparisi@aoshearman.com | I3: named person | J3: Open page | K3: OC306763 | L3: Open | M3: Group | N3: 38016 | O3: One Bishops Square, London | P3: E1 6AD | Q3: No | W3: Liverpool St - Attlee Centre | X3: 6 | Y3: Shoreditch Powerleague (6.5) | Z3: Shoreditch Powerleague | AA3: 6 | AB3: =IFERROR(INDEX(Venues!$E$2:$E$17,MATCH(Z3,Venues!$A$2:$A$17,0)),"Not checked") | AC3: =IFERROR(INDEX(Venues!$F$2:$F$17,MATCH(Z3,Venues!$A$2:$A$17,0)),0) | AD3: =IFERROR(INDEX(Venues!$M$2:$M$17,MATCH(Z3,Venues!$A$2:$A$17,0)),"") | AE3: =IFERROR(INDEX(Venues!$N$2:$N$17,MATCH(Z3,Venues!$A$2:$A$17,0)),"5-a-side") | AF3: =IF(Offer!$C$4="","",Offer!$C$4) | AG3: =Z3&" ("&AA3&" min walk) · "&IF(ISNUMBER(AD3),TEXT(AD3,"ddd d mmm, hh:mm"),"slot to confirm with venue")&" · "&AE3&" · "&IF(AF3<>"","£"&TEXT(AF3,"0.00")&" pp","price TBC") | AH3: =IF(U3<>"",U3,IF(H3<>"",H3,"")) | AI3: ="After-work football for "&F3&" · "&Z3&", "&AA3&" min from your office" | AJ3: ="Hi "&IF(R3<>"",R3,F3&" team")&","&CHAR(10)&CHAR(10)&"I'm "&IF(AM3<>"",AM3,IF(Offer!$C$5<>"",Offer!$C$5,"[NAME]"))&" from FC Urban. We organise after-work football for teams in the City and Canary Wharf."&CHAR(10)&CHAR(10)&"We have a "&AE3&" pitch at "&Z3&", "&IF(OR(AA3=8,AA3=11,AA3=18),"an ","a ")&AA3&"-minute walk from your "&P3&" office, "&IF(ISNUMBER(AD3),"on "&TEXT(AD3,"dddd d mmmm")&" at "&TEXT(AD3,"hh:mm"),"on a weekday evening that suits your team")&". It's "&IF(AF3<>"","£"&IF(AF3=INT(AF3),TEXT(AF3,"0"),TEXT(AF3,"0.00")),"[PRICE PER PLAYER]")&" a player and we handle the pitch booking, sign-ups and payments, so all it takes is one person sharing a link with the team."&CHAR(10)&CHAR(10)&"It works well as a team social or "&IF(ISNUMBER(SEARCH(LEFT(F3,1),"AEIOU")),"an ","a ")&F3&" vs clients game. Would your team be up for it, or is there someone who'd enjoy organising it?"&IF(Offer!$C$7<>""," Spots are held until "&TEXT(Offer!$C$7,"dddd d mmmm")&".","")&" "&IF(Offer!$C$6<>"",Offer!$C$6,"[JOINING LINK]")&CHAR(10)&CHAR(10)&"Best,"&CHAR(10)&IF(AM3<>"",AM3,IF(Offer!$C$5<>"",Offer!$C$5,"[NAME]"))&CHAR(10)&"FC Urban" | AK3: ="Hi "&IF(R3<>"",R3,F3&" team")&","&CHAR(10)&CHAR(10)&"Just bumping this up. The "&AE3&" pitch at "&Z3&" is still free "&IF(ISNUMBER(AD3),TEXT(AD3,"ddd d mmm")&", "&TEXT(AD3,"hh:mm"),"weekday evenings")&", "&IF(OR(AA3=8,AA3=11,AA3=18),"an ","a ")&AA3&"-minute walk from your office, "&IF(AF3<>"","£"&IF(AF3=INT(AF3),TEXT(AF3,"0"),TEXT(AF3,"0.00")),"[PRICE PER PLAYER]")&" a player. Happy to hold it for "&F3&" if someone on the team fancies organising a game."&IF(Offer!$C$7<>""," Spots are held until "&TEXT(Offer!$C$7,"dddd d mmmm")&".","")&" "&IF(Offer!$C$6<>"",Offer!$C$6,"[JOINING LINK]")&CHAR(10)&CHAR(10)&"Best,"&CHAR(10)&IF(AM3<>"",AM3,IF(Offer!$C$5<>"",Offer!$C$5,"[NAME]"))&CHAR(10)&"FC Urban" | AL3: =IF(AH3="","No email yet",IF(ISNUMBER(SEARCH("[",AJ3)),"Fill placeholders",IF(ISNUMBER(AD3),"Ready to send","Ready · no fixed slot")))
A4: 2 | B4: 1 | C4: Law firm | D4: City of London | E4: Baker & McKenzie LLP | F4: Baker McKenzie | G4: https://www.bakermckenzie.com | H4: hkalumni@bakermckenzie.com | I4: named person | J4: Open page | K4: OC311297 | L4: Open | M4: Group | N4: 38384 | O4: 280 Bishopsgate, London | P4: EC2M 4AG | Q4: No | W4: Shoreditch Powerleague | X4: 7 | Y4: Liverpool St - Attlee Centre (7.1) | Z4: Shoreditch Powerleague | AA4: 7 | AB4: =IFERROR(INDEX(Venues!$E$2:$E$17,MATCH(Z4,Venues!$A$2:$A$17,0)),"Not checked") | AC4: =IFERROR(INDEX(Venues!$F$2:$F$17,MATCH(Z4,Venues!$A$2:$A$17,0)),0) | AD4: =IFERROR(INDEX(Venues!$M$2:$M$17,MATCH(Z4,Venues!$A$2:$A$17,0)),"") | AE4: =IFERROR(INDEX(Venues!$N$2:$N$17,MATCH(Z4,Venues!$A$2:$A$17,0)),"5-a-side") | AF4: =IF(Offer!$C$4="","",Offer!$C$4) | AG4: =Z4&" ("&AA4&" min walk) · "&IF(ISNUMBER(AD4),TEXT(AD4,"ddd d mmm, hh:mm"),"slot to confirm with venue")&" · "&AE4&" · "&IF(AF4<>"","£"&TEXT(AF4,"0.00")&" pp","price TBC") | AH4: =IF(U4<>"",U4,IF(H4<>"",H4,"")) | AI4: ="After-work football for "&F4&" · "&Z4&", "&AA4&" min from your office" | AJ4: ="Hi "&IF(R4<>"",R4,F4&" team")&","&CHAR(10)&CHAR(10)&"I'm "&IF(AM4<>"",AM4,IF(Offer!$C$5<>"",Offer!$C$5,"[NAME]"))&" from FC Urban. We organise after-work football for teams in the City and Canary Wharf."&CHAR(10)&CHAR(10)&"We have a "&AE4&" pitch at "&Z4&", "&IF(OR(AA4=8,AA4=11,AA4=18),"an ","a ")&AA4&"-minute walk from your "&P4&" office, "&IF(ISNUMBER(AD4),"on "&TEXT(AD4,"dddd d mmmm")&" at "&TEXT(AD4,"hh:mm"),"on a weekday evening that suits your team")&". It's "&IF(AF4<>"","£"&IF(AF4=INT(AF4),TEXT(AF4,"0"),TEXT(AF4,"0.00")),"[PRICE PER PLAYER]")&" a player and we handle the pitch booking, sign-ups and payments, so all it takes is one person sharing a link with the team."&CHAR(10)&CHAR(10)&"It works well as a team social or "&IF(ISNUMBER(SEARCH(LEFT(F4,1),"AEIOU")),"an ","a ")&F4&" vs clients game. Would your team be up for it, or is there someone who'd enjoy organising it?"&IF(Offer!$C$7<>""," Spots are held until "&TEXT(Offer!$C$7,"dddd d mmmm")&".","")&" "&IF(Offer!$C$6<>"",Offer!$C$6,"[JOINING LINK]")&CHAR(10)&CHAR(10)&"Best,"&CHAR(10)&IF(AM4<>"",AM4,IF(Offer!$C$5<>"",Offer!$C$5,"[NAME]"))&CHAR(10)&"FC Urban" | AK4: ="Hi "&IF(R4<>"",R4,F4&" team")&","&CHAR(10)&CHAR(10)&"Just bumping this up. The "&AE4&" pitch at "&Z4&" is still free "&IF(ISNUMBER(AD4),TEXT(AD4,"ddd d mmm")&", "&TEXT(AD4,"hh:mm"),"weekday evenings")&", "&IF(OR(AA4=8,AA4=11,AA4=18),"an ","a ")&AA4&"-minute walk from your office, "&IF(AF4<>"","£"&IF(AF4=INT(AF4),TEXT(AF4,"0"),TEXT(AF4,"0.00")),"[PRICE PER PLAYER]")&" a player. Happy to hold it for "&F4&" if someone on the team fancies organising a game."&IF(Offer!$C$7<>""," Spots are held until "&TEXT(Offer!$C$7,"dddd d mmmm")&".","")&" "&IF(Offer!$C$6<>"",Offer!$C$6,"[JOINING LINK]")&CHAR(10)&CHAR(10)&"Best,"&CHAR(10)&IF(AM4<>"",AM4,IF(Offer!$C$5<>"",Offer!$C$5,"[NAME]"))&CHAR(10)&"FC Urban" | AL4: =IF(AH4="","No email yet",IF(ISNUMBER(SEARCH("[",AJ4)),"Fill placeholders",IF(ISNUMBER(AD4),"Ready to send","Ready · no fixed slot")))
A5: 3 | B5: 1 | C5: Law firm | D5: City of London | E5: Shoosmiths LLP | F5: Shoosmiths | G5: https://www.shoosmiths.com | H5: generalenquiries@shoosmiths.com | I5: named person | J5: Open page | K5: OC374987 | L5: Open | M5: Group | N5: 41033 | O5: 1 Bow Churchyard, London | P5: EC4M 9DQ | Q5: No | W5: City of London School (EC4V 3AL) | X5: 8 | Y5: Marlborough Sports Garden (SE1 1SD) (18.1) | Z5: City of London School (EC4V 3AL) | AA5: 8 | AB5: =IFERROR(INDEX(Venues!$E$2:$E$17,MATCH(Z5,Venues!$A$2:$A$17,0)),"Not checked") | AC5: =IFERROR(INDEX(Venues!$F$2:$F$17,MATCH(Z5,Venues!$A$2:$A$17,0)),0) | AD5: =IFERROR(INDEX(Venues!$M$2:$M$17,MATCH(Z5,Venues!$A$2:$A$17,0)),"") | AE5: =IFERROR(INDEX(Venues!$N$2:$N$17,MATCH(Z5,Venues!$A$2:$A$17,0)),"5-a-side") | AF5: =IF(Offer!$C$4="","",Offer!$C$4) | AG5: =Z5&" ("&AA5&" min walk) · "&IF(ISNUMBER(AD5),TEXT(AD5,"ddd d mmm, hh:mm"),"slot to confirm with venue")&" · "&AE5&" · "&IF(AF5<>"","£"&TEXT(AF5,"0.00")&" pp","price TBC") | AH5: =IF(U5<>"",U5,IF(H5<>"",H5,"")) | AI5: ="After-work football for "&F5&" · "&Z5&", "&AA5&" min from your office" | AJ5: ="Hi "&IF(R5<>"",R5,F5&" team")&","&CHAR(10)&CHAR(10)&"I'm "&IF(AM5<>"",AM5,IF(Offer!$C$5<>"",Offer!$C$5,"[NAME]"))&" from FC Urban. We organise after-work football for teams in the City and Canary Wharf."&CHAR(10)&CHAR(10)&"We have a "&AE5&" pitch at "&Z5&", "&IF(OR(AA5=8,AA5=11,AA5=18),"an ","a ")&AA5&"-minute walk from your "&P5&" office, "&IF(ISNUMBER(AD5),"on "&TEXT(AD5,"dddd d mmmm")&" at "&TEXT(AD5,"hh:mm"),"on a weekday evening that suits your team")&". It's "&IF(AF5<>"","£"&IF(AF5=INT(AF5),TEXT(AF5,"0"),TEXT(AF5,"0.00")),"[PRICE PER PLAYER]")&" a player and we handle the pitch booking, sign-ups and payments, so all it takes is one person sharing a link with the team."&CHAR(10)&CHAR(10)&"It works well as a team social or "&IF(ISNUMBER(SEARCH(LEFT(F5,1),"AEIOU")),"an ","a ")&F5&" vs clients game. Would your team be up for it, or is there someone who'd enjoy organising it?"&IF(Offer!$C$7<>""," Spots are held until "&TEXT(Offer!$C$7,"dddd d mmmm")&".","")&" "&IF(Offer!$C$6<>"",Offer!$C$6,"[JOINING LINK]")&CHAR(10)&CHAR(10)&"Best,"&CHAR(10)&IF(AM5<>"",AM5,IF(Offer!$C$5<>"",Offer!$C$5,"[NAME]"))&CHAR(10)&"FC Urban" | AK5: ="Hi "&IF(R5<>"",R5,F5&" team")&","&CHAR(10)&CHAR(10)&"Just bumping this up. The "&AE5&" pitch at "&Z5&" is still free "&IF(ISNUMBER(AD5),TEXT(AD5,"ddd d mmm")&", "&TEXT(AD5,"hh:mm"),"weekday evenings")&", "&IF(OR(AA5=8,AA5=11,AA5=18),"an ","a ")&AA5&"-minute walk from your office, "&IF(AF5<>"","£"&IF(AF5=INT(AF5),TEXT(AF5,"0"),TEXT(AF5,"0.00")),"[PRICE PER PLAYER]")&" a player. Happy to hold it for "&F5&" if someone on the team fancies organising a game."&IF(Offer!$C$7<>""," Spots are held until "&TEXT(Offer!$C$7,"dddd d mmmm")&".","")&" "&IF(Offer!$C$6<>"",Offer!$C$6,"[JOINING LINK]")&CHAR(10)&CHAR(10)&"Best,"&CHAR(10)&IF(AM5<>"",AM5,IF(Offer!$C$5<>"",Offer!$C$5,"[NAME]"))&CHAR(10)&"FC Urban" | AL5: =IF(AH5="","No email yet",IF(ISNUMBER(SEARCH("[",AJ5)),"Fill placeholders",IF(ISNUMBER(AD5),"Ready to send","Ready · no fixed slot")))
A6: 4 | B6: 1 | C6: Law firm | D6: City of London | E6: Herbert Smith Freehills Kramer Global LLP | F6: Herbert Smith Freehills Kramer | G6: https://www.hsfkramer.com | I6: Not found | K6: OC375784 | L6: Open | M6: Group | N6: 41066 | O6: Exchange House, Primrose Street, London | P6: EC2A 2EG | Q6: No | W6: Shoreditch Powerleague | X6: 8 | Y6: Liverpool St - Attlee Centre (9.8) | Z6: Shoreditch Powerleague | AA6: 8 | AB6: =IFERROR(INDEX(Venues!$E$2:$E$17,MATCH(Z6,Venues!$A$2:$A$17,0)),"Not checked") | AC6: =IFERROR(INDEX(Venues!$F$2:$F$17,MATCH(Z6,Venues!$A$2:$A$17,0)),0) | AD6: =IFERROR(INDEX(Venues!$M$2:$M$17,MATCH(Z6,Venues!$A$2:$A$17,0)),"") | AE6: =IFERROR(INDEX(Venues!$N$2:$N$17,MATCH(Z6,Venues!$A$2:$A$17,0)),"5-a-side") | AF6: =IF(Offer!$C$4="","",Offer!$C$4) | AG6: =Z6&" ("&AA6&" min walk) · "&IF(ISNUMBER(AD6),TEXT(AD6,"ddd d mmm, hh:mm"),"slot to confirm with venue")&" · "&AE6&" · "&IF(AF6<>"","£"&TEXT(AF6,"0.00")&" pp","price TBC") | AH6: =IF(U6<>"",U6,IF(H6<>"",H6,"")) | AI6: ="After-work football for "&F6&" · "&Z6&", "&AA6&" min from your office" | AJ6: ="Hi "&IF(R6<>"",R6,F6&" team")&","&CHAR(10)&CHAR(10)&"I'm "&IF(AM6<>"",AM6,IF(Offer!$C$5<>"",Offer!$C$5,"[NAME]"))&" from FC Urban. We organise after-work football for teams in the City and Canary Wharf."&CHAR(10)&CHAR(10)&"We have a "&AE6&" pitch at "&Z6&", "&IF(OR(AA6=8,AA6=11,AA6=18),"an ","a ")&AA6&"-minute walk from your "&P6&" office, "&IF(ISNUMBER(AD6),"on "&TEXT(AD6,"dddd d mmmm")&" at "&TEXT(AD6,"hh:mm"),"on a weekday evening that suits your team")&". It's "&IF(AF6<>"","£"&IF(AF6=INT(AF6),TEXT(AF6,"0"),TEXT(AF6,"0.00")),"[PRICE PER PLAYER]")&" a player and we handle the pitch booking, sign-ups and payments, so all it takes is one person sharing a link with the team."&CHAR(10)&CHAR(10)&"It works well as a team social or "&IF(ISNUMBER(SEARCH(LEFT(F6,1),"AEIOU")),"an ","a ")&F6&" vs clients game. Would your team be up for it, or is there someone who'd enjoy organising it?"&IF(Offer!$C$7<>""," Spots are held until "&TEXT(Offer!$C$7,"dddd d mmmm")&".","")&" "&IF(Offer!$C$6<>"",Offer!$C$6,"[JOINING LINK]")&CHAR(10)&CHAR(10)&"Best,"&CHAR(10)&IF(AM6<>"",AM6,IF(Offer!$C$5<>"",Offer!$C$5,"[NAME]"))&CHAR(10)&"FC Urban" | AK6: ="Hi "&IF(R6<>"",R6,F6&" team")&","&CHAR(10)&CHAR(10)&"Just bumping this up. The "&AE6&" pitch at "&Z6&" is still free "&IF(ISNUMBER(AD6),TEXT(AD6,"ddd d mmm")&", "&TEXT(AD6,"hh:mm"),"weekday evenings")&", "&IF(OR(AA6=8,AA6=11,AA6=18),"an ","a ")&AA6&"-minute walk from your office, "&IF(AF6<>"","£"&IF(AF6=INT(AF6),TEXT(AF6,"0"),TEXT(AF6,"0.00")),"[PRICE PER PLAYER]")&" a player. Happy to hold it for "&F6&" if someone on the team fancies organising a game."&IF(Offer!$C$7<>""," Spots are held until "&TEXT(Offer!$C$7,"dddd d mmmm")&".","")&" "&IF(Offer!$C$6<>"",Offer!$C$6,"[JOINING LINK]")&CHAR(10)&CHAR(10)&"Best,"&CHAR(10)&IF(AM6<>"",AM6,IF(Offer!$C$5<>"",Offer!$C$5,"[NAME]"))&CHAR(10)&"FC Urban" | AL6: =IF(AH6="","No email yet",IF(ISNUMBER(SEARCH("[",AJ6)),"Fill placeholders",IF(ISNUMBER(AD6),"Ready to send","Ready · no fixed slot")))
A7: 5 | B7: 1 | C7: Law firm | D7: City of London | E7: Ashurst Perkins Coie UK LLP | F7: Ashurst Perkins Coie | G7: https://www.ashurstperkinscoie.com | H7: london@ashurstperkinscoie.com | I7: general | J7: Open page | K7: OC330252 | L7: Open | M7: Group | N7: 39294 | O7: 1 Duval Square, London Fruit And Wool Exchange, London | P7: E1 6PW | Q7: No | W7: Liverpool St - Attlee Centre | X7: 3 | Y7: Shoreditch Powerleague (8.1); Whitechapel (18.6) | Z7: Shoreditch Powerleague | AA7: 8 | AB7: =IFERROR(INDEX(Venues!$E$2:$E$17,MATCH(Z7,Venues!$A$2:$A$17,0)),"Not checked") | AC7: =IFERROR(INDEX(Venues!$F$2:$F$17,MATCH(Z7,Venues!$A$2:$A$17,0)),0) | AD7: =IFERROR(INDEX(Venues!$M$2:$M$17,MATCH(Z7,Venues!$A$2:$A$17,0)),"") | AE7: =IFERROR(INDEX(Venues!$N$2:$N$17,MATCH(Z7,Venues!$A$2:$A$17,0)),"5-a-side") | AF7: =IF(Offer!$C$4="","",Offer!$C$4) | AG7: =Z7&" ("&AA7&" min walk) · "&IF(ISNUMBER(AD7),TEXT(AD7,"ddd d mmm, hh:mm"),"slot to confirm with venue")&" · "&AE7&" · "&IF(AF7<>"","£"&TEXT(AF7,"0.00")&" pp","price TBC") | AH7: =IF(U7<>"",U7,IF(H7<>"",H7,"")) | AI7: ="After-work football for "&F7&" · "&Z7&", "&AA7&" min from your office" | AJ7: ="Hi "&IF(R7<>"",R7,F7&" team")&","&CHAR(10)&CHAR(10)&"I'm "&IF(AM7<>"",AM7,IF(Offer!$C$5<>"",Offer!$C$5,"[NAME]"))&" from FC Urban. We organise after-work football for teams in the City and Canary Wharf."&CHAR(10)&CHAR(10)&"We have a "&AE7&" pitch at "&Z7&", "&IF(OR(AA7=8,AA7=11,AA7=18),"an ","a ")&AA7&"-minute walk from your "&P7&" office, "&IF(ISNUMBER(AD7),"on "&TEXT(AD7,"dddd d mmmm")&" at "&TEXT(AD7,"hh:mm"),"on a weekday evening that suits your team")&". It's "&IF(AF7<>"","£"&IF(AF7=INT(AF7),TEXT(AF7,"0"),TEXT(AF7,"0.00")),"[PRICE PER PLAYER]")&" a player and we handle the pitch booking, sign-ups and payments, so all it takes is one person sharing a link with the team."&CHAR(10)&CHAR(10)&"It works well as a team social or "&IF(ISNUMBER(SEARCH(LEFT(F7,1),"AEIOU")),"an ","a ")&F7&" vs clients game. Would your team be up for it, or is there someone who'd enjoy organising it?"&IF(Offer!$C$7<>""," Spots are held until "&TEXT(Offer!$C$7,"dddd d mmmm")&".","")&" "&IF(Offer!$C$6<>"",Offer!$C$6,"[JOINING LINK]")&CHAR(10)&CHAR(10)&"Best,"&CHAR(10)&IF(AM7<>"",AM7,IF(Offer!$C$5<>"",Offer!$C$5,"[NAME]"))&CHAR(10)&"FC Urban" | AK7: ="Hi "&IF(R7<>"",R7,F7&" team")&","&CHAR(10)&CHAR(10)&"Just bumping this up. The "&AE7&" pitch at "&Z7&" is still free "&IF(ISNUMBER(AD7),TEXT(AD7,"ddd d mmm")&", "&TEXT(AD7,"hh:mm"),"weekday evenings")&", "&IF(OR(AA7=8,AA7=11,AA7=18),"an ","a ")&AA7&"-minute walk from your office, "&IF(AF7<>"","£"&IF(AF7=INT(AF7),TEXT(AF7,"0"),TEXT(AF7,"0.00")),"[PRICE PER PLAYER]")&" a player. Happy to hold it for "&F7&" if someone on the team fancies organising a game."&IF(Offer!$C$7<>""," Spots are held until "&TEXT(Offer!$C$7,"dddd d mmmm")&".","")&" "&IF(Offer!$C$6<>"",Offer!$C$6,"[JOINING LINK]")&CHAR(10)&CHAR(10)&"Best,"&CHAR(10)&IF(AM7<>"",AM7,IF(Offer!$C$5<>"",Offer!$C$5,"[NAME]"))&CHAR(10)&"FC Urban" | AL7: =IF(AH7="","No email yet",IF(ISNUMBER(SEARCH("[",AJ7)),"Fill placeholders",IF(ISNUMBER(AD7),"Ready to send","Ready · no fixed slot")))
A8: 6 | B8: 1 | C8: Law firm | D8: City of London | E8: Carey Olsen LLP | F8: Carey Olsen | G8: https://www.careyolsen.com | H8: londonco@careyolsen.com | I8: general | J8: Open page | K8: OC345292 | L8: Open | M8: Group | N8: 39932 | O8: Forum St Pauls, 33 Gutter Lane, London | P8: EC2V 8AS | Q8: No | W8: City of London School (EC4V 3AL) | X8: 9 | Z8: City of London School (EC4V 3AL) | AA8: 9 | AB8: =IFERROR(INDEX(Venues!$E$2:$E$17,MATCH(Z8,Venues!$A$2:$A$17,0)),"Not checked") | AC8: =IFERROR(INDEX(Venues!$F$2:$F$17,MATCH(Z8,Venues!$A$2:$A$17,0)),0) | AD8: =IFERROR(INDEX(Venues!$M$2:$M$17,MATCH(Z8,Venues!$A$2:$A$17,0)),"") | AE8: =IFERROR(INDEX(Venues!$N$2:$N$17,MATCH(Z8,Venues!$A$2:$A$17,0)),"5-a-side") | AF8: =IF(Offer!$C$4="","",Offer!$C$4) | AG8: =Z8&" ("&AA8&" min walk) · "&IF(ISNUMBER(AD8),TEXT(AD8,"ddd d mmm, hh:mm"),"slot to confirm with venue")&" · "&AE8&" · "&IF(AF8<>"","£"&TEXT(AF8,"0.00")&" pp","price TBC") | AH8: =IF(U8<>"",U8,IF(H8<>"",H8,"")) | AI8: ="After-work football for "&F8&" · "&Z8&", "&AA8&" min from your office" | AJ8: ="Hi "&IF(R8<>"",R8,F8&" team")&","&CHAR(10)&CHAR(10)&"I'm "&IF(AM8<>"",AM8,IF(Offer!$C$5<>"",Offer!$C$5,"[NAME]"))&" from FC Urban. We organise after-work football for teams in the City and Canary Wharf."&CHAR(10)&CHAR(10)&"We have a "&AE8&" pitch at "&Z8&", "&IF(OR(AA8=8,AA8=11,AA8=18),"an ","a ")&AA8&"-minute walk from your "&P8&" office, "&IF(ISNUMBER(AD8),"on "&TEXT(AD8,"dddd d mmmm")&" at "&TEXT(AD8,"hh:mm"),"on a weekday evening that suits your team")&". It's "&IF(AF8<>"","£"&IF(AF8=INT(AF8),TEXT(AF8,"0"),TEXT(AF8,"0.00")),"[PRICE PER PLAYER]")&" a player and we handle the pitch booking, sign-ups and payments, so all it takes is one person sharing a link with the team."&CHAR(10)&CHAR(10)&"It works well as a team social or "&IF(ISNUMBER(SEARCH(LEFT(F8,1),"AEIOU")),"an ","a ")&F8&" vs clients game. Would your team be up for it, or is there someone who'd enjoy organising it?"&IF(Offer!$C$7<>""," Spots are held until "&TEXT(Offer!$C$7,"dddd d mmmm")&".","")&" "&IF(Offer!$C$6<>"",Offer!$C$6,"[JOINING LINK]")&CHAR(10)&CHAR(10)&"Best,"&CHAR(10)&IF(AM8<>"",AM8,IF(Offer!$C$5<>"",Offer!$C$5,"[NAME]"))&CHAR(10)&"FC Urban" | AK8: ="Hi "&IF(R8<>"",R8,F8&" team")&","&CHAR(10)&CHAR(10)&"Just bumping this up. The "&AE8&" pitch at "&Z8&" is still free "&IF(ISNUMBER(AD8),TEXT(AD8,"ddd d mmm")&", "&TEXT(AD8,"hh:mm"),"weekday evenings")&", "&IF(OR(AA8=8,AA8=11,AA8=18),"an ","a ")&AA8&"-minute walk from your office, "&IF(AF8<>"","£"&IF(AF8=INT(AF8),TEXT(AF8,"0"),TEXT(AF8,"0.00")),"[PRICE PER PLAYER]")&" a player. Happy to hold it for "&F8&" if someone on the team fancies organising a game."&IF(Offer!$C$7<>""," Spots are held until "&TEXT(Offer!$C$7,"dddd d mmmm")&".","")&" "&IF(Offer!$C$6<>"",Offer!$C$6,"[JOINING LINK]")&CHAR(10)&CHAR(10)&"Best,"&CHAR(10)&IF(AM8<>"",AM8,IF(Offer!$C$5<>"",Offer!$C$5,"[NAME]"))&CHAR(10)&"FC Urban" | AL8: =IF(AH8="","No email yet",IF(ISNUMBER(SEARCH("[",AJ8)),"Fill placeholders",IF(ISNUMBER(AD8),"Ready to send","Ready · no fixed slot")))
A9: 7 | B9: 1 | C9: Law firm | D9: City of London | E9: Eversheds Sutherland (International) LLP | F9: Eversheds Sutherland | G9: https://www.eversheds-sutherland.com | H9: rachelreid@eversheds-sutherland.com | I9: named person | J9: Open page | K9: OC304065 | L9: Open | M9: Group | N9: 37685 | O9: One Wood Street, London | P9: EC2V 7WS | Q9: No | W9: City of London School (EC4V 3AL) | X9: 9 | Z9: City of London School (EC4V 3AL) | AA9: 9 | AB9: =IFERROR(INDEX(Venues!$E$2:$E$17,MATCH(Z9,Venues!$A$2:$A$17,0)),"Not checked") | AC9: =IFERROR(INDEX(Venues!$F$2:$F$17,MATCH(Z9,Venues!$A$2:$A$17,0)),0) | AD9: =IFERROR(INDEX(Venues!$M$2:$M$17,MATCH(Z9,Venues!$A$2:$A$17,0)),"") | AE9: =IFERROR(INDEX(Venues!$N$2:$N$17,MATCH(Z9,Venues!$A$2:$A$17,0)),"5-a-side") | AF9: =IF(Offer!$C$4="","",Offer!$C$4) | AG9: =Z9&" ("&AA9&" min walk) · "&IF(ISNUMBER(AD9),TEXT(AD9,"ddd d mmm, hh:mm"),"slot to confirm with venue")&" · "&AE9&" · "&IF(AF9<>"","£"&TEXT(AF9,"0.00")&" pp","price TBC") | AH9: =IF(U9<>"",U9,IF(H9<>"",H9,"")) | AI9: ="After-work football for "&F9&" · "&Z9&", "&AA9&" min from your office" | AJ9: ="Hi "&IF(R9<>"",R9,F9&" team")&","&CHAR(10)&CHAR(10)&"I'm "&IF(AM9<>"",AM9,IF(Offer!$C$5<>"",Offer!$C$5,"[NAME]"))&" from FC Urban. We organise after-work football for teams in the City and Canary Wharf."&CHAR(10)&CHAR(10)&"We have a "&AE9&" pitch at "&Z9&", "&IF(OR(AA9=8,AA9=11,AA9=18),"an ","a ")&AA9&"-minute walk from your "&P9&" office, "&IF(ISNUMBER(AD9),"on "&TEXT(AD9,"dddd d mmmm")&" at "&TEXT(AD9,"hh:mm"),"on a weekday evening that suits your team")&". It's "&IF(AF9<>"","£"&IF(AF9=INT(AF9),TEXT(AF9,"0"),TEXT(AF9,"0.00")),"[PRICE PER PLAYER]")&" a player and we handle the pitch booking, sign-ups and payments, so all it takes is one person sharing a link with the team."&CHAR(10)&CHAR(10)&"It works well as a team social or "&IF(ISNUMBER(SEARCH(LEFT(F9,1),"AEIOU")),"an ","a ")&F9&" vs clients game. Would your team be up for it, or is there someone who'd enjoy organising it?"&IF(Offer!$C$7<>""," Spots are held until "&TEXT(Offer!$C$7,"dddd d mmmm")&".","")&" "&IF(Offer!$C$6<>"",Offer!$C$6,"[JOINING LINK]")&CHAR(10)&CHAR(10)&"Best,"&CHAR(10)&IF(AM9<>"",AM9,IF(Offer!$C$5<>"",Offer!$C$5,"[NAME]"))&CHAR(10)&"FC Urban" | AK9: ="Hi "&IF(R9<>"",R9,F9&" team")&","&CHAR(10)&CHAR(10)&"Just bumping this up. The "&AE9&" pitch at "&Z9&" is still free "&IF(ISNUMBER(AD9),TEXT(AD9,"ddd d mmm")&", "&TEXT(AD9,"hh:mm"),"weekday evenings")&", "&IF(OR(AA9=8,AA9=11,AA9=18),"an ","a ")&AA9&"-minute walk from your office, "&IF(AF9<>"","£"&IF(AF9=INT(AF9),TEXT(AF9,"0"),TEXT(AF9,"0.00")),"[PRICE PER PLAYER]")&" a player. Happy to hold it for "&F9&" if someone on the team fancies organising a game."&IF(Offer!$C$7<>""," Spots are held until "&TEXT(Offer!$C$7,"dddd d mmmm")&".","")&" "&IF(Offer!$C$6<>"",Offer!$C$6,"[JOINING LINK]")&CHAR(10)&CHAR(10)&"Best,"&CHAR(10)&IF(AM9<>"",AM9,IF(Offer!$C$5<>"",Offer!$C$5,"[NAME]"))&CHAR(10)&"FC Urban" | AL9: =IF(AH9="","No email yet",IF(ISNUMBER(SEARCH("[",AJ9)),"Fill placeholders",IF(ISNUMBER(AD9),"Ready to send","Ready · no fixed slot")))
A10: 8 | B10: 1 | C10: Law firm | D10: City of London | E10: Goodwin Procter (UK) LLP | F10: Goodwin Procter | G10: https://www.goodwinlaw.com | H10: etan@goodwinlaw.com | I10: named person | J10: Open page | K10: OC362294 | L10: Open | M10: Group | N10: 40603 | O10: Sancroft, Newgate Street, London | P10: EC1A 7AZ | Q10: No | W10: City of London School (EC4V 3AL) | X10: 9 | Z10: City of London School (EC4V 3AL) | AA10: 9 | AB10: =IFERROR(INDEX(Venues!$E$2:$E$17,MATCH(Z10,Venues!$A$2:$A$17,0)),"Not checked") | AC10: =IFERROR(INDEX(Venues!$F$2:$F$17,MATCH(Z10,Venues!$A$2:$A$17,0)),0) | AD10: =IFERROR(INDEX(Venues!$M$2:$M$17,MATCH(Z10,Venues!$A$2:$A$17,0)),"") | AE10: =IFERROR(INDEX(Venues!$N$2:$N$17,MATCH(Z10,Venues!$A$2:$A$17,0)),"5-a-side") | AF10: =IF(Offer!$C$4="","",Offer!$C$4) | AG10: =Z10&" ("&AA10&" min walk) · "&IF(ISNUMBER(AD10),TEXT(AD10,"ddd d mmm, hh:mm"),"slot to confirm with venue")&" · "&AE10&" · "&IF(AF10<>"","£"&TEXT(AF10,"0.00")&" pp","price TBC") | AH10: =IF(U10<>"",U10,IF(H10<>"",H10,"")) | AI10: ="After-work football for "&F10&" · "&Z10&", "&AA10&" min from your office" | AJ10: ="Hi "&IF(R10<>"",R10,F10&" team")&","&CHAR(10)&CHAR(10)&"I'm "&IF(AM10<>"",AM10,IF(Offer!$C$5<>"",Offer!$C$5,"[NAME]"))&" from FC Urban. We organise after-work football for teams in the City and Canary Wharf."&CHAR(10)&CHAR(10)&"We have a "&AE10&" pitch at "&Z10&", "&IF(OR(AA10=8,AA10=11,AA10=18),"an ","a ")&AA10&"-minute walk from your "&P10&" office, "&IF(ISNUMBER(AD10),"on "&TEXT(AD10,"dddd d mmmm")&" at "&TEXT(AD10,"hh:mm"),"on a weekday evening that suits your team")&". It's "&IF(AF10<>"","£"&IF(AF10=INT(AF10),TEXT(AF10,"0"),TEXT(AF10,"0.00")),"[PRICE PER PLAYER]")&" a player and we handle the pitch booking, sign-ups and payments, so all it takes is one person sharing a link with the team."&CHAR(10)&CHAR(10)&"It works well as a team social or "&IF(ISNUMBER(SEARCH(LEFT(F10,1),"AEIOU")),"an ","a ")&F10&" vs clients game. Would your team be up for it, or is there someone who'd enjoy organising it?"&IF(Offer!$C$7<>""," Spots are held until "&TEXT(Offer!$C$7,"dddd d mmmm")&".","")&" "&IF(Offer!$C$6<>"",Offer!$C$6,"[JOINING LINK]")&CHAR(10)&CHAR(10)&"Best,"&CHAR(10)&IF(AM10<>"",AM10,IF(Offer!$C$5<>"",Offer!$C$5,"[NAME]"))&CHAR(10)&"FC Urban" | AK10: ="Hi "&IF(R10<>"",R10,F10&" team")&","&CHAR(10)&CHAR(10)&"Just bumping this up. The "&AE10&" pitch at "&Z10&" is still free "&IF(ISNUMBER(AD10),TEXT(AD10,"ddd d mmm")&", "&TEXT(AD10,"hh:mm"),"weekday evenings")&", "&IF(OR(AA10=8,AA10=11,AA10=18),"an ","a ")&AA10&"-minute walk from your office, "&IF(AF10<>"","£"&IF(AF10=INT(AF10),TEXT(AF10,"0"),TEXT(AF10,"0.00")),"[PRICE PER PLAYER]")&" a player. Happy to hold it for "&F10&" if someone on the team fancies organising a game."&IF(Offer!$C$7<>""," Spots are held until "&TEXT(Offer!$C$7,"dddd d mmmm")&".","")&" "&IF(Offer!$C$6<>"",Offer!$C$6,"[JOINING LINK]")&CHAR(10)&CHAR(10)&"Best,"&CHAR(10)&IF(AM10<>"",AM10,IF(Offer!$C$5<>"",Offer!$C$5,"[NAME]"))&CHAR(10)&"FC Urban" | AL10: =IF(AH10="","No email yet",IF(ISNUMBER(SEARCH("[",AJ10)),"Fill placeholders",IF(ISNUMBER(AD10),"Ready to send","Ready · no fixed slot")))
A11: 9 | B11: 1 | C11: Law firm | D11: City of London | E11: Withers LLP | F11: Withers | G11: https://www.withersworldwide.com | H11: hello@withersworldwide.com | I11: general | J11: Open page | K11: OC301149 | L11: Open | M11: Group | N11: 37238 | O11: Third Floor, 20 Old Bailey, London | P11: EC4M 7AN | Q11: No | W11: City of London School (EC4V 3AL) | X11: 9 | Z11: City of London School (EC4V 3AL) | AA11: 9 | AB11: =IFERROR(INDEX(Venues!$E$2:$E$17,MATCH(Z11,Venues!$A$2:$A$17,0)),"Not checked") | AC11: =IFERROR(INDEX(Venues!$F$2:$F$17,MATCH(Z11,Venues!$A$2:$A$17,0)),0) | AD11: =IFERROR(INDEX(Venues!$M$2:$M$17,MATCH(Z11,Venues!$A$2:$A$17,0)),"") | AE11: =IFERROR(INDEX(Venues!$N$2:$N$17,MATCH(Z11,Venues!$A$2:$A$17,0)),"5-a-side") | AF11: =IF(Offer!$C$4="","",Offer!$C$4) | AG11: =Z11&" ("&AA11&" min walk) · "&IF(ISNUMBER(AD11),TEXT(AD11,"ddd d mmm, hh:mm"),"slot to confirm with venue")&" · "&AE11&" · "&IF(AF11<>"","£"&TEXT(AF11,"0.00")&" pp","price TBC") | AH11: =IF(U11<>"",U11,IF(H11<>"",H11,"")) | AI11: ="After-work football for "&F11&" · "&Z11&", "&AA11&" min from your office" | AJ11: ="Hi "&IF(R11<>"",R11,F11&" team")&","&CHAR(10)&CHAR(10)&"I'm "&IF(AM11<>"",AM11,IF(Offer!$C$5<>"",Offer!$C$5,"[NAME]"))&" from FC Urban. We organise after-work football for teams in the City and Canary Wharf."&CHAR(10)&CHAR(10)&"We have a "&AE11&" pitch at "&Z11&", "&IF(OR(AA11=8,AA11=11,AA11=18),"an ","a ")&AA11&"-minute walk from your "&P11&" office, "&IF(ISNUMBER(AD11),"on "&TEXT(AD11,"dddd d mmmm")&" at "&TEXT(AD11,"hh:mm"),"on a weekday evening that suits your team")&". It's "&IF(AF11<>"","£"&IF(AF11=INT(AF11),TEXT(AF11,"0"),TEXT(AF11,"0.00")),"[PRICE PER PLAYER]")&" a player and we handle the pitch booking, sign-ups and payments, so all it takes is one person sharing a link with the team."&CHAR(10)&CHAR(10)&"It works well as a team social or "&IF(ISNUMBER(SEARCH(LEFT(F11,1),"AEIOU")),"an ","a ")&F11&" vs clients game. Would your team be up for it, or is there someone who'd enjoy organising it?"&IF(Offer!$C$7<>""," Spots are held until "&TEXT(Offer!$C$7,"dddd d mmmm")&".","")&" "&IF(Offer!$C$6<>"",Offer!$C$6,"[JOINING LINK]")&CHAR(10)&CHAR(10)&"Best,"&CHAR(10)&IF(AM11<>"",AM11,IF(Offer!$C$5<>"",Offer!$C$5,"[NAME]"))&CHAR(10)&"FC Urban" | AK11: ="Hi "&IF(R11<>"",R11,F11&" team")&","&CHAR(10)&CHAR(10)&"Just bumping this up. The "&AE11&" pitch at "&Z11&" is still free "&IF(ISNUMBER(AD11),TEXT(AD11,"ddd d mmm")&", "&TEXT(AD11,"hh:mm"),"weekday evenings")&", "&IF(OR(AA11=8,AA11=11,AA11=18),"an ","a ")&AA11&"-minute walk from your office, "&IF(AF11<>"","£"&IF(AF11=INT(AF11),TEXT(AF11,"0"),TEXT(AF11,"0.00")),"[PRICE PER PLAYER]")&" a player. Happy to hold it for "&F11&" if someone on the team fancies organising a game."&IF(Offer!$C$7<>""," Spots are held until "&TEXT(Offer!$C$7,"dddd d mmmm")&".","")&" "&IF(Offer!$C$6<>"",Offer!$C$6,"[JOINING LINK]")&CHAR(10)&CHAR(10)&"Best,"&CHAR(10)&IF(AM11<>"",AM11,IF(Offer!$C$5<>"",Offer!$C$5,"[NAME]"))&CHAR(10)&"FC Urban" | AL11: =IF(AH11="","No email yet",IF(ISNUMBER(SEARCH("[",AJ11)),"Fill placeholders",IF(ISNUMBER(AD11),"Ready to send","Ready · no fixed slot")))
A12: 10 | B12: 1 | C12: Law firm | D12: City of London | E12: Charles Russell Speechlys LLP | F12: Charles Russell Speechlys | G12: https://www.charlesrussellspeechlys.com | H12: london@charlesrussellspeechlys.com | I12: general | J12: Open page | K12: OC311850 | L12: Open | M12: Group | N12: 38407 | O12: 5 Fleet Place, London | P12: EC4M 7RD | Q12: No | W12: City of London School (EC4V 3AL) | X12: 9 | Z12: City of London School (EC4V 3AL) | AA12: 9 | AB12: =IFERROR(INDEX(Venues!$E$2:$E$17,MATCH(Z12,Venues!$A$2:$A$17,0)),"Not checked") | AC12: =IFERROR(INDEX(Venues!$F$2:$F$17,MATCH(Z12,Venues!$A$2:$A$17,0)),0) | AD12: =IFERROR(INDEX(Venues!$M$2:$M$17,MATCH(Z12,Venues!$A$2:$A$17,0)),"") | AE12: =IFERROR(INDEX(Venues!$N$2:$N$17,MATCH(Z12,Venues!$A$2:$A$17,0)),"5-a-side") | AF12: =IF(Offer!$C$4="","",Offer!$C$4) | AG12: =Z12&" ("&AA12&" min walk) · "&IF(ISNUMBER(AD12),TEXT(AD12,"ddd d mmm, hh:mm"),"slot to confirm with venue")&" · "&AE12&" · "&IF(AF12<>"","£"&TEXT(AF12,"0.00")&" pp","price TBC") | AH12: =IF(U12<>"",U12,IF(H12<>"",H12,"")) | AI12: ="After-work football for "&F12&" · "&Z12&", "&AA12&" min from your office" | AJ12: ="Hi "&IF(R12<>"",R12,F12&" team")&","&CHAR(10)&CHAR(10)&"I'm "&IF(AM12<>"",AM12,IF(Offer!$C$5<>"",Offer!$C$5,"[NAME]"))&" from FC Urban. We organise after-work football for teams in the City and Canary Wharf."&CHAR(10)&CHAR(10)&"We have a "&AE12&" pitch at "&Z12&", "&IF(OR(AA12=8,AA12=11,AA12=18),"an ","a ")&AA12&"-minute walk from your "&P12&" office, "&IF(ISNUMBER(AD12),"on "&TEXT(AD12,"dddd d mmmm")&" at "&TEXT(AD12,"hh:mm"),"on a weekday evening that suits your team")&". It's "&IF(AF12<>"","£"&IF(AF12=INT(AF12),TEXT(AF12,"0"),TEXT(AF12,"0.00")),"[PRICE PER PLAYER]")&" a player and we handle the pitch booking, sign-ups and payments, so all it takes is one person sharing a link with the team."&CHAR(10)&CHAR(10)&"It works well as a team social or "&IF(ISNUMBER(SEARCH(LEFT(F12,1),"AEIOU")),"an ","a ")&F12&" vs clients game. Would your team be up for it, or is there someone who'd enjoy organising it?"&IF(Offer!$C$7<>""," Spots are held until "&TEXT(Offer!$C$7,"dddd d mmmm")&".","")&" "&IF(Offer!$C$6<>"",Offer!$C$6,"[JOINING LINK]")&CHAR(10)&CHAR(10)&"Best,"&CHAR(10)&IF(AM12<>"",AM12,IF(Offer!$C$5<>"",Offer!$C$5,"[NAME]"))&CHAR(10)&"FC Urban" | AK12: ="Hi "&IF(R12<>"",R12,F12&" team")&","&CHAR(10)&CHAR(10)&"Just bumping this up. The "&AE12&" pitch at "&Z12&" is still free "&IF(ISNUMBER(AD12),TEXT(AD12,"ddd d mmm")&", "&TEXT(AD12,"hh:mm"),"weekday evenings")&", "&IF(OR(AA12=8,AA12=11,AA12=18),"an ","a ")&AA12&"-minute walk from your office, "&IF(AF12<>"","£"&IF(AF12=INT(AF12),TEXT(AF12,"0"),TEXT(AF12,"0.00")),"[PRICE PER PLAYER]")&" a player. Happy to hold it for "&F12&" if someone on the team fancies organising a game."&IF(Offer!$C$7<>""," Spots are held until "&TEXT(Offer!$C$7,"dddd d mmmm")&".","")&" "&IF(Offer!$C$6<>"",Offer!$C$6,"[JOINING LINK]")&CHAR(10)&CHAR(10)&"Best,"&CHAR(10)&IF(AM12<>"",AM12,IF(Offer!$C$5<>"",Offer!$C$5,"[NAME]"))&CHAR(10)&"FC Urban" | AL12: =IF(AH12="","No email yet",IF(ISNUMBER(SEARCH("[",AJ12)),"Fill placeholders",IF(ISNUMBER(AD12),"Ready to send","Ready · no fixed slot")))
A13: 11 | B13: 1 | C13: Law firm | D13: City of London | E13: CMS Cameron McKenna Nabarro Olswang LLP | F13: CMS Cameron McKenna Nabarro Olswang | G13: https://cms.law | I13: Not found | K13: OC310335 | L13: Open | M13: Group | N13: 38323 | O13: Cannon Place, 78 Cannon Street, London | P13: EC4N 6AF | Q13: No | W13: City of London School (EC4V 3AL) | X13: 10 | Y13: Marlborough Sports Garden (SE1 1SD) (14.7) | Z13: City of London School (EC4V 3AL) | AA13: 10 | AB13: =IFERROR(INDEX(Venues!$E$2:$E$17,MATCH(Z13,Venues!$A$2:$A$17,0)),"Not checked") | AC13: =IFERROR(INDEX(Venues!$F$2:$F$17,MATCH(Z13,Venues!$A$2:$A$17,0)),0) | AD13: =IFERROR(INDEX(Venues!$M$2:$M$17,MATCH(Z13,Venues!$A$2:$A$17,0)),"") | AE13: =IFERROR(INDEX(Venues!$N$2:$N$17,MATCH(Z13,Venues!$A$2:$A$17,0)),"5-a-side") | AF13: =IF(Offer!$C$4="","",Offer!$C$4) | AG13: =Z13&" ("&AA13&" min walk) · "&IF(ISNUMBER(AD13),TEXT(AD13,"ddd d mmm, hh:mm"),"slot to confirm with venue")&" · "&AE13&" · "&IF(AF13<>"","£"&TEXT(AF13,"0.00")&" pp","price TBC") | AH13: =IF(U13<>"",U13,IF(H13<>"",H13,"")) | AI13: ="After-work football for "&F13&" · "&Z13&", "&AA13&" min from your office" | AJ13: ="Hi "&IF(R13<>"",R13,F13&" team")&","&CHAR(10)&CHAR(10)&"I'm "&IF(AM13<>"",AM13,IF(Offer!$C$5<>"",Offer!$C$5,"[NAME]"))&" from FC Urban. We organise after-work football for teams in the City and Canary Wharf."&CHAR(10)&CHAR(10)&"We have a "&AE13&" pitch at "&Z13&", "&IF(OR(AA13=8,AA13=11,AA13=18),"an ","a ")&AA13&"-minute walk from your "&P13&" office, "&IF(ISNUMBER(AD13),"on "&TEXT(AD13,"dddd d mmmm")&" at "&TEXT(AD13,"hh:mm"),"on a weekday evening that suits your team")&". It's "&IF(AF13<>"","£"&IF(AF13=INT(AF13),TEXT(AF13,"0"),TEXT(AF13,"0.00")),"[PRICE PER PLAYER]")&" a player and we handle the pitch booking, sign-ups and payments, so all it takes is one person sharing a link with the team."&CHAR(10)&CHAR(10)&"It works well as a team social or "&IF(ISNUMBER(SEARCH(LEFT(F13,1),"AEIOU")),"an ","a ")&F13&" vs clients game. Would your team be up for it, or is there someone who'd enjoy organising it?"&IF(Offer!$C$7<>""," Spots are held until "&TEXT(Offer!$C$7,"dddd d mmmm")&".","")&" "&IF(Offer!$C$6<>"",Offer!$C$6,"[JOINING LINK]")&CHAR(10)&CHAR(10)&"Best,"&CHAR(10)&IF(AM13<>"",AM13,IF(Offer!$C$5<>"",Offer!$C$5,"[NAME]"))&CHAR(10)&"FC Urban" | AK13: ="Hi "&IF(R13<>"",R13,F13&" team")&","&CHAR(10)&CHAR(10)&"Just bumping this up. The "&AE13&" pitch at "&Z13&" is still free "&IF(ISNUMBER(AD13),TEXT(AD13,"ddd d mmm")&", "&TEXT(AD13,"hh:mm"),"weekday evenings")&", "&IF(OR(AA13=8,AA13=11,AA13=18),"an ","a ")&AA13&"-minute walk from your office, "&IF(AF13<>"","£"&IF(AF13=INT(AF13),TEXT(AF13,"0"),TEXT(AF13,"0.00")),"[PRICE PER PLAYER]")&" a player. Happy to hold it for "&F13&" if someone on the team fancies organising a game."&IF(Offer!$C$7<>""," Spots are held until "&TEXT(Offer!$C$7,"dddd d mmmm")&".","")&" "&IF(Offer!$C$6<>"",Offer!$C$6,"[JOINING LINK]")&CHAR(10)&CHAR(10)&"Best,"&CHAR(10)&IF(AM13<>"",AM13,IF(Offer!$C$5<>"",Offer!$C$5,"[NAME]"))&CHAR(10)&"FC Urban" | AL13: =IF(AH13="","No email yet",IF(ISNUMBER(SEARCH("[",AJ13)),"Fill placeholders",IF(ISNUMBER(AD13),"Ready to send","Ready · no fixed slot")))
A14: 12 | B14: 1 | C14: Law firm | D14: City of London | E14: Bryan Cave Leighton Paisner LLP | F14: Bryan Cave Leighton Paisner | G14: https://www.bclplaw.com | H14: kwfries@bclplaw.com | I14: named person | J14: Open page | K14: OC315919 | L14: Open | M14: Group | N14: 38657 | O14: Governor'S House, 5 Laurence Pountney Hill, London | P14: EC4R 0BR | Q14: No | W14: City of London School (EC4V 3AL) | X14: 12 | Y14: Marlborough Sports Garden (SE1 1SD) (13.4) | Z14: City of London School (EC4V 3AL) | AA14: 12 | AB14: =IFERROR(INDEX(Venues!$E$2:$E$17,MATCH(Z14,Venues!$A$2:$A$17,0)),"Not checked") | AC14: =IFERROR(INDEX(Venues!$F$2:$F$17,MATCH(Z14,Venues!$A$2:$A$17,0)),0) | AD14: =IFERROR(INDEX(Venues!$M$2:$M$17,MATCH(Z14,Venues!$A$2:$A$17,0)),"") | AE14: =IFERROR(INDEX(Venues!$N$2:$N$17,MATCH(Z14,Venues!$A$2:$A$17,0)),"5-a-side") | AF14: =IF(Offer!$C$4="","",Offer!$C$4) | AG14: =Z14&" ("&AA14&" min walk) · "&IF(ISNUMBER(AD14),TEXT(AD14,"ddd d mmm, hh:mm"),"slot to confirm with venue")&" · "&AE14&" · "&IF(AF14<>"","£"&TEXT(AF14,"0.00")&" pp","price TBC") | AH14: =IF(U14<>"",U14,IF(H14<>"",H14,"")) | AI14: ="After-work football for "&F14&" · "&Z14&", "&AA14&" min from your office" | AJ14: ="Hi "&IF(R14<>"",R14,F14&" team")&","&CHAR(10)&CHAR(10)&"I'm "&IF(AM14<>"",AM14,IF(Offer!$C$5<>"",Offer!$C$5,"[NAME]"))&" from FC Urban. We organise after-work football for teams in the City and Canary Wharf."&CHAR(10)&CHAR(10)&"We have a "&AE14&" pitch at "&Z14&", "&IF(OR(AA14=8,AA14=11,AA14=18),"an ","a ")&AA14&"-minute walk from your "&P14&" office, "&IF(ISNUMBER(AD14),"on "&TEXT(AD14,"dddd d mmmm")&" at "&TEXT(AD14,"hh:mm"),"on a weekday evening that suits your team")&". It's "&IF(AF14<>"","£"&IF(AF14=INT(AF14),TEXT(AF14,"0"),TEXT(AF14,"0.00")),"[PRICE PER PLAYER]")&" a player and we handle the pitch booking, sign-ups and payments, so all it takes is one person sharing a link with the team."&CHAR(10)&CHAR(10)&"It works well as a team social or "&IF(ISNUMBER(SEARCH(LEFT(F14,1),"AEIOU")),"an ","a ")&F14&" vs clients game. Would your team be up for it, or is there someone who'd enjoy organising it?"&IF(Offer!$C$7<>""," Spots are held until "&TEXT(Offer!$C$7,"dddd d mmmm")&".","")&" "&IF(Offer!$C$6<>"",Offer!$C$6,"[JOINING LINK]")&CHAR(10)&CHAR(10)&"Best,"&CHAR(10)&IF(AM14<>"",AM14,IF(Offer!$C$5<>"",Offer!$C$5,"[NAME]"))&CHAR(10)&"FC Urban" | AK14: ="Hi "&IF(R14<>"",R14,F14&" team")&","&CHAR(10)&CHAR(10)&"Just bumping this up. The "&AE14&" pitch at "&Z14&" is still free "&IF(ISNUMBER(AD14),TEXT(AD14,"ddd d mmm")&", "&TEXT(AD14,"hh:mm"),"weekday evenings")&", "&IF(OR(AA14=8,AA14=11,AA14=18),"an ","a ")&AA14&"-minute walk from your office, "&IF(AF14<>"","£"&IF(AF14=INT(AF14),TEXT(AF14,"0"),TEXT(AF14,"0.00")),"[PRICE PER PLAYER]")&" a player. Happy to hold it for "&F14&" if someone on the team fancies organising a game."&IF(Offer!$C$7<>""," Spots are held until "&TEXT(Offer!$C$7,"dddd d mmmm")&".","")&" "&IF(Offer!$C$6<>"",Offer!$C$6,"[JOINING LINK]")&CHAR(10)&CHAR(10)&"Best,"&CHAR(10)&IF(AM14<>"",AM14,IF(Offer!$C$5<>"",Offer!$C$5,"[NAME]"))&CHAR(10)&"FC Urban" | AL14: =IF(AH14="","No email yet",IF(ISNUMBER(SEARCH("[",AJ14)),"Fill placeholders",IF(ISNUMBER(AD14),"Ready to send","Ready · no fixed slot")))
A15: 13 | B15: 1 | C15: Law firm | D15: City of London | E15: Osborne Clarke LLP | F15: Osborne Clarke | G15: https://www.osborneclarke.com | H15: luis.gil@osborneclarke.com | I15: named person | J15: Open page | K15: OC397443 | L15: Open | M15: Group | N15: 42016 | O15: One London Wall, London | P15: EC2Y 5EB | Q15: No | W15: City of London School (EC4V 3AL) | X15: 12 | Y15: Finsbury Leisure Centre (EC1V 3PU) (16) | Z15: City of London School (EC4V 3AL) | AA15: 12 | AB15: =IFERROR(INDEX(Venues!$E$2:$E$17,MATCH(Z15,Venues!$A$2:$A$17,0)),"Not checked") | AC15: =IFERROR(INDEX(Venues!$F$2:$F$17,MATCH(Z15,Venues!$A$2:$A$17,0)),0) | AD15: =IFERROR(INDEX(Venues!$M$2:$M$17,MATCH(Z15,Venues!$A$2:$A$17,0)),"") | AE15: =IFERROR(INDEX(Venues!$N$2:$N$17,MATCH(Z15,Venues!$A$2:$A$17,0)),"5-a-side") | AF15: =IF(Offer!$C$4="","",Offer!$C$4) | AG15: =Z15&" ("&AA15&" min walk) · "&IF(ISNUMBER(AD15),TEXT(AD15,"ddd d mmm, hh:mm"),"slot to confirm with venue")&" · "&AE15&" · "&IF(AF15<>"","£"&TEXT(AF15,"0.00")&" pp","price TBC") | AH15: =IF(U15<>"",U15,IF(H15<>"",H15,"")) | AI15: ="After-work football for "&F15&" · "&Z15&", "&AA15&" min from your office" | AJ15: ="Hi "&IF(R15<>"",R15,F15&" team")&","&CHAR(10)&CHAR(10)&"I'm "&IF(AM15<>"",AM15,IF(Offer!$C$5<>"",Offer!$C$5,"[NAME]"))&" from FC Urban. We organise after-work football for teams in the City and Canary Wharf."&CHAR(10)&CHAR(10)&"We have a "&AE15&" pitch at "&Z15&", "&IF(OR(AA15=8,AA15=11,AA15=18),"an ","a ")&AA15&"-minute walk from your "&P15&" office, "&IF(ISNUMBER(AD15),"on "&TEXT(AD15,"dddd d mmmm")&" at "&TEXT(AD15,"hh:mm"),"on a weekday evening that suits your team")&". It's "&IF(AF15<>"","£"&IF(AF15=INT(AF15),TEXT(AF15,"0"),TEXT(AF15,"0.00")),"[PRICE PER PLAYER]")&" a player and we handle the pitch booking, sign-ups and payments, so all it takes is one person sharing a link with the team."&CHAR(10)&CHAR(10)&"It works well as a team social or "&IF(ISNUMBER(SEARCH(LEFT(F15,1),"AEIOU")),"an ","a ")&F15&" vs clients game. Would your team be up for it, or is there someone who'd enjoy organising it?"&IF(Offer!$C$7<>""," Spots are held until "&TEXT(Offer!$C$7,"dddd d mmmm")&".","")&" "&IF(Offer!$C$6<>"",Offer!$C$6,"[JOINING LINK]")&CHAR(10)&CHAR(10)&"Best,"&CHAR(10)&IF(AM15<>"",AM15,IF(Offer!$C$5<>"",Offer!$C$5,"[NAME]"))&CHAR(10)&"FC Urban" | AK15: ="Hi "&IF(R15<>"",R15,F15&" team")&","&CHAR(10)&CHAR(10)&"Just bumping this up. The "&AE15&" pitch at "&Z15&" is still free "&IF(ISNUMBER(AD15),TEXT(AD15,"ddd d mmm")&", "&TEXT(AD15,"hh:mm"),"weekday evenings")&", "&IF(OR(AA15=8,AA15=11,AA15=18),"an ","a ")&AA15&"-minute walk from your office, "&IF(AF15<>"","£"&IF(AF15=INT(AF15),TEXT(AF15,"0"),TEXT(AF15,"0.00")),"[PRICE PER PLAYER]")&" a player. Happy to hold it for "&F15&" if someone on the team fancies organising a game."&IF(Offer!$C$7<>""," Spots are held until "&TEXT(Offer!$C$7,"dddd d mmmm")&".","")&" "&IF(Offer!$C$6<>"",Offer!$C$6,"[JOINING LINK]")&CHAR(10)&CHAR(10)&"Best,"&CHAR(10)&IF(AM15<>"",AM15,IF(Offer!$C$5<>"",Offer!$C$5,"[NAME]"))&CHAR(10)&"FC Urban" | AL15: =IF(AH15="","No email yet",IF(ISNUMBER(SEARCH("[",AJ15)),"Fill placeholders",IF(ISNUMBER(AD15),"Ready to send","Ready · no fixed slot")))
A16: 14 | B16: 1 | C16: Law firm | D16: City of London | E16: Fragomen (GB) Limited | F16: Fragomen | G16: https://www.fragomen.com | H16: london@fragomen.com | I16: general | J16: Open page | K16: 04732334 | L16: Open | M16: Group | N16: 37724 | O16: 95 Gresham Street, 1St Floor, London | P16: EC2V 7NA | Q16: No | W16: City of London School (EC4V 3AL) | X16: 12 | Z16: City of London School (EC4V 3AL) | AA16: 12 | AB16: =IFERROR(INDEX(Venues!$E$2:$E$17,MATCH(Z16,Venues!$A$2:$A$17,0)),"Not checked") | AC16: =IFERROR(INDEX(Venues!$F$2:$F$17,MATCH(Z16,Venues!$A$2:$A$17,0)),0) | AD16: =IFERROR(INDEX(Venues!$M$2:$M$17,MATCH(Z16,Venues!$A$2:$A$17,0)),"") | AE16: =IFERROR(INDEX(Venues!$N$2:$N$17,MATCH(Z16,Venues!$A$2:$A$17,0)),"5-a-side") | AF16: =IF(Offer!$C$4="","",Offer!$C$4) | AG16: =Z16&" ("&AA16&" min walk) · "&IF(ISNUMBER(AD16),TEXT(AD16,"ddd d mmm, hh:mm"),"slot to confirm with venue")&" · "&AE16&" · "&IF(AF16<>"","£"&TEXT(AF16,"0.00")&" pp","price TBC") | AH16: =IF(U16<>"",U16,IF(H16<>"",H16,"")) | AI16: ="After-work football for "&F16&" · "&Z16&", "&AA16&" min from your office" | AJ16: ="Hi "&IF(R16<>"",R16,F16&" team")&","&CHAR(10)&CHAR(10)&"I'm "&IF(AM16<>"",AM16,IF(Offer!$C$5<>"",Offer!$C$5,"[NAME]"))&" from FC Urban. We organise after-work football for teams in the City and Canary Wharf."&CHAR(10)&CHAR(10)&"We have a "&AE16&" pitch at "&Z16&", "&IF(OR(AA16=8,AA16=11,AA16=18),"an ","a ")&AA16&"-minute walk from your "&P16&" office, "&IF(ISNUMBER(AD16),"on "&TEXT(AD16,"dddd d mmmm")&" at "&TEXT(AD16,"hh:mm"),"on a weekday evening that suits your team")&". It's "&IF(AF16<>"","£"&IF(AF16=INT(AF16),TEXT(AF16,"0"),TEXT(AF16,"0.00")),"[PRICE PER PLAYER]")&" a player and we handle the pitch booking, sign-ups and payments, so all it takes is one person sharing a link with the team."&CHAR(10)&CHAR(10)&"It works well as a team social or "&IF(ISNUMBER(SEARCH(LEFT(F16,1),"AEIOU")),"an ","a ")&F16&" vs clients game. Would your team be up for it, or is there someone who'd enjoy organising it?"&IF(Offer!$C$7<>""," Spots are held until "&TEXT(Offer!$C$7,"dddd d mmmm")&".","")&" "&IF(Offer!$C$6<>"",Offer!$C$6,"[JOINING LINK]")&CHAR(10)&CHAR(10)&"Best,"&CHAR(10)&IF(AM16<>"",AM16,IF(Offer!$C$5<>"",Offer!$C$5,"[NAME]"))&CHAR(10)&"FC Urban" | AK16: ="Hi "&IF(R16<>"",R16,F16&" team")&","&CHAR(10)&CHAR(10)&"Just bumping this up. The "&AE16&" pitch at "&Z16&" is still free "&IF(ISNUMBER(AD16),TEXT(AD16,"ddd d mmm")&", "&TEXT(AD16,"hh:mm"),"weekday evenings")&", "&IF(OR(AA16=8,AA16=11,AA16=18),"an ","a ")&AA16&"-minute walk from your office, "&IF(AF16<>"","£"&IF(AF16=INT(AF16),TEXT(AF16,"0"),TEXT(AF16,"0.00")),"[PRICE PER PLAYER]")&" a player. Happy to hold it for "&F16&" if someone on the team fancies organising a game."&IF(Offer!$C$7<>""," Spots are held until "&TEXT(Offer!$C$7,"dddd d mmmm")&".","")&" "&IF(Offer!$C$6<>"",Offer!$C$6,"[JOINING LINK]")&CHAR(10)&CHAR(10)&"Best,"&CHAR(10)&IF(AM16<>"",AM16,IF(Offer!$C$5<>"",Offer!$C$5,"[NAME]"))&CHAR(10)&"FC Urban" | AL16: =IF(AH16="","No email yet",IF(ISNUMBER(SEARCH("[",AJ16)),"Fill placeholders",IF(ISNUMBER(AD16),"Ready to send","Ready · no fixed slot")))
A17: 15 | B17: 1 | C17: Law firm | D17: City of London | E17: Fieldfisher LLP | F17: Fieldfisher | G17: https://www.fieldfisher.com | H17: london@fieldfisher.com | I17: general | J17: Open page | K17: OC318472 | L17: Open | M17: Group | N17: 38792 | O17: Riverbank House, 2 Swan Lane, London | P17: EC4R 3TT | Q17: No | W17: City of London School (EC4V 3AL) | X17: 12 | Y17: Marlborough Sports Garden (SE1 1SD) (12.4) | Z17: City of London School (EC4V 3AL) | AA17: 12 | AB17: =IFERROR(INDEX(Venues!$E$2:$E$17,MATCH(Z17,Venues!$A$2:$A$17,0)),"Not checked") | AC17: =IFERROR(INDEX(Venues!$F$2:$F$17,MATCH(Z17,Venues!$A$2:$A$17,0)),0) | AD17: =IFERROR(INDEX(Venues!$M$2:$M$17,MATCH(Z17,Venues!$A$2:$A$17,0)),"") | AE17: =IFERROR(INDEX(Venues!$N$2:$N$17,MATCH(Z17,Venues!$A$2:$A$17,0)),"5-a-side") | AF17: =IF(Offer!$C$4="","",Offer!$C$4) | AG17: =Z17&" ("&AA17&" min walk) · "&IF(ISNUMBER(AD17),TEXT(AD17,"ddd d mmm, hh:mm"),"slot to confirm with venue")&" · "&AE17&" · "&IF(AF17<>"","£"&TEXT(AF17,"0.00")&" pp","price TBC") | AH17: =IF(U17<>"",U17,IF(H17<>"",H17,"")) | AI17: ="After-work football for "&F17&" · "&Z17&", "&AA17&" min from your office" | AJ17: ="Hi "&IF(R17<>"",R17,F17&" team")&","&CHAR(10)&CHAR(10)&"I'm "&IF(AM17<>"",AM17,IF(Offer!$C$5<>"",Offer!$C$5,"[NAME]"))&" from FC Urban. We organise after-work football for teams in the City and Canary Wharf."&CHAR(10)&CHAR(10)&"We have a "&AE17&" pitch at "&Z17&", "&IF(OR(AA17=8,AA17=11,AA17=18),"an ","a ")&AA17&"-minute walk from your "&P17&" office, "&IF(ISNUMBER(AD17),"on "&TEXT(AD17,"dddd d mmmm")&" at "&TEXT(AD17,"hh:mm"),"on a weekday evening that suits your team")&". It's "&IF(AF17<>"","£"&IF(AF17=INT(AF17),TEXT(AF17,"0"),TEXT(AF17,"0.00")),"[PRICE PER PLAYER]")&" a player and we handle the pitch booking, sign-ups and payments, so all it takes is one person sharing a link with the team."&CHAR(10)&CHAR(10)&"It works well as a team social or "&IF(ISNUMBER(SEARCH(LEFT(F17,1),"AEIOU")),"an ","a ")&F17&" vs clients game. Would your team be up for it, or is there someone who'd enjoy organising it?"&IF(Offer!$C$7<>""," Spots are held until "&TEXT(Offer!$C$7,"dddd d mmmm")&".","")&" "&IF(Offer!$C$6<>"",Offer!$C$6,"[JOINING LINK]")&CHAR(10)&CHAR(10)&"Best,"&CHAR(10)&IF(AM17<>"",AM17,IF(Offer!$C$5<>"",Offer!$C$5,"[NAME]"))&CHAR(10)&"FC Urban" | AK17: ="Hi "&IF(R17<>"",R17,F17&" team")&","&CHAR(10)&CHAR(10)&"Just bumping this up. The "&AE17&" pitch at "&Z17&" is still free "&IF(ISNUMBER(AD17),TEXT(AD17,"ddd d mmm")&", "&TEXT(AD17,"hh:mm"),"weekday evenings")&", "&IF(OR(AA17=8,AA17=11,AA17=18),"an ","a ")&AA17&"-minute walk from your office, "&IF(AF17<>"","£"&IF(AF17=INT(AF17),TEXT(AF17,"0"),TEXT(AF17,"0.00")),"[PRICE PER PLAYER]")&" a player. Happy to hold it for "&F17&" if someone on the team fancies organising a game."&IF(Offer!$C$7<>""," Spots are held until "&TEXT(Offer!$C$7,"dddd d mmmm")&".","")&" "&IF(Offer!$C$6<>"",Offer!$C$6,"[JOINING LINK]")&CHAR(10)&CHAR(10)&"Best,"&CHAR(10)&IF(AM17<>"",AM17,IF(Offer!$C$5<>"",Offer!$C$5,"[NAME]"))&CHAR(10)&"FC Urban" | AL17: =IF(AH17="","No email yet",IF(ISNUMBER(SEARCH("[",AJ17)),"Fill placeholders",IF(ISNUMBER(AD17),"Ready to send","Ready · no fixed slot")))
A18: 16 | B18: 1 | C18: Law firm | D18: City of London | E18: Hogan Lovells Cadwalader International LLP | F18: Hogan Lovells Cadwalader | G18: https://www.hlc.com | H18: connect@hlc.com | I18: named person | J18: Open page | K18: OC323639 | L18: Open | M18: Group | N18: 39023 | O18: Atlantic House, Holborn Viaduct, London | P18: EC1A 2FG | Q18: Yes | W18: City of London School (EC4V 3AL) | X18: 14 | Z18: City of London School (EC4V 3AL) | AA18: 14 | AB18: =IFERROR(INDEX(Venues!$E$2:$E$17,MATCH(Z18,Venues!$A$2:$A$17,0)),"Not checked") | AC18: =IFERROR(INDEX(Venues!$F$2:$F$17,MATCH(Z18,Venues!$A$2:$A$17,0)),0) | AD18: =IFERROR(INDEX(Venues!$M$2:$M$17,MATCH(Z18,Venues!$A$2:$A$17,0)),"") | AE18: =IFERROR(INDEX(Venues!$N$2:$N$17,MATCH(Z18,Venues!$A$2:$A$17,0)),"5-a-side") | AF18: =IF(Offer!$C$4="","",Offer!$C$4) | AG18: =Z18&" ("&AA18&" min walk) · "&IF(ISNUMBER(AD18),TEXT(AD18,"ddd d mmm, hh:mm"),"slot to confirm with venue")&" · "&AE18&" · "&IF(AF18<>"","£"&TEXT(AF18,"0.00")&" pp","price TBC") | AH18: =IF(U18<>"",U18,IF(H18<>"",H18,"")) | AI18: ="After-work football for "&F18&" · "&Z18&", "&AA18&" min from your office" | AJ18: ="Hi "&IF(R18<>"",R18,F18&" team")&","&CHAR(10)&CHAR(10)&"I'm "&IF(AM18<>"",AM18,IF(Offer!$C$5<>"",Offer!$C$5,"[NAME]"))&" from FC Urban. We organise after-work football for teams in the City and Canary Wharf."&CHAR(10)&CHAR(10)&"We have a "&AE18&" pitch at "&Z18&", "&IF(OR(AA18=8,AA18=11,AA18=18),"an ","a ")&AA18&"-minute walk from your "&P18&" office, "&IF(ISNUMBER(AD18),"on "&TEXT(AD18,"dddd d mmmm")&" at "&TEXT(AD18,"hh:mm"),"on a weekday evening that suits your team")&". It's "&IF(AF18<>"","£"&IF(AF18=INT(AF18),TEXT(AF18,"0"),TEXT(AF18,"0.00")),"[PRICE PER PLAYER]")&" a player and we handle the pitch booking, sign-ups and payments, so all it takes is one person sharing a link with the team."&CHAR(10)&CHAR(10)&"It works well as a team social or "&IF(ISNUMBER(SEARCH(LEFT(F18,1),"AEIOU")),"an ","a ")&F18&" vs clients game. Would your team be up for it, or is there someone who'd enjoy organising it?"&IF(Offer!$C$7<>""," Spots are held until "&TEXT(Offer!$C$7,"dddd d mmmm")&".","")&" "&IF(Offer!$C$6<>"",Offer!$C$6,"[JOINING LINK]")&CHAR(10)&CHAR(10)&"Best,"&CHAR(10)&IF(AM18<>"",AM18,IF(Offer!$C$5<>"",Offer!$C$5,"[NAME]"))&CHAR(10)&"FC Urban" | AK18: ="Hi "&IF(R18<>"",R18,F18&" team")&","&CHAR(10)&CHAR(10)&"Just bumping this up. The "&AE18&" pitch at "&Z18&" is still free "&IF(ISNUMBER(AD18),TEXT(AD18,"ddd d mmm")&", "&TEXT(AD18,"hh:mm"),"weekday evenings")&", "&IF(OR(AA18=8,AA18=11,AA18=18),"an ","a ")&AA18&"-minute walk from your office, "&IF(AF18<>"","£"&IF(AF18=INT(AF18),TEXT(AF18,"0"),TEXT(AF18,"0.00")),"[PRICE PER PLAYER]")&" a player. Happy to hold it for "&F18&" if someone on the team fancies organising a game."&IF(Offer!$C$7<>""," Spots are held until "&TEXT(Offer!$C$7,"dddd d mmmm")&".","")&" "&IF(Offer!$C$6<>"",Offer!$C$6,"[JOINING LINK]")&CHAR(10)&CHAR(10)&"Best,"&CHAR(10)&IF(AM18<>"",AM18,IF(Offer!$C$5<>"",Offer!$C$5,"[NAME]"))&CHAR(10)&"FC Urban" | AL18: =IF(AH18="","No email yet",IF(ISNUMBER(SEARCH("[",AJ18)),"Fill placeholders",IF(ISNUMBER(AD18),"Ready to send","Ready · no fixed slot")))
A19: 17 | B19: 1 | C19: Law firm | D19: City of London | E19: Mills & Reeve LLP | F19: Mills & Reeve | G19: https://www.mills-reeve.com | H19: info@mills-reeve.com | I19: general | J19: Open page | K19: OC326165 | L19: Open | M19: Group | N19: 39133 | O19: 24 King William Street, London | P19: EC4R 9AT | Q19: No | W19: City of London School (EC4V 3AL) | X19: 14 | Y19: Marlborough Sports Garden (SE1 1SD) (14.5) | Z19: City of London School (EC4V 3AL) | AA19: 14 | AB19: =IFERROR(INDEX(Venues!$E$2:$E$17,MATCH(Z19,Venues!$A$2:$A$17,0)),"Not checked") | AC19: =IFERROR(INDEX(Venues!$F$2:$F$17,MATCH(Z19,Venues!$A$2:$A$17,0)),0) | AD19: =IFERROR(INDEX(Venues!$M$2:$M$17,MATCH(Z19,Venues!$A$2:$A$17,0)),"") | AE19: =IFERROR(INDEX(Venues!$N$2:$N$17,MATCH(Z19,Venues!$A$2:$A$17,0)),"5-a-side") | AF19: =IF(Offer!$C$4="","",Offer!$C$4) | AG19: =Z19&" ("&AA19&" min walk) · "&IF(ISNUMBER(AD19),TEXT(AD19,"ddd d mmm, hh:mm"),"slot to confirm with venue")&" · "&AE19&" · "&IF(AF19<>"","£"&TEXT(AF19,"0.00")&" pp","price TBC") | AH19: =IF(U19<>"",U19,IF(H19<>"",H19,"")) | AI19: ="After-work football for "&F19&" · "&Z19&", "&AA19&" min from your office" | AJ19: ="Hi "&IF(R19<>"",R19,F19&" team")&","&CHAR(10)&CHAR(10)&"I'm "&IF(AM19<>"",AM19,IF(Offer!$C$5<>"",Offer!$C$5,"[NAME]"))&" from FC Urban. We organise after-work football for teams in the City and Canary Wharf."&CHAR(10)&CHAR(10)&"We have a "&AE19&" pitch at "&Z19&", "&IF(OR(AA19=8,AA19=11,AA19=18),"an ","a ")&AA19&"-minute walk from your "&P19&" office, "&IF(ISNUMBER(AD19),"on "&TEXT(AD19,"dddd d mmmm")&" at "&TEXT(AD19,"hh:mm"),"on a weekday evening that suits your team")&". It's "&IF(AF19<>"","£"&IF(AF19=INT(AF19),TEXT(AF19,"0"),TEXT(AF19,"0.00")),"[PRICE PER PLAYER]")&" a player and we handle the pitch booking, sign-ups and payments, so all it takes is one person sharing a link with the team."&CHAR(10)&CHAR(10)&"It works well as a team social or "&IF(ISNUMBER(SEARCH(LEFT(F19,1),"AEIOU")),"an ","a ")&F19&" vs clients game. Would your team be up for it, or is there someone who'd enjoy organising it?"&IF(Offer!$C$7<>""," Spots are held until "&TEXT(Offer!$C$7,"dddd d mmmm")&".","")&" "&IF(Offer!$C$6<>"",Offer!$C$6,"[JOINING LINK]")&CHAR(10)&CHAR(10)&"Best,"&CHAR(10)&IF(AM19<>"",AM19,IF(Offer!$C$5<>"",Offer!$C$5,"[NAME]"))&CHAR(10)&"FC Urban" | AK19: ="Hi "&IF(R19<>"",R19,F19&" team")&","&CHAR(10)&CHAR(10)&"Just bumping this up. The "&AE19&" pitch at "&Z19&" is still free "&IF(ISNUMBER(AD19),TEXT(AD19,"ddd d mmm")&", "&TEXT(AD19,"hh:mm"),"weekday evenings")&", "&IF(OR(AA19=8,AA19=11,AA19=18),"an ","a ")&AA19&"-minute walk from your office, "&IF(AF19<>"","£"&IF(AF19=INT(AF19),TEXT(AF19,"0"),TEXT(AF19,"0.00")),"[PRICE PER PLAYER]")&" a player. Happy to hold it for "&F19&" if someone on the team fancies organising a game."&IF(Offer!$C$7<>""," Spots are held until "&TEXT(Offer!$C$7,"dddd d mmmm")&".","")&" "&IF(Offer!$C$6<>"",Offer!$C$6,"[JOINING LINK]")&CHAR(10)&CHAR(10)&"Best,"&CHAR(10)&IF(AM19<>"",AM19,IF(Offer!$C$5<>"",Offer!$C$5,"[NAME]"))&CHAR(10)&"FC Urban" | AL19: =IF(AH19="","No email yet",IF(ISNUMBER(SEARCH("[",AJ19)),"Fill placeholders",IF(ISNUMBER(AD19),"Ready to send","Ready · no fixed slot")))
A20: 18 | B20: 1 | C20: Law firm | D20: City of London | E20: DLA Piper International LLP | F20: DLA Piper | G20: https://www.dlapiper.com | H20: communications@dlapiper.com | I20: role (press / marketing) | J20: Open page | K20: OC305357 | L20: Open | M20: Group | N20: 37855 | O20: 160 Aldersgate Street, London | P20: EC1A 4HT | Q20: No | W20: Finsbury Leisure Centre (EC1V 3PU) | X20: 14 | Y20: City of London School (EC4V 3AL) (14); Old St - Moreland Primary School (18.4) | Z20: City of London School (EC4V 3AL) | AA20: 14 | AB20: =IFERROR(INDEX(Venues!$E$2:$E$17,MATCH(Z20,Venues!$A$2:$A$17,0)),"Not checked") | AC20: =IFERROR(INDEX(Venues!$F$2:$F$17,MATCH(Z20,Venues!$A$2:$A$17,0)),0) | AD20: =IFERROR(INDEX(Venues!$M$2:$M$17,MATCH(Z20,Venues!$A$2:$A$17,0)),"") | AE20: =IFERROR(INDEX(Venues!$N$2:$N$17,MATCH(Z20,Venues!$A$2:$A$17,0)),"5-a-side") | AF20: =IF(Offer!$C$4="","",Offer!$C$4) | AG20: =Z20&" ("&AA20&" min walk) · "&IF(ISNUMBER(AD20),TEXT(AD20,"ddd d mmm, hh:mm"),"slot to confirm with venue")&" · "&AE20&" · "&IF(AF20<>"","£"&TEXT(AF20,"0.00")&" pp","price TBC") | AH20: =IF(U20<>"",U20,IF(H20<>"",H20,"")) | AI20: ="After-work football for "&F20&" · "&Z20&", "&AA20&" min from your office" | AJ20: ="Hi "&IF(R20<>"",R20,F20&" team")&","&CHAR(10)&CHAR(10)&"I'm "&IF(AM20<>"",AM20,IF(Offer!$C$5<>"",Offer!$C$5,"[NAME]"))&" from FC Urban. We organise after-work football for teams in the City and Canary Wharf."&CHAR(10)&CHAR(10)&"We have a "&AE20&" pitch at "&Z20&", "&IF(OR(AA20=8,AA20=11,AA20=18),"an ","a ")&AA20&"-minute walk from your "&P20&" office, "&IF(ISNUMBER(AD20),"on "&TEXT(AD20,"dddd d mmmm")&" at "&TEXT(AD20,"hh:mm"),"on a weekday evening that suits your team")&". It's "&IF(AF20<>"","£"&IF(AF20=INT(AF20),TEXT(AF20,"0"),TEXT(AF20,"0.00")),"[PRICE PER PLAYER]")&" a player and we handle the pitch booking, sign-ups and payments, so all it takes is one person sharing a link with the team."&CHAR(10)&CHAR(10)&"It works well as a team social or "&IF(ISNUMBER(SEARCH(LEFT(F20,1),"AEIOU")),"an ","a ")&F20&" vs clients game. Would your team be up for it, or is there someone who'd enjoy organising it?"&IF(Offer!$C$7<>""," Spots are held until "&TEXT(Offer!$C$7,"dddd d mmmm")&".","")&" "&IF(Offer!$C$6<>"",Offer!$C$6,"[JOINING LINK]")&CHAR(10)&CHAR(10)&"Best,"&CHAR(10)&IF(AM20<>"",AM20,IF(Offer!$C$5<>"",Offer!$C$5,"[NAME]"))&CHAR(10)&"FC Urban" | AK20: ="Hi "&IF(R20<>"",R20,F20&" team")&","&CHAR(10)&CHAR(10)&"Just bumping this up. The "&AE20&" pitch at "&Z20&" is still free "&IF(ISNUMBER(AD20),TEXT(AD20,"ddd d mmm")&", "&TEXT(AD20,"hh:mm"),"weekday evenings")&", "&IF(OR(AA20=8,AA20=11,AA20=18),"an ","a ")&AA20&"-minute walk from your office, "&IF(AF20<>"","£"&IF(AF20=INT(AF20),TEXT(AF20,"0"),TEXT(AF20,"0.00")),"[PRICE PER PLAYER]")&" a player. Happy to hold it for "&F20&" if someone on the team fancies organising a game."&IF(Offer!$C$7<>""," Spots are held until "&TEXT(Offer!$C$7,"dddd d mmmm")&".","")&" "&IF(Offer!$C$6<>"",Offer!$C$6,"[JOINING LINK]")&CHAR(10)&CHAR(10)&"Best,"&CHAR(10)&IF(AM20<>"",AM20,IF(Offer!$C$5<>"",Offer!$C$5,"[NAME]"))&CHAR(10)&"FC Urban" | AL20: =IF(AH20="","No email yet",IF(ISNUMBER(SEARCH("[",AJ20)),"Fill placeholders",IF(ISNUMBER(AD20),"Ready to send","Ready · no fixed slot")))
A21: 19 | B21: 1 | C21: Law firm | D21: City of London | E21: Lighthouse Global Europe Limited | F21: Lighthouse | G21: https://lighthouse.com | I21: Not found | K21: 09610972 | L21: Open | M21: Group | N21: 42151 | O21: 68 King William Street, London | P21: EC4N 7HR | Q21: No | W21: City of London School (EC4V 3AL) | X21: 14 | Y21: Marlborough Sports Garden (SE1 1SD) (15.6) | Z21: City of London School (EC4V 3AL) | AA21: 14 | AB21: =IFERROR(INDEX(Venues!$E$2:$E$17,MATCH(Z21,Venues!$A$2:$A$17,0)),"Not checked") | AC21: =IFERROR(INDEX(Venues!$F$2:$F$17,MATCH(Z21,Venues!$A$2:$A$17,0)),0) | AD21: =IFERROR(INDEX(Venues!$M$2:$M$17,MATCH(Z21,Venues!$A$2:$A$17,0)),"") | AE21: =IFERROR(INDEX(Venues!$N$2:$N$17,MATCH(Z21,Venues!$A$2:$A$17,0)),"5-a-side") | AF21: =IF(Offer!$C$4="","",Offer!$C$4) | AG21: =Z21&" ("&AA21&" min walk) · "&IF(ISNUMBER(AD21),TEXT(AD21,"ddd d mmm, hh:mm"),"slot to confirm with venue")&" · "&AE21&" · "&IF(AF21<>"","£"&TEXT(AF21,"0.00")&" pp","price TBC") | AH21: =IF(U21<>"",U21,IF(H21<>"",H21,"")) | AI21: ="After-work football for "&F21&" · "&Z21&", "&AA21&" min from your office" | AJ21: ="Hi "&IF(R21<>"",R21,F21&" team")&","&CHAR(10)&CHAR(10)&"I'm "&IF(AM21<>"",AM21,IF(Offer!$C$5<>"",Offer!$C$5,"[NAME]"))&" from FC Urban. We organise after-work football for teams in the City and Canary Wharf."&CHAR(10)&CHAR(10)&"We have a "&AE21&" pitch at "&Z21&", "&IF(OR(AA21=8,AA21=11,AA21=18),"an ","a ")&AA21&"-minute walk from your "&P21&" office, "&IF(ISNUMBER(AD21),"on "&TEXT(AD21,"dddd d mmmm")&" at "&TEXT(AD21,"hh:mm"),"on a weekday evening that suits your team")&". It's "&IF(AF21<>"","£"&IF(AF21=INT(AF21),TEXT(AF21,"0"),TEXT(AF21,"0.00")),"[PRICE PER PLAYER]")&" a player and we handle the pitch booking, sign-ups and payments, so all it takes is one person sharing a link with the team."&CHAR(10)&CHAR(10)&"It works well as a team social or "&IF(ISNUMBER(SEARCH(LEFT(F21,1),"AEIOU")),"an ","a ")&F21&" vs clients game. Would your team be up for it, or is there someone who'd enjoy organising it?"&IF(Offer!$C$7<>""," Spots are held until "&TEXT(Offer!$C$7,"dddd d mmmm")&".","")&" "&IF(Offer!$C$6<>"",Offer!$C$6,"[JOINING LINK]")&CHAR(10)&CHAR(10)&"Best,"&CHAR(10)&IF(AM21<>"",AM21,IF(Offer!$C$5<>"",Offer!$C$5,"[NAME]"))&CHAR(10)&"FC Urban" | AK21: ="Hi "&IF(R21<>"",R21,F21&" team")&","&CHAR(10)&CHAR(10)&"Just bumping this up. The "&AE21&" pitch at "&Z21&" is still free "&IF(ISNUMBER(AD21),TEXT(AD21,"ddd d mmm")&", "&TEXT(AD21,"hh:mm"),"weekday evenings")&", "&IF(OR(AA21=8,AA21=11,AA21=18),"an ","a ")&AA21&"-minute walk from your office, "&IF(AF21<>"","£"&IF(AF21=INT(AF21),TEXT(AF21,"0"),TEXT(AF21,"0.00")),"[PRICE PER PLAYER]")&" a player. Happy to hold it for "&F21&" if someone on the team fancies organising a game."&IF(Offer!$C$7<>""," Spots are held until "&TEXT(Offer!$C$7,"dddd d mmmm")&".","")&" "&IF(Offer!$C$6<>"",Offer!$C$6,"[JOINING LINK]")&CHAR(10)&CHAR(10)&"Best,"&CHAR(10)&IF(AM21<>"",AM21,IF(Offer!$C$5<>"",Offer!$C$5,"[NAME]"))&CHAR(10)&"FC Urban" | AL21: =IF(AH21="","No email yet",IF(ISNUMBER(SEARCH("[",AJ21)),"Fill placeholders",IF(ISNUMBER(AD21),"Ready to send","Ready · no fixed slot")))
A22: 20 | B22: 1 | C22: Law firm | D22: City of London | E22: Howard Kennedy LLP | F22: Howard Kennedy | G22: https://www.howardkennedy.com | H22: london@howardkennedy.com | I22: general | J22: Open page | K22: OC361417 | L22: Open | M22: Group | N22: 40575 | O22: No.1, London Bridge, London | P22: SE1 9BG | Q22: No | W22: Marlborough Sports Garden (SE1 1SD) | X22: 8 | Y22: City of London School (EC4V 3AL) (15.5); Borough Academy (16.1) | Z22: City of London School (EC4V 3AL) | AA22: 16 | AB22: =IFERROR(INDEX(Venues!$E$2:$E$17,MATCH(Z22,Venues!$A$2:$A$17,0)),"Not checked") | AC22: =IFERROR(INDEX(Venues!$F$2:$F$17,MATCH(Z22,Venues!$A$2:$A$17,0)),0) | AD22: =IFERROR(INDEX(Venues!$M$2:$M$17,MATCH(Z22,Venues!$A$2:$A$17,0)),"") | AE22: =IFERROR(INDEX(Venues!$N$2:$N$17,MATCH(Z22,Venues!$A$2:$A$17,0)),"5-a-side") | AF22: =IF(Offer!$C$4="","",Offer!$C$4) | AG22: =Z22&" ("&AA22&" min walk) · "&IF(ISNUMBER(AD22),TEXT(AD22,"ddd d mmm, hh:mm"),"slot to confirm with venue")&" · "&AE22&" · "&IF(AF22<>"","£"&TEXT(AF22,"0.00")&" pp","price TBC") | AH22: =IF(U22<>"",U22,IF(H22<>"",H22,"")) | AI22: ="After-work football for "&F22&" · "&Z22&", "&AA22&" min from your office" | AJ22: ="Hi "&IF(R22<>"",R22,F22&" team")&","&CHAR(10)&CHAR(10)&"I'm "&IF(AM22<>"",AM22,IF(Offer!$C$5<>"",Offer!$C$5,"[NAME]"))&" from FC Urban. We organise after-work football for teams in the City and Canary Wharf."&CHAR(10)&CHAR(10)&"We have a "&AE22&" pitch at "&Z22&", "&IF(OR(AA22=8,AA22=11,AA22=18),"an ","a ")&AA22&"-minute walk from your "&P22&" office, "&IF(ISNUMBER(AD22),"on "&TEXT(AD22,"dddd d mmmm")&" at "&TEXT(AD22,"hh:mm"),"on a weekday evening that suits your team")&". It's "&IF(AF22<>"","£"&IF(AF22=INT(AF22),TEXT(AF22,"0"),TEXT(AF22,"0.00")),"[PRICE PER PLAYER]")&" a player and we handle the pitch booking, sign-ups and payments, so all it takes is one person sharing a link with the team."&CHAR(10)&CHAR(10)&"It works well as a team social or "&IF(ISNUMBER(SEARCH(LEFT(F22,1),"AEIOU")),"an ","a ")&F22&" vs clients game. Would your team be up for it, or is there someone who'd enjoy organising it?"&IF(Offer!$C$7<>""," Spots are held until "&TEXT(Offer!$C$7,"dddd d mmmm")&".","")&" "&IF(Offer!$C$6<>"",Offer!$C$6,"[JOINING LINK]")&CHAR(10)&CHAR(10)&"Best,"&CHAR(10)&IF(AM22<>"",AM22,IF(Offer!$C$5<>"",Offer!$C$5,"[NAME]"))&CHAR(10)&"FC Urban" | AK22: ="Hi "&IF(R22<>"",R22,F22&" team")&","&CHAR(10)&CHAR(10)&"Just bumping this up. The "&AE22&" pitch at "&Z22&" is still free "&IF(ISNUMBER(AD22),TEXT(AD22,"ddd d mmm")&", "&TEXT(AD22,"hh:mm"),"weekday evenings")&", "&IF(OR(AA22=8,AA22=11,AA22=18),"an ","a ")&AA22&"-minute walk from your office, "&IF(AF22<>"","£"&IF(AF22=INT(AF22),TEXT(AF22,"0"),TEXT(AF22,"0.00")),"[PRICE PER PLAYER]")&" a player. Happy to hold it for "&F22&" if someone on the team fancies organising a game."&IF(Offer!$C$7<>""," Spots are held until "&TEXT(Offer!$C$7,"dddd d mmmm")&".","")&" "&IF(Offer!$C$6<>"",Offer!$C$6,"[JOINING LINK]")&CHAR(10)&CHAR(10)&"Best,"&CHAR(10)&IF(AM22<>"",AM22,IF(Offer!$C$5<>"",Offer!$C$5,"[NAME]"))&CHAR(10)&"FC Urban" | AL22: =IF(AH22="","No email yet",IF(ISNUMBER(SEARCH("[",AJ22)),"Fill placeholders",IF(ISNUMBER(AD22),"Ready to send","Ready · no fixed slot")))
A23: 21 | B23: 1 | C23: Law firm | D23: City of London | E23: Linklaters LLP | F23: Linklaters | G23: https://www.linklaters.com | H23: pressoffice@linklaters.com | I23: role (press / marketing) | J23: Open page | K23: OC326345 | L23: Open | M23: Group | N23: 39140 | O23: 20 Ropemaker Street, London | P23: EC2Y 9AR | Q23: No | W23: Finsbury Leisure Centre (EC1V 3PU) | X23: 14 | Y23: Shoreditch Powerleague (15.7); Liverpool St - Attlee Centre (17.7) | Z23: Shoreditch Powerleague | AA23: 16 | AB23: =IFERROR(INDEX(Venues!$E$2:$E$17,MATCH(Z23,Venues!$A$2:$A$17,0)),"Not checked") | AC23: =IFERROR(INDEX(Venues!$F$2:$F$17,MATCH(Z23,Venues!$A$2:$A$17,0)),0) | AD23: =IFERROR(INDEX(Venues!$M$2:$M$17,MATCH(Z23,Venues!$A$2:$A$17,0)),"") | AE23: =IFERROR(INDEX(Venues!$N$2:$N$17,MATCH(Z23,Venues!$A$2:$A$17,0)),"5-a-side") | AF23: =IF(Offer!$C$4="","",Offer!$C$4) | AG23: =Z23&" ("&AA23&" min walk) · "&IF(ISNUMBER(AD23),TEXT(AD23,"ddd d mmm, hh:mm"),"slot to confirm with venue")&" · "&AE23&" · "&IF(AF23<>"","£"&TEXT(AF23,"0.00")&" pp","price TBC") | AH23: =IF(U23<>"",U23,IF(H23<>"",H23,"")) | AI23: ="After-work football for "&F23&" · "&Z23&", "&AA23&" min from your office" | AJ23: ="Hi "&IF(R23<>"",R23,F23&" team")&","&CHAR(10)&CHAR(10)&"I'm "&IF(AM23<>"",AM23,IF(Offer!$C$5<>"",Offer!$C$5,"[NAME]"))&" from FC Urban. We organise after-work football for teams in the City and Canary Wharf."&CHAR(10)&CHAR(10)&"We have a "&AE23&" pitch at "&Z23&", "&IF(OR(AA23=8,AA23=11,AA23=18),"an ","a ")&AA23&"-minute walk from your "&P23&" office, "&IF(ISNUMBER(AD23),"on "&TEXT(AD23,"dddd d mmmm")&" at "&TEXT(AD23,"hh:mm"),"on a weekday evening that suits your team")&". It's "&IF(AF23<>"","£"&IF(AF23=INT(AF23),TEXT(AF23,"0"),TEXT(AF23,"0.00")),"[PRICE PER PLAYER]")&" a player and we handle the pitch booking, sign-ups and payments, so all it takes is one person sharing a link with the team."&CHAR(10)&CHAR(10)&"It works well as a team social or "&IF(ISNUMBER(SEARCH(LEFT(F23,1),"AEIOU")),"an ","a ")&F23&" vs clients game. Would your team be up for it, or is there someone who'd enjoy organising it?"&IF(Offer!$C$7<>""," Spots are held until "&TEXT(Offer!$C$7,"dddd d mmmm")&".","")&" "&IF(Offer!$C$6<>"",Offer!$C$6,"[JOINING LINK]")&CHAR(10)&CHAR(10)&"Best,"&CHAR(10)&IF(AM23<>"",AM23,IF(Offer!$C$5<>"",Offer!$C$5,"[NAME]"))&CHAR(10)&"FC Urban" | AK23: ="Hi "&IF(R23<>"",R23,F23&" team")&","&CHAR(10)&CHAR(10)&"Just bumping this up. The "&AE23&" pitch at "&Z23&" is still free "&IF(ISNUMBER(AD23),TEXT(AD23,"ddd d mmm")&", "&TEXT(AD23,"hh:mm"),"weekday evenings")&", "&IF(OR(AA23=8,AA23=11,AA23=18),"an ","a ")&AA23&"-minute walk from your office, "&IF(AF23<>"","£"&IF(AF23=INT(AF23),TEXT(AF23,"0"),TEXT(AF23,"0.00")),"[PRICE PER PLAYER]")&" a player. Happy to hold it for "&F23&" if someone on the team fancies organising a game."&IF(Offer!$C$7<>""," Spots are held until "&TEXT(Offer!$C$7,"dddd d mmmm")&".","")&" "&IF(Offer!$C$6<>"",Offer!$C$6,"[JOINING LINK]")&CHAR(10)&CHAR(10)&"Best,"&CHAR(10)&IF(AM23<>"",AM23,IF(Offer!$C$5<>"",Offer!$C$5,"[NAME]"))&CHAR(10)&"FC Urban" | AL23: =IF(AH23="","No email yet",IF(ISNUMBER(SEARCH("[",AJ23)),"Fill placeholders",IF(ISNUMBER(AD23),"Ready to send","Ready · no fixed slot")))
A24: 22 | B24: 1 | C24: Law firm | D24: City of London | E24: Three Crowns (Services) LLP | F24: Three Crowns | G24: https://www.threecrownsllp.com | H24: london@threecrownsllp.com | I24: general | J24: Open page | K24: OC389628 | L24: Open | M24: Group | N24: 41610 | O24: The Jj Mack Building, 33 Charterhouse Street, London | P24: EC1M 6HA | Q24: No | W24: City of London School (EC4V 3AL) | X24: 16 | Y24: Finsbury Leisure Centre (EC1V 3PU) (15.7); Old St - Moreland Primary School (18.5) | Z24: City of London School (EC4V 3AL) | AA24: 16 | AB24: =IFERROR(INDEX(Venues!$E$2:$E$17,MATCH(Z24,Venues!$A$2:$A$17,0)),"Not checked") | AC24: =IFERROR(INDEX(Venues!$F$2:$F$17,MATCH(Z24,Venues!$A$2:$A$17,0)),0) | AD24: =IFERROR(INDEX(Venues!$M$2:$M$17,MATCH(Z24,Venues!$A$2:$A$17,0)),"") | AE24: =IFERROR(INDEX(Venues!$N$2:$N$17,MATCH(Z24,Venues!$A$2:$A$17,0)),"5-a-side") | AF24: =IF(Offer!$C$4="","",Offer!$C$4) | AG24: =Z24&" ("&AA24&" min walk) · "&IF(ISNUMBER(AD24),TEXT(AD24,"ddd d mmm, hh:mm"),"slot to confirm with venue")&" · "&AE24&" · "&IF(AF24<>"","£"&TEXT(AF24,"0.00")&" pp","price TBC") | AH24: =IF(U24<>"",U24,IF(H24<>"",H24,"")) | AI24: ="After-work football for "&F24&" · "&Z24&", "&AA24&" min from your office" | AJ24: ="Hi "&IF(R24<>"",R24,F24&" team")&","&CHAR(10)&CHAR(10)&"I'm "&IF(AM24<>"",AM24,IF(Offer!$C$5<>"",Offer!$C$5,"[NAME]"))&" from FC Urban. We organise after-work football for teams in the City and Canary Wharf."&CHAR(10)&CHAR(10)&"We have a "&AE24&" pitch at "&Z24&", "&IF(OR(AA24=8,AA24=11,AA24=18),"an ","a ")&AA24&"-minute walk from your "&P24&" office, "&IF(ISNUMBER(AD24),"on "&TEXT(AD24,"dddd d mmmm")&" at "&TEXT(AD24,"hh:mm"),"on a weekday evening that suits your team")&". It's "&IF(AF24<>"","£"&IF(AF24=INT(AF24),TEXT(AF24,"0"),TEXT(AF24,"0.00")),"[PRICE PER PLAYER]")&" a player and we handle the pitch booking, sign-ups and payments, so all it takes is one person sharing a link with the team."&CHAR(10)&CHAR(10)&"It works well as a team social or "&IF(ISNUMBER(SEARCH(LEFT(F24,1),"AEIOU")),"an ","a ")&F24&" vs clients game. Would your team be up for it, or is there someone who'd enjoy organising it?"&IF(Offer!$C$7<>""," Spots are held until "&TEXT(Offer!$C$7,"dddd d mmmm")&".","")&" "&IF(Offer!$C$6<>"",Offer!$C$6,"[JOINING LINK]")&CHAR(10)&CHAR(10)&"Best,"&CHAR(10)&IF(AM24<>"",AM24,IF(Offer!$C$5<>"",Offer!$C$5,"[NAME]"))&CHAR(10)&"FC Urban" | AK24: ="Hi "&IF(R24<>"",R24,F24&" team")&","&CHAR(10)&CHAR(10)&"Just bumping this up. The "&AE24&" pitch at "&Z24&" is still free "&IF(ISNUMBER(AD24),TEXT(AD24,"ddd d mmm")&", "&TEXT(AD24,"hh:mm"),"weekday evenings")&", "&IF(OR(AA24=8,AA24=11,AA24=18),"an ","a ")&AA24&"-minute walk from your office, "&IF(AF24<>"","£"&IF(AF24=INT(AF24),TEXT(AF24,"0"),TEXT(AF24,"0.00")),"[PRICE PER PLAYER]")&" a player. Happy to hold it for "&F24&" if someone on the team fancies organising a game."&IF(Offer!$C$7<>""," Spots are held until "&TEXT(Offer!$C$7,"dddd d mmmm")&".","")&" "&IF(Offer!$C$6<>"",Offer!$C$6,"[JOINING LINK]")&CHAR(10)&CHAR(10)&"Best,"&CHAR(10)&IF(AM24<>"",AM24,IF(Offer!$C$5<>"",Offer!$C$5,"[NAME]"))&CHAR(10)&"FC Urban" | AL24: =IF(AH24="","No email yet",IF(ISNUMBER(SEARCH("[",AJ24)),"Fill placeholders",IF(ISNUMBER(AD24),"Ready to send","Ready · no fixed slot")))
A25: 23 | B25: 1 | C25: Law firm | D25: City of London | E25: Stephenson Harwood LLP | F25: Stephenson Harwood | G25: https://www.stephensonharwood.com | H25: info@stephensonharwood.com | I25: general | J25: Open page | K25: OC373597 | L25: Open | M25: Group | N25: 40989 | O25: 1 Finsbury Circus, London | P25: EC2M 7SH | Q25: No | W25: Shoreditch Powerleague | X25: 16 | Y25: Liverpool St - Attlee Centre (16.3); Finsbury Leisure Centre (EC1V 3PU) (16.6) | Z25: Shoreditch Powerleague | AA25: 16 | AB25: =IFERROR(INDEX(Venues!$E$2:$E$17,MATCH(Z25,Venues!$A$2:$A$17,0)),"Not checked") | AC25: =IFERROR(INDEX(Venues!$F$2:$F$17,MATCH(Z25,Venues!$A$2:$A$17,0)),0) | AD25: =IFERROR(INDEX(Venues!$M$2:$M$17,MATCH(Z25,Venues!$A$2:$A$17,0)),"") | AE25: =IFERROR(INDEX(Venues!$N$2:$N$17,MATCH(Z25,Venues!$A$2:$A$17,0)),"5-a-side") | AF25: =IF(Offer!$C$4="","",Offer!$C$4) | AG25: =Z25&" ("&AA25&" min walk) · "&IF(ISNUMBER(AD25),TEXT(AD25,"ddd d mmm, hh:mm"),"slot to confirm with venue")&" · "&AE25&" · "&IF(AF25<>"","£"&TEXT(AF25,"0.00")&" pp","price TBC") | AH25: =IF(U25<>"",U25,IF(H25<>"",H25,"")) | AI25: ="After-work football for "&F25&" · "&Z25&", "&AA25&" min from your office" | AJ25: ="Hi "&IF(R25<>"",R25,F25&" team")&","&CHAR(10)&CHAR(10)&"I'm "&IF(AM25<>"",AM25,IF(Offer!$C$5<>"",Offer!$C$5,"[NAME]"))&" from FC Urban. We organise after-work football for teams in the City and Canary Wharf."&CHAR(10)&CHAR(10)&"We have a "&AE25&" pitch at "&Z25&", "&IF(OR(AA25=8,AA25=11,AA25=18),"an ","a ")&AA25&"-minute walk from your "&P25&" office, "&IF(ISNUMBER(AD25),"on "&TEXT(AD25,"dddd d mmmm")&" at "&TEXT(AD25,"hh:mm"),"on a weekday evening that suits your team")&". It's "&IF(AF25<>"","£"&IF(AF25=INT(AF25),TEXT(AF25,"0"),TEXT(AF25,"0.00")),"[PRICE PER PLAYER]")&" a player and we handle the pitch booking, sign-ups and payments, so all it takes is one person sharing a link with the team."&CHAR(10)&CHAR(10)&"It works well as a team social or "&IF(ISNUMBER(SEARCH(LEFT(F25,1),"AEIOU")),"an ","a ")&F25&" vs clients game. Would your team be up for it, or is there someone who'd enjoy organising it?"&IF(Offer!$C$7<>""," Spots are held until "&TEXT(Offer!$C$7,"dddd d mmmm")&".","")&" "&IF(Offer!$C$6<>"",Offer!$C$6,"[JOINING LINK]")&CHAR(10)&CHAR(10)&"Best,"&CHAR(10)&IF(AM25<>"",AM25,IF(Offer!$C$5<>"",Offer!$C$5,"[NAME]"))&CHAR(10)&"FC Urban" | AK25: ="Hi "&IF(R25<>"",R25,F25&" team")&","&CHAR(10)&CHAR(10)&"Just bumping this up. The "&AE25&" pitch at "&Z25&" is still free "&IF(ISNUMBER(AD25),TEXT(AD25,"ddd d mmm")&", "&TEXT(AD25,"hh:mm"),"weekday evenings")&", "&IF(OR(AA25=8,AA25=11,AA25=18),"an ","a ")&AA25&"-minute walk from your office, "&IF(AF25<>"","£"&IF(AF25=INT(AF25),TEXT(AF25,"0"),TEXT(AF25,"0.00")),"[PRICE PER PLAYER]")&" a player. Happy to hold it for "&F25&" if someone on the team fancies organising a game."&IF(Offer!$C$7<>""," Spots are held until "&TEXT(Offer!$C$7,"dddd d mmmm")&".","")&" "&IF(Offer!$C$6<>"",Offer!$C$6,"[JOINING LINK]")&CHAR(10)&CHAR(10)&"Best,"&CHAR(10)&IF(AM25<>"",AM25,IF(Offer!$C$5<>"",Offer!$C$5,"[NAME]"))&CHAR(10)&"FC Urban" | AL25: =IF(AH25="","No email yet",IF(ISNUMBER(SEARCH("[",AJ25)),"Fill placeholders",IF(ISNUMBER(AD25),"Ready to send","Ready · no fixed slot")))
A26: 24 | B26: 1 | C26: Law firm | D26: City of London | E26: Devonshires Solicitors LLP | F26: Devonshires Solicitors | G26: https://www.devonshires.com | H26: info@devonshires.co.uk | I26: general | J26: Open page | K26: OC397401 | L26: Open | M26: Group | N26: 42011 | O26: 30 Finsbury Circus, London | P26: EC2M 7DT | Q26: No | W26: Liverpool St - Attlee Centre | X26: 16 | Y26: Shoreditch Powerleague (16.7); Finsbury Leisure Centre (EC1V 3PU) (17.4) | Z26: Shoreditch Powerleague | AA26: 17 | AB26: =IFERROR(INDEX(Venues!$E$2:$E$17,MATCH(Z26,Venues!$A$2:$A$17,0)),"Not checked") | AC26: =IFERROR(INDEX(Venues!$F$2:$F$17,MATCH(Z26,Venues!$A$2:$A$17,0)),0) | AD26: =IFERROR(INDEX(Venues!$M$2:$M$17,MATCH(Z26,Venues!$A$2:$A$17,0)),"") | AE26: =IFERROR(INDEX(Venues!$N$2:$N$17,MATCH(Z26,Venues!$A$2:$A$17,0)),"5-a-side") | AF26: =IF(Offer!$C$4="","",Offer!$C$4) | AG26: =Z26&" ("&AA26&" min walk) · "&IF(ISNUMBER(AD26),TEXT(AD26,"ddd d mmm, hh:mm"),"slot to confirm with venue")&" · "&AE26&" · "&IF(AF26<>"","£"&TEXT(AF26,"0.00")&" pp","price TBC") | AH26: =IF(U26<>"",U26,IF(H26<>"",H26,"")) | AI26: ="After-work football for "&F26&" · "&Z26&", "&AA26&" min from your office" | AJ26: ="Hi "&IF(R26<>"",R26,F26&" team")&","&CHAR(10)&CHAR(10)&"I'm "&IF(AM26<>"",AM26,IF(Offer!$C$5<>"",Offer!$C$5,"[NAME]"))&" from FC Urban. We organise after-work football for teams in the City and Canary Wharf."&CHAR(10)&CHAR(10)&"We have a "&AE26&" pitch at "&Z26&", "&IF(OR(AA26=8,AA26=11,AA26=18),"an ","a ")&AA26&"-minute walk from your "&P26&" office, "&IF(ISNUMBER(AD26),"on "&TEXT(AD26,"dddd d mmmm")&" at "&TEXT(AD26,"hh:mm"),"on a weekday evening that suits your team")&". It's "&IF(AF26<>"","£"&IF(AF26=INT(AF26),TEXT(AF26,"0"),TEXT(AF26,"0.00")),"[PRICE PER PLAYER]")&" a player and we handle the pitch booking, sign-ups and payments, so all it takes is one person sharing a link with the team."&CHAR(10)&CHAR(10)&"It works well as a team social or "&IF(ISNUMBER(SEARCH(LEFT(F26,1),"AEIOU")),"an ","a ")&F26&" vs clients game. Would your team be up for it, or is there someone who'd enjoy organising it?"&IF(Offer!$C$7<>""," Spots are held until "&TEXT(Offer!$C$7,"dddd d mmmm")&".","")&" "&IF(Offer!$C$6<>"",Offer!$C$6,"[JOINING LINK]")&CHAR(10)&CHAR(10)&"Best,"&CHAR(10)&IF(AM26<>"",AM26,IF(Offer!$C$5<>"",Offer!$C$5,"[NAME]"))&CHAR(10)&"FC Urban" | AK26: ="Hi "&IF(R26<>"",R26,F26&" team")&","&CHAR(10)&CHAR(10)&"Just bumping this up. The "&AE26&" pitch at "&Z26&" is still free "&IF(ISNUMBER(AD26),TEXT(AD26,"ddd d mmm")&", "&TEXT(AD26,"hh:mm"),"weekday evenings")&", "&IF(OR(AA26=8,AA26=11,AA26=18),"an ","a ")&AA26&"-minute walk from your office, "&IF(AF26<>"","£"&IF(AF26=INT(AF26),TEXT(AF26,"0"),TEXT(AF26,"0.00")),"[PRICE PER PLAYER]")&" a player. Happy to hold it for "&F26&" if someone on the team fancies organising a game."&IF(Offer!$C$7<>""," Spots are held until "&TEXT(Offer!$C$7,"dddd d mmmm")&".","")&" "&IF(Offer!$C$6<>"",Offer!$C$6,"[JOINING LINK]")&CHAR(10)&CHAR(10)&"Best,"&CHAR(10)&IF(AM26<>"",AM26,IF(Offer!$C$5<>"",Offer!$C$5,"[NAME]"))&CHAR(10)&"FC Urban" | AL26: =IF(AH26="","No email yet",IF(ISNUMBER(SEARCH("[",AJ26)),"Fill placeholders",IF(ISNUMBER(AD26),"Ready to send","Ready · no fixed slot")))
A27: 25 | B27: 1 | C27: Law firm | D27: City of London | E27: PGMBM Ltd | F27: Pogust Goodhead | G27: https://pogustgoodhead.com | H27: mydata@pogustgoodhead.com | I27: privacy / compliance | J27: Open page | K27: 11468874 | L27: Open | M27: Group | N27: 43298 | O27: Chancery House, 53 - 64 Chancery Lane, London | P27: WC2A 1QS | Q27: No | W27: St Pancras - Coram's Fields 3G | X27: 17 | Z27: St Pancras - Coram's Fields 3G | AA27: 17 | AB27: =IFERROR(INDEX(Venues!$E$2:$E$17,MATCH(Z27,Venues!$A$2:$A$17,0)),"Not checked") | AC27: =IFERROR(INDEX(Venues!$F$2:$F$17,MATCH(Z27,Venues!$A$2:$A$17,0)),0) | AD27: =IFERROR(INDEX(Venues!$M$2:$M$17,MATCH(Z27,Venues!$A$2:$A$17,0)),"") | AE27: =IFERROR(INDEX(Venues!$N$2:$N$17,MATCH(Z27,Venues!$A$2:$A$17,0)),"5-a-side") | AF27: =IF(Offer!$C$4="","",Offer!$C$4) | AG27: =Z27&" ("&AA27&" min walk) · "&IF(ISNUMBER(AD27),TEXT(AD27,"ddd d mmm, hh:mm"),"slot to confirm with venue")&" · "&AE27&" · "&IF(AF27<>"","£"&TEXT(AF27,"0.00")&" pp","price TBC") | AH27: =IF(U27<>"",U27,IF(H27<>"",H27,"")) | AI27: ="After-work football for "&F27&" · "&Z27&", "&AA27&" min from your office" | AJ27: ="Hi "&IF(R27<>"",R27,F27&" team")&","&CHAR(10)&CHAR(10)&"I'm "&IF(AM27<>"",AM27,IF(Offer!$C$5<>"",Offer!$C$5,"[NAME]"))&" from FC Urban. We organise after-work football for teams in the City and Canary Wharf."&CHAR(10)&CHAR(10)&"We have a "&AE27&" pitch at "&Z27&", "&IF(OR(AA27=8,AA27=11,AA27=18),"an ","a ")&AA27&"-minute walk from your "&P27&" office, "&IF(ISNUMBER(AD27),"on "&TEXT(AD27,"dddd d mmmm")&" at "&TEXT(AD27,"hh:mm"),"on a weekday evening that suits your team")&". It's "&IF(AF27<>"","£"&IF(AF27=INT(AF27),TEXT(AF27,"0"),TEXT(AF27,"0.00")),"[PRICE PER PLAYER]")&" a player and we handle the pitch booking, sign-ups and payments, so all it takes is one person sharing a link with the team."&CHAR(10)&CHAR(10)&"It works well as a team social or "&IF(ISNUMBER(SEARCH(LEFT(F27,1),"AEIOU")),"an ","a ")&F27&" vs clients game. Would your team be up for it, or is there someone who'd enjoy organising it?"&IF(Offer!$C$7<>""," Spots are held until "&TEXT(Offer!$C$7,"dddd d mmmm")&".","")&" "&IF(Offer!$C$6<>"",Offer!$C$6,"[JOINING LINK]")&CHAR(10)&CHAR(10)&"Best,"&CHAR(10)&IF(AM27<>"",AM27,IF(Offer!$C$5<>"",Offer!$C$5,"[NAME]"))&CHAR(10)&"FC Urban" | AK27: ="Hi "&IF(R27<>"",R27,F27&" team")&","&CHAR(10)&CHAR(10)&"Just bumping this up. The "&AE27&" pitch at "&Z27&" is still free "&IF(ISNUMBER(AD27),TEXT(AD27,"ddd d mmm")&", "&TEXT(AD27,"hh:mm"),"weekday evenings")&", "&IF(OR(AA27=8,AA27=11,AA27=18),"an ","a ")&AA27&"-minute walk from your office, "&IF(AF27<>"","£"&IF(AF27=INT(AF27),TEXT(AF27,"0"),TEXT(AF27,"0.00")),"[PRICE PER PLAYER]")&" a player. Happy to hold it for "&F27&" if someone on the team fancies organising a game."&IF(Offer!$C$7<>""," Spots are held until "&TEXT(Offer!$C$7,"dddd d mmmm")&".","")&" "&IF(Offer!$C$6<>"",Offer!$C$6,"[JOINING LINK]")&CHAR(10)&CHAR(10)&"Best,"&CHAR(10)&IF(AM27<>"",AM27,IF(Offer!$C$5<>"",Offer!$C$5,"[NAME]"))&CHAR(10)&"FC Urban" | AL27: =IF(AH27="","No email yet",IF(ISNUMBER(SEARCH("[",AJ27)),"Fill placeholders",IF(ISNUMBER(AD27),"Ready to send","Ready · no fixed slot")))
A28: 26 | B28: 1 | C28: Law firm | D28: City of London | E28: Squire Patton Boggs (UK) LLP | F28: Squire Patton Boggs | G28: https://www.squirepattonboggs.com | H28: enquiries@squirepb.com | I28: general | J28: Open page | K28: OC335584 | L28: Open | M28: Group | N28: 39521 | O28: 60 London Wall, London | P28: EC2M 5TQ | Q28: No | W28: Liverpool St - Attlee Centre | X28: 16 | Y28: Shoreditch Powerleague (17.1); City of London School (EC4V 3AL) (17.6) | Z28: Shoreditch Powerleague | AA28: 17 | AB28: =IFERROR(INDEX(Venues!$E$2:$E$17,MATCH(Z28,Venues!$A$2:$A$17,0)),"Not checked") | AC28: =IFERROR(INDEX(Venues!$F$2:$F$17,MATCH(Z28,Venues!$A$2:$A$17,0)),0) | AD28: =IFERROR(INDEX(Venues!$M$2:$M$17,MATCH(Z28,Venues!$A$2:$A$17,0)),"") | AE28: =IFERROR(INDEX(Venues!$N$2:$N$17,MATCH(Z28,Venues!$A$2:$A$17,0)),"5-a-side") | AF28: =IF(Offer!$C$4="","",Offer!$C$4) | AG28: =Z28&" ("&AA28&" min walk) · "&IF(ISNUMBER(AD28),TEXT(AD28,"ddd d mmm, hh:mm"),"slot to confirm with venue")&" · "&AE28&" · "&IF(AF28<>"","£"&TEXT(AF28,"0.00")&" pp","price TBC") | AH28: =IF(U28<>"",U28,IF(H28<>"",H28,"")) | AI28: ="After-work football for "&F28&" · "&Z28&", "&AA28&" min from your office" | AJ28: ="Hi "&IF(R28<>"",R28,F28&" team")&","&CHAR(10)&CHAR(10)&"I'm "&IF(AM28<>"",AM28,IF(Offer!$C$5<>"",Offer!$C$5,"[NAME]"))&" from FC Urban. We organise after-work football for teams in the City and Canary Wharf."&CHAR(10)&CHAR(10)&"We have a "&AE28&" pitch at "&Z28&", "&IF(OR(AA28=8,AA28=11,AA28=18),"an ","a ")&AA28&"-minute walk from your "&P28&" office, "&IF(ISNUMBER(AD28),"on "&TEXT(AD28,"dddd d mmmm")&" at "&TEXT(AD28,"hh:mm"),"on a weekday evening that suits your team")&". It's "&IF(AF28<>"","£"&IF(AF28=INT(AF28),TEXT(AF28,"0"),TEXT(AF28,"0.00")),"[PRICE PER PLAYER]")&" a player and we handle the pitch booking, sign-ups and payments, so all it takes is one person sharing a link with the team."&CHAR(10)&CHAR(10)&"It works well as a team social or "&IF(ISNUMBER(SEARCH(LEFT(F28,1),"AEIOU")),"an ","a ")&F28&" vs clients game. Would your team be up for it, or is there someone who'd enjoy organising it?"&IF(Offer!$C$7<>""," Spots are held until "&TEXT(Offer!$C$7,"dddd d mmmm")&".","")&" "&IF(Offer!$C$6<>"",Offer!$C$6,"[JOINING LINK]")&CHAR(10)&CHAR(10)&"Best,"&CHAR(10)&IF(AM28<>"",AM28,IF(Offer!$C$5<>"",Offer!$C$5,"[NAME]"))&CHAR(10)&"FC Urban" | AK28: ="Hi "&IF(R28<>"",R28,F28&" team")&","&CHAR(10)&CHAR(10)&"Just bumping this up. The "&AE28&" pitch at "&Z28&" is still free "&IF(ISNUMBER(AD28),TEXT(AD28,"ddd d mmm")&", "&TEXT(AD28,"hh:mm"),"weekday evenings")&", "&IF(OR(AA28=8,AA28=11,AA28=18),"an ","a ")&AA28&"-minute walk from your office, "&IF(AF28<>"","£"&IF(AF28=INT(AF28),TEXT(AF28,"0"),TEXT(AF28,"0.00")),"[PRICE PER PLAYER]")&" a player. Happy to hold it for "&F28&" if someone on the team fancies organising a game."&IF(Offer!$C$7<>""," Spots are held until "&TEXT(Offer!$C$7,"dddd d mmmm")&".","")&" "&IF(Offer!$C$6<>"",Offer!$C$6,"[JOINING LINK]")&CHAR(10)&CHAR(10)&"Best,"&CHAR(10)&IF(AM28<>"",AM28,IF(Offer!$C$5<>"",Offer!$C$5,"[NAME]"))&CHAR(10)&"FC Urban" | AL28: =IF(AH28="","No email yet",IF(ISNUMBER(SEARCH("[",AJ28)),"Fill placeholders",IF(ISNUMBER(AD28),"Ready to send","Ready · no fixed slot")))
A29: 27 | B29: 1 | C29: Law firm | D29: City of London | E29: Simmons & Simmons LLP | F29: Simmons & Simmons | G29: https://www.simmons-simmons.com | H29: london@simmons-simmons.com | I29: general | J29: Open page | K29: OC352713 | L29: Open | M29: Group | N29: 40238 | O29: Citypoint, One Ropemaker Street, London | P29: EC2Y 9SS | Q29: No | W29: Finsbury Leisure Centre (EC1V 3PU) | X29: 14 | Y29: Shoreditch Powerleague (17.2); City of London School (EC4V 3AL) (18.6) | Z29: Shoreditch Powerleague | AA29: 17 | AB29: =IFERROR(INDEX(Venues!$E$2:$E$17,MATCH(Z29,Venues!$A$2:$A$17,0)),"Not checked") | AC29: =IFERROR(INDEX(Venues!$F$2:$F$17,MATCH(Z29,Venues!$A$2:$A$17,0)),0) | AD29: =IFERROR(INDEX(Venues!$M$2:$M$17,MATCH(Z29,Venues!$A$2:$A$17,0)),"") | AE29: =IFERROR(INDEX(Venues!$N$2:$N$17,MATCH(Z29,Venues!$A$2:$A$17,0)),"5-a-side") | AF29: =IF(Offer!$C$4="","",Offer!$C$4) | AG29: =Z29&" ("&AA29&" min walk) · "&IF(ISNUMBER(AD29),TEXT(AD29,"ddd d mmm, hh:mm"),"slot to confirm with venue")&" · "&AE29&" · "&IF(AF29<>"","£"&TEXT(AF29,"0.00")&" pp","price TBC") | AH29: =IF(U29<>"",U29,IF(H29<>"",H29,"")) | AI29: ="After-work football for "&F29&" · "&Z29&", "&AA29&" min from your office" | AJ29: ="Hi "&IF(R29<>"",R29,F29&" team")&","&CHAR(10)&CHAR(10)&"I'm "&IF(AM29<>"",AM29,IF(Offer!$C$5<>"",Offer!$C$5,"[NAME]"))&" from FC Urban. We organise after-work football for teams in the City and Canary Wharf."&CHAR(10)&CHAR(10)&"We have a "&AE29&" pitch at "&Z29&", "&IF(OR(AA29=8,AA29=11,AA29=18),"an ","a ")&AA29&"-minute walk from your "&P29&" office, "&IF(ISNUMBER(AD29),"on "&TEXT(AD29,"dddd d mmmm")&" at "&TEXT(AD29,"hh:mm"),"on a weekday evening that suits your team")&". It's "&IF(AF29<>"","£"&IF(AF29=INT(AF29),TEXT(AF29,"0"),TEXT(AF29,"0.00")),"[PRICE PER PLAYER]")&" a player and we handle the pitch booking, sign-ups and payments, so all it takes is one person sharing a link with the team."&CHAR(10)&CHAR(10)&"It works well as a team social or "&IF(ISNUMBER(SEARCH(LEFT(F29,1),"AEIOU")),"an ","a ")&F29&" vs clients game. Would your team be up for it, or is there someone who'd enjoy organising it?"&IF(Offer!$C$7<>""," Spots are held until "&TEXT(Offer!$C$7,"dddd d mmmm")&".","")&" "&IF(Offer!$C$6<>"",Offer!$C$6,"[JOINING LINK]")&CHAR(10)&CHAR(10)&"Best,"&CHAR(10)&IF(AM29<>"",AM29,IF(Offer!$C$5<>"",Offer!$C$5,"[NAME]"))&CHAR(10)&"FC Urban" | AK29: ="Hi "&IF(R29<>"",R29,F29&" team")&","&CHAR(10)&CHAR(10)&"Just bumping this up. The "&AE29&" pitch at "&Z29&" is still free "&IF(ISNUMBER(AD29),TEXT(AD29,"ddd d mmm")&", "&TEXT(AD29,"hh:mm"),"weekday evenings")&", "&IF(OR(AA29=8,AA29=11,AA29=18),"an ","a ")&AA29&"-minute walk from your office, "&IF(AF29<>"","£"&IF(AF29=INT(AF29),TEXT(AF29,"0"),TEXT(AF29,"0.00")),"[PRICE PER PLAYER]")&" a player. Happy to hold it for "&F29&" if someone on the team fancies organising a game."&IF(Offer!$C$7<>""," Spots are held until "&TEXT(Offer!$C$7,"dddd d mmmm")&".","")&" "&IF(Offer!$C$6<>"",Offer!$C$6,"[JOINING LINK]")&CHAR(10)&CHAR(10)&"Best,"&CHAR(10)&IF(AM29<>"",AM29,IF(Offer!$C$5<>"",Offer!$C$5,"[NAME]"))&CHAR(10)&"FC Urban" | AL29: =IF(AH29="","No email yet",IF(ISNUMBER(SEARCH("[",AJ29)),"Fill placeholders",IF(ISNUMBER(AD29),"Ready to send","Ready · no fixed slot")))
A30: 28 | B30: 1 | C30: Law firm | D30: City of London | E30: Beale & Company Solicitors LLP | F30: Beale & Company Solicitors | G30: https://beale.co.uk | H30: graham@beale.co.uk | I30: named person | J30: Open page | K30: OC310010 | L30: Open | M30: Group | N30: 38306 | O30: 7 Bishopsgate, London | P30: EC2N 3AR | Q30: No | W30: Liverpool St - Attlee Centre | X30: 13 | Y30: Shoreditch Powerleague (17.7) | Z30: Shoreditch Powerleague | AA30: 18 | AB30: =IFERROR(INDEX(Venues!$E$2:$E$17,MATCH(Z30,Venues!$A$2:$A$17,0)),"Not checked") | AC30: =IFERROR(INDEX(Venues!$F$2:$F$17,MATCH(Z30,Venues!$A$2:$A$17,0)),0) | AD30: =IFERROR(INDEX(Venues!$M$2:$M$17,MATCH(Z30,Venues!$A$2:$A$17,0)),"") | AE30: =IFERROR(INDEX(Venues!$N$2:$N$17,MATCH(Z30,Venues!$A$2:$A$17,0)),"5-a-side") | AF30: =IF(Offer!$C$4="","",Offer!$C$4) | AG30: =Z30&" ("&AA30&" min walk) · "&IF(ISNUMBER(AD30),TEXT(AD30,"ddd d mmm, hh:mm"),"slot to confirm with venue")&" · "&AE30&" · "&IF(AF30<>"","£"&TEXT(AF30,"0.00")&" pp","price TBC") | AH30: =IF(U30<>"",U30,IF(H30<>"",H30,"")) | AI30: ="After-work football for "&F30&" · "&Z30&", "&AA30&" min from your office" | AJ30: ="Hi "&IF(R30<>"",R30,F30&" team")&","&CHAR(10)&CHAR(10)&"I'm "&IF(AM30<>"",AM30,IF(Offer!$C$5<>"",Offer!$C$5,"[NAME]"))&" from FC Urban. We organise after-work football for teams in the City and Canary Wharf."&CHAR(10)&CHAR(10)&"We have a "&AE30&" pitch at "&Z30&", "&IF(OR(AA30=8,AA30=11,AA30=18),"an ","a ")&AA30&"-minute walk from your "&P30&" office, "&IF(ISNUMBER(AD30),"on "&TEXT(AD30,"dddd d mmmm")&" at "&TEXT(AD30,"hh:mm"),"on a weekday evening that suits your team")&". It's "&IF(AF30<>"","£"&IF(AF30=INT(AF30),TEXT(AF30,"0"),TEXT(AF30,"0.00")),"[PRICE PER PLAYER]")&" a player and we handle the pitch booking, sign-ups and payments, so all it takes is one person sharing a link with the team."&CHAR(10)&CHAR(10)&"It works well as a team social or "&IF(ISNUMBER(SEARCH(LEFT(F30,1),"AEIOU")),"an ","a ")&F30&" vs clients game. Would your team be up for it, or is there someone who'd enjoy organising it?"&IF(Offer!$C$7<>""," Spots are held until "&TEXT(Offer!$C$7,"dddd d mmmm")&".","")&" "&IF(Offer!$C$6<>"",Offer!$C$6,"[JOINING LINK]")&CHAR(10)&CHAR(10)&"Best,"&CHAR(10)&IF(AM30<>"",AM30,IF(Offer!$C$5<>"",Offer!$C$5,"[NAME]"))&CHAR(10)&"FC Urban" | AK30: ="Hi "&IF(R30<>"",R30,F30&" team")&","&CHAR(10)&CHAR(10)&"Just bumping this up. The "&AE30&" pitch at "&Z30&" is still free "&IF(ISNUMBER(AD30),TEXT(AD30,"ddd d mmm")&", "&TEXT(AD30,"hh:mm"),"weekday evenings")&", "&IF(OR(AA30=8,AA30=11,AA30=18),"an ","a ")&AA30&"-minute walk from your office, "&IF(AF30<>"","£"&IF(AF30=INT(AF30),TEXT(AF30,"0"),TEXT(AF30,"0.00")),"[PRICE PER PLAYER]")&" a player. Happy to hold it for "&F30&" if someone on the team fancies organising a game."&IF(Offer!$C$7<>""," Spots are held until "&TEXT(Offer!$C$7,"dddd d mmmm")&".","")&" "&IF(Offer!$C$6<>"",Offer!$C$6,"[JOINING LINK]")&CHAR(10)&CHAR(10)&"Best,"&CHAR(10)&IF(AM30<>"",AM30,IF(Offer!$C$5<>"",Offer!$C$5,"[NAME]"))&CHAR(10)&"FC Urban" | AL30: =IF(AH30="","No email yet",IF(ISNUMBER(SEARCH("[",AJ30)),"Fill placeholders",IF(ISNUMBER(AD30),"Ready to send","Ready · no fixed slot")))
A31: 29 | B31: 1 | C31: Law firm | D31: City of London | E31: Kennedys Law LLP | F31: Kennedys | G31: https://www.kennedyslaw.com | H31: contactus@kennedyslaw.com | I31: named person | J31: Open page | K31: OC353214 | L31: Open | M31: Group | N31: 40252 | O31: Kennedys, 20 Fenchurch Street, London | P31: EC3M 3BY | Q31: No | W31: Liverpool St - Attlee Centre | X31: 17 | Y31: City of London School (EC4V 3AL) (17.8); Marlborough Sports Garden (SE1 1SD) (18.1) | Z31: City of London School (EC4V 3AL) | AA31: 18 | AB31: =IFERROR(INDEX(Venues!$E$2:$E$17,MATCH(Z31,Venues!$A$2:$A$17,0)),"Not checked") | AC31: =IFERROR(INDEX(Venues!$F$2:$F$17,MATCH(Z31,Venues!$A$2:$A$17,0)),0) | AD31: =IFERROR(INDEX(Venues!$M$2:$M$17,MATCH(Z31,Venues!$A$2:$A$17,0)),"") | AE31: =IFERROR(INDEX(Venues!$N$2:$N$17,MATCH(Z31,Venues!$A$2:$A$17,0)),"5-a-side") | AF31: =IF(Offer!$C$4="","",Offer!$C$4) | AG31: =Z31&" ("&AA31&" min walk) · "&IF(ISNUMBER(AD31),TEXT(AD31,"ddd d mmm, hh:mm"),"slot to confirm with venue")&" · "&AE31&" · "&IF(AF31<>"","£"&TEXT(AF31,"0.00")&" pp","price TBC") | AH31: =IF(U31<>"",U31,IF(H31<>"",H31,"")) | AI31: ="After-work football for "&F31&" · "&Z31&", "&AA31&" min from your office" | AJ31: ="Hi "&IF(R31<>"",R31,F31&" team")&","&CHAR(10)&CHAR(10)&"I'm "&IF(AM31<>"",AM31,IF(Offer!$C$5<>"",Offer!$C$5,"[NAME]"))&" from FC Urban. We organise after-work football for teams in the City and Canary Wharf."&CHAR(10)&CHAR(10)&"We have a "&AE31&" pitch at "&Z31&", "&IF(OR(AA31=8,AA31=11,AA31=18),"an ","a ")&AA31&"-minute walk from your "&P31&" office, "&IF(ISNUMBER(AD31),"on "&TEXT(AD31,"dddd d mmmm")&" at "&TEXT(AD31,"hh:mm"),"on a weekday evening that suits your team")&". It's "&IF(AF31<>"","£"&IF(AF31=INT(AF31),TEXT(AF31,"0"),TEXT(AF31,"0.00")),"[PRICE PER PLAYER]")&" a player and we handle the pitch booking, sign-ups and payments, so all it takes is one person sharing a link with the team."&CHAR(10)&CHAR(10)&"It works well as a team social or "&IF(ISNUMBER(SEARCH(LEFT(F31,1),"AEIOU")),"an ","a ")&F31&" vs clients game. Would your team be up for it, or is there someone who'd enjoy organising it?"&IF(Offer!$C$7<>""," Spots are held until "&TEXT(Offer!$C$7,"dddd d mmmm")&".","")&" "&IF(Offer!$C$6<>"",Offer!$C$6,"[JOINING LINK]")&CHAR(10)&CHAR(10)&"Best,"&CHAR(10)&IF(AM31<>"",AM31,IF(Offer!$C$5<>"",Offer!$C$5,"[NAME]"))&CHAR(10)&"FC Urban" | AK31: ="Hi "&IF(R31<>"",R31,F31&" team")&","&CHAR(10)&CHAR(10)&"Just bumping this up. The "&AE31&" pitch at "&Z31&" is still free "&IF(ISNUMBER(AD31),TEXT(AD31,"ddd d mmm")&", "&TEXT(AD31,"hh:mm"),"weekday evenings")&", "&IF(OR(AA31=8,AA31=11,AA31=18),"an ","a ")&AA31&"-minute walk from your office, "&IF(AF31<>"","£"&IF(AF31=INT(AF31),TEXT(AF31,"0"),TEXT(AF31,"0.00")),"[PRICE PER PLAYER]")&" a player. Happy to hold it for "&F31&" if someone on the team fancies organising a game."&IF(Offer!$C$7<>""," Spots are held until "&TEXT(Offer!$C$7,"dddd d mmmm")&".","")&" "&IF(Offer!$C$6<>"",Offer!$C$6,"[JOINING LINK]")&CHAR(10)&CHAR(10)&"Best,"&CHAR(10)&IF(AM31<>"",AM31,IF(Offer!$C$5<>"",Offer!$C$5,"[NAME]"))&CHAR(10)&"FC Urban" | AL31: =IF(AH31="","No email yet",IF(ISNUMBER(SEARCH("[",AJ31)),"Fill placeholders",IF(ISNUMBER(AD31),"Ready to send","Ready · no fixed slot")))
A32: 30 | B32: 1 | C32: Law firm | D32: City of London | E32: Holman Fenwick Willan LLP | F32: Holman Fenwick Willan | G32: https://www.hfw.com | H32: hello@hfw.com | I32: general | J32: Open page | K32: OC343361 | L32: Open | M32: Group | N32: 39860 | O32: 8 Bishopsgate, London | P32: EC2N 4BQ | Q32: No | W32: Liverpool St - Attlee Centre | X32: 14 | Y32: City of London School (EC4V 3AL) (18.7); Shoreditch Powerleague (18.7) | Z32: City of London School (EC4V 3AL) | AA32: 19 | AB32: =IFERROR(INDEX(Venues!$E$2:$E$17,MATCH(Z32,Venues!$A$2:$A$17,0)),"Not checked") | AC32: =IFERROR(INDEX(Venues!$F$2:$F$17,MATCH(Z32,Venues!$A$2:$A$17,0)),0) | AD32: =IFERROR(INDEX(Venues!$M$2:$M$17,MATCH(Z32,Venues!$A$2:$A$17,0)),"") | AE32: =IFERROR(INDEX(Venues!$N$2:$N$17,MATCH(Z32,Venues!$A$2:$A$17,0)),"5-a-side") | AF32: =IF(Offer!$C$4="","",Offer!$C$4) | AG32: =Z32&" ("&AA32&" min walk) · "&IF(ISNUMBER(AD32),TEXT(AD32,"ddd d mmm, hh:mm"),"slot to confirm with venue")&" · "&AE32&" · "&IF(AF32<>"","£"&TEXT(AF32,"0.00")&" pp","price TBC") | AH32: =IF(U32<>"",U32,IF(H32<>"",H32,"")) | AI32: ="After-work football for "&F32&" · "&Z32&", "&AA32&" min from your office" | AJ32: ="Hi "&IF(R32<>"",R32,F32&" team")&","&CHAR(10)&CHAR(10)&"I'm "&IF(AM32<>"",AM32,IF(Offer!$C$5<>"",Offer!$C$5,"[NAME]"))&" from FC Urban. We organise after-work football for teams in the City and Canary Wharf."&CHAR(10)&CHAR(10)&"We have a "&AE32&" pitch at "&Z32&", "&IF(OR(AA32=8,AA32=11,AA32=18),"an ","a ")&AA32&"-minute walk from your "&P32&" office, "&IF(ISNUMBER(AD32),"on "&TEXT(AD32,"dddd d mmmm")&" at "&TEXT(AD32,"hh:mm"),"on a weekday evening that suits your team")&". It's "&IF(AF32<>"","£"&IF(AF32=INT(AF32),TEXT(AF32,"0"),TEXT(AF32,"0.00")),"[PRICE PER PLAYER]")&" a player and we handle the pitch booking, sign-ups and payments, so all it takes is one person sharing a link with the team."&CHAR(10)&CHAR(10)&"It works well as a team social or "&IF(ISNUMBER(SEARCH(LEFT(F32,1),"AEIOU")),"an ","a ")&F32&" vs clients game. Would your team be up for it, or is there someone who'd enjoy organising it?"&IF(Offer!$C$7<>""," Spots are held until "&TEXT(Offer!$C$7,"dddd d mmmm")&".","")&" "&IF(Offer!$C$6<>"",Offer!$C$6,"[JOINING LINK]")&CHAR(10)&CHAR(10)&"Best,"&CHAR(10)&IF(AM32<>"",AM32,IF(Offer!$C$5<>"",Offer!$C$5,"[NAME]"))&CHAR(10)&"FC Urban" | AK32: ="Hi "&IF(R32<>"",R32,F32&" team")&","&CHAR(10)&CHAR(10)&"Just bumping this up. The "&AE32&" pitch at "&Z32&" is still free "&IF(ISNUMBER(AD32),TEXT(AD32,"ddd d mmm")&", "&TEXT(AD32,"hh:mm"),"weekday evenings")&", "&IF(OR(AA32=8,AA32=11,AA32=18),"an ","a ")&AA32&"-minute walk from your office, "&IF(AF32<>"","£"&IF(AF32=INT(AF32),TEXT(AF32,"0"),TEXT(AF32,"0.00")),"[PRICE PER PLAYER]")&" a player. Happy to hold it for "&F32&" if someone on the team fancies organising a game."&IF(Offer!$C$7<>""," Spots are held until "&TEXT(Offer!$C$7,"dddd d mmmm")&".","")&" "&IF(Offer!$C$6<>"",Offer!$C$6,"[JOINING LINK]")&CHAR(10)&CHAR(10)&"Best,"&CHAR(10)&IF(AM32<>"",AM32,IF(Offer!$C$5<>"",Offer!$C$5,"[NAME]"))&CHAR(10)&"FC Urban" | AL32: =IF(AH32="","No email yet",IF(ISNUMBER(SEARCH("[",AJ32)),"Fill placeholders",IF(ISNUMBER(AD32),"Ready to send","Ready · no fixed slot")))
A33: 31 | B33: 1 | C33: Law firm | D33: City of London | E33: Duncan Lewis Solicitors Ltd | F33: Duncan Lewis Solicitors | G33: https://www.duncanlewis.co.uk | H33: contact@duncanlewis.com | I33: general | J33: Open page | K33: 03718422 | L33: Open | M33: Group | N33: 36214 | O33: Sackville House 143-149, Fenchurch Street, London | P33: EC3M 6BL | Q33: No | W33: Liverpool St - Attlee Centre | X33: 16 | Y33: City of London School (EC4V 3AL) (19) | Z33: City of London School (EC4V 3AL) | AA33: 19 | AB33: =IFERROR(INDEX(Venues!$E$2:$E$17,MATCH(Z33,Venues!$A$2:$A$17,0)),"Not checked") | AC33: =IFERROR(INDEX(Venues!$F$2:$F$17,MATCH(Z33,Venues!$A$2:$A$17,0)),0) | AD33: =IFERROR(INDEX(Venues!$M$2:$M$17,MATCH(Z33,Venues!$A$2:$A$17,0)),"") | AE33: =IFERROR(INDEX(Venues!$N$2:$N$17,MATCH(Z33,Venues!$A$2:$A$17,0)),"5-a-side") | AF33: =IF(Offer!$C$4="","",Offer!$C$4) | AG33: =Z33&" ("&AA33&" min walk) · "&IF(ISNUMBER(AD33),TEXT(AD33,"ddd d mmm, hh:mm"),"slot to confirm with venue")&" · "&AE33&" · "&IF(AF33<>"","£"&TEXT(AF33,"0.00")&" pp","price TBC") | AH33: =IF(U33<>"",U33,IF(H33<>"",H33,"")) | AI33: ="After-work football for "&F33&" · "&Z33&", "&AA33&" min from your office" | AJ33: ="Hi "&IF(R33<>"",R33,F33&" team")&","&CHAR(10)&CHAR(10)&"I'm "&IF(AM33<>"",AM33,IF(Offer!$C$5<>"",Offer!$C$5,"[NAME]"))&" from FC Urban. We organise after-work football for teams in the City and Canary Wharf."&CHAR(10)&CHAR(10)&"We have a "&AE33&" pitch at "&Z33&", "&IF(OR(AA33=8,AA33=11,AA33=18),"an ","a ")&AA33&"-minute walk from your "&P33&" office, "&IF(ISNUMBER(AD33),"on "&TEXT(AD33,"dddd d mmmm")&" at "&TEXT(AD33,"hh:mm"),"on a weekday evening that suits your team")&". It's "&IF(AF33<>"","£"&IF(AF33=INT(AF33),TEXT(AF33,"0"),TEXT(AF33,"0.00")),"[PRICE PER PLAYER]")&" a player and we handle the pitch booking, sign-ups and payments, so all it takes is one person sharing a link with the team."&CHAR(10)&CHAR(10)&"It works well as a team social or "&IF(ISNUMBER(SEARCH(LEFT(F33,1),"AEIOU")),"an ","a ")&F33&" vs clients game. Would your team be up for it, or is there someone who'd enjoy organising it?"&IF(Offer!$C$7<>""," Spots are held until "&TEXT(Offer!$C$7,"dddd d mmmm")&".","")&" "&IF(Offer!$C$6<>"",Offer!$C$6,"[JOINING LINK]")&CHAR(10)&CHAR(10)&"Best,"&CHAR(10)&IF(AM33<>"",AM33,IF(Offer!$C$5<>"",Offer!$C$5,"[NAME]"))&CHAR(10)&"FC Urban" | AK33: ="Hi "&IF(R33<>"",R33,F33&" team")&","&CHAR(10)&CHAR(10)&"Just bumping this up. The "&AE33&" pitch at "&Z33&" is still free "&IF(ISNUMBER(AD33),TEXT(AD33,"ddd d mmm")&", "&TEXT(AD33,"hh:mm"),"weekday evenings")&", "&IF(OR(AA33=8,AA33=11,AA33=18),"an ","a ")&AA33&"-minute walk from your office, "&IF(AF33<>"","£"&IF(AF33=INT(AF33),TEXT(AF33,"0"),TEXT(AF33,"0.00")),"[PRICE PER PLAYER]")&" a player. Happy to hold it for "&F33&" if someone on the team fancies organising a game."&IF(Offer!$C$7<>""," Spots are held until "&TEXT(Offer!$C$7,"dddd d mmmm")&".","")&" "&IF(Offer!$C$6<>"",Offer!$C$6,"[JOINING LINK]")&CHAR(10)&CHAR(10)&"Best,"&CHAR(10)&IF(AM33<>"",AM33,IF(Offer!$C$5<>"",Offer!$C$5,"[NAME]"))&CHAR(10)&"FC Urban" | AL33: =IF(AH33="","No email yet",IF(ISNUMBER(SEARCH("[",AJ33)),"Fill placeholders",IF(ISNUMBER(AD33),"Ready to send","Ready · no fixed slot")))
A34: 32 | B34: 1 | C34: Bank | D34: City of London | E34: Cynergy Bank PLC | F34: Cynergy Bank | G34: https://www.cynergybank.co.uk | H34: businessbanking@cynergybank.co.uk | I34: role (other) | J34: Open page | K34: 04728421 | L34: Open | M34: Group | N34: 37720 | O34: 4Th Floor, One New Change, London | P34: EC4M 9AF | Q34: No | W34: City of London School (EC4V 3AL) | X34: 6 | Y34: Marlborough Sports Garden (SE1 1SD) (18.5) | Z34: City of London School (EC4V 3AL) | AA34: 6 | AB34: =IFERROR(INDEX(Venues!$E$2:$E$17,MATCH(Z34,Venues!$A$2:$A$17,0)),"Not checked") | AC34: =IFERROR(INDEX(Venues!$F$2:$F$17,MATCH(Z34,Venues!$A$2:$A$17,0)),0) | AD34: =IFERROR(INDEX(Venues!$M$2:$M$17,MATCH(Z34,Venues!$A$2:$A$17,0)),"") | AE34: =IFERROR(INDEX(Venues!$N$2:$N$17,MATCH(Z34,Venues!$A$2:$A$17,0)),"5-a-side") | AF34: =IF(Offer!$C$4="","",Offer!$C$4) | AG34: =Z34&" ("&AA34&" min walk) · "&IF(ISNUMBER(AD34),TEXT(AD34,"ddd d mmm, hh:mm"),"slot to confirm with venue")&" · "&AE34&" · "&IF(AF34<>"","£"&TEXT(AF34,"0.00")&" pp","price TBC") | AH34: =IF(U34<>"",U34,IF(H34<>"",H34,"")) | AI34: ="After-work football for "&F34&" · "&Z34&", "&AA34&" min from your office" | AJ34: ="Hi "&IF(R34<>"",R34,F34&" team")&","&CHAR(10)&CHAR(10)&"I'm "&IF(AM34<>"",AM34,IF(Offer!$C$5<>"",Offer!$C$5,"[NAME]"))&" from FC Urban. We organise after-work football for teams in the City and Canary Wharf."&CHAR(10)&CHAR(10)&"We have a "&AE34&" pitch at "&Z34&", "&IF(OR(AA34=8,AA34=11,AA34=18),"an ","a ")&AA34&"-minute walk from your "&P34&" office, "&IF(ISNUMBER(AD34),"on "&TEXT(AD34,"dddd d mmmm")&" at "&TEXT(AD34,"hh:mm"),"on a weekday evening that suits your team")&". It's "&IF(AF34<>"","£"&IF(AF34=INT(AF34),TEXT(AF34,"0"),TEXT(AF34,"0.00")),"[PRICE PER PLAYER]")&" a player and we handle the pitch booking, sign-ups and payments, so all it takes is one person sharing a link with the team."&CHAR(10)&CHAR(10)&"It works well as a team social or "&IF(ISNUMBER(SEARCH(LEFT(F34,1),"AEIOU")),"an ","a ")&F34&" vs clients game. Would your team be up for it, or is there someone who'd enjoy organising it?"&IF(Offer!$C$7<>""," Spots are held until "&TEXT(Offer!$C$7,"dddd d mmmm")&".","")&" "&IF(Offer!$C$6<>"",Offer!$C$6,"[JOINING LINK]")&CHAR(10)&CHAR(10)&"Best,"&CHAR(10)&IF(AM34<>"",AM34,IF(Offer!$C$5<>"",Offer!$C$5,"[NAME]"))&CHAR(10)&"FC Urban" | AK34: ="Hi "&IF(R34<>"",R34,F34&" team")&","&CHAR(10)&CHAR(10)&"Just bumping this up. The "&AE34&" pitch at "&Z34&" is still free "&IF(ISNUMBER(AD34),TEXT(AD34,"ddd d mmm")&", "&TEXT(AD34,"hh:mm"),"weekday evenings")&", "&IF(OR(AA34=8,AA34=11,AA34=18),"an ","a ")&AA34&"-minute walk from your office, "&IF(AF34<>"","£"&IF(AF34=INT(AF34),TEXT(AF34,"0"),TEXT(AF34,"0.00")),"[PRICE PER PLAYER]")&" a player. Happy to hold it for "&F34&" if someone on the team fancies organising a game."&IF(Offer!$C$7<>""," Spots are held until "&TEXT(Offer!$C$7,"dddd d mmmm")&".","")&" "&IF(Offer!$C$6<>"",Offer!$C$6,"[JOINING LINK]")&CHAR(10)&CHAR(10)&"Best,"&CHAR(10)&IF(AM34<>"",AM34,IF(Offer!$C$5<>"",Offer!$C$5,"[NAME]"))&CHAR(10)&"FC Urban" | AL34: =IF(AH34="","No email yet",IF(ISNUMBER(SEARCH("[",AJ34)),"Fill placeholders",IF(ISNUMBER(AD34),"Ready to send","Ready · no fixed slot")))
A35: 33 | B35: 1 | C35: Bank | D35: City of London | E35: Itaú BBA International PLC | F35: Itaú BBA | G35: https://www.itaubba.eu | H35: enquiries@itaubba.eu | I35: general | J35: Open page | K35: 07425398 | L35: Open | M35: Group | N35: 40483 | O35: The Broadgate Tower, Level 10A, 20 Primrose Street, London | P35: EC2A 2EW | Q35: Yes | W35: Shoreditch Powerleague | X35: 6 | Y35: Liverpool St - Attlee Centre (9.9) | Z35: Shoreditch Powerleague | AA35: 6 | AB35: =IFERROR(INDEX(Venues!$E$2:$E$17,MATCH(Z35,Venues!$A$2:$A$17,0)),"Not checked") | AC35: =IFERROR(INDEX(Venues!$F$2:$F$17,MATCH(Z35,Venues!$A$2:$A$17,0)),0) | AD35: =IFERROR(INDEX(Venues!$M$2:$M$17,MATCH(Z35,Venues!$A$2:$A$17,0)),"") | AE35: =IFERROR(INDEX(Venues!$N$2:$N$17,MATCH(Z35,Venues!$A$2:$A$17,0)),"5-a-side") | AF35: =IF(Offer!$C$4="","",Offer!$C$4) | AG35: =Z35&" ("&AA35&" min walk) · "&IF(ISNUMBER(AD35),TEXT(AD35,"ddd d mmm, hh:mm"),"slot to confirm with venue")&" · "&AE35&" · "&IF(AF35<>"","£"&TEXT(AF35,"0.00")&" pp","price TBC") | AH35: =IF(U35<>"",U35,IF(H35<>"",H35,"")) | AI35: ="After-work football for "&F35&" · "&Z35&", "&AA35&" min from your office" | AJ35: ="Hi "&IF(R35<>"",R35,F35&" team")&","&CHAR(10)&CHAR(10)&"I'm "&IF(AM35<>"",AM35,IF(Offer!$C$5<>"",Offer!$C$5,"[NAME]"))&" from FC Urban. We organise after-work football for teams in the City and Canary Wharf."&CHAR(10)&CHAR(10)&"We have a "&AE35&" pitch at "&Z35&", "&IF(OR(AA35=8,AA35=11,AA35=18),"an ","a ")&AA35&"-minute walk from your "&P35&" office, "&IF(ISNUMBER(AD35),"on "&TEXT(AD35,"dddd d mmmm")&" at "&TEXT(AD35,"hh:mm"),"on a weekday evening that suits your team")&". It's "&IF(AF35<>"","£"&IF(AF35=INT(AF35),TEXT(AF35,"0"),TEXT(AF35,"0.00")),"[PRICE PER PLAYER]")&" a player and we handle the pitch booking, sign-ups and payments, so all it takes is one person sharing a link with the team."&CHAR(10)&CHAR(10)&"It works well as a team social or "&IF(ISNUMBER(SEARCH(LEFT(F35,1),"AEIOU")),"an ","a ")&F35&" vs clients game. Would your team be up for it, or is there someone who'd enjoy organising it?"&IF(Offer!$C$7<>""," Spots are held until "&TEXT(Offer!$C$7,"dddd d mmmm")&".","")&" "&IF(Offer!$C$6<>"",Offer!$C$6,"[JOINING LINK]")&CHAR(10)&CHAR(10)&"Best,"&CHAR(10)&IF(AM35<>"",AM35,IF(Offer!$C$5<>"",Offer!$C$5,"[NAME]"))&CHAR(10)&"FC Urban" | AK35: ="Hi "&IF(R35<>"",R35,F35&" team")&","&CHAR(10)&CHAR(10)&"Just bumping this up. The "&AE35&" pitch at "&Z35&" is still free "&IF(ISNUMBER(AD35),TEXT(AD35,"ddd d mmm")&", "&TEXT(AD35,"hh:mm"),"weekday evenings")&", "&IF(OR(AA35=8,AA35=11,AA35=18),"an ","a ")&AA35&"-minute walk from your office, "&IF(AF35<>"","£"&IF(AF35=INT(AF35),TEXT(AF35,"0"),TEXT(AF35,"0.00")),"[PRICE PER PLAYER]")&" a player. Happy to hold it for "&F35&" if someone on the team fancies organising a game."&IF(Offer!$C$7<>""," Spots are held until "&TEXT(Offer!$C$7,"dddd d mmmm")&".","")&" "&IF(Offer!$C$6<>"",Offer!$C$6,"[JOINING LINK]")&CHAR(10)&CHAR(10)&"Best,"&CHAR(10)&IF(AM35<>"",AM35,IF(Offer!$C$5<>"",Offer!$C$5,"[NAME]"))&CHAR(10)&"FC Urban" | AL35: =IF(AH35="","No email yet",IF(ISNUMBER(SEARCH("[",AJ35)),"Fill placeholders",IF(ISNUMBER(AD35),"Ready to send","Ready · no fixed slot")))
A36: 34 | B36: 1 | C36: Bank | D36: City of London | E36: Mizuho International PLC | F36: Mizuho | G36: https://www.mizuho.com | H36: customerservice@mizuho.com | I36: general | J36: Open page | K36: 01203696 | L36: Open | M36: Group | N36: 27467 | O36: 30 Old Bailey, London | P36: EC4M 7AU | Q36: Yes | W36: City of London School (EC4V 3AL) | X36: 8 | Z36: City of London School (EC4V 3AL) | AA36: 8 | AB36: =IFERROR(INDEX(Venues!$E$2:$E$17,MATCH(Z36,Venues!$A$2:$A$17,0)),"Not checked") | AC36: =IFERROR(INDEX(Venues!$F$2:$F$17,MATCH(Z36,Venues!$A$2:$A$17,0)),0) | AD36: =IFERROR(INDEX(Venues!$M$2:$M$17,MATCH(Z36,Venues!$A$2:$A$17,0)),"") | AE36: =IFERROR(INDEX(Venues!$N$2:$N$17,MATCH(Z36,Venues!$A$2:$A$17,0)),"5-a-side") | AF36: =IF(Offer!$C$4="","",Offer!$C$4) | AG36: =Z36&" ("&AA36&" min walk) · "&IF(ISNUMBER(AD36),TEXT(AD36,"ddd d mmm, hh:mm"),"slot to confirm with venue")&" · "&AE36&" · "&IF(AF36<>"","£"&TEXT(AF36,"0.00")&" pp","price TBC") | AH36: =IF(U36<>"",U36,IF(H36<>"",H36,"")) | AI36: ="After-work football for "&F36&" · "&Z36&", "&AA36&" min from your office" | AJ36: ="Hi "&IF(R36<>"",R36,F36&" team")&","&CHAR(10)&CHAR(10)&"I'm "&IF(AM36<>"",AM36,IF(Offer!$C$5<>"",Offer!$C$5,"[NAME]"))&" from FC Urban. We organise after-work football for teams in the City and Canary Wharf."&CHAR(10)&CHAR(10)&"We have a "&AE36&" pitch at "&Z36&", "&IF(OR(AA36=8,AA36=11,AA36=18),"an ","a ")&AA36&"-minute walk from your "&P36&" office, "&IF(ISNUMBER(AD36),"on "&TEXT(AD36,"dddd d mmmm")&" at "&TEXT(AD36,"hh:mm"),"on a weekday evening that suits your team")&". It's "&IF(AF36<>"","£"&IF(AF36=INT(AF36),TEXT(AF36,"0"),TEXT(AF36,"0.00")),"[PRICE PER PLAYER]")&" a player and we handle the pitch booking, sign-ups and payments, so all it takes is one person sharing a link with the team."&CHAR(10)&CHAR(10)&"It works well as a team social or "&IF(ISNUMBER(SEARCH(LEFT(F36,1),"AEIOU")),"an ","a ")&F36&" vs clients game. Would your team be up for it, or is there someone who'd enjoy organising it?"&IF(Offer!$C$7<>""," Spots are held until "&TEXT(Offer!$C$7,"dddd d mmmm")&".","")&" "&IF(Offer!$C$6<>"",Offer!$C$6,"[JOINING LINK]")&CHAR(10)&CHAR(10)&"Best,"&CHAR(10)&IF(AM36<>"",AM36,IF(Offer!$C$5<>"",Offer!$C$5,"[NAME]"))&CHAR(10)&"FC Urban" | AK36: ="Hi "&IF(R36<>"",R36,F36&" team")&","&CHAR(10)&CHAR(10)&"Just bumping this up. The "&AE36&" pitch at "&Z36&" is still free "&IF(ISNUMBER(AD36),TEXT(AD36,"ddd d mmm")&", "&TEXT(AD36,"hh:mm"),"weekday evenings")&", "&IF(OR(AA36=8,AA36=11,AA36=18),"an ","a ")&AA36&"-minute walk from your office, "&IF(AF36<>"","£"&IF(AF36=INT(AF36),TEXT(AF36,"0"),TEXT(AF36,"0.00")),"[PRICE PER PLAYER]")&" a player. Happy to hold it for "&F36&" if someone on the team fancies organising a game."&IF(Offer!$C$7<>""," Spots are held until "&TEXT(Offer!$C$7,"dddd d mmmm")&".","")&" "&IF(Offer!$C$6<>"",Offer!$C$6,"[JOINING LINK]")&CHAR(10)&CHAR(10)&"Best,"&CHAR(10)&IF(AM36<>"",AM36,IF(Offer!$C$5<>"",Offer!$C$5,"[NAME]"))&CHAR(10)&"FC Urban" | AL36: =IF(AH36="","No email yet",IF(ISNUMBER(SEARCH("[",AJ36)),"Fill placeholders",IF(ISNUMBER(AD36),"Ready to send","Ready · no fixed slot")))
A37: 35 | B37: 1 | C37: Bank | D37: City of London | E37: National Westminster Bank Public Limited Company | F37: NatWest | G37: https://www.natwest.com | I37: Not found | K37: 00929027 | L37: Open | M37: Group | N37: 24915 | O37: 250 Bishopsgate, London | P37: EC2M 4AA | Q37: No | W37: Liverpool St - Attlee Centre | X37: 7 | Y37: Shoreditch Powerleague (7.8) | Z37: Shoreditch Powerleague | AA37: 8 | AB37: =IFERROR(INDEX(Venues!$E$2:$E$17,MATCH(Z37,Venues!$A$2:$A$17,0)),"Not checked") | AC37: =IFERROR(INDEX(Venues!$F$2:$F$17,MATCH(Z37,Venues!$A$2:$A$17,0)),0) | AD37: =IFERROR(INDEX(Venues!$M$2:$M$17,MATCH(Z37,Venues!$A$2:$A$17,0)),"") | AE37: =IFERROR(INDEX(Venues!$N$2:$N$17,MATCH(Z37,Venues!$A$2:$A$17,0)),"5-a-side") | AF37: =IF(Offer!$C$4="","",Offer!$C$4) | AG37: =Z37&" ("&AA37&" min walk) · "&IF(ISNUMBER(AD37),TEXT(AD37,"ddd d mmm, hh:mm"),"slot to confirm with venue")&" · "&AE37&" · "&IF(AF37<>"","£"&TEXT(AF37,"0.00")&" pp","price TBC") | AH37: =IF(U37<>"",U37,IF(H37<>"",H37,"")) | AI37: ="After-work football for "&F37&" · "&Z37&", "&AA37&" min from your office" | AJ37: ="Hi "&IF(R37<>"",R37,F37&" team")&","&CHAR(10)&CHAR(10)&"I'm "&IF(AM37<>"",AM37,IF(Offer!$C$5<>"",Offer!$C$5,"[NAME]"))&" from FC Urban. We organise after-work football for teams in the City and Canary Wharf."&CHAR(10)&CHAR(10)&"We have a "&AE37&" pitch at "&Z37&", "&IF(OR(AA37=8,AA37=11,AA37=18),"an ","a ")&AA37&"-minute walk from your "&P37&" office, "&IF(ISNUMBER(AD37),"on "&TEXT(AD37,"dddd d mmmm")&" at "&TEXT(AD37,"hh:mm"),"on a weekday evening that suits your team")&". It's "&IF(AF37<>"","£"&IF(AF37=INT(AF37),TEXT(AF37,"0"),TEXT(AF37,"0.00")),"[PRICE PER PLAYER]")&" a player and we handle the pitch booking, sign-ups and payments, so all it takes is one person sharing a link with the team."&CHAR(10)&CHAR(10)&"It works well as a team social or "&IF(ISNUMBER(SEARCH(LEFT(F37,1),"AEIOU")),"an ","a ")&F37&" vs clients game. Would your team be up for it, or is there someone who'd enjoy organising it?"&IF(Offer!$C$7<>""," Spots are held until "&TEXT(Offer!$C$7,"dddd d mmmm")&".","")&" "&IF(Offer!$C$6<>"",Offer!$C$6,"[JOINING LINK]")&CHAR(10)&CHAR(10)&"Best,"&CHAR(10)&IF(AM37<>"",AM37,IF(Offer!$C$5<>"",Offer!$C$5,"[NAME]"))&CHAR(10)&"FC Urban" | AK37: ="Hi "&IF(R37<>"",R37,F37&" team")&","&CHAR(10)&CHAR(10)&"Just bumping this up. The "&AE37&" pitch at "&Z37&" is still free "&IF(ISNUMBER(AD37),TEXT(AD37,"ddd d mmm")&", "&TEXT(AD37,"hh:mm"),"weekday evenings")&", "&IF(OR(AA37=8,AA37=11,AA37=18),"an ","a ")&AA37&"-minute walk from your office, "&IF(AF37<>"","£"&IF(AF37=INT(AF37),TEXT(AF37,"0"),TEXT(AF37,"0.00")),"[PRICE PER PLAYER]")&" a player. Happy to hold it for "&F37&" if someone on the team fancies organising a game."&IF(Offer!$C$7<>""," Spots are held until "&TEXT(Offer!$C$7,"dddd d mmmm")&".","")&" "&IF(Offer!$C$6<>"",Offer!$C$6,"[JOINING LINK]")&CHAR(10)&CHAR(10)&"Best,"&CHAR(10)&IF(AM37<>"",AM37,IF(Offer!$C$5<>"",Offer!$C$5,"[NAME]"))&CHAR(10)&"FC Urban" | AL37: =IF(AH37="","No email yet",IF(ISNUMBER(SEARCH("[",AJ37)),"Fill placeholders",IF(ISNUMBER(AD37),"Ready to send","Ready · no fixed slot")))
A38: 36 | B38: 1 | C38: Bank | D38: City of London | E38: Starling Bank Limited | F38: Starling Bank | G38: https://www.starlingbank.com | H38: help@starlingbank.com | I38: general | J38: Open page | K38: 09092149 | L38: Open | M38: Group | N38: 41808 | O38: 5Th Floor London Fruit And Wool Exchange, 1 Duval Square, London | P38: E1 6PW | Q38: No | W38: Liverpool St - Attlee Centre | X38: 3 | Y38: Shoreditch Powerleague (8.1); Whitechapel (18.6) | Z38: Shoreditch Powerleague | AA38: 8 | AB38: =IFERROR(INDEX(Venues!$E$2:$E$17,MATCH(Z38,Venues!$A$2:$A$17,0)),"Not checked") | AC38: =IFERROR(INDEX(Venues!$F$2:$F$17,MATCH(Z38,Venues!$A$2:$A$17,0)),0) | AD38: =IFERROR(INDEX(Venues!$M$2:$M$17,MATCH(Z38,Venues!$A$2:$A$17,0)),"") | AE38: =IFERROR(INDEX(Venues!$N$2:$N$17,MATCH(Z38,Venues!$A$2:$A$17,0)),"5-a-side") | AF38: =IF(Offer!$C$4="","",Offer!$C$4) | AG38: =Z38&" ("&AA38&" min walk) · "&IF(ISNUMBER(AD38),TEXT(AD38,"ddd d mmm, hh:mm"),"slot to confirm with venue")&" · "&AE38&" · "&IF(AF38<>"","£"&TEXT(AF38,"0.00")&" pp","price TBC") | AH38: =IF(U38<>"",U38,IF(H38<>"",H38,"")) | AI38: ="After-work football for "&F38&" · "&Z38&", "&AA38&" min from your office" | AJ38: ="Hi "&IF(R38<>"",R38,F38&" team")&","&CHAR(10)&CHAR(10)&"I'm "&IF(AM38<>"",AM38,IF(Offer!$C$5<>"",Offer!$C$5,"[NAME]"))&" from FC Urban. We organise after-work football for teams in the City and Canary Wharf."&CHAR(10)&CHAR(10)&"We have a "&AE38&" pitch at "&Z38&", "&IF(OR(AA38=8,AA38=11,AA38=18),"an ","a ")&AA38&"-minute walk from your "&P38&" office, "&IF(ISNUMBER(AD38),"on "&TEXT(AD38,"dddd d mmmm")&" at "&TEXT(AD38,"hh:mm"),"on a weekday evening that suits your team")&". It's "&IF(AF38<>"","£"&IF(AF38=INT(AF38),TEXT(AF38,"0"),TEXT(AF38,"0.00")),"[PRICE PER PLAYER]")&" a player and we handle the pitch booking, sign-ups and payments, so all it takes is one person sharing a link with the team."&CHAR(10)&CHAR(10)&"It works well as a team social or "&IF(ISNUMBER(SEARCH(LEFT(F38,1),"AEIOU")),"an ","a ")&F38&" vs clients game. Would your team be up for it, or is there someone who'd enjoy organising it?"&IF(Offer!$C$7<>""," Spots are held until "&TEXT(Offer!$C$7,"dddd d mmmm")&".","")&" "&IF(Offer!$C$6<>"",Offer!$C$6,"[JOINING LINK]")&CHAR(10)&CHAR(10)&"Best,"&CHAR(10)&IF(AM38<>"",AM38,IF(Offer!$C$5<>"",Offer!$C$5,"[NAME]"))&CHAR(10)&"FC Urban" | AK38: ="Hi "&IF(R38<>"",R38,F38&" team")&","&CHAR(10)&CHAR(10)&"Just bumping this up. The "&AE38&" pitch at "&Z38&" is still free "&IF(ISNUMBER(AD38),TEXT(AD38,"ddd d mmm")&", "&TEXT(AD38,"hh:mm"),"weekday evenings")&", "&IF(OR(AA38=8,AA38=11,AA38=18),"an ","a ")&AA38&"-minute walk from your office, "&IF(AF38<>"","£"&IF(AF38=INT(AF38),TEXT(AF38,"0"),TEXT(AF38,"0.00")),"[PRICE PER PLAYER]")&" a player. Happy to hold it for "&F38&" if someone on the team fancies organising a game."&IF(Offer!$C$7<>""," Spots are held until "&TEXT(Offer!$C$7,"dddd d mmmm")&".","")&" "&IF(Offer!$C$6<>"",Offer!$C$6,"[JOINING LINK]")&CHAR(10)&CHAR(10)&"Best,"&CHAR(10)&IF(AM38<>"",AM38,IF(Offer!$C$5<>"",Offer!$C$5,"[NAME]"))&CHAR(10)&"FC Urban" | AL38: =IF(AH38="","No email yet",IF(ISNUMBER(SEARCH("[",AJ38)),"Fill placeholders",IF(ISNUMBER(AD38),"Ready to send","Ready · no fixed slot")))
A39: 37 | B39: 1 | C39: Bank | D39: City of London | E39: Lloyds Bank PLC | F39: Lloyds Bank | G39: https://www.lloydsbank.com | H39: worldwideservice@lloydsbank.com | I39: role (other) | J39: Open page | K39: 00002065 | L39: Open | M39: Group | N39: -12672 | O39: 25 Gresham Street, London | P39: EC2V 7HN | Q39: No | W39: City of London School (EC4V 3AL) | X39: 10 | Y39: Finsbury Leisure Centre (EC1V 3PU) (17.8) | Z39: City of London School (EC4V 3AL) | AA39: 10 | AB39: =IFERROR(INDEX(Venues!$E$2:$E$17,MATCH(Z39,Venues!$A$2:$A$17,0)),"Not checked") | AC39: =IFERROR(INDEX(Venues!$F$2:$F$17,MATCH(Z39,Venues!$A$2:$A$17,0)),0) | AD39: =IFERROR(INDEX(Venues!$M$2:$M$17,MATCH(Z39,Venues!$A$2:$A$17,0)),"") | AE39: =IFERROR(INDEX(Venues!$N$2:$N$17,MATCH(Z39,Venues!$A$2:$A$17,0)),"5-a-side") | AF39: =IF(Offer!$C$4="","",Offer!$C$4) | AG39: =Z39&" ("&AA39&" min walk) · "&IF(ISNUMBER(AD39),TEXT(AD39,"ddd d mmm, hh:mm"),"slot to confirm with venue")&" · "&AE39&" · "&IF(AF39<>"","£"&TEXT(AF39,"0.00")&" pp","price TBC") | AH39: =IF(U39<>"",U39,IF(H39<>"",H39,"")) | AI39: ="After-work football for "&F39&" · "&Z39&", "&AA39&" min from your office" | AJ39: ="Hi "&IF(R39<>"",R39,F39&" team")&","&CHAR(10)&CHAR(10)&"I'm "&IF(AM39<>"",AM39,IF(Offer!$C$5<>"",Offer!$C$5,"[NAME]"))&" from FC Urban. We organise after-work football for teams in the City and Canary Wharf."&CHAR(10)&CHAR(10)&"We have a "&AE39&" pitch at "&Z39&", "&IF(OR(AA39=8,AA39=11,AA39=18),"an ","a ")&AA39&"-minute walk from your "&P39&" office, "&IF(ISNUMBER(AD39),"on "&TEXT(AD39,"dddd d mmmm")&" at "&TEXT(AD39,"hh:mm"),"on a weekday evening that suits your team")&". It's "&IF(AF39<>"","£"&IF(AF39=INT(AF39),TEXT(AF39,"0"),TEXT(AF39,"0.00")),"[PRICE PER PLAYER]")&" a player and we handle the pitch booking, sign-ups and payments, so all it takes is one person sharing a link with the team."&CHAR(10)&CHAR(10)&"It works well as a team social or "&IF(ISNUMBER(SEARCH(LEFT(F39,1),"AEIOU")),"an ","a ")&F39&" vs clients game. Would your team be up for it, or is there someone who'd enjoy organising it?"&IF(Offer!$C$7<>""," Spots are held until "&TEXT(Offer!$C$7,"dddd d mmmm")&".","")&" "&IF(Offer!$C$6<>"",Offer!$C$6,"[JOINING LINK]")&CHAR(10)&CHAR(10)&"Best,"&CHAR(10)&IF(AM39<>"",AM39,IF(Offer!$C$5<>"",Offer!$C$5,"[NAME]"))&CHAR(10)&"FC Urban" | AK39: ="Hi "&IF(R39<>"",R39,F39&" team")&","&CHAR(10)&CHAR(10)&"Just bumping this up. The "&AE39&" pitch at "&Z39&" is still free "&IF(ISNUMBER(AD39),TEXT(AD39,"ddd d mmm")&", "&TEXT(AD39,"hh:mm"),"weekday evenings")&", "&IF(OR(AA39=8,AA39=11,AA39=18),"an ","a ")&AA39&"-minute walk from your office, "&IF(AF39<>"","£"&IF(AF39=INT(AF39),TEXT(AF39,"0"),TEXT(AF39,"0.00")),"[PRICE PER PLAYER]")&" a player. Happy to hold it for "&F39&" if someone on the team fancies organising a game."&IF(Offer!$C$7<>""," Spots are held until "&TEXT(Offer!$C$7,"dddd d mmmm")&".","")&" "&IF(Offer!$C$6<>"",Offer!$C$6,"[JOINING LINK]")&CHAR(10)&CHAR(10)&"Best,"&CHAR(10)&IF(AM39<>"",AM39,IF(Offer!$C$5<>"",Offer!$C$5,"[NAME]"))&CHAR(10)&"FC Urban" | AL39: =IF(AH39="","No email yet",IF(ISNUMBER(SEARCH("[",AJ39)),"Fill placeholders",IF(ISNUMBER(AD39),"Ready to send","Ready · no fixed slot")))
A40: 38 | B40: 1 | C40: Bank | D40: City of London | E40: Allica Bank Limited | F40: Allica Bank | G40: https://www.allica.bank | H40: customer.services@allica.bank | I40: role (other) | J40: Open page | K40: 07706156 | L40: Open | M40: Group | N40: 40739 | O40: 4Th/5Th Floor, 15 Worship Street, London | P40: EC2A 2DT | Q40: Yes | W40: Shoreditch Powerleague | X40: 12 | Y40: Finsbury Leisure Centre (EC1V 3PU) (12.2); Liverpool St - Attlee Centre (16.9) | Z40: Shoreditch Powerleague | AA40: 12 | AB40: =IFERROR(INDEX(Venues!$E$2:$E$17,MATCH(Z40,Venues!$A$2:$A$17,0)),"Not checked") | AC40: =IFERROR(INDEX(Venues!$F$2:$F$17,MATCH(Z40,Venues!$A$2:$A$17,0)),0) | AD40: =IFERROR(INDEX(Venues!$M$2:$M$17,MATCH(Z40,Venues!$A$2:$A$17,0)),"") | AE40: =IFERROR(INDEX(Venues!$N$2:$N$17,MATCH(Z40,Venues!$A$2:$A$17,0)),"5-a-side") | AF40: =IF(Offer!$C$4="","",Offer!$C$4) | AG40: =Z40&" ("&AA40&" min walk) · "&IF(ISNUMBER(AD40),TEXT(AD40,"ddd d mmm, hh:mm"),"slot to confirm with venue")&" · "&AE40&" · "&IF(AF40<>"","£"&TEXT(AF40,"0.00")&" pp","price TBC") | AH40: =IF(U40<>"",U40,IF(H40<>"",H40,"")) | AI40: ="After-work football for "&F40&" · "&Z40&", "&AA40&" min from your office" | AJ40: ="Hi "&IF(R40<>"",R40,F40&" team")&","&CHAR(10)&CHAR(10)&"I'm "&IF(AM40<>"",AM40,IF(Offer!$C$5<>"",Offer!$C$5,"[NAME]"))&" from FC Urban. We organise after-work football for teams in the City and Canary Wharf."&CHAR(10)&CHAR(10)&"We have a "&AE40&" pitch at "&Z40&", "&IF(OR(AA40=8,AA40=11,AA40=18),"an ","a ")&AA40&"-minute walk from your "&P40&" office, "&IF(ISNUMBER(AD40),"on "&TEXT(AD40,"dddd d mmmm")&" at "&TEXT(AD40,"hh:mm"),"on a weekday evening that suits your team")&". It's "&IF(AF40<>"","£"&IF(AF40=INT(AF40),TEXT(AF40,"0"),TEXT(AF40,"0.00")),"[PRICE PER PLAYER]")&" a player and we handle the pitch booking, sign-ups and payments, so all it takes is one person sharing a link with the team."&CHAR(10)&CHAR(10)&"It works well as a team social or "&IF(ISNUMBER(SEARCH(LEFT(F40,1),"AEIOU")),"an ","a ")&F40&" vs clients game. Would your team be up for it, or is there someone who'd enjoy organising it?"&IF(Offer!$C$7<>""," Spots are held until "&TEXT(Offer!$C$7,"dddd d mmmm")&".","")&" "&IF(Offer!$C$6<>"",Offer!$C$6,"[JOINING LINK]")&CHAR(10)&CHAR(10)&"Best,"&CHAR(10)&IF(AM40<>"",AM40,IF(Offer!$C$5<>"",Offer!$C$5,"[NAME]"))&CHAR(10)&"FC Urban" | AK40: ="Hi "&IF(R40<>"",R40,F40&" team")&","&CHAR(10)&CHAR(10)&"Just bumping this up. The "&AE40&" pitch at "&Z40&" is still free "&IF(ISNUMBER(AD40),TEXT(AD40,"ddd d mmm")&", "&TEXT(AD40,"hh:mm"),"weekday evenings")&", "&IF(OR(AA40=8,AA40=11,AA40=18),"an ","a ")&AA40&"-minute walk from your office, "&IF(AF40<>"","£"&IF(AF40=INT(AF40),TEXT(AF40,"0"),TEXT(AF40,"0.00")),"[PRICE PER PLAYER]")&" a player. Happy to hold it for "&F40&" if someone on the team fancies organising a game."&IF(Offer!$C$7<>""," Spots are held until "&TEXT(Offer!$C$7,"dddd d mmmm")&".","")&" "&IF(Offer!$C$6<>"",Offer!$C$6,"[JOINING LINK]")&CHAR(10)&CHAR(10)&"Best,"&CHAR(10)&IF(AM40<>"",AM40,IF(Offer!$C$5<>"",Offer!$C$5,"[NAME]"))&CHAR(10)&"FC Urban" | AL40: =IF(AH40="","No email yet",IF(ISNUMBER(SEARCH("[",AJ40)),"Fill placeholders",IF(ISNUMBER(AD40),"Ready to send","Ready · no fixed slot")))
A41: 39 | B41: 1 | C41: Bank | D41: City of London | E41: Standard Chartered Bank | F41: Standard Chartered Bank | G41: https://www.sc.com | H41: info@sc.com | I41: general | J41: Open page | K41: ZC000018 | L41: Open | M41: Group | N41: 19722 | O41: 1 Basinghall Avenue, London | P41: EC2V 5DD | Q41: No | W41: City of London School (EC4V 3AL) | X41: 15 | Y41: Finsbury Leisure Centre (EC1V 3PU) (17.1) | Z41: City of London School (EC4V 3AL) | AA41: 15 | AB41: =IFERROR(INDEX(Venues!$E$2:$E$17,MATCH(Z41,Venues!$A$2:$A$17,0)),"Not checked") | AC41: =IFERROR(INDEX(Venues!$F$2:$F$17,MATCH(Z41,Venues!$A$2:$A$17,0)),0) | AD41: =IFERROR(INDEX(Venues!$M$2:$M$17,MATCH(Z41,Venues!$A$2:$A$17,0)),"") | AE41: =IFERROR(INDEX(Venues!$N$2:$N$17,MATCH(Z41,Venues!$A$2:$A$17,0)),"5-a-side") | AF41: =IF(Offer!$C$4="","",Offer!$C$4) | AG41: =Z41&" ("&AA41&" min walk) · "&IF(ISNUMBER(AD41),TEXT(AD41,"ddd d mmm, hh:mm"),"slot to confirm with venue")&" · "&AE41&" · "&IF(AF41<>"","£"&TEXT(AF41,"0.00")&" pp","price TBC") | AH41: =IF(U41<>"",U41,IF(H41<>"",H41,"")) | AI41: ="After-work football for "&F41&" · "&Z41&", "&AA41&" min from your office" | AJ41: ="Hi "&IF(R41<>"",R41,F41&" team")&","&CHAR(10)&CHAR(10)&"I'm "&IF(AM41<>"",AM41,IF(Offer!$C$5<>"",Offer!$C$5,"[NAME]"))&" from FC Urban. We organise after-work football for teams in the City and Canary Wharf."&CHAR(10)&CHAR(10)&"We have a "&AE41&" pitch at "&Z41&", "&IF(OR(AA41=8,AA41=11,AA41=18),"an ","a ")&AA41&"-minute walk from your "&P41&" office, "&IF(ISNUMBER(AD41),"on "&TEXT(AD41,"dddd d mmmm")&" at "&TEXT(AD41,"hh:mm"),"on a weekday evening that suits your team")&". It's "&IF(AF41<>"","£"&IF(AF41=INT(AF41),TEXT(AF41,"0"),TEXT(AF41,"0.00")),"[PRICE PER PLAYER]")&" a player and we handle the pitch booking, sign-ups and payments, so all it takes is one person sharing a link with the team."&CHAR(10)&CHAR(10)&"It works well as a team social or "&IF(ISNUMBER(SEARCH(LEFT(F41,1),"AEIOU")),"an ","a ")&F41&" vs clients game. Would your team be up for it, or is there someone who'd enjoy organising it?"&IF(Offer!$C$7<>""," Spots are held until "&TEXT(Offer!$C$7,"dddd d mmmm")&".","")&" "&IF(Offer!$C$6<>"",Offer!$C$6,"[JOINING LINK]")&CHAR(10)&CHAR(10)&"Best,"&CHAR(10)&IF(AM41<>"",AM41,IF(Offer!$C$5<>"",Offer!$C$5,"[NAME]"))&CHAR(10)&"FC Urban" | AK41: ="Hi "&IF(R41<>"",R41,F41&" team")&","&CHAR(10)&CHAR(10)&"Just bumping this up. The "&AE41&" pitch at "&Z41&" is still free "&IF(ISNUMBER(AD41),TEXT(AD41,"ddd d mmm")&", "&TEXT(AD41,"hh:mm"),"weekday evenings")&", "&IF(OR(AA41=8,AA41=11,AA41=18),"an ","a ")&AA41&"-minute walk from your office, "&IF(AF41<>"","£"&IF(AF41=INT(AF41),TEXT(AF41,"0"),TEXT(AF41,"0.00")),"[PRICE PER PLAYER]")&" a player. Happy to hold it for "&F41&" if someone on the team fancies organising a game."&IF(Offer!$C$7<>""," Spots are held until "&TEXT(Offer!$C$7,"dddd d mmmm")&".","")&" "&IF(Offer!$C$6<>"",Offer!$C$6,"[JOINING LINK]")&CHAR(10)&CHAR(10)&"Best,"&CHAR(10)&IF(AM41<>"",AM41,IF(Offer!$C$5<>"",Offer!$C$5,"[NAME]"))&CHAR(10)&"FC Urban" | AL41: =IF(AH41="","No email yet",IF(ISNUMBER(SEARCH("[",AJ41)),"Fill placeholders",IF(ISNUMBER(AD41),"Ready to send","Ready · no fixed slot")))
A42: 40 | B42: 1 | C42: Bank | D42: City of London | E42: Gatehouse Bank PLC | F42: Gatehouse Bank | G42: https://gatehousebank.com | H42: bdteam@gatehousebank.com | I42: role (other) | J42: Open page | K42: 06260053 | L42: Open | M42: Group | N42: 39227 | O42: The Helicon, One South Place, London | P42: EC2M 2RB | Q42: Yes | W42: Shoreditch Powerleague | X42: 15 | Y42: Finsbury Leisure Centre (EC1V 3PU) (15.2); Liverpool St - Attlee Centre (16.3) | Z42: Shoreditch Powerleague | AA42: 15 | AB42: =IFERROR(INDEX(Venues!$E$2:$E$17,MATCH(Z42,Venues!$A$2:$A$17,0)),"Not checked") | AC42: =IFERROR(INDEX(Venues!$F$2:$F$17,MATCH(Z42,Venues!$A$2:$A$17,0)),0) | AD42: =IFERROR(INDEX(Venues!$M$2:$M$17,MATCH(Z42,Venues!$A$2:$A$17,0)),"") | AE42: =IFERROR(INDEX(Venues!$N$2:$N$17,MATCH(Z42,Venues!$A$2:$A$17,0)),"5-a-side") | AF42: =IF(Offer!$C$4="","",Offer!$C$4) | AG42: =Z42&" ("&AA42&" min walk) · "&IF(ISNUMBER(AD42),TEXT(AD42,"ddd d mmm, hh:mm"),"slot to confirm with venue")&" · "&AE42&" · "&IF(AF42<>"","£"&TEXT(AF42,"0.00")&" pp","price TBC") | AH42: =IF(U42<>"",U42,IF(H42<>"",H42,"")) | AI42: ="After-work football for "&F42&" · "&Z42&", "&AA42&" min from your office" | AJ42: ="Hi "&IF(R42<>"",R42,F42&" team")&","&CHAR(10)&CHAR(10)&"I'm "&IF(AM42<>"",AM42,IF(Offer!$C$5<>"",Offer!$C$5,"[NAME]"))&" from FC Urban. We organise after-work football for teams in the City and Canary Wharf."&CHAR(10)&CHAR(10)&"We have a "&AE42&" pitch at "&Z42&", "&IF(OR(AA42=8,AA42=11,AA42=18),"an ","a ")&AA42&"-minute walk from your "&P42&" office, "&IF(ISNUMBER(AD42),"on "&TEXT(AD42,"dddd d mmmm")&" at "&TEXT(AD42,"hh:mm"),"on a weekday evening that suits your team")&". It's "&IF(AF42<>"","£"&IF(AF42=INT(AF42),TEXT(AF42,"0"),TEXT(AF42,"0.00")),"[PRICE PER PLAYER]")&" a player and we handle the pitch booking, sign-ups and payments, so all it takes is one person sharing a link with the team."&CHAR(10)&CHAR(10)&"It works well as a team social or "&IF(ISNUMBER(SEARCH(LEFT(F42,1),"AEIOU")),"an ","a ")&F42&" vs clients game. Would your team be up for it, or is there someone who'd enjoy organising it?"&IF(Offer!$C$7<>""," Spots are held until "&TEXT(Offer!$C$7,"dddd d mmmm")&".","")&" "&IF(Offer!$C$6<>"",Offer!$C$6,"[JOINING LINK]")&CHAR(10)&CHAR(10)&"Best,"&CHAR(10)&IF(AM42<>"",AM42,IF(Offer!$C$5<>"",Offer!$C$5,"[NAME]"))&CHAR(10)&"FC Urban" | AK42: ="Hi "&IF(R42<>"",R42,F42&" team")&","&CHAR(10)&CHAR(10)&"Just bumping this up. The "&AE42&" pitch at "&Z42&" is still free "&IF(ISNUMBER(AD42),TEXT(AD42,"ddd d mmm")&", "&TEXT(AD42,"hh:mm"),"weekday evenings")&", "&IF(OR(AA42=8,AA42=11,AA42=18),"an ","a ")&AA42&"-minute walk from your office, "&IF(AF42<>"","£"&IF(AF42=INT(AF42),TEXT(AF42,"0"),TEXT(AF42,"0.00")),"[PRICE PER PLAYER]")&" a player. Happy to hold it for "&F42&" if someone on the team fancies organising a game."&IF(Offer!$C$7<>""," Spots are held until "&TEXT(Offer!$C$7,"dddd d mmmm")&".","")&" "&IF(Offer!$C$6<>"",Offer!$C$6,"[JOINING LINK]")&CHAR(10)&CHAR(10)&"Best,"&CHAR(10)&IF(AM42<>"",AM42,IF(Offer!$C$5<>"",Offer!$C$5,"[NAME]"))&CHAR(10)&"FC Urban" | AL42: =IF(AH42="","No email yet",IF(ISNUMBER(SEARCH("[",AJ42)),"Fill placeholders",IF(ISNUMBER(AD42),"Ready to send","Ready · no fixed slot")))
A43: 41 | B43: 1 | C43: Bank | D43: City of London | E43: Hampshire Trust Bank PLC | F43: Hampshire Trust Bank | G43: https://www.htb.co.uk | H43: bfenquiries@htb.co.uk | I43: named person | J43: Open page | K43: 01311315 | L43: Open | M43: Group | N43: 28243 | O43: 80 Fenchurch Street, London | P43: EC3M 4BY | Q43: No | W43: Liverpool St - Attlee Centre | X43: 10 | Y43: Shoreditch Powerleague (18.7) | Z43: Shoreditch Powerleague | AA43: 19 | AB43: =IFERROR(INDEX(Venues!$E$2:$E$17,MATCH(Z43,Venues!$A$2:$A$17,0)),"Not checked") | AC43: =IFERROR(INDEX(Venues!$F$2:$F$17,MATCH(Z43,Venues!$A$2:$A$17,0)),0) | AD43: =IFERROR(INDEX(Venues!$M$2:$M$17,MATCH(Z43,Venues!$A$2:$A$17,0)),"") | AE43: =IFERROR(INDEX(Venues!$N$2:$N$17,MATCH(Z43,Venues!$A$2:$A$17,0)),"5-a-side") | AF43: =IF(Offer!$C$4="","",Offer!$C$4) | AG43: =Z43&" ("&AA43&" min walk) · "&IF(ISNUMBER(AD43),TEXT(AD43,"ddd d mmm, hh:mm"),"slot to confirm with venue")&" · "&AE43&" · "&IF(AF43<>"","£"&TEXT(AF43,"0.00")&" pp","price TBC") | AH43: =IF(U43<>"",U43,IF(H43<>"",H43,"")) | AI43: ="After-work football for "&F43&" · "&Z43&", "&AA43&" min from your office" | AJ43: ="Hi "&IF(R43<>"",R43,F43&" team")&","&CHAR(10)&CHAR(10)&"I'm "&IF(AM43<>"",AM43,IF(Offer!$C$5<>"",Offer!$C$5,"[NAME]"))&" from FC Urban. We organise after-work football for teams in the City and Canary Wharf."&CHAR(10)&CHAR(10)&"We have a "&AE43&" pitch at "&Z43&", "&IF(OR(AA43=8,AA43=11,AA43=18),"an ","a ")&AA43&"-minute walk from your "&P43&" office, "&IF(ISNUMBER(AD43),"on "&TEXT(AD43,"dddd d mmmm")&" at "&TEXT(AD43,"hh:mm"),"on a weekday evening that suits your team")&". It's "&IF(AF43<>"","£"&IF(AF43=INT(AF43),TEXT(AF43,"0"),TEXT(AF43,"0.00")),"[PRICE PER PLAYER]")&" a player and we handle the pitch booking, sign-ups and payments, so all it takes is one person sharing a link with the team."&CHAR(10)&CHAR(10)&"It works well as a team social or "&IF(ISNUMBER(SEARCH(LEFT(F43,1),"AEIOU")),"an ","a ")&F43&" vs clients game. Would your team be up for it, or is there someone who'd enjoy organising it?"&IF(Offer!$C$7<>""," Spots are held until "&TEXT(Offer!$C$7,"dddd d mmmm")&".","")&" "&IF(Offer!$C$6<>"",Offer!$C$6,"[JOINING LINK]")&CHAR(10)&CHAR(10)&"Best,"&CHAR(10)&IF(AM43<>"",AM43,IF(Offer!$C$5<>"",Offer!$C$5,"[NAME]"))&CHAR(10)&"FC Urban" | AK43: ="Hi "&IF(R43<>"",R43,F43&" team")&","&CHAR(10)&CHAR(10)&"Just bumping this up. The "&AE43&" pitch at "&Z43&" is still free "&IF(ISNUMBER(AD43),TEXT(AD43,"ddd d mmm")&", "&TEXT(AD43,"hh:mm"),"weekday evenings")&", "&IF(OR(AA43=8,AA43=11,AA43=18),"an ","a ")&AA43&"-minute walk from your office, "&IF(AF43<>"","£"&IF(AF43=INT(AF43),TEXT(AF43,"0"),TEXT(AF43,"0.00")),"[PRICE PER PLAYER]")&" a player. Happy to hold it for "&F43&" if someone on the team fancies organising a game."&IF(Offer!$C$7<>""," Spots are held until "&TEXT(Offer!$C$7,"dddd d mmmm")&".","")&" "&IF(Offer!$C$6<>"",Offer!$C$6,"[JOINING LINK]")&CHAR(10)&CHAR(10)&"Best,"&CHAR(10)&IF(AM43<>"",AM43,IF(Offer!$C$5<>"",Offer!$C$5,"[NAME]"))&CHAR(10)&"FC Urban" | AL43: =IF(AH43="","No email yet",IF(ISNUMBER(SEARCH("[",AJ43)),"Fill placeholders",IF(ISNUMBER(AD43),"Ready to send","Ready · no fixed slot")))
A44: 42 | B44: 1 | C44: Bank | D44: City of London | E44: Shawbrook Bank Limited | F44: Shawbrook Bank | G44: https://www.shawbrook.co.uk | H44: media@shawbrook.co.uk | I44: role (press / marketing) | J44: Open page | K44: 00388466 | L44: Open | M44: Group | N44: 16252 | O44: Floor 10,, 40 Leadenhall Street, London | P44: EC3A 2BJ | Q44: Yes | W44: Liverpool St - Attlee Centre | X44: 11 | Y44: Shoreditch Powerleague (18.7) | Z44: Shoreditch Powerleague | AA44: 19 | AB44: =IFERROR(INDEX(Venues!$E$2:$E$17,MATCH(Z44,Venues!$A$2:$A$17,0)),"Not checked") | AC44: =IFERROR(INDEX(Venues!$F$2:$F$17,MATCH(Z44,Venues!$A$2:$A$17,0)),0) | AD44: =IFERROR(INDEX(Venues!$M$2:$M$17,MATCH(Z44,Venues!$A$2:$A$17,0)),"") | AE44: =IFERROR(INDEX(Venues!$N$2:$N$17,MATCH(Z44,Venues!$A$2:$A$17,0)),"5-a-side") | AF44: =IF(Offer!$C$4="","",Offer!$C$4) | AG44: =Z44&" ("&AA44&" min walk) · "&IF(ISNUMBER(AD44),TEXT(AD44,"ddd d mmm, hh:mm"),"slot to confirm with venue")&" · "&AE44&" · "&IF(AF44<>"","£"&TEXT(AF44,"0.00")&" pp","price TBC") | AH44: =IF(U44<>"",U44,IF(H44<>"",H44,"")) | AI44: ="After-work football for "&F44&" · "&Z44&", "&AA44&" min from your office" | AJ44: ="Hi "&IF(R44<>"",R44,F44&" team")&","&CHAR(10)&CHAR(10)&"I'm "&IF(AM44<>"",AM44,IF(Offer!$C$5<>"",Offer!$C$5,"[NAME]"))&" from FC Urban. We organise after-work football for teams in the City and Canary Wharf."&CHAR(10)&CHAR(10)&"We have a "&AE44&" pitch at "&Z44&", "&IF(OR(AA44=8,AA44=11,AA44=18),"an ","a ")&AA44&"-minute walk from your "&P44&" office, "&IF(ISNUMBER(AD44),"on "&TEXT(AD44,"dddd d mmmm")&" at "&TEXT(AD44,"hh:mm"),"on a weekday evening that suits your team")&". It's "&IF(AF44<>"","£"&IF(AF44=INT(AF44),TEXT(AF44,"0"),TEXT(AF44,"0.00")),"[PRICE PER PLAYER]")&" a player and we handle the pitch booking, sign-ups and payments, so all it takes is one person sharing a link with the team."&CHAR(10)&CHAR(10)&"It works well as a team social or "&IF(ISNUMBER(SEARCH(LEFT(F44,1),"AEIOU")),"an ","a ")&F44&" vs clients game. Would your team be up for it, or is there someone who'd enjoy organising it?"&IF(Offer!$C$7<>""," Spots are held until "&TEXT(Offer!$C$7,"dddd d mmmm")&".","")&" "&IF(Offer!$C$6<>"",Offer!$C$6,"[JOINING LINK]")&CHAR(10)&CHAR(10)&"Best,"&CHAR(10)&IF(AM44<>"",AM44,IF(Offer!$C$5<>"",Offer!$C$5,"[NAME]"))&CHAR(10)&"FC Urban" | AK44: ="Hi "&IF(R44<>"",R44,F44&" team")&","&CHAR(10)&CHAR(10)&"Just bumping this up. The "&AE44&" pitch at "&Z44&" is still free "&IF(ISNUMBER(AD44),TEXT(AD44,"ddd d mmm")&", "&TEXT(AD44,"hh:mm"),"weekday evenings")&", "&IF(OR(AA44=8,AA44=11,AA44=18),"an ","a ")&AA44&"-minute walk from your office, "&IF(AF44<>"","£"&IF(AF44=INT(AF44),TEXT(AF44,"0"),TEXT(AF44,"0.00")),"[PRICE PER PLAYER]")&" a player. Happy to hold it for "&F44&" if someone on the team fancies organising a game."&IF(Offer!$C$7<>""," Spots are held until "&TEXT(Offer!$C$7,"dddd d mmmm")&".","")&" "&IF(Offer!$C$6<>"",Offer!$C$6,"[JOINING LINK]")&CHAR(10)&CHAR(10)&"Best,"&CHAR(10)&IF(AM44<>"",AM44,IF(Offer!$C$5<>"",Offer!$C$5,"[NAME]"))&CHAR(10)&"FC Urban" | AL44: =IF(AH44="","No email yet",IF(ISNUMBER(SEARCH("[",AJ44)),"Fill placeholders",IF(ISNUMBER(AD44),"Ready to send","Ready · no fixed slot")))
A45: 43 | B45: 1 | C45: Public / state-owned bank | D45: City of London | E45: ICBC Standard Bank PLC | F45: ICBC Standard Bank | G45: https://www.icbcstandard.com | H45: londonmarketing@icbcstandard.com | I45: general | J45: Open page | K45: 02130447 | L45: Open | M45: Group | N45: 31908 | O45: 20 Gresham Street, London | P45: EC2V 7JE | Q45: Yes | W45: City of London School (EC4V 3AL) | X45: 10 | Z45: City of London School (EC4V 3AL) | AA45: 10 | AB45: =IFERROR(INDEX(Venues!$E$2:$E$17,MATCH(Z45,Venues!$A$2:$A$17,0)),"Not checked") | AC45: =IFERROR(INDEX(Venues!$F$2:$F$17,MATCH(Z45,Venues!$A$2:$A$17,0)),0) | AD45: =IFERROR(INDEX(Venues!$M$2:$M$17,MATCH(Z45,Venues!$A$2:$A$17,0)),"") | AE45: =IFERROR(INDEX(Venues!$N$2:$N$17,MATCH(Z45,Venues!$A$2:$A$17,0)),"5-a-side") | AF45: =IF(Offer!$C$4="","",Offer!$C$4) | AG45: =Z45&" ("&AA45&" min walk) · "&IF(ISNUMBER(AD45),TEXT(AD45,"ddd d mmm, hh:mm"),"slot to confirm with venue")&" · "&AE45&" · "&IF(AF45<>"","£"&TEXT(AF45,"0.00")&" pp","price TBC") | AH45: =IF(U45<>"",U45,IF(H45<>"",H45,"")) | AI45: ="After-work football for "&F45&" · "&Z45&", "&AA45&" min from your office" | AJ45: ="Hi "&IF(R45<>"",R45,F45&" team")&","&CHAR(10)&CHAR(10)&"I'm "&IF(AM45<>"",AM45,IF(Offer!$C$5<>"",Offer!$C$5,"[NAME]"))&" from FC Urban. We organise after-work football for teams in the City and Canary Wharf."&CHAR(10)&CHAR(10)&"We have a "&AE45&" pitch at "&Z45&", "&IF(OR(AA45=8,AA45=11,AA45=18),"an ","a ")&AA45&"-minute walk from your "&P45&" office, "&IF(ISNUMBER(AD45),"on "&TEXT(AD45,"dddd d mmmm")&" at "&TEXT(AD45,"hh:mm"),"on a weekday evening that suits your team")&". It's "&IF(AF45<>"","£"&IF(AF45=INT(AF45),TEXT(AF45,"0"),TEXT(AF45,"0.00")),"[PRICE PER PLAYER]")&" a player and we handle the pitch booking, sign-ups and payments, so all it takes is one person sharing a link with the team."&CHAR(10)&CHAR(10)&"It works well as a team social or "&IF(ISNUMBER(SEARCH(LEFT(F45,1),"AEIOU")),"an ","a ")&F45&" vs clients game. Would your team be up for it, or is there someone who'd enjoy organising it?"&IF(Offer!$C$7<>""," Spots are held until "&TEXT(Offer!$C$7,"dddd d mmmm")&".","")&" "&IF(Offer!$C$6<>"",Offer!$C$6,"[JOINING LINK]")&CHAR(10)&CHAR(10)&"Best,"&CHAR(10)&IF(AM45<>"",AM45,IF(Offer!$C$5<>"",Offer!$C$5,"[NAME]"))&CHAR(10)&"FC Urban" | AK45: ="Hi "&IF(R45<>"",R45,F45&" team")&","&CHAR(10)&CHAR(10)&"Just bumping this up. The "&AE45&" pitch at "&Z45&" is still free "&IF(ISNUMBER(AD45),TEXT(AD45,"ddd d mmm")&", "&TEXT(AD45,"hh:mm"),"weekday evenings")&", "&IF(OR(AA45=8,AA45=11,AA45=18),"an ","a ")&AA45&"-minute walk from your office, "&IF(AF45<>"","£"&IF(AF45=INT(AF45),TEXT(AF45,"0"),TEXT(AF45,"0.00")),"[PRICE PER PLAYER]")&" a player. Happy to hold it for "&F45&" if someone on the team fancies organising a game."&IF(Offer!$C$7<>""," Spots are held until "&TEXT(Offer!$C$7,"dddd d mmmm")&".","")&" "&IF(Offer!$C$6<>"",Offer!$C$6,"[JOINING LINK]")&CHAR(10)&CHAR(10)&"Best,"&CHAR(10)&IF(AM45<>"",AM45,IF(Offer!$C$5<>"",Offer!$C$5,"[NAME]"))&CHAR(10)&"FC Urban" | AL45: =IF(AH45="","No email yet",IF(ISNUMBER(SEARCH("[",AJ45)),"Fill placeholders",IF(ISNUMBER(AD45),"Ready to send","Ready · no fixed slot")))
A46: 44 | B46: 1 | C46: Public / state-owned bank | D46: City of London | E46: Bank of England | F46: the Bank of England | G46: https://www.bankofengland.co.uk | H46: outreach@bankofengland.co.uk | I46: named person | J46: Open page | M46: Statutory corporation | O46: Threadneedle Street, London | P46: EC2R 8AH | Q46: Yes | W46: City of London School (EC4V 3AL) | X46: 13 | Y46: Liverpool St - Attlee Centre (18.9) | Z46: City of London School (EC4V 3AL) | AA46: 13 | AB46: =IFERROR(INDEX(Venues!$E$2:$E$17,MATCH(Z46,Venues!$A$2:$A$17,0)),"Not checked") | AC46: =IFERROR(INDEX(Venues!$F$2:$F$17,MATCH(Z46,Venues!$A$2:$A$17,0)),0) | AD46: =IFERROR(INDEX(Venues!$M$2:$M$17,MATCH(Z46,Venues!$A$2:$A$17,0)),"") | AE46: =IFERROR(INDEX(Venues!$N$2:$N$17,MATCH(Z46,Venues!$A$2:$A$17,0)),"5-a-side") | AF46: =IF(Offer!$C$4="","",Offer!$C$4) | AG46: =Z46&" ("&AA46&" min walk) · "&IF(ISNUMBER(AD46),TEXT(AD46,"ddd d mmm, hh:mm"),"slot to confirm with venue")&" · "&AE46&" · "&IF(AF46<>"","£"&TEXT(AF46,"0.00")&" pp","price TBC") | AH46: =IF(U46<>"",U46,IF(H46<>"",H46,"")) | AI46: ="After-work football for "&F46&" · "&Z46&", "&AA46&" min from your office" | AJ46: ="Hi "&IF(R46<>"",R46,F46&" team")&","&CHAR(10)&CHAR(10)&"I'm "&IF(AM46<>"",AM46,IF(Offer!$C$5<>"",Offer!$C$5,"[NAME]"))&" from FC Urban. We organise after-work football for teams in the City and Canary Wharf."&CHAR(10)&CHAR(10)&"We have a "&AE46&" pitch at "&Z46&", "&IF(OR(AA46=8,AA46=11,AA46=18),"an ","a ")&AA46&"-minute walk from your "&P46&" office, "&IF(ISNUMBER(AD46),"on "&TEXT(AD46,"dddd d mmmm")&" at "&TEXT(AD46,"hh:mm"),"on a weekday evening that suits your team")&". It's "&IF(AF46<>"","£"&IF(AF46=INT(AF46),TEXT(AF46,"0"),TEXT(AF46,"0.00")),"[PRICE PER PLAYER]")&" a player and we handle the pitch booking, sign-ups and payments, so all it takes is one person sharing a link with the team."&CHAR(10)&CHAR(10)&"It works well as a team social or "&IF(ISNUMBER(SEARCH(LEFT(F46,1),"AEIOU")),"an ","a ")&F46&" vs clients game. Would your team be up for it, or is there someone who'd enjoy organising it?"&IF(Offer!$C$7<>""," Spots are held until "&TEXT(Offer!$C$7,"dddd d mmmm")&".","")&" "&IF(Offer!$C$6<>"",Offer!$C$6,"[JOINING LINK]")&CHAR(10)&CHAR(10)&"Best,"&CHAR(10)&IF(AM46<>"",AM46,IF(Offer!$C$5<>"",Offer!$C$5,"[NAME]"))&CHAR(10)&"FC Urban" | AK46: ="Hi "&IF(R46<>"",R46,F46&" team")&","&CHAR(10)&CHAR(10)&"Just bumping this up. The "&AE46&" pitch at "&Z46&" is still free "&IF(ISNUMBER(AD46),TEXT(AD46,"ddd d mmm")&", "&TEXT(AD46,"hh:mm"),"weekday evenings")&", "&IF(OR(AA46=8,AA46=11,AA46=18),"an ","a ")&AA46&"-minute walk from your office, "&IF(AF46<>"","£"&IF(AF46=INT(AF46),TEXT(AF46,"0"),TEXT(AF46,"0.00")),"[PRICE PER PLAYER]")&" a player. Happy to hold it for "&F46&" if someone on the team fancies organising a game."&IF(Offer!$C$7<>""," Spots are held until "&TEXT(Offer!$C$7,"dddd d mmmm")&".","")&" "&IF(Offer!$C$6<>"",Offer!$C$6,"[JOINING LINK]")&CHAR(10)&CHAR(10)&"Best,"&CHAR(10)&IF(AM46<>"",AM46,IF(Offer!$C$5<>"",Offer!$C$5,"[NAME]"))&CHAR(10)&"FC Urban" | AL46: =IF(AH46="","No email yet",IF(ISNUMBER(SEARCH("[",AJ46)),"Fill placeholders",IF(ISNUMBER(AD46),"Ready to send","Ready · no fixed slot")))
A47: 45 | B47: 1 | C47: Public / state-owned bank | D47: City of London | E47: Agdevco Limited | F47: AgDevCo | G47: https://www.agdevco.com | H47: info@agdevco.com | I47: general | J47: Open page | K47: 07026479 | L47: Open | M47: Group | N47: 40078 | O47: Chancery House 53-64 Chancery Lane, Holborn, London | P47: WC2A 1QS | Q47: No | W47: St Pancras - Coram's Fields 3G | X47: 17 | Z47: St Pancras - Coram's Fields 3G | AA47: 17 | AB47: =IFERROR(INDEX(Venues!$E$2:$E$17,MATCH(Z47,Venues!$A$2:$A$17,0)),"Not checked") | AC47: =IFERROR(INDEX(Venues!$F$2:$F$17,MATCH(Z47,Venues!$A$2:$A$17,0)),0) | AD47: =IFERROR(INDEX(Venues!$M$2:$M$17,MATCH(Z47,Venues!$A$2:$A$17,0)),"") | AE47: =IFERROR(INDEX(Venues!$N$2:$N$17,MATCH(Z47,Venues!$A$2:$A$17,0)),"5-a-side") | AF47: =IF(Offer!$C$4="","",Offer!$C$4) | AG47: =Z47&" ("&AA47&" min walk) · "&IF(ISNUMBER(AD47),TEXT(AD47,"ddd d mmm, hh:mm"),"slot to confirm with venue")&" · "&AE47&" · "&IF(AF47<>"","£"&TEXT(AF47,"0.00")&" pp","price TBC") | AH47: =IF(U47<>"",U47,IF(H47<>"",H47,"")) | AI47: ="After-work football for "&F47&" · "&Z47&", "&AA47&" min from your office" | AJ47: ="Hi "&IF(R47<>"",R47,F47&" team")&","&CHAR(10)&CHAR(10)&"I'm "&IF(AM47<>"",AM47,IF(Offer!$C$5<>"",Offer!$C$5,"[NAME]"))&" from FC Urban. We organise after-work football for teams in the City and Canary Wharf."&CHAR(10)&CHAR(10)&"We have a "&AE47&" pitch at "&Z47&", "&IF(OR(AA47=8,AA47=11,AA47=18),"an ","a ")&AA47&"-minute walk from your "&P47&" office, "&IF(ISNUMBER(AD47),"on "&TEXT(AD47,"dddd d mmmm")&" at "&TEXT(AD47,"hh:mm"),"on a weekday evening that suits your team")&". It's "&IF(AF47<>"","£"&IF(AF47=INT(AF47),TEXT(AF47,"0"),TEXT(AF47,"0.00")),"[PRICE PER PLAYER]")&" a player and we handle the pitch booking, sign-ups and payments, so all it takes is one person sharing a link with the team."&CHAR(10)&CHAR(10)&"It works well as a team social or "&IF(ISNUMBER(SEARCH(LEFT(F47,1),"AEIOU")),"an ","a ")&F47&" vs clients game. Would your team be up for it, or is there someone who'd enjoy organising it?"&IF(Offer!$C$7<>""," Spots are held until "&TEXT(Offer!$C$7,"dddd d mmmm")&".","")&" "&IF(Offer!$C$6<>"",Offer!$C$6,"[JOINING LINK]")&CHAR(10)&CHAR(10)&"Best,"&CHAR(10)&IF(AM47<>"",AM47,IF(Offer!$C$5<>"",Offer!$C$5,"[NAME]"))&CHAR(10)&"FC Urban" | AK47: ="Hi "&IF(R47<>"",R47,F47&" team")&","&CHAR(10)&CHAR(10)&"Just bumping this up. The "&AE47&" pitch at "&Z47&" is still free "&IF(ISNUMBER(AD47),TEXT(AD47,"ddd d mmm")&", "&TEXT(AD47,"hh:mm"),"weekday evenings")&", "&IF(OR(AA47=8,AA47=11,AA47=18),"an ","a ")&AA47&"-minute walk from your office, "&IF(AF47<>"","£"&IF(AF47=INT(AF47),TEXT(AF47,"0"),TEXT(AF47,"0.00")),"[PRICE PER PLAYER]")&" a player. Happy to hold it for "&F47&" if someone on the team fancies organising a game."&IF(Offer!$C$7<>""," Spots are held until "&TEXT(Offer!$C$7,"dddd d mmmm")&".","")&" "&IF(Offer!$C$6<>"",Offer!$C$6,"[JOINING LINK]")&CHAR(10)&CHAR(10)&"Best,"&CHAR(10)&IF(AM47<>"",AM47,IF(Offer!$C$5<>"",Offer!$C$5,"[NAME]"))&CHAR(10)&"FC Urban" | AL47: =IF(AH47="","No email yet",IF(ISNUMBER(SEARCH("[",AJ47)),"Fill placeholders",IF(ISNUMBER(AD47),"Ready to send","Ready · no fixed slot")))
A48: 46 | B48: 1 | C48: Private bank | D48: City of London | E48: Investec Bank PLC | F48: Investec Bank | G48: https://www.investec.com | I48: Not found | K48: 00489604 | L48: Open | M48: Group | N48: 18617 | O48: 30 Gresham Street, London | P48: EC2V 7QP | Q48: No | W48: City of London School (EC4V 3AL) | X48: 10 | Z48: City of London School (EC4V 3AL) | AA48: 10 | AB48: =IFERROR(INDEX(Venues!$E$2:$E$17,MATCH(Z48,Venues!$A$2:$A$17,0)),"Not checked") | AC48: =IFERROR(INDEX(Venues!$F$2:$F$17,MATCH(Z48,Venues!$A$2:$A$17,0)),0) | AD48: =IFERROR(INDEX(Venues!$M$2:$M$17,MATCH(Z48,Venues!$A$2:$A$17,0)),"") | AE48: =IFERROR(INDEX(Venues!$N$2:$N$17,MATCH(Z48,Venues!$A$2:$A$17,0)),"5-a-side") | AF48: =IF(Offer!$C$4="","",Offer!$C$4) | AG48: =Z48&" ("&AA48&" min walk) · "&IF(ISNUMBER(AD48),TEXT(AD48,"ddd d mmm, hh:mm"),"slot to confirm with venue")&" · "&AE48&" · "&IF(AF48<>"","£"&TEXT(AF48,"0.00")&" pp","price TBC") | AH48: =IF(U48<>"",U48,IF(H48<>"",H48,"")) | AI48: ="After-work football for "&F48&" · "&Z48&", "&AA48&" min from your office" | AJ48: ="Hi "&IF(R48<>"",R48,F48&" team")&","&CHAR(10)&CHAR(10)&"I'm "&IF(AM48<>"",AM48,IF(Offer!$C$5<>"",Offer!$C$5,"[NAME]"))&" from FC Urban. We organise after-work football for teams in the City and Canary Wharf."&CHAR(10)&CHAR(10)&"We have a "&AE48&" pitch at "&Z48&", "&IF(OR(AA48=8,AA48=11,AA48=18),"an ","a ")&AA48&"-minute walk from your "&P48&" office, "&IF(ISNUMBER(AD48),"on "&TEXT(AD48,"dddd d mmmm")&" at "&TEXT(AD48,"hh:mm"),"on a weekday evening that suits your team")&". It's "&IF(AF48<>"","£"&IF(AF48=INT(AF48),TEXT(AF48,"0"),TEXT(AF48,"0.00")),"[PRICE PER PLAYER]")&" a player and we handle the pitch booking, sign-ups and payments, so all it takes is one person sharing a link with the team."&CHAR(10)&CHAR(10)&"It works well as a team social or "&IF(ISNUMBER(SEARCH(LEFT(F48,1),"AEIOU")),"an ","a ")&F48&" vs clients game. Would your team be up for it, or is there someone who'd enjoy organising it?"&IF(Offer!$C$7<>""," Spots are held until "&TEXT(Offer!$C$7,"dddd d mmmm")&".","")&" "&IF(Offer!$C$6<>"",Offer!$C$6,"[JOINING LINK]")&CHAR(10)&CHAR(10)&"Best,"&CHAR(10)&IF(AM48<>"",AM48,IF(Offer!$C$5<>"",Offer!$C$5,"[NAME]"))&CHAR(10)&"FC Urban" | AK48: ="Hi "&IF(R48<>"",R48,F48&" team")&","&CHAR(10)&CHAR(10)&"Just bumping this up. The "&AE48&" pitch at "&Z48&" is still free "&IF(ISNUMBER(AD48),TEXT(AD48,"ddd d mmm")&", "&TEXT(AD48,"hh:mm"),"weekday evenings")&", "&IF(OR(AA48=8,AA48=11,AA48=18),"an ","a ")&AA48&"-minute walk from your office, "&IF(AF48<>"","£"&IF(AF48=INT(AF48),TEXT(AF48,"0"),TEXT(AF48,"0.00")),"[PRICE PER PLAYER]")&" a player. Happy to hold it for "&F48&" if someone on the team fancies organising a game."&IF(Offer!$C$7<>""," Spots are held until "&TEXT(Offer!$C$7,"dddd d mmmm")&".","")&" "&IF(Offer!$C$6<>"",Offer!$C$6,"[JOINING LINK]")&CHAR(10)&CHAR(10)&"Best,"&CHAR(10)&IF(AM48<>"",AM48,IF(Offer!$C$5<>"",Offer!$C$5,"[NAME]"))&CHAR(10)&"FC Urban" | AL48: =IF(AH48="","No email yet",IF(ISNUMBER(SEARCH("[",AJ48)),"Fill placeholders",IF(ISNUMBER(AD48),"Ready to send","Ready · no fixed slot")))
A49: 47 | B49: 2 | C49: Law firm | D49: City of London | E49: Morgan, Lewis & Bockius UK LLP | F49: Morgan, Lewis & Bockius | G49: https://www.morganlewis.com | H49: london@morganlewis.com | I49: general | J49: Open page | K49: OC378797 | L49: Open | M49: Full | N49: 41178 | O49: Condor House 5-10, St. Paul'S Churchyard, London | P49: EC4M 8AL | Q49: No | W49: City of London School (EC4V 3AL) | X49: 4 | Y49: Marlborough Sports Garden (SE1 1SD) (19) | Z49: City of London School (EC4V 3AL) | AA49: 4 | AB49: =IFERROR(INDEX(Venues!$E$2:$E$17,MATCH(Z49,Venues!$A$2:$A$17,0)),"Not checked") | AC49: =IFERROR(INDEX(Venues!$F$2:$F$17,MATCH(Z49,Venues!$A$2:$A$17,0)),0) | AD49: =IFERROR(INDEX(Venues!$M$2:$M$17,MATCH(Z49,Venues!$A$2:$A$17,0)),"") | AE49: =IFERROR(INDEX(Venues!$N$2:$N$17,MATCH(Z49,Venues!$A$2:$A$17,0)),"5-a-side") | AF49: =IF(Offer!$C$4="","",Offer!$C$4) | AG49: =Z49&" ("&AA49&" min walk) · "&IF(ISNUMBER(AD49),TEXT(AD49,"ddd d mmm, hh:mm"),"slot to confirm with venue")&" · "&AE49&" · "&IF(AF49<>"","£"&TEXT(AF49,"0.00")&" pp","price TBC") | AH49: =IF(U49<>"",U49,IF(H49<>"",H49,"")) | AI49: ="After-work football for "&F49&" · "&Z49&", "&AA49&" min from your office" | AJ49: ="Hi "&IF(R49<>"",R49,F49&" team")&","&CHAR(10)&CHAR(10)&"I'm "&IF(AM49<>"",AM49,IF(Offer!$C$5<>"",Offer!$C$5,"[NAME]"))&" from FC Urban. We organise after-work football for teams in the City and Canary Wharf."&CHAR(10)&CHAR(10)&"We have a "&AE49&" pitch at "&Z49&", "&IF(OR(AA49=8,AA49=11,AA49=18),"an ","a ")&AA49&"-minute walk from your "&P49&" office, "&IF(ISNUMBER(AD49),"on "&TEXT(AD49,"dddd d mmmm")&" at "&TEXT(AD49,"hh:mm"),"on a weekday evening that suits your team")&". It's "&IF(AF49<>"","£"&IF(AF49=INT(AF49),TEXT(AF49,"0"),TEXT(AF49,"0.00")),"[PRICE PER PLAYER]")&" a player and we handle the pitch booking, sign-ups and payments, so all it takes is one person sharing a link with the team."&CHAR(10)&CHAR(10)&"It works well as a team social or "&IF(ISNUMBER(SEARCH(LEFT(F49,1),"AEIOU")),"an ","a ")&F49&" vs clients game. Would your team be up for it, or is there someone who'd enjoy organising it?"&IF(Offer!$C$7<>""," Spots are held until "&TEXT(Offer!$C$7,"dddd d mmmm")&".","")&" "&IF(Offer!$C$6<>"",Offer!$C$6,"[JOINING LINK]")&CHAR(10)&CHAR(10)&"Best,"&CHAR(10)&IF(AM49<>"",AM49,IF(Offer!$C$5<>"",Offer!$C$5,"[NAME]"))&CHAR(10)&"FC Urban" | AK49: ="Hi "&IF(R49<>"",R49,F49&" team")&","&CHAR(10)&CHAR(10)&"Just bumping this up. The "&AE49&" pitch at "&Z49&" is still free "&IF(ISNUMBER(AD49),TEXT(AD49,"ddd d mmm")&", "&TEXT(AD49,"hh:mm"),"weekday evenings")&", "&IF(OR(AA49=8,AA49=11,AA49=18),"an ","a ")&AA49&"-minute walk from your office, "&IF(AF49<>"","£"&IF(AF49=INT(AF49),TEXT(AF49,"0"),TEXT(AF49,"0.00")),"[PRICE PER PLAYER]")&" a player. Happy to hold it for "&F49&" if someone on the team fancies organising a game."&IF(Offer!$C$7<>""," Spots are held until "&TEXT(Offer!$C$7,"dddd d mmmm")&".","")&" "&IF(Offer!$C$6<>"",Offer!$C$6,"[JOINING LINK]")&CHAR(10)&CHAR(10)&"Best,"&CHAR(10)&IF(AM49<>"",AM49,IF(Offer!$C$5<>"",Offer!$C$5,"[NAME]"))&CHAR(10)&"FC Urban" | AL49: =IF(AH49="","No email yet",IF(ISNUMBER(SEARCH("[",AJ49)),"Fill placeholders",IF(ISNUMBER(AD49),"Ready to send","Ready · no fixed slot")))
A50: 48 | B50: 2 | C50: Law firm | D50: City of London | E50: Dechert LLP | F50: Dechert | G50: https://www.dechert.com | H50: londonlateralrecruitment@dechert.com | I50: general | J50: Open page | K50: OC306029 | L50: Open | M50: Full | N50: 37937 | O50: 25 Cannon Street, London | P50: EC4M 5UB | Q50: No | W50: City of London School (EC4V 3AL) | X50: 6 | Y50: Marlborough Sports Garden (SE1 1SD) (17.5) | Z50: City of London School (EC4V 3AL) | AA50: 6 | AB50: =IFERROR(INDEX(Venues!$E$2:$E$17,MATCH(Z50,Venues!$A$2:$A$17,0)),"Not checked") | AC50: =IFERROR(INDEX(Venues!$F$2:$F$17,MATCH(Z50,Venues!$A$2:$A$17,0)),0) | AD50: =IFERROR(INDEX(Venues!$M$2:$M$17,MATCH(Z50,Venues!$A$2:$A$17,0)),"") | AE50: =IFERROR(INDEX(Venues!$N$2:$N$17,MATCH(Z50,Venues!$A$2:$A$17,0)),"5-a-side") | AF50: =IF(Offer!$C$4="","",Offer!$C$4) | AG50: =Z50&" ("&AA50&" min walk) · "&IF(ISNUMBER(AD50),TEXT(AD50,"ddd d mmm, hh:mm"),"slot to confirm with venue")&" · "&AE50&" · "&IF(AF50<>"","£"&TEXT(AF50,"0.00")&" pp","price TBC") | AH50: =IF(U50<>"",U50,IF(H50<>"",H50,"")) | AI50: ="After-work football for "&F50&" · "&Z50&", "&AA50&" min from your office" | AJ50: ="Hi "&IF(R50<>"",R50,F50&" team")&","&CHAR(10)&CHAR(10)&"I'm "&IF(AM50<>"",AM50,IF(Offer!$C$5<>"",Offer!$C$5,"[NAME]"))&" from FC Urban. We organise after-work football for teams in the City and Canary Wharf."&CHAR(10)&CHAR(10)&"We have a "&AE50&" pitch at "&Z50&", "&IF(OR(AA50=8,AA50=11,AA50=18),"an ","a ")&AA50&"-minute walk from your "&P50&" office, "&IF(ISNUMBER(AD50),"on "&TEXT(AD50,"dddd d mmmm")&" at "&TEXT(AD50,"hh:mm"),"on a weekday evening that suits your team")&". It's "&IF(AF50<>"","£"&IF(AF50=INT(AF50),TEXT(AF50,"0"),TEXT(AF50,"0.00")),"[PRICE PER PLAYER]")&" a player and we handle the pitch booking, sign-ups and payments, so all it takes is one person sharing a link with the team."&CHAR(10)&CHAR(10)&"It works well as a team social or "&IF(ISNUMBER(SEARCH(LEFT(F50,1),"AEIOU")),"an ","a ")&F50&" vs clients game. Would your team be up for it, or is there someone who'd enjoy organising it?"&IF(Offer!$C$7<>""," Spots are held until "&TEXT(Offer!$C$7,"dddd d mmmm")&".","")&" "&IF(Offer!$C$6<>"",Offer!$C$6,"[JOINING LINK]")&CHAR(10)&CHAR(10)&"Best,"&CHAR(10)&IF(AM50<>"",AM50,IF(Offer!$C$5<>"",Offer!$C$5,"[NAME]"))&CHAR(10)&"FC Urban" | AK50: ="Hi "&IF(R50<>"",R50,F50&" team")&","&CHAR(10)&CHAR(10)&"Just bumping this up. The "&AE50&" pitch at "&Z50&" is still free "&IF(ISNUMBER(AD50),TEXT(AD50,"ddd d mmm")&", "&TEXT(AD50,"hh:mm"),"weekday evenings")&", "&IF(OR(AA50=8,AA50=11,AA50=18),"an ","a ")&AA50&"-minute walk from your office, "&IF(AF50<>"","£"&IF(AF50=INT(AF50),TEXT(AF50,"0"),TEXT(AF50,"0.00")),"[PRICE PER PLAYER]")&" a player. Happy to hold it for "&F50&" if someone on the team fancies organising a game."&IF(Offer!$C$7<>""," Spots are held until "&TEXT(Offer!$C$7,"dddd d mmmm")&".","")&" "&IF(Offer!$C$6<>"",Offer!$C$6,"[JOINING LINK]")&CHAR(10)&CHAR(10)&"Best,"&CHAR(10)&IF(AM50<>"",AM50,IF(Offer!$C$5<>"",Offer!$C$5,"[NAME]"))&CHAR(10)&"FC Urban" | AL50: =IF(AH50="","No email yet",IF(ISNUMBER(SEARCH("[",AJ50)),"Fill placeholders",IF(ISNUMBER(AD50),"Ready to send","Ready · no fixed slot")))
A51: 49 | B51: 2 | C51: Law firm | D51: City of London | E51: K&L Gates LLP | F51: K&L Gates | G51: https://www.klgates.com | H51: infoaus@klgates.com | I51: general | J51: Open page | K51: OC309508 | L51: Open | M51: Full | N51: 38267 | O51: One, New Change, London | P51: EC4M 9AF | Q51: No | W51: City of London School (EC4V 3AL) | X51: 6 | Y51: Marlborough Sports Garden (SE1 1SD) (18.5) | Z51: City of London School (EC4V 3AL) | AA51: 6 | AB51: =IFERROR(INDEX(Venues!$E$2:$E$17,MATCH(Z51,Venues!$A$2:$A$17,0)),"Not checked") | AC51: =IFERROR(INDEX(Venues!$F$2:$F$17,MATCH(Z51,Venues!$A$2:$A$17,0)),0) | AD51: =IFERROR(INDEX(Venues!$M$2:$M$17,MATCH(Z51,Venues!$A$2:$A$17,0)),"") | AE51: =IFERROR(INDEX(Venues!$N$2:$N$17,MATCH(Z51,Venues!$A$2:$A$17,0)),"5-a-side") | AF51: =IF(Offer!$C$4="","",Offer!$C$4) | AG51: =Z51&" ("&AA51&" min walk) · "&IF(ISNUMBER(AD51),TEXT(AD51,"ddd d mmm, hh:mm"),"slot to confirm with venue")&" · "&AE51&" · "&IF(AF51<>"","£"&TEXT(AF51,"0.00")&" pp","price TBC") | AH51: =IF(U51<>"",U51,IF(H51<>"",H51,"")) | AI51: ="After-work football for "&F51&" · "&Z51&", "&AA51&" min from your office" | AJ51: ="Hi "&IF(R51<>"",R51,F51&" team")&","&CHAR(10)&CHAR(10)&"I'm "&IF(AM51<>"",AM51,IF(Offer!$C$5<>"",Offer!$C$5,"[NAME]"))&" from FC Urban. We organise after-work football for teams in the City and Canary Wharf."&CHAR(10)&CHAR(10)&"We have a "&AE51&" pitch at "&Z51&", "&IF(OR(AA51=8,AA51=11,AA51=18),"an ","a ")&AA51&"-minute walk from your "&P51&" office, "&IF(ISNUMBER(AD51),"on "&TEXT(AD51,"dddd d mmmm")&" at "&TEXT(AD51,"hh:mm"),"on a weekday evening that suits your team")&". It's "&IF(AF51<>"","£"&IF(AF51=INT(AF51),TEXT(AF51,"0"),TEXT(AF51,"0.00")),"[PRICE PER PLAYER]")&" a player and we handle the pitch booking, sign-ups and payments, so all it takes is one person sharing a link with the team."&CHAR(10)&CHAR(10)&"It works well as a team social or "&IF(ISNUMBER(SEARCH(LEFT(F51,1),"AEIOU")),"an ","a ")&F51&" vs clients game. Would your team be up for it, or is there someone who'd enjoy organising it?"&IF(Offer!$C$7<>""," Spots are held until "&TEXT(Offer!$C$7,"dddd d mmmm")&".","")&" "&IF(Offer!$C$6<>"",Offer!$C$6,"[JOINING LINK]")&CHAR(10)&CHAR(10)&"Best,"&CHAR(10)&IF(AM51<>"",AM51,IF(Offer!$C$5<>"",Offer!$C$5,"[NAME]"))&CHAR(10)&"FC Urban" | AK51: ="Hi "&IF(R51<>"",R51,F51&" team")&","&CHAR(10)&CHAR(10)&"Just bumping this up. The "&AE51&" pitch at "&Z51&" is still free "&IF(ISNUMBER(AD51),TEXT(AD51,"ddd d mmm")&", "&TEXT(AD51,"hh:mm"),"weekday evenings")&", "&IF(OR(AA51=8,AA51=11,AA51=18),"an ","a ")&AA51&"-minute walk from your office, "&IF(AF51<>"","£"&IF(AF51=INT(AF51),TEXT(AF51,"0"),TEXT(AF51,"0.00")),"[PRICE PER PLAYER]")&" a player. Happy to hold it for "&F51&" if someone on the team fancies organising a game."&IF(Offer!$C$7<>""," Spots are held until "&TEXT(Offer!$C$7,"dddd d mmmm")&".","")&" "&IF(Offer!$C$6<>"",Offer!$C$6,"[JOINING LINK]")&CHAR(10)&CHAR(10)&"Best,"&CHAR(10)&IF(AM51<>"",AM51,IF(Offer!$C$5<>"",Offer!$C$5,"[NAME]"))&CHAR(10)&"FC Urban" | AL51: =IF(AH51="","No email yet",IF(ISNUMBER(SEARCH("[",AJ51)),"Fill placeholders",IF(ISNUMBER(AD51),"Ready to send","Ready · no fixed slot")))
A52: 50 | B52: 2 | C52: Law firm | D52: City of London | E52: Burford Capital Services Limited | F52: Burford Capital | G52: https://burford.com | H52: info@burford.com | I52: general | J52: Open page | K52: 13128424 | L52: Open | M52: Full | N52: 44208 | O52: Paternoster House, 4Th Floor, 65 St Paul'S Churchyard, London | P52: EC4M 8AB | Q52: No | W52: City of London School (EC4V 3AL) | X52: 6 | Z52: City of London School (EC4V 3AL) | AA52: 6 | AB52: =IFERROR(INDEX(Venues!$E$2:$E$17,MATCH(Z52,Venues!$A$2:$A$17,0)),"Not checked") | AC52: =IFERROR(INDEX(Venues!$F$2:$F$17,MATCH(Z52,Venues!$A$2:$A$17,0)),0) | AD52: =IFERROR(INDEX(Venues!$M$2:$M$17,MATCH(Z52,Venues!$A$2:$A$17,0)),"") | AE52: =IFERROR(INDEX(Venues!$N$2:$N$17,MATCH(Z52,Venues!$A$2:$A$17,0)),"5-a-side") | AF52: =IF(Offer!$C$4="","",Offer!$C$4) | AG52: =Z52&" ("&AA52&" min walk) · "&IF(ISNUMBER(AD52),TEXT(AD52,"ddd d mmm, hh:mm"),"slot to confirm with venue")&" · "&AE52&" · "&IF(AF52<>"","£"&TEXT(AF52,"0.00")&" pp","price TBC") | AH52: =IF(U52<>"",U52,IF(H52<>"",H52,"")) | AI52: ="After-work football for "&F52&" · "&Z52&", "&AA52&" min from your office" | AJ52: ="Hi "&IF(R52<>"",R52,F52&" team")&","&CHAR(10)&CHAR(10)&"I'm "&IF(AM52<>"",AM52,IF(Offer!$C$5<>"",Offer!$C$5,"[NAME]"))&" from FC Urban. We organise after-work football for teams in the City and Canary Wharf."&CHAR(10)&CHAR(10)&"We have a "&AE52&" pitch at "&Z52&", "&IF(OR(AA52=8,AA52=11,AA52=18),"an ","a ")&AA52&"-minute walk from your "&P52&" office, "&IF(ISNUMBER(AD52),"on "&TEXT(AD52,"dddd d mmmm")&" at "&TEXT(AD52,"hh:mm"),"on a weekday evening that suits your team")&". It's "&IF(AF52<>"","£"&IF(AF52=INT(AF52),TEXT(AF52,"0"),TEXT(AF52,"0.00")),"[PRICE PER PLAYER]")&" a player and we handle the pitch booking, sign-ups and payments, so all it takes is one person sharing a link with the team."&CHAR(10)&CHAR(10)&"It works well as a team social or "&IF(ISNUMBER(SEARCH(LEFT(F52,1),"AEIOU")),"an ","a ")&F52&" vs clients game. Would your team be up for it, or is there someone who'd enjoy organising it?"&IF(Offer!$C$7<>""," Spots are held until "&TEXT(Offer!$C$7,"dddd d mmmm")&".","")&" "&IF(Offer!$C$6<>"",Offer!$C$6,"[JOINING LINK]")&CHAR(10)&CHAR(10)&"Best,"&CHAR(10)&IF(AM52<>"",AM52,IF(Offer!$C$5<>"",Offer!$C$5,"[NAME]"))&CHAR(10)&"FC Urban" | AK52: ="Hi "&IF(R52<>"",R52,F52&" team")&","&CHAR(10)&CHAR(10)&"Just bumping this up. The "&AE52&" pitch at "&Z52&" is still free "&IF(ISNUMBER(AD52),TEXT(AD52,"ddd d mmm")&", "&TEXT(AD52,"hh:mm"),"weekday evenings")&", "&IF(OR(AA52=8,AA52=11,AA52=18),"an ","a ")&AA52&"-minute walk from your office, "&IF(AF52<>"","£"&IF(AF52=INT(AF52),TEXT(AF52,"0"),TEXT(AF52,"0.00")),"[PRICE PER PLAYER]")&" a player. Happy to hold it for "&F52&" if someone on the team fancies organising a game."&IF(Offer!$C$7<>""," Spots are held until "&TEXT(Offer!$C$7,"dddd d mmmm")&".","")&" "&IF(Offer!$C$6<>"",Offer!$C$6,"[JOINING LINK]")&CHAR(10)&CHAR(10)&"Best,"&CHAR(10)&IF(AM52<>"",AM52,IF(Offer!$C$5<>"",Offer!$C$5,"[NAME]"))&CHAR(10)&"FC Urban" | AL52: =IF(AH52="","No email yet",IF(ISNUMBER(SEARCH("[",AJ52)),"Fill placeholders",IF(ISNUMBER(AD52),"Ready to send","Ready · no fixed slot")))
A53: 51 | B53: 2 | C53: Law firm | D53: City of London | E53: Katten Muchin Rosenman UK LLP | F53: Katten Muchin Rosenman | G53: https://katten.com | H53: gil.soffer@katten.com | I53: named person | J53: Open page | K53: OC312814 | L53: Open | M53: Full | N53: 38460 | O53: Paternoster House, 65 St Paul'S Churchyard, London | P53: EC4M 8AB | Q53: No | W53: City of London School (EC4V 3AL) | X53: 6 | Z53: City of London School (EC4V 3AL) | AA53: 6 | AB53: =IFERROR(INDEX(Venues!$E$2:$E$17,MATCH(Z53,Venues!$A$2:$A$17,0)),"Not checked") | AC53: =IFERROR(INDEX(Venues!$F$2:$F$17,MATCH(Z53,Venues!$A$2:$A$17,0)),0) | AD53: =IFERROR(INDEX(Venues!$M$2:$M$17,MATCH(Z53,Venues!$A$2:$A$17,0)),"") | AE53: =IFERROR(INDEX(Venues!$N$2:$N$17,MATCH(Z53,Venues!$A$2:$A$17,0)),"5-a-side") | AF53: =IF(Offer!$C$4="","",Offer!$C$4) | AG53: =Z53&" ("&AA53&" min walk) · "&IF(ISNUMBER(AD53),TEXT(AD53,"ddd d mmm, hh:mm"),"slot to confirm with venue")&" · "&AE53&" · "&IF(AF53<>"","£"&TEXT(AF53,"0.00")&" pp","price TBC") | AH53: =IF(U53<>"",U53,IF(H53<>"",H53,"")) | AI53: ="After-work football for "&F53&" · "&Z53&", "&AA53&" min from your office" | AJ53: ="Hi "&IF(R53<>"",R53,F53&" team")&","&CHAR(10)&CHAR(10)&"I'm "&IF(AM53<>"",AM53,IF(Offer!$C$5<>"",Offer!$C$5,"[NAME]"))&" from FC Urban. We organise after-work football for teams in the City and Canary Wharf."&CHAR(10)&CHAR(10)&"We have a "&AE53&" pitch at "&Z53&", "&IF(OR(AA53=8,AA53=11,AA53=18),"an ","a ")&AA53&"-minute walk from your "&P53&" office, "&IF(ISNUMBER(AD53),"on "&TEXT(AD53,"dddd d mmmm")&" at "&TEXT(AD53,"hh:mm"),"on a weekday evening that suits your team")&". It's "&IF(AF53<>"","£"&IF(AF53=INT(AF53),TEXT(AF53,"0"),TEXT(AF53,"0.00")),"[PRICE PER PLAYER]")&" a player and we handle the pitch booking, sign-ups and payments, so all it takes is one person sharing a link with the team."&CHAR(10)&CHAR(10)&"It works well as a team social or "&IF(ISNUMBER(SEARCH(LEFT(F53,1),"AEIOU")),"an ","a ")&F53&" vs clients game. Would your team be up for it, or is there someone who'd enjoy organising it?"&IF(Offer!$C$7<>""," Spots are held until "&TEXT(Offer!$C$7,"dddd d mmmm")&".","")&" "&IF(Offer!$C$6<>"",Offer!$C$6,"[JOINING LINK]")&CHAR(10)&CHAR(10)&"Best,"&CHAR(10)&IF(AM53<>"",AM53,IF(Offer!$C$5<>"",Offer!$C$5,"[NAME]"))&CHAR(10)&"FC Urban" | AK53: ="Hi "&IF(R53<>"",R53,F53&" team")&","&CHAR(10)&CHAR(10)&"Just bumping this up. The "&AE53&" pitch at "&Z53&" is still free "&IF(ISNUMBER(AD53),TEXT(AD53,"ddd d mmm")&", "&TEXT(AD53,"hh:mm"),"weekday evenings")&", "&IF(OR(AA53=8,AA53=11,AA53=18),"an ","a ")&AA53&"-minute walk from your office, "&IF(AF53<>"","£"&IF(AF53=INT(AF53),TEXT(AF53,"0"),TEXT(AF53,"0.00")),"[PRICE PER PLAYER]")&" a player. Happy to hold it for "&F53&" if someone on the team fancies organising a game."&IF(Offer!$C$7<>""," Spots are held until "&TEXT(Offer!$C$7,"dddd d mmmm")&".","")&" "&IF(Offer!$C$6<>"",Offer!$C$6,"[JOINING LINK]")&CHAR(10)&CHAR(10)&"Best,"&CHAR(10)&IF(AM53<>"",AM53,IF(Offer!$C$5<>"",Offer!$C$5,"[NAME]"))&CHAR(10)&"FC Urban" | AL53: =IF(AH53="","No email yet",IF(ISNUMBER(SEARCH("[",AJ53)),"Fill placeholders",IF(ISNUMBER(AD53),"Ready to send","Ready · no fixed slot")))
A54: 52 | B54: 2 | C54: Law firm | D54: City of London | E54: Bristows (Services) Limited | F54: Bristows | G54: https://www.bristows.com | H54: london@bristows.com | I54: general | J54: Open page | K54: 07422632 | L54: Open | M54: Full | N54: 40479 | O54: 100 Victoria Embankment, London | P54: EC4Y 0DH | Q54: No | W54: City of London School (EC4V 3AL) | X54: 6 | Z54: City of London School (EC4V 3AL) | AA54: 6 | AB54: =IFERROR(INDEX(Venues!$E$2:$E$17,MATCH(Z54,Venues!$A$2:$A$17,0)),"Not checked") | AC54: =IFERROR(INDEX(Venues!$F$2:$F$17,MATCH(Z54,Venues!$A$2:$A$17,0)),0) | AD54: =IFERROR(INDEX(Venues!$M$2:$M$17,MATCH(Z54,Venues!$A$2:$A$17,0)),"") | AE54: =IFERROR(INDEX(Venues!$N$2:$N$17,MATCH(Z54,Venues!$A$2:$A$17,0)),"5-a-side") | AF54: =IF(Offer!$C$4="","",Offer!$C$4) | AG54: =Z54&" ("&AA54&" min walk) · "&IF(ISNUMBER(AD54),TEXT(AD54,"ddd d mmm, hh:mm"),"slot to confirm with venue")&" · "&AE54&" · "&IF(AF54<>"","£"&TEXT(AF54,"0.00")&" pp","price TBC") | AH54: =IF(U54<>"",U54,IF(H54<>"",H54,"")) | AI54: ="After-work football for "&F54&" · "&Z54&", "&AA54&" min from your office" | AJ54: ="Hi "&IF(R54<>"",R54,F54&" team")&","&CHAR(10)&CHAR(10)&"I'm "&IF(AM54<>"",AM54,IF(Offer!$C$5<>"",Offer!$C$5,"[NAME]"))&" from FC Urban. We organise after-work football for teams in the City and Canary Wharf."&CHAR(10)&CHAR(10)&"We have a "&AE54&" pitch at "&Z54&", "&IF(OR(AA54=8,AA54=11,AA54=18),"an ","a ")&AA54&"-minute walk from your "&P54&" office, "&IF(ISNUMBER(AD54),"on "&TEXT(AD54,"dddd d mmmm")&" at "&TEXT(AD54,"hh:mm"),"on a weekday evening that suits your team")&". It's "&IF(AF54<>"","£"&IF(AF54=INT(AF54),TEXT(AF54,"0"),TEXT(AF54,"0.00")),"[PRICE PER PLAYER]")&" a player and we handle the pitch booking, sign-ups and payments, so all it takes is one person sharing a link with the team."&CHAR(10)&CHAR(10)&"It works well as a team social or "&IF(ISNUMBER(SEARCH(LEFT(F54,1),"AEIOU")),"an ","a ")&F54&" vs clients game. Would your team be up for it, or is there someone who'd enjoy organising it?"&IF(Offer!$C$7<>""," Spots are held until "&TEXT(Offer!$C$7,"dddd d mmmm")&".","")&" "&IF(Offer!$C$6<>"",Offer!$C$6,"[JOINING LINK]")&CHAR(10)&CHAR(10)&"Best,"&CHAR(10)&IF(AM54<>"",AM54,IF(Offer!$C$5<>"",Offer!$C$5,"[NAME]"))&CHAR(10)&"FC Urban" | AK54: ="Hi "&IF(R54<>"",R54,F54&" team")&","&CHAR(10)&CHAR(10)&"Just bumping this up. The "&AE54&" pitch at "&Z54&" is still free "&IF(ISNUMBER(AD54),TEXT(AD54,"ddd d mmm")&", "&TEXT(AD54,"hh:mm"),"weekday evenings")&", "&IF(OR(AA54=8,AA54=11,AA54=18),"an ","a ")&AA54&"-minute walk from your office, "&IF(AF54<>"","£"&IF(AF54=INT(AF54),TEXT(AF54,"0"),TEXT(AF54,"0.00")),"[PRICE PER PLAYER]")&" a player. Happy to hold it for "&F54&" if someone on the team fancies organising a game."&IF(Offer!$C$7<>""," Spots are held until "&TEXT(Offer!$C$7,"dddd d mmmm")&".","")&" "&IF(Offer!$C$6<>"",Offer!$C$6,"[JOINING LINK]")&CHAR(10)&CHAR(10)&"Best,"&CHAR(10)&IF(AM54<>"",AM54,IF(Offer!$C$5<>"",Offer!$C$5,"[NAME]"))&CHAR(10)&"FC Urban" | AL54: =IF(AH54="","No email yet",IF(ISNUMBER(SEARCH("[",AJ54)),"Fill placeholders",IF(ISNUMBER(AD54),"Ready to send","Ready · no fixed slot")))
A55: 53 | B55: 2 | C55: Law firm | D55: City of London | E55: Maples and Calder | F55: Maples Group | G55: https://maples.com | H55: london@maplesandcalder.com | I55: general | J55: Open page | K55: 03369233 | L55: Open | M55: Full | N55: 35556 | O55: Duo Level 6, 280 Bishopsgate, London | P55: EC2M 4RB | Q55: No | W55: Shoreditch Powerleague | X55: 7 | Y55: Liverpool St - Attlee Centre (7.1) | Z55: Shoreditch Powerleague | AA55: 7 | AB55: =IFERROR(INDEX(Venues!$E$2:$E$17,MATCH(Z55,Venues!$A$2:$A$17,0)),"Not checked") | AC55: =IFERROR(INDEX(Venues!$F$2:$F$17,MATCH(Z55,Venues!$A$2:$A$17,0)),0) | AD55: =IFERROR(INDEX(Venues!$M$2:$M$17,MATCH(Z55,Venues!$A$2:$A$17,0)),"") | AE55: =IFERROR(INDEX(Venues!$N$2:$N$17,MATCH(Z55,Venues!$A$2:$A$17,0)),"5-a-side") | AF55: =IF(Offer!$C$4="","",Offer!$C$4) | AG55: =Z55&" ("&AA55&" min walk) · "&IF(ISNUMBER(AD55),TEXT(AD55,"ddd d mmm, hh:mm"),"slot to confirm with venue")&" · "&AE55&" · "&IF(AF55<>"","£"&TEXT(AF55,"0.00")&" pp","price TBC") | AH55: =IF(U55<>"",U55,IF(H55<>"",H55,"")) | AI55: ="After-work football for "&F55&" · "&Z55&", "&AA55&" min from your office" | AJ55: ="Hi "&IF(R55<>"",R55,F55&" team")&","&CHAR(10)&CHAR(10)&"I'm "&IF(AM55<>"",AM55,IF(Offer!$C$5<>"",Offer!$C$5,"[NAME]"))&" from FC Urban. We organise after-work football for teams in the City and Canary Wharf."&CHAR(10)&CHAR(10)&"We have a "&AE55&" pitch at "&Z55&", "&IF(OR(AA55=8,AA55=11,AA55=18),"an ","a ")&AA55&"-minute walk from your "&P55&" office, "&IF(ISNUMBER(AD55),"on "&TEXT(AD55,"dddd d mmmm")&" at "&TEXT(AD55,"hh:mm"),"on a weekday evening that suits your team")&". It's "&IF(AF55<>"","£"&IF(AF55=INT(AF55),TEXT(AF55,"0"),TEXT(AF55,"0.00")),"[PRICE PER PLAYER]")&" a player and we handle the pitch booking, sign-ups and payments, so all it takes is one person sharing a link with the team."&CHAR(10)&CHAR(10)&"It works well as a team social or "&IF(ISNUMBER(SEARCH(LEFT(F55,1),"AEIOU")),"an ","a ")&F55&" vs clients game. Would your team be up for it, or is there someone who'd enjoy organising it?"&IF(Offer!$C$7<>""," Spots are held until "&TEXT(Offer!$C$7,"dddd d mmmm")&".","")&" "&IF(Offer!$C$6<>"",Offer!$C$6,"[JOINING LINK]")&CHAR(10)&CHAR(10)&"Best,"&CHAR(10)&IF(AM55<>"",AM55,IF(Offer!$C$5<>"",Offer!$C$5,"[NAME]"))&CHAR(10)&"FC Urban" | AK55: ="Hi "&IF(R55<>"",R55,F55&" team")&","&CHAR(10)&CHAR(10)&"Just bumping this up. The "&AE55&" pitch at "&Z55&" is still free "&IF(ISNUMBER(AD55),TEXT(AD55,"ddd d mmm")&", "&TEXT(AD55,"hh:mm"),"weekday evenings")&", "&IF(OR(AA55=8,AA55=11,AA55=18),"an ","a ")&AA55&"-minute walk from your office, "&IF(AF55<>"","£"&IF(AF55=INT(AF55),TEXT(AF55,"0"),TEXT(AF55,"0.00")),"[PRICE PER PLAYER]")&" a player. Happy to hold it for "&F55&" if someone on the team fancies organising a game."&IF(Offer!$C$7<>""," Spots are held until "&TEXT(Offer!$C$7,"dddd d mmmm")&".","")&" "&IF(Offer!$C$6<>"",Offer!$C$6,"[JOINING LINK]")&CHAR(10)&CHAR(10)&"Best,"&CHAR(10)&IF(AM55<>"",AM55,IF(Offer!$C$5<>"",Offer!$C$5,"[NAME]"))&CHAR(10)&"FC Urban" | AL55: =IF(AH55="","No email yet",IF(ISNUMBER(SEARCH("[",AJ55)),"Fill placeholders",IF(ISNUMBER(AD55),"Ready to send","Ready · no fixed slot")))
A56: 54 | B56: 2 | C56: Law firm | D56: City of London | E56: Enyo Law LLP | F56: Enyo Law | G56: https://enyo.co.uk | H56: enquiries@enyolaw.com | I56: general | J56: Open page | K56: OC356313 | L56: Open | M56: Full | N56: 40367 | O56: 1 Tudor Street, London | P56: EC4Y 0AH | Q56: No | W56: City of London School (EC4V 3AL) | X56: 7 | Z56: City of London School (EC4V 3AL) | AA56: 7 | AB56: =IFERROR(INDEX(Venues!$E$2:$E$17,MATCH(Z56,Venues!$A$2:$A$17,0)),"Not checked") | AC56: =IFERROR(INDEX(Venues!$F$2:$F$17,MATCH(Z56,Venues!$A$2:$A$17,0)),0) | AD56: =IFERROR(INDEX(Venues!$M$2:$M$17,MATCH(Z56,Venues!$A$2:$A$17,0)),"") | AE56: =IFERROR(INDEX(Venues!$N$2:$N$17,MATCH(Z56,Venues!$A$2:$A$17,0)),"5-a-side") | AF56: =IF(Offer!$C$4="","",Offer!$C$4) | AG56: =Z56&" ("&AA56&" min walk) · "&IF(ISNUMBER(AD56),TEXT(AD56,"ddd d mmm, hh:mm"),"slot to confirm with venue")&" · "&AE56&" · "&IF(AF56<>"","£"&TEXT(AF56,"0.00")&" pp","price TBC") | AH56: =IF(U56<>"",U56,IF(H56<>"",H56,"")) | AI56: ="After-work football for "&F56&" · "&Z56&", "&AA56&" min from your office" | AJ56: ="Hi "&IF(R56<>"",R56,F56&" team")&","&CHAR(10)&CHAR(10)&"I'm "&IF(AM56<>"",AM56,IF(Offer!$C$5<>"",Offer!$C$5,"[NAME]"))&" from FC Urban. We organise after-work football for teams in the City and Canary Wharf."&CHAR(10)&CHAR(10)&"We have a "&AE56&" pitch at "&Z56&", "&IF(OR(AA56=8,AA56=11,AA56=18),"an ","a ")&AA56&"-minute walk from your "&P56&" office, "&IF(ISNUMBER(AD56),"on "&TEXT(AD56,"dddd d mmmm")&" at "&TEXT(AD56,"hh:mm"),"on a weekday evening that suits your team")&". It's "&IF(AF56<>"","£"&IF(AF56=INT(AF56),TEXT(AF56,"0"),TEXT(AF56,"0.00")),"[PRICE PER PLAYER]")&" a player and we handle the pitch booking, sign-ups and payments, so all it takes is one person sharing a link with the team."&CHAR(10)&CHAR(10)&"It works well as a team social or "&IF(ISNUMBER(SEARCH(LEFT(F56,1),"AEIOU")),"an ","a ")&F56&" vs clients game. Would your team be up for it, or is there someone who'd enjoy organising it?"&IF(Offer!$C$7<>""," Spots are held until "&TEXT(Offer!$C$7,"dddd d mmmm")&".","")&" "&IF(Offer!$C$6<>"",Offer!$C$6,"[JOINING LINK]")&CHAR(10)&CHAR(10)&"Best,"&CHAR(10)&IF(AM56<>"",AM56,IF(Offer!$C$5<>"",Offer!$C$5,"[NAME]"))&CHAR(10)&"FC Urban" | AK56: ="Hi "&IF(R56<>"",R56,F56&" team")&","&CHAR(10)&CHAR(10)&"Just bumping this up. The "&AE56&" pitch at "&Z56&" is still free "&IF(ISNUMBER(AD56),TEXT(AD56,"ddd d mmm")&", "&TEXT(AD56,"hh:mm"),"weekday evenings")&", "&IF(OR(AA56=8,AA56=11,AA56=18),"an ","a ")&AA56&"-minute walk from your office, "&IF(AF56<>"","£"&IF(AF56=INT(AF56),TEXT(AF56,"0"),TEXT(AF56,"0.00")),"[PRICE PER PLAYER]")&" a player. Happy to hold it for "&F56&" if someone on the team fancies organising a game."&IF(Offer!$C$7<>""," Spots are held until "&TEXT(Offer!$C$7,"dddd d mmmm")&".","")&" "&IF(Offer!$C$6<>"",Offer!$C$6,"[JOINING LINK]")&CHAR(10)&CHAR(10)&"Best,"&CHAR(10)&IF(AM56<>"",AM56,IF(Offer!$C$5<>"",Offer!$C$5,"[NAME]"))&CHAR(10)&"FC Urban" | AL56: =IF(AH56="","No email yet",IF(ISNUMBER(SEARCH("[",AJ56)),"Fill placeholders",IF(ISNUMBER(AD56),"Ready to send","Ready · no fixed slot")))
A57: 55 | B57: 2 | C57: Law firm | D57: City of London | E57: Bates Wells & Braithwaite London LLP | F57: Bates Wells & Braithwaite London | G57: https://bates-wells.co.uk | H57: mail@bates-wells.co.uk | I57: general | J57: Open page | K57: OC325522 | L57: Open | M57: Full | N57: 39106 | O57: 10 Queen Street Place, London | P57: EC4R 1BE | Q57: No | W57: City of London School (EC4V 3AL) | X57: 7 | Y57: Marlborough Sports Garden (SE1 1SD) (12.2); Borough Academy (17.4) | Z57: City of London School (EC4V 3AL) | AA57: 7 | AB57: =IFERROR(INDEX(Venues!$E$2:$E$17,MATCH(Z57,Venues!$A$2:$A$17,0)),"Not checked") | AC57: =IFERROR(INDEX(Venues!$F$2:$F$17,MATCH(Z57,Venues!$A$2:$A$17,0)),0) | AD57: =IFERROR(INDEX(Venues!$M$2:$M$17,MATCH(Z57,Venues!$A$2:$A$17,0)),"") | AE57: =IFERROR(INDEX(Venues!$N$2:$N$17,MATCH(Z57,Venues!$A$2:$A$17,0)),"5-a-side") | AF57: =IF(Offer!$C$4="","",Offer!$C$4) | AG57: =Z57&" ("&AA57&" min walk) · "&IF(ISNUMBER(AD57),TEXT(AD57,"ddd d mmm, hh:mm"),"slot to confirm with venue")&" · "&AE57&" · "&IF(AF57<>"","£"&TEXT(AF57,"0.00")&" pp","price TBC") | AH57: =IF(U57<>"",U57,IF(H57<>"",H57,"")) | AI57: ="After-work football for "&F57&" · "&Z57&", "&AA57&" min from your office" | AJ57: ="Hi "&IF(R57<>"",R57,F57&" team")&","&CHAR(10)&CHAR(10)&"I'm "&IF(AM57<>"",AM57,IF(Offer!$C$5<>"",Offer!$C$5,"[NAME]"))&" from FC Urban. We organise after-work football for teams in the City and Canary Wharf."&CHAR(10)&CHAR(10)&"We have a "&AE57&" pitch at "&Z57&", "&IF(OR(AA57=8,AA57=11,AA57=18),"an ","a ")&AA57&"-minute walk from your "&P57&" office, "&IF(ISNUMBER(AD57),"on "&TEXT(AD57,"dddd d mmmm")&" at "&TEXT(AD57,"hh:mm"),"on a weekday evening that suits your team")&". It's "&IF(AF57<>"","£"&IF(AF57=INT(AF57),TEXT(AF57,"0"),TEXT(AF57,"0.00")),"[PRICE PER PLAYER]")&" a player and we handle the pitch booking, sign-ups and payments, so all it takes is one person sharing a link with the team."&CHAR(10)&CHAR(10)&"It works well as a team social or "&IF(ISNUMBER(SEARCH(LEFT(F57,1),"AEIOU")),"an ","a ")&F57&" vs clients game. Would your team be up for it, or is there someone who'd enjoy organising it?"&IF(Offer!$C$7<>""," Spots are held until "&TEXT(Offer!$C$7,"dddd d mmmm")&".","")&" "&IF(Offer!$C$6<>"",Offer!$C$6,"[JOINING LINK]")&CHAR(10)&CHAR(10)&"Best,"&CHAR(10)&IF(AM57<>"",AM57,IF(Offer!$C$5<>"",Offer!$C$5,"[NAME]"))&CHAR(10)&"FC Urban" | AK57: ="Hi "&IF(R57<>"",R57,F57&" team")&","&CHAR(10)&CHAR(10)&"Just bumping this up. The "&AE57&" pitch at "&Z57&" is still free "&IF(ISNUMBER(AD57),TEXT(AD57,"ddd d mmm")&", "&TEXT(AD57,"hh:mm"),"weekday evenings")&", "&IF(OR(AA57=8,AA57=11,AA57=18),"an ","a ")&AA57&"-minute walk from your office, "&IF(AF57<>"","£"&IF(AF57=INT(AF57),TEXT(AF57,"0"),TEXT(AF57,"0.00")),"[PRICE PER PLAYER]")&" a player. Happy to hold it for "&F57&" if someone on the team fancies organising a game."&IF(Offer!$C$7<>""," Spots are held until "&TEXT(Offer!$C$7,"dddd d mmmm")&".","")&" "&IF(Offer!$C$6<>"",Offer!$C$6,"[JOINING LINK]")&CHAR(10)&CHAR(10)&"Best,"&CHAR(10)&IF(AM57<>"",AM57,IF(Offer!$C$5<>"",Offer!$C$5,"[NAME]"))&CHAR(10)&"FC Urban" | AL57: =IF(AH57="","No email yet",IF(ISNUMBER(SEARCH("[",AJ57)),"Fill placeholders",IF(ISNUMBER(AD57),"Ready to send","Ready · no fixed slot")))
A58: 56 | B58: 2 | C58: Law firm | D58: City of London | E58: Abion UK Limited | F58: Abion | G58: https://abion.com | H58: support@abion.com | I58: role (other) | J58: Open page | K58: 08093380 | L58: Open | M58: Medium | N58: 41066 | O58: 33 Gutter Lane, London | P58: EC2V 8AS | Q58: No | W58: City of London School (EC4V 3AL) | X58: 9 | Z58: City of London School (EC4V 3AL) | AA58: 9 | AB58: =IFERROR(INDEX(Venues!$E$2:$E$17,MATCH(Z58,Venues!$A$2:$A$17,0)),"Not checked") | AC58: =IFERROR(INDEX(Venues!$F$2:$F$17,MATCH(Z58,Venues!$A$2:$A$17,0)),0) | AD58: =IFERROR(INDEX(Venues!$M$2:$M$17,MATCH(Z58,Venues!$A$2:$A$17,0)),"") | AE58: =IFERROR(INDEX(Venues!$N$2:$N$17,MATCH(Z58,Venues!$A$2:$A$17,0)),"5-a-side") | AF58: =IF(Offer!$C$4="","",Offer!$C$4) | AG58: =Z58&" ("&AA58&" min walk) · "&IF(ISNUMBER(AD58),TEXT(AD58,"ddd d mmm, hh:mm"),"slot to confirm with venue")&" · "&AE58&" · "&IF(AF58<>"","£"&TEXT(AF58,"0.00")&" pp","price TBC") | AH58: =IF(U58<>"",U58,IF(H58<>"",H58,"")) | AI58: ="After-work football for "&F58&" · "&Z58&", "&AA58&" min from your office" | AJ58: ="Hi "&IF(R58<>"",R58,F58&" team")&","&CHAR(10)&CHAR(10)&"I'm "&IF(AM58<>"",AM58,IF(Offer!$C$5<>"",Offer!$C$5,"[NAME]"))&" from FC Urban. We organise after-work football for teams in the City and Canary Wharf."&CHAR(10)&CHAR(10)&"We have a "&AE58&" pitch at "&Z58&", "&IF(OR(AA58=8,AA58=11,AA58=18),"an ","a ")&AA58&"-minute walk from your "&P58&" office, "&IF(ISNUMBER(AD58),"on "&TEXT(AD58,"dddd d mmmm")&" at "&TEXT(AD58,"hh:mm"),"on a weekday evening that suits your team")&". It's "&IF(AF58<>"","£"&IF(AF58=INT(AF58),TEXT(AF58,"0"),TEXT(AF58,"0.00")),"[PRICE PER PLAYER]")&" a player and we handle the pitch booking, sign-ups and payments, so all it takes is one person sharing a link with the team."&CHAR(10)&CHAR(10)&"It works well as a team social or "&IF(ISNUMBER(SEARCH(LEFT(F58,1),"AEIOU")),"an ","a ")&F58&" vs clients game. Would your team be up for it, or is there someone who'd enjoy organising it?"&IF(Offer!$C$7<>""," Spots are held until "&TEXT(Offer!$C$7,"dddd d mmmm")&".","")&" "&IF(Offer!$C$6<>"",Offer!$C$6,"[JOINING LINK]")&CHAR(10)&CHAR(10)&"Best,"&CHAR(10)&IF(AM58<>"",AM58,IF(Offer!$C$5<>"",Offer!$C$5,"[NAME]"))&CHAR(10)&"FC Urban" | AK58: ="Hi "&IF(R58<>"",R58,F58&" team")&","&CHAR(10)&CHAR(10)&"Just bumping this up. The "&AE58&" pitch at "&Z58&" is still free "&IF(ISNUMBER(AD58),TEXT(AD58,"ddd d mmm")&", "&TEXT(AD58,"hh:mm"),"weekday evenings")&", "&IF(OR(AA58=8,AA58=11,AA58=18),"an ","a ")&AA58&"-minute walk from your office, "&IF(AF58<>"","£"&IF(AF58=INT(AF58),TEXT(AF58,"0"),TEXT(AF58,"0.00")),"[PRICE PER PLAYER]")&" a player. Happy to hold it for "&F58&" if someone on the team fancies organising a game."&IF(Offer!$C$7<>""," Spots are held until "&TEXT(Offer!$C$7,"dddd d mmmm")&".","")&" "&IF(Offer!$C$6<>"",Offer!$C$6,"[JOINING LINK]")&CHAR(10)&CHAR(10)&"Best,"&CHAR(10)&IF(AM58<>"",AM58,IF(Offer!$C$5<>"",Offer!$C$5,"[NAME]"))&CHAR(10)&"FC Urban" | AL58: =IF(AH58="","No email yet",IF(ISNUMBER(SEARCH("[",AJ58)),"Fill placeholders",IF(ISNUMBER(AD58),"Ready to send","Ready · no fixed slot")))
A59: 57 | B59: 2 | C59: Law firm | D59: City of London | E59: Orrick, Herrington & Sutcliffe (Europe) LLP | F59: Orrick, Herrington & Sutcliffe | G59: https://www.orrick.com | H59: london@orrick.com | I59: general | J59: Open page | K59: OC347108 | L59: Open | M59: Full | N59: 40004 | O59: 9Th Floor, 107 Cheapside, London | P59: EC2V 6DN | Q59: No | W59: City of London School (EC4V 3AL) | X59: 9 | Z59: City of London School (EC4V 3AL) | AA59: 9 | AB59: =IFERROR(INDEX(Venues!$E$2:$E$17,MATCH(Z59,Venues!$A$2:$A$17,0)),"Not checked") | AC59: =IFERROR(INDEX(Venues!$F$2:$F$17,MATCH(Z59,Venues!$A$2:$A$17,0)),0) | AD59: =IFERROR(INDEX(Venues!$M$2:$M$17,MATCH(Z59,Venues!$A$2:$A$17,0)),"") | AE59: =IFERROR(INDEX(Venues!$N$2:$N$17,MATCH(Z59,Venues!$A$2:$A$17,0)),"5-a-side") | AF59: =IF(Offer!$C$4="","",Offer!$C$4) | AG59: =Z59&" ("&AA59&" min walk) · "&IF(ISNUMBER(AD59),TEXT(AD59,"ddd d mmm, hh:mm"),"slot to confirm with venue")&" · "&AE59&" · "&IF(AF59<>"","£"&TEXT(AF59,"0.00")&" pp","price TBC") | AH59: =IF(U59<>"",U59,IF(H59<>"",H59,"")) | AI59: ="After-work football for "&F59&" · "&Z59&", "&AA59&" min from your office" | AJ59: ="Hi "&IF(R59<>"",R59,F59&" team")&","&CHAR(10)&CHAR(10)&"I'm "&IF(AM59<>"",AM59,IF(Offer!$C$5<>"",Offer!$C$5,"[NAME]"))&" from FC Urban. We organise after-work football for teams in the City and Canary Wharf."&CHAR(10)&CHAR(10)&"We have a "&AE59&" pitch at "&Z59&", "&IF(OR(AA59=8,AA59=11,AA59=18),"an ","a ")&AA59&"-minute walk from your "&P59&" office, "&IF(ISNUMBER(AD59),"on "&TEXT(AD59,"dddd d mmmm")&" at "&TEXT(AD59,"hh:mm"),"on a weekday evening that suits your team")&". It's "&IF(AF59<>"","£"&IF(AF59=INT(AF59),TEXT(AF59,"0"),TEXT(AF59,"0.00")),"[PRICE PER PLAYER]")&" a player and we handle the pitch booking, sign-ups and payments, so all it takes is one person sharing a link with the team."&CHAR(10)&CHAR(10)&"It works well as a team social or "&IF(ISNUMBER(SEARCH(LEFT(F59,1),"AEIOU")),"an ","a ")&F59&" vs clients game. Would your team be up for it, or is there someone who'd enjoy organising it?"&IF(Offer!$C$7<>""," Spots are held until "&TEXT(Offer!$C$7,"dddd d mmmm")&".","")&" "&IF(Offer!$C$6<>"",Offer!$C$6,"[JOINING LINK]")&CHAR(10)&CHAR(10)&"Best,"&CHAR(10)&IF(AM59<>"",AM59,IF(Offer!$C$5<>"",Offer!$C$5,"[NAME]"))&CHAR(10)&"FC Urban" | AK59: ="Hi "&IF(R59<>"",R59,F59&" team")&","&CHAR(10)&CHAR(10)&"Just bumping this up. The "&AE59&" pitch at "&Z59&" is still free "&IF(ISNUMBER(AD59),TEXT(AD59,"ddd d mmm")&", "&TEXT(AD59,"hh:mm"),"weekday evenings")&", "&IF(OR(AA59=8,AA59=11,AA59=18),"an ","a ")&AA59&"-minute walk from your office, "&IF(AF59<>"","£"&IF(AF59=INT(AF59),TEXT(AF59,"0"),TEXT(AF59,"0.00")),"[PRICE PER PLAYER]")&" a player. Happy to hold it for "&F59&" if someone on the team fancies organising a game."&IF(Offer!$C$7<>""," Spots are held until "&TEXT(Offer!$C$7,"dddd d mmmm")&".","")&" "&IF(Offer!$C$6<>"",Offer!$C$6,"[JOINING LINK]")&CHAR(10)&CHAR(10)&"Best,"&CHAR(10)&IF(AM59<>"",AM59,IF(Offer!$C$5<>"",Offer!$C$5,"[NAME]"))&CHAR(10)&"FC Urban" | AL59: =IF(AH59="","No email yet",IF(ISNUMBER(SEARCH("[",AJ59)),"Fill placeholders",IF(ISNUMBER(AD59),"Ready to send","Ready · no fixed slot")))
A60: 58 | B60: 2 | C60: Law firm | D60: City of London | E60: National Legal Service Limited | F60: National Legal Service | G60: https://nationallegalservice.co.uk | H60: info@nationallegalservice.co.uk | I60: general | J60: Open page | K60: 10786983 | L60: Open | M60: Full | N60: 42879 | O60: Dowgate Hill House, 14/16 Dowgate Hill, London | P60: EC4R 2SU | Q60: No | W60: City of London School (EC4V 3AL) | X60: 9 | Y60: Marlborough Sports Garden (SE1 1SD) (13.9) | Z60: City of London School (EC4V 3AL) | AA60: 9 | AB60: =IFERROR(INDEX(Venues!$E$2:$E$17,MATCH(Z60,Venues!$A$2:$A$17,0)),"Not checked") | AC60: =IFERROR(INDEX(Venues!$F$2:$F$17,MATCH(Z60,Venues!$A$2:$A$17,0)),0) | AD60: =IFERROR(INDEX(Venues!$M$2:$M$17,MATCH(Z60,Venues!$A$2:$A$17,0)),"") | AE60: =IFERROR(INDEX(Venues!$N$2:$N$17,MATCH(Z60,Venues!$A$2:$A$17,0)),"5-a-side") | AF60: =IF(Offer!$C$4="","",Offer!$C$4) | AG60: =Z60&" ("&AA60&" min walk) · "&IF(ISNUMBER(AD60),TEXT(AD60,"ddd d mmm, hh:mm"),"slot to confirm with venue")&" · "&AE60&" · "&IF(AF60<>"","£"&TEXT(AF60,"0.00")&" pp","price TBC") | AH60: =IF(U60<>"",U60,IF(H60<>"",H60,"")) | AI60: ="After-work football for "&F60&" · "&Z60&", "&AA60&" min from your office" | AJ60: ="Hi "&IF(R60<>"",R60,F60&" team")&","&CHAR(10)&CHAR(10)&"I'm "&IF(AM60<>"",AM60,IF(Offer!$C$5<>"",Offer!$C$5,"[NAME]"))&" from FC Urban. We organise after-work football for teams in the City and Canary Wharf."&CHAR(10)&CHAR(10)&"We have a "&AE60&" pitch at "&Z60&", "&IF(OR(AA60=8,AA60=11,AA60=18),"an ","a ")&AA60&"-minute walk from your "&P60&" office, "&IF(ISNUMBER(AD60),"on "&TEXT(AD60,"dddd d mmmm")&" at "&TEXT(AD60,"hh:mm"),"on a weekday evening that suits your team")&". It's "&IF(AF60<>"","£"&IF(AF60=INT(AF60),TEXT(AF60,"0"),TEXT(AF60,"0.00")),"[PRICE PER PLAYER]")&" a player and we handle the pitch booking, sign-ups and payments, so all it takes is one person sharing a link with the team."&CHAR(10)&CHAR(10)&"It works well as a team social or "&IF(ISNUMBER(SEARCH(LEFT(F60,1),"AEIOU")),"an ","a ")&F60&" vs clients game. Would your team be up for it, or is there someone who'd enjoy organising it?"&IF(Offer!$C$7<>""," Spots are held until "&TEXT(Offer!$C$7,"dddd d mmmm")&".","")&" "&IF(Offer!$C$6<>"",Offer!$C$6,"[JOINING LINK]")&CHAR(10)&CHAR(10)&"Best,"&CHAR(10)&IF(AM60<>"",AM60,IF(Offer!$C$5<>"",Offer!$C$5,"[NAME]"))&CHAR(10)&"FC Urban" | AK60: ="Hi "&IF(R60<>"",R60,F60&" team")&","&CHAR(10)&CHAR(10)&"Just bumping this up. The "&AE60&" pitch at "&Z60&" is still free "&IF(ISNUMBER(AD60),TEXT(AD60,"ddd d mmm")&", "&TEXT(AD60,"hh:mm"),"weekday evenings")&", "&IF(OR(AA60=8,AA60=11,AA60=18),"an ","a ")&AA60&"-minute walk from your office, "&IF(AF60<>"","£"&IF(AF60=INT(AF60),TEXT(AF60,"0"),TEXT(AF60,"0.00")),"[PRICE PER PLAYER]")&" a player. Happy to hold it for "&F60&" if someone on the team fancies organising a game."&IF(Offer!$C$7<>""," Spots are held until "&TEXT(Offer!$C$7,"dddd d mmmm")&".","")&" "&IF(Offer!$C$6<>"",Offer!$C$6,"[JOINING LINK]")&CHAR(10)&CHAR(10)&"Best,"&CHAR(10)&IF(AM60<>"",AM60,IF(Offer!$C$5<>"",Offer!$C$5,"[NAME]"))&CHAR(10)&"FC Urban" | AL60: =IF(AH60="","No email yet",IF(ISNUMBER(SEARCH("[",AJ60)),"Fill placeholders",IF(ISNUMBER(AD60),"Ready to send","Ready · no fixed slot")))
A61: 59 | B61: 2 | C61: Law firm | D61: City of London | E61: Marriott Harrison LLP | F61: Marriott Harrison | G61: https://www.marriottharrison.com | H61: enquiries@marriottharrison.com | I61: general | J61: Open page | K61: OC372774 | L61: Open | M61: Full | N61: 40962 | O61: 80 Cheapside, London | P61: EC2V 6EE | Q61: No | W61: City of London School (EC4V 3AL) | X61: 10 | Y61: Marlborough Sports Garden (SE1 1SD) (18.4) | Z61: City of London School (EC4V 3AL) | AA61: 10 | AB61: =IFERROR(INDEX(Venues!$E$2:$E$17,MATCH(Z61,Venues!$A$2:$A$17,0)),"Not checked") | AC61: =IFERROR(INDEX(Venues!$F$2:$F$17,MATCH(Z61,Venues!$A$2:$A$17,0)),0) | AD61: =IFERROR(INDEX(Venues!$M$2:$M$17,MATCH(Z61,Venues!$A$2:$A$17,0)),"") | AE61: =IFERROR(INDEX(Venues!$N$2:$N$17,MATCH(Z61,Venues!$A$2:$A$17,0)),"5-a-side") | AF61: =IF(Offer!$C$4="","",Offer!$C$4) | AG61: =Z61&" ("&AA61&" min walk) · "&IF(ISNUMBER(AD61),TEXT(AD61,"ddd d mmm, hh:mm"),"slot to confirm with venue")&" · "&AE61&" · "&IF(AF61<>"","£"&TEXT(AF61,"0.00")&" pp","price TBC") | AH61: =IF(U61<>"",U61,IF(H61<>"",H61,"")) | AI61: ="After-work football for "&F61&" · "&Z61&", "&AA61&" min from your office" | AJ61: ="Hi "&IF(R61<>"",R61,F61&" team")&","&CHAR(10)&CHAR(10)&"I'm "&IF(AM61<>"",AM61,IF(Offer!$C$5<>"",Offer!$C$5,"[NAME]"))&" from FC Urban. We organise after-work football for teams in the City and Canary Wharf."&CHAR(10)&CHAR(10)&"We have a "&AE61&" pitch at "&Z61&", "&IF(OR(AA61=8,AA61=11,AA61=18),"an ","a ")&AA61&"-minute walk from your "&P61&" office, "&IF(ISNUMBER(AD61),"on "&TEXT(AD61,"dddd d mmmm")&" at "&TEXT(AD61,"hh:mm"),"on a weekday evening that suits your team")&". It's "&IF(AF61<>"","£"&IF(AF61=INT(AF61),TEXT(AF61,"0"),TEXT(AF61,"0.00")),"[PRICE PER PLAYER]")&" a player and we handle the pitch booking, sign-ups and payments, so all it takes is one person sharing a link with the team."&CHAR(10)&CHAR(10)&"It works well as a team social or "&IF(ISNUMBER(SEARCH(LEFT(F61,1),"AEIOU")),"an ","a ")&F61&" vs clients game. Would your team be up for it, or is there someone who'd enjoy organising it?"&IF(Offer!$C$7<>""," Spots are held until "&TEXT(Offer!$C$7,"dddd d mmmm")&".","")&" "&IF(Offer!$C$6<>"",Offer!$C$6,"[JOINING LINK]")&CHAR(10)&CHAR(10)&"Best,"&CHAR(10)&IF(AM61<>"",AM61,IF(Offer!$C$5<>"",Offer!$C$5,"[NAME]"))&CHAR(10)&"FC Urban" | AK61: ="Hi "&IF(R61<>"",R61,F61&" team")&","&CHAR(10)&CHAR(10)&"Just bumping this up. The "&AE61&" pitch at "&Z61&" is still free "&IF(ISNUMBER(AD61),TEXT(AD61,"ddd d mmm")&", "&TEXT(AD61,"hh:mm"),"weekday evenings")&", "&IF(OR(AA61=8,AA61=11,AA61=18),"an ","a ")&AA61&"-minute walk from your office, "&IF(AF61<>"","£"&IF(AF61=INT(AF61),TEXT(AF61,"0"),TEXT(AF61,"0.00")),"[PRICE PER PLAYER]")&" a player. Happy to hold it for "&F61&" if someone on the team fancies organising a game."&IF(Offer!$C$7<>""," Spots are held until "&TEXT(Offer!$C$7,"dddd d mmmm")&".","")&" "&IF(Offer!$C$6<>"",Offer!$C$6,"[JOINING LINK]")&CHAR(10)&CHAR(10)&"Best,"&CHAR(10)&IF(AM61<>"",AM61,IF(Offer!$C$5<>"",Offer!$C$5,"[NAME]"))&CHAR(10)&"FC Urban" | AL61: =IF(AH61="","No email yet",IF(ISNUMBER(SEARCH("[",AJ61)),"Fill placeholders",IF(ISNUMBER(AD61),"Ready to send","Ready · no fixed slot")))
A62: 60 | B62: 2 | C62: Law firm | D62: City of London | E62: Watson Farley & Williams LLP | F62: Watson Farley & Williams | G62: https://www.wfw.com | H62: info@wfw.com | I62: general | J62: Open page | K62: OC312252 | L62: Open | M62: Full | N62: 38428 | O62: 15 Appold Street, London | P62: EC2A 2HB | Q62: No | W62: Shoreditch Powerleague | X62: 10 | Y62: Liverpool St - Attlee Centre (12.1); Finsbury Leisure Centre (EC1V 3PU) (17.3) | Z62: Shoreditch Powerleague | AA62: 10 | AB62: =IFERROR(INDEX(Venues!$E$2:$E$17,MATCH(Z62,Venues!$A$2:$A$17,0)),"Not checked") | AC62: =IFERROR(INDEX(Venues!$F$2:$F$17,MATCH(Z62,Venues!$A$2:$A$17,0)),0) | AD62: =IFERROR(INDEX(Venues!$M$2:$M$17,MATCH(Z62,Venues!$A$2:$A$17,0)),"") | AE62: =IFERROR(INDEX(Venues!$N$2:$N$17,MATCH(Z62,Venues!$A$2:$A$17,0)),"5-a-side") | AF62: =IF(Offer!$C$4="","",Offer!$C$4) | AG62: =Z62&" ("&AA62&" min walk) · "&IF(ISNUMBER(AD62),TEXT(AD62,"ddd d mmm, hh:mm"),"slot to confirm with venue")&" · "&AE62&" · "&IF(AF62<>"","£"&TEXT(AF62,"0.00")&" pp","price TBC") | AH62: =IF(U62<>"",U62,IF(H62<>"",H62,"")) | AI62: ="After-work football for "&F62&" · "&Z62&", "&AA62&" min from your office" | AJ62: ="Hi "&IF(R62<>"",R62,F62&" team")&","&CHAR(10)&CHAR(10)&"I'm "&IF(AM62<>"",AM62,IF(Offer!$C$5<>"",Offer!$C$5,"[NAME]"))&" from FC Urban. We organise after-work football for teams in the City and Canary Wharf."&CHAR(10)&CHAR(10)&"We have a "&AE62&" pitch at "&Z62&", "&IF(OR(AA62=8,AA62=11,AA62=18),"an ","a ")&AA62&"-minute walk from your "&P62&" office, "&IF(ISNUMBER(AD62),"on "&TEXT(AD62,"dddd d mmmm")&" at "&TEXT(AD62,"hh:mm"),"on a weekday evening that suits your team")&". It's "&IF(AF62<>"","£"&IF(AF62=INT(AF62),TEXT(AF62,"0"),TEXT(AF62,"0.00")),"[PRICE PER PLAYER]")&" a player and we handle the pitch booking, sign-ups and payments, so all it takes is one person sharing a link with the team."&CHAR(10)&CHAR(10)&"It works well as a team social or "&IF(ISNUMBER(SEARCH(LEFT(F62,1),"AEIOU")),"an ","a ")&F62&" vs clients game. Would your team be up for it, or is there someone who'd enjoy organising it?"&IF(Offer!$C$7<>""," Spots are held until "&TEXT(Offer!$C$7,"dddd d mmmm")&".","")&" "&IF(Offer!$C$6<>"",Offer!$C$6,"[JOINING LINK]")&CHAR(10)&CHAR(10)&"Best,"&CHAR(10)&IF(AM62<>"",AM62,IF(Offer!$C$5<>"",Offer!$C$5,"[NAME]"))&CHAR(10)&"FC Urban" | AK62: ="Hi "&IF(R62<>"",R62,F62&" team")&","&CHAR(10)&CHAR(10)&"Just bumping this up. The "&AE62&" pitch at "&Z62&" is still free "&IF(ISNUMBER(AD62),TEXT(AD62,"ddd d mmm")&", "&TEXT(AD62,"hh:mm"),"weekday evenings")&", "&IF(OR(AA62=8,AA62=11,AA62=18),"an ","a ")&AA62&"-minute walk from your office, "&IF(AF62<>"","£"&IF(AF62=INT(AF62),TEXT(AF62,"0"),TEXT(AF62,"0.00")),"[PRICE PER PLAYER]")&" a player. Happy to hold it for "&F62&" if someone on the team fancies organising a game."&IF(Offer!$C$7<>""," Spots are held until "&TEXT(Offer!$C$7,"dddd d mmmm")&".","")&" "&IF(Offer!$C$6<>"",Offer!$C$6,"[JOINING LINK]")&CHAR(10)&CHAR(10)&"Best,"&CHAR(10)&IF(AM62<>"",AM62,IF(Offer!$C$5<>"",Offer!$C$5,"[NAME]"))&CHAR(10)&"FC Urban" | AL62: =IF(AH62="","No email yet",IF(ISNUMBER(SEARCH("[",AJ62)),"Fill placeholders",IF(ISNUMBER(AD62),"Ready to send","Ready · no fixed slot")))
A63: 61 | B63: 2 | C63: Law firm | D63: City of London | E63: Sacker & Partners LLP | F63: Sacker & Partners | G63: https://www.sackers.com | H63: enquiries@sackers.com | I63: general | J63: Open page | K63: OC308089 | L63: Open | M63: Full | N63: 38131 | O63: 20 Gresham Street, London | P63: EC2V 7JE | Q63: No | W63: City of London School (EC4V 3AL) | X63: 10 | Z63: City of London School (EC4V 3AL) | AA63: 10 | AB63: =IFERROR(INDEX(Venues!$E$2:$E$17,MATCH(Z63,Venues!$A$2:$A$17,0)),"Not checked") | AC63: =IFERROR(INDEX(Venues!$F$2:$F$17,MATCH(Z63,Venues!$A$2:$A$17,0)),0) | AD63: =IFERROR(INDEX(Venues!$M$2:$M$17,MATCH(Z63,Venues!$A$2:$A$17,0)),"") | AE63: =IFERROR(INDEX(Venues!$N$2:$N$17,MATCH(Z63,Venues!$A$2:$A$17,0)),"5-a-side") | AF63: =IF(Offer!$C$4="","",Offer!$C$4) | AG63: =Z63&" ("&AA63&" min walk) · "&IF(ISNUMBER(AD63),TEXT(AD63,"ddd d mmm, hh:mm"),"slot to confirm with venue")&" · "&AE63&" · "&IF(AF63<>"","£"&TEXT(AF63,"0.00")&" pp","price TBC") | AH63: =IF(U63<>"",U63,IF(H63<>"",H63,"")) | AI63: ="After-work football for "&F63&" · "&Z63&", "&AA63&" min from your office" | AJ63: ="Hi "&IF(R63<>"",R63,F63&" team")&","&CHAR(10)&CHAR(10)&"I'm "&IF(AM63<>"",AM63,IF(Offer!$C$5<>"",Offer!$C$5,"[NAME]"))&" from FC Urban. We organise after-work football for teams in the City and Canary Wharf."&CHAR(10)&CHAR(10)&"We have a "&AE63&" pitch at "&Z63&", "&IF(OR(AA63=8,AA63=11,AA63=18),"an ","a ")&AA63&"-minute walk from your "&P63&" office, "&IF(ISNUMBER(AD63),"on "&TEXT(AD63,"dddd d mmmm")&" at "&TEXT(AD63,"hh:mm"),"on a weekday evening that suits your team")&". It's "&IF(AF63<>"","£"&IF(AF63=INT(AF63),TEXT(AF63,"0"),TEXT(AF63,"0.00")),"[PRICE PER PLAYER]")&" a player and we handle the pitch booking, sign-ups and payments, so all it takes is one person sharing a link with the team."&CHAR(10)&CHAR(10)&"It works well as a team social or "&IF(ISNUMBER(SEARCH(LEFT(F63,1),"AEIOU")),"an ","a ")&F63&" vs clients game. Would your team be up for it, or is there someone who'd enjoy organising it?"&IF(Offer!$C$7<>""," Spots are held until "&TEXT(Offer!$C$7,"dddd d mmmm")&".","")&" "&IF(Offer!$C$6<>"",Offer!$C$6,"[JOINING LINK]")&CHAR(10)&CHAR(10)&"Best,"&CHAR(10)&IF(AM63<>"",AM63,IF(Offer!$C$5<>"",Offer!$C$5,"[NAME]"))&CHAR(10)&"FC Urban" | AK63: ="Hi "&IF(R63<>"",R63,F63&" team")&","&CHAR(10)&CHAR(10)&"Just bumping this up. The "&AE63&" pitch at "&Z63&" is still free "&IF(ISNUMBER(AD63),TEXT(AD63,"ddd d mmm")&", "&TEXT(AD63,"hh:mm"),"weekday evenings")&", "&IF(OR(AA63=8,AA63=11,AA63=18),"an ","a ")&AA63&"-minute walk from your office, "&IF(AF63<>"","£"&IF(AF63=INT(AF63),TEXT(AF63,"0"),TEXT(AF63,"0.00")),"[PRICE PER PLAYER]")&" a player. Happy to hold it for "&F63&" if someone on the team fancies organising a game."&IF(Offer!$C$7<>""," Spots are held until "&TEXT(Offer!$C$7,"dddd d mmmm")&".","")&" "&IF(Offer!$C$6<>"",Offer!$C$6,"[JOINING LINK]")&CHAR(10)&CHAR(10)&"Best,"&CHAR(10)&IF(AM63<>"",AM63,IF(Offer!$C$5<>"",Offer!$C$5,"[NAME]"))&CHAR(10)&"FC Urban" | AL63: =IF(AH63="","No email yet",IF(ISNUMBER(SEARCH("[",AJ63)),"Fill placeholders",IF(ISNUMBER(AD63),"Ready to send","Ready · no fixed slot")))
A64: 62 | B64: 2 | C64: Law firm | D64: City of London | E64: Haynes and Boone Cdg LLP | F64: Haynes and Boone Cdg | G64: https://www.haynesboone.com | H64: london@haynesboone.com | I64: general | J64: Open page | K64: OC317056 | L64: Open | M64: Medium | N64: 38723 | O64: Alder Castle, Noble Street, London | P64: EC2V 7JX | Q64: No | W64: City of London School (EC4V 3AL) | X64: 11 | Y64: Finsbury Leisure Centre (EC1V 3PU) (17) | Z64: City of London School (EC4V 3AL) | AA64: 11 | AB64: =IFERROR(INDEX(Venues!$E$2:$E$17,MATCH(Z64,Venues!$A$2:$A$17,0)),"Not checked") | AC64: =IFERROR(INDEX(Venues!$F$2:$F$17,MATCH(Z64,Venues!$A$2:$A$17,0)),0) | AD64: =IFERROR(INDEX(Venues!$M$2:$M$17,MATCH(Z64,Venues!$A$2:$A$17,0)),"") | AE64: =IFERROR(INDEX(Venues!$N$2:$N$17,MATCH(Z64,Venues!$A$2:$A$17,0)),"5-a-side") | AF64: =IF(Offer!$C$4="","",Offer!$C$4) | AG64: =Z64&" ("&AA64&" min walk) · "&IF(ISNUMBER(AD64),TEXT(AD64,"ddd d mmm, hh:mm"),"slot to confirm with venue")&" · "&AE64&" · "&IF(AF64<>"","£"&TEXT(AF64,"0.00")&" pp","price TBC") | AH64: =IF(U64<>"",U64,IF(H64<>"",H64,"")) | AI64: ="After-work football for "&F64&" · "&Z64&", "&AA64&" min from your office" | AJ64: ="Hi "&IF(R64<>"",R64,F64&" team")&","&CHAR(10)&CHAR(10)&"I'm "&IF(AM64<>"",AM64,IF(Offer!$C$5<>"",Offer!$C$5,"[NAME]"))&" from FC Urban. We organise after-work football for teams in the City and Canary Wharf."&CHAR(10)&CHAR(10)&"We have a "&AE64&" pitch at "&Z64&", "&IF(OR(AA64=8,AA64=11,AA64=18),"an ","a ")&AA64&"-minute walk from your "&P64&" office, "&IF(ISNUMBER(AD64),"on "&TEXT(AD64,"dddd d mmmm")&" at "&TEXT(AD64,"hh:mm"),"on a weekday evening that suits your team")&". It's "&IF(AF64<>"","£"&IF(AF64=INT(AF64),TEXT(AF64,"0"),TEXT(AF64,"0.00")),"[PRICE PER PLAYER]")&" a player and we handle the pitch booking, sign-ups and payments, so all it takes is one person sharing a link with the team."&CHAR(10)&CHAR(10)&"It works well as a team social or "&IF(ISNUMBER(SEARCH(LEFT(F64,1),"AEIOU")),"an ","a ")&F64&" vs clients game. Would your team be up for it, or is there someone who'd enjoy organising it?"&IF(Offer!$C$7<>""," Spots are held until "&TEXT(Offer!$C$7,"dddd d mmmm")&".","")&" "&IF(Offer!$C$6<>"",Offer!$C$6,"[JOINING LINK]")&CHAR(10)&CHAR(10)&"Best,"&CHAR(10)&IF(AM64<>"",AM64,IF(Offer!$C$5<>"",Offer!$C$5,"[NAME]"))&CHAR(10)&"FC Urban" | AK64: ="Hi "&IF(R64<>"",R64,F64&" team")&","&CHAR(10)&CHAR(10)&"Just bumping this up. The "&AE64&" pitch at "&Z64&" is still free "&IF(ISNUMBER(AD64),TEXT(AD64,"ddd d mmm")&", "&TEXT(AD64,"hh:mm"),"weekday evenings")&", "&IF(OR(AA64=8,AA64=11,AA64=18),"an ","a ")&AA64&"-minute walk from your office, "&IF(AF64<>"","£"&IF(AF64=INT(AF64),TEXT(AF64,"0"),TEXT(AF64,"0.00")),"[PRICE PER PLAYER]")&" a player. Happy to hold it for "&F64&" if someone on the team fancies organising a game."&IF(Offer!$C$7<>""," Spots are held until "&TEXT(Offer!$C$7,"dddd d mmmm")&".","")&" "&IF(Offer!$C$6<>"",Offer!$C$6,"[JOINING LINK]")&CHAR(10)&CHAR(10)&"Best,"&CHAR(10)&IF(AM64<>"",AM64,IF(Offer!$C$5<>"",Offer!$C$5,"[NAME]"))&CHAR(10)&"FC Urban" | AL64: =IF(AH64="","No email yet",IF(ISNUMBER(SEARCH("[",AJ64)),"Fill placeholders",IF(ISNUMBER(AD64),"Ready to send","Ready · no fixed slot")))
