Workbook

Sheet Outreach
A1: Lead | M1: Tagged venue | R1: Fallback pitch | W1: Lead with (message) | AB1: Tracking — fill in
A2: # | B2: Tier | C2: Segment | D2: List | E2: Business | F2: Industry | G2: Email | H2: Email type | I2: Phone | J2: Website | K2: Address | L2: Postcode | M2: Tagged venue | N2: Walk (min) | O2: Status | P2: Open slots | Q2: Earliest slot | R2: Bookable nearby? | S2: Fallback venue | T2: Fallback slot | U2: Format | V2: Cost per player at cost (£) | W2: Lead with: venue | X2: Lead with: slot | Y2: Lead with: format | Z2: Lead with: price per player (£) | AA2: Lead-with line (for drafting) | AB2: Owner | AC2: Channel | AD2: Contacted on | AE2: Replied | AF2: Call booked | AG2: Group created | AH2: First game booked | AI2: Second game booked | AJ2: Sees us as competitor? | AK2: Objection (exact words) | AL2: Next step | AM2: Notes
A3: 1 | B3: 1 · E2 Haggerston | C3: Hospitality | D3: Local businesses | E3: E. Pellicci | F3: amenity: cafe | G3: epelliccicafe@gmail.com | H3: openstreetmap_tag | I3: +44 20 7739 4873 | J3: https://epellicci.co.uk/ | K3: Bethnal Green Road 332, London | L3: E2 0AG | M3: Stepney 3G | N3: 18 | O3: =IFERROR(INDEX(Venues!$C$2:$C$10,MATCH(M3,Venues!$A$2:$A$10,0)),"Not checked") | P3: =IFERROR(INDEX(Venues!$D$2:$D$10,MATCH(M3,Venues!$A$2:$A$10,0)),0) | Q3: =IFERROR(INDEX(Venues!$E$2:$E$10,MATCH(M3,Venues!$A$2:$A$10,0)),"") | R3: =IF(P3>0,"Yes","No") | S3: COLA Shoreditch Park | T3: =IFERROR(INDEX(Venues!$E$2:$E$10,MATCH(S3,Venues!$A$2:$A$10,0)),"") | U3: =IFERROR(INDEX(Venues!$F$2:$F$10,MATCH(S3,Venues!$A$2:$A$10,0)),"") | V3: =IFERROR(INDEX(Venues!$H$2:$H$10,MATCH(S3,Venues!$A$2:$A$10,0)),"") | W3: =IF('Pilot offer'!$C$24="Yes",'Pilot offer'!$C$3,S3) | X3: =IF('Pilot offer'!$C$24="Yes",'Pilot offer'!$C$5+'Pilot offer'!$C$6,T3) | Y3: =IF('Pilot offer'!$C$24="Yes",'Pilot offer'!$C$8,U3) | Z3: =IF('Pilot offer'!$C$24="Yes",'Pilot offer'!$C$11,"") | AA3: =IF(X3="","",W3&" · "&TEXT(X3,"ddd d mmm, hh:mm")&" · "&Y3&IF(Z3<>""," · £"&TEXT(Z3,"0.00")&" per player"," · price TBC (cost £"&TEXT(V3,"0.00")&" pp)"))
A4: 2 | B4: 1 · E2 Haggerston | C4: Retail | D4: Local businesses | E4: Trotters Jewellers | F4: shop: jewelry | G4: info@trottersjewellers.com | H4: general | I4: +44 7399 606868 | J4: http://www.trottersjewellers.com/ | K4: Bethnal Green Road 350, London | L4: E2 0AH | M4: Stepney 3G | N4: 17 | O4: =IFERROR(INDEX(Venues!$C$2:$C$10,MATCH(M4,Venues!$A$2:$A$10,0)),"Not checked") | P4: =IFERROR(INDEX(Venues!$D$2:$D$10,MATCH(M4,Venues!$A$2:$A$10,0)),0) | Q4: =IFERROR(INDEX(Venues!$E$2:$E$10,MATCH(M4,Venues!$A$2:$A$10,0)),"") | R4: =IF(P4>0,"Yes","No") | S4: COLA Shoreditch Park | T4: =IFERROR(INDEX(Venues!$E$2:$E$10,MATCH(S4,Venues!$A$2:$A$10,0)),"") | U4: =IFERROR(INDEX(Venues!$F$2:$F$10,MATCH(S4,Venues!$A$2:$A$10,0)),"") | V4: =IFERROR(INDEX(Venues!$H$2:$H$10,MATCH(S4,Venues!$A$2:$A$10,0)),"") | W4: =IF('Pilot offer'!$C$24="Yes",'Pilot offer'!$C$3,S4) | X4: =IF('Pilot offer'!$C$24="Yes",'Pilot offer'!$C$5+'Pilot offer'!$C$6,T4) | Y4: =IF('Pilot offer'!$C$24="Yes",'Pilot offer'!$C$8,U4) | Z4: =IF('Pilot offer'!$C$24="Yes",'Pilot offer'!$C$11,"") | AA4: =IF(X4="","",W4&" · "&TEXT(X4,"ddd d mmm, hh:mm")&" · "&Y4&IF(Z4<>""," · £"&TEXT(Z4,"0.00")&" per player"," · price TBC (cost £"&TEXT(V4,"0.00")&" pp)"))
A5: 3 | B5: 1 · E2 Haggerston | C5: Hospitality | D5: Local businesses | E5: The Old George | F5: amenity: pub | G5: oldgeorge@anticlondon.com | H5: openstreetmap_tag | I5: +44 20 7033 9726 | J5: https://www.crafted-social.co.uk/old-george-bethnal-green | K5: Bethnal Green Road 379, London | L5: E2 0AN | M5: Stepney 3G | N5: 15 | O5: =IFERROR(INDEX(Venues!$C$2:$C$10,MATCH(M5,Venues!$A$2:$A$10,0)),"Not checked") | P5: =IFERROR(INDEX(Venues!$D$2:$D$10,MATCH(M5,Venues!$A$2:$A$10,0)),0) | Q5: =IFERROR(INDEX(Venues!$E$2:$E$10,MATCH(M5,Venues!$A$2:$A$10,0)),"") | R5: =IF(P5>0,"Yes","No") | S5: COLA Shoreditch Park | T5: =IFERROR(INDEX(Venues!$E$2:$E$10,MATCH(S5,Venues!$A$2:$A$10,0)),"") | U5: =IFERROR(INDEX(Venues!$F$2:$F$10,MATCH(S5,Venues!$A$2:$A$10,0)),"") | V5: =IFERROR(INDEX(Venues!$H$2:$H$10,MATCH(S5,Venues!$A$2:$A$10,0)),"") | W5: =IF('Pilot offer'!$C$24="Yes",'Pilot offer'!$C$3,S5) | X5: =IF('Pilot offer'!$C$24="Yes",'Pilot offer'!$C$5+'Pilot offer'!$C$6,T5) | Y5: =IF('Pilot offer'!$C$24="Yes",'Pilot offer'!$C$8,U5) | Z5: =IF('Pilot offer'!$C$24="Yes",'Pilot offer'!$C$11,"") | AA5: =IF(X5="","",W5&" · "&TEXT(X5,"ddd d mmm, hh:mm")&" · "&Y5&IF(Z5<>""," · £"&TEXT(Z5,"0.00")&" per player"," · price TBC (cost £"&TEXT(V5,"0.00")&" pp)"))
A6: 4 | B6: 1 · E2 Haggerston | C6: Hospitality | D6: Local businesses | E6: The Sun Tavern | F6: amenity: pub | G6: info@thesuntavern.co.uk | H6: general | J6: https://www.thesuntavern.co.uk/ | K6: Bethnal Green Road 441, London | L6: E2 0AN | M6: Stepney 3G | N6: 13 | O6: =IFERROR(INDEX(Venues!$C$2:$C$10,MATCH(M6,Venues!$A$2:$A$10,0)),"Not checked") | P6: =IFERROR(INDEX(Venues!$D$2:$D$10,MATCH(M6,Venues!$A$2:$A$10,0)),0) | Q6: =IFERROR(INDEX(Venues!$E$2:$E$10,MATCH(M6,Venues!$A$2:$A$10,0)),"") | R6: =IF(P6>0,"Yes","No") | S6: COLA Shoreditch Park | T6: =IFERROR(INDEX(Venues!$E$2:$E$10,MATCH(S6,Venues!$A$2:$A$10,0)),"") | U6: =IFERROR(INDEX(Venues!$F$2:$F$10,MATCH(S6,Venues!$A$2:$A$10,0)),"") | V6: =IFERROR(INDEX(Venues!$H$2:$H$10,MATCH(S6,Venues!$A$2:$A$10,0)),"") | W6: =IF('Pilot offer'!$C$24="Yes",'Pilot offer'!$C$3,S6) | X6: =IF('Pilot offer'!$C$24="Yes",'Pilot offer'!$C$5+'Pilot offer'!$C$6,T6) | Y6: =IF('Pilot offer'!$C$24="Yes",'Pilot offer'!$C$8,U6) | Z6: =IF('Pilot offer'!$C$24="Yes",'Pilot offer'!$C$11,"") | AA6: =IF(X6="","",W6&" · "&TEXT(X6,"ddd d mmm, hh:mm")&" · "&Y6&IF(Z6<>""," · £"&TEXT(Z6,"0.00")&" per player"," · price TBC (cost £"&TEXT(V6,"0.00")&" pp)"))
A7: 5 | B7: 1 · E2 Haggerston | C7: Hospitality | D7: Local businesses | E7: Hostelle | F7: tourism: hostel | G7: info@hostelle.co.uk | H7: general | I7: +44 20 7646 6671 | J7: https://www.hostelle.co.uk/ | K7: Bethnal Green Road 458, London | L7: E2 0EA | M7: Stepney 3G | N7: 12 | O7: =IFERROR(INDEX(Venues!$C$2:$C$10,MATCH(M7,Venues!$A$2:$A$10,0)),"Not checked") | P7: =IFERROR(INDEX(Venues!$D$2:$D$10,MATCH(M7,Venues!$A$2:$A$10,0)),0) | Q7: =IFERROR(INDEX(Venues!$E$2:$E$10,MATCH(M7,Venues!$A$2:$A$10,0)),"") | R7: =IF(P7>0,"Yes","No") | S7: COLA Shoreditch Park | T7: =IFERROR(INDEX(Venues!$E$2:$E$10,MATCH(S7,Venues!$A$2:$A$10,0)),"") | U7: =IFERROR(INDEX(Venues!$F$2:$F$10,MATCH(S7,Venues!$A$2:$A$10,0)),"") | V7: =IFERROR(INDEX(Venues!$H$2:$H$10,MATCH(S7,Venues!$A$2:$A$10,0)),"") | W7: =IF('Pilot offer'!$C$24="Yes",'Pilot offer'!$C$3,S7) | X7: =IF('Pilot offer'!$C$24="Yes",'Pilot offer'!$C$5+'Pilot offer'!$C$6,T7) | Y7: =IF('Pilot offer'!$C$24="Yes",'Pilot offer'!$C$8,U7) | Z7: =IF('Pilot offer'!$C$24="Yes",'Pilot offer'!$C$11,"") | AA7: =IF(X7="","",W7&" · "&TEXT(X7,"ddd d mmm, hh:mm")&" · "&Y7&IF(Z7<>""," · £"&TEXT(Z7,"0.00")&" per player"," · price TBC (cost £"&TEXT(V7,"0.00")&" pp)"))
A8: 6 | B8: 1 · E2 Haggerston | C8: Leisure & culture | D8: Local businesses | E8: Backyard Comedy Club | F8: amenity: theatre | G8: info@backyardcomedyclub.co.uk | H8: general | J8: https://backyardcomedyclub.co.uk/ | K8: Cambridge Heath Road 231, London | L8: E2 0EL | M8: Stepney 3G | N8: 9 | O8: =IFERROR(INDEX(Venues!$C$2:$C$10,MATCH(M8,Venues!$A$2:$A$10,0)),"Not checked") | P8: =IFERROR(INDEX(Venues!$D$2:$D$10,MATCH(M8,Venues!$A$2:$A$10,0)),0) | Q8: =IFERROR(INDEX(Venues!$E$2:$E$10,MATCH(M8,Venues!$A$2:$A$10,0)),"") | R8: =IF(P8>0,"Yes","No") | S8: COLA Shoreditch Park | T8: =IFERROR(INDEX(Venues!$E$2:$E$10,MATCH(S8,Venues!$A$2:$A$10,0)),"") | U8: =IFERROR(INDEX(Venues!$F$2:$F$10,MATCH(S8,Venues!$A$2:$A$10,0)),"") | V8: =IFERROR(INDEX(Venues!$H$2:$H$10,MATCH(S8,Venues!$A$2:$A$10,0)),"") | W8: =IF('Pilot offer'!$C$24="Yes",'Pilot offer'!$C$3,S8) | X8: =IF('Pilot offer'!$C$24="Yes",'Pilot offer'!$C$5+'Pilot offer'!$C$6,T8) | Y8: =IF('Pilot offer'!$C$24="Yes",'Pilot offer'!$C$8,U8) | Z8: =IF('Pilot offer'!$C$24="Yes",'Pilot offer'!$C$11,"") | AA8: =IF(X8="","",W8&" · "&TEXT(X8,"ddd d mmm, hh:mm")&" · "&Y8&IF(Z8<>""," · £"&TEXT(Z8,"0.00")&" per player"," · price TBC (cost £"&TEXT(V8,"0.00")&" pp)"))
A9: 7 | B9: 1 · E2 Haggerston | C9: Hospitality | D9: Local businesses | E9: Three Colts Tavern | F9: amenity: pub | G9: info@threecoltstavern.co.uk | H9: general | J9: https://www.threecoltstavern.co.uk/ | K9: Cambridge Heath Road 199, London | L9: E2 0EL | M9: Stepney 3G | N9: 8 | O9: =IFERROR(INDEX(Venues!$C$2:$C$10,MATCH(M9,Venues!$A$2:$A$10,0)),"Not checked") | P9: =IFERROR(INDEX(Venues!$D$2:$D$10,MATCH(M9,Venues!$A$2:$A$10,0)),0) | Q9: =IFERROR(INDEX(Venues!$E$2:$E$10,MATCH(M9,Venues!$A$2:$A$10,0)),"") | R9: =IF(P9>0,"Yes","No") | S9: COLA Shoreditch Park | T9: =IFERROR(INDEX(Venues!$E$2:$E$10,MATCH(S9,Venues!$A$2:$A$10,0)),"") | U9: =IFERROR(INDEX(Venues!$F$2:$F$10,MATCH(S9,Venues!$A$2:$A$10,0)),"") | V9: =IFERROR(INDEX(Venues!$H$2:$H$10,MATCH(S9,Venues!$A$2:$A$10,0)),"") | W9: =IF('Pilot offer'!$C$24="Yes",'Pilot offer'!$C$3,S9) | X9: =IF('Pilot offer'!$C$24="Yes",'Pilot offer'!$C$5+'Pilot offer'!$C$6,T9) | Y9: =IF('Pilot offer'!$C$24="Yes",'Pilot offer'!$C$8,U9) | Z9: =IF('Pilot offer'!$C$24="Yes",'Pilot offer'!$C$11,"") | AA9: =IF(X9="","",W9&" · "&TEXT(X9,"ddd d mmm, hh:mm")&" · "&Y9&IF(Z9<>""," · £"&TEXT(Z9,"0.00")&" per player"," · price TBC (cost £"&TEXT(V9,"0.00")&" pp)"))
A10: 8 | B10: 1 · E2 Haggerston | C10: Education | D10: Local businesses | E10: Darul Hadis Latifiah | F10: amenity: school | G10: info@darulhadis.org.uk | H10: general | I10: +44 20 8983 3663 | J10: https://www.darulhadis.org.uk/ | K10: Cornwall Avenue 1, London | L10: E2 0HW | M10: Stepney 3G | N10: 8 | O10: =IFERROR(INDEX(Venues!$C$2:$C$10,MATCH(M10,Venues!$A$2:$A$10,0)),"Not checked") | P10: =IFERROR(INDEX(Venues!$D$2:$D$10,MATCH(M10,Venues!$A$2:$A$10,0)),0) | Q10: =IFERROR(INDEX(Venues!$E$2:$E$10,MATCH(M10,Venues!$A$2:$A$10,0)),"") | R10: =IF(P10>0,"Yes","No") | S10: COLA Shoreditch Park | T10: =IFERROR(INDEX(Venues!$E$2:$E$10,MATCH(S10,Venues!$A$2:$A$10,0)),"") | U10: =IFERROR(INDEX(Venues!$F$2:$F$10,MATCH(S10,Venues!$A$2:$A$10,0)),"") | V10: =IFERROR(INDEX(Venues!$H$2:$H$10,MATCH(S10,Venues!$A$2:$A$10,0)),"") | W10: =IF('Pilot offer'!$C$24="Yes",'Pilot offer'!$C$3,S10) | X10: =IF('Pilot offer'!$C$24="Yes",'Pilot offer'!$C$5+'Pilot offer'!$C$6,T10) | Y10: =IF('Pilot offer'!$C$24="Yes",'Pilot offer'!$C$8,U10) | Z10: =IF('Pilot offer'!$C$24="Yes",'Pilot offer'!$C$11,"") | AA10: =IF(X10="","",W10&" · "&TEXT(X10,"ddd d mmm, hh:mm")&" · "&Y10&IF(Z10<>""," · £"&TEXT(Z10,"0.00")&" per player"," · price TBC (cost £"&TEXT(V10,"0.00")&" pp)"))
A11: 9 | B11: 1 · E2 Haggerston | C11: Retail | D11: Local businesses | E11: Quality Dry Cleaners | F11: shop: dry cleaning | G11: info@qualitydrycleaners.org.uk | H11: openstreetmap_tag | I11: +44 20 8983 4502 | J11: https://qualitydrycleaners.org.uk/ | K11: Globe Road 262, London | L11: E2 0JD | M11: Stepney 3G | N11: 9 | O11: =IFERROR(INDEX(Venues!$C$2:$C$10,MATCH(M11,Venues!$A$2:$A$10,0)),"Not checked") | P11: =IFERROR(INDEX(Venues!$D$2:$D$10,MATCH(M11,Venues!$A$2:$A$10,0)),0) | Q11: =IFERROR(INDEX(Venues!$E$2:$E$10,MATCH(M11,Venues!$A$2:$A$10,0)),"") | R11: =IF(P11>0,"Yes","No") | S11: COLA Shoreditch Park | T11: =IFERROR(INDEX(Venues!$E$2:$E$10,MATCH(S11,Venues!$A$2:$A$10,0)),"") | U11: =IFERROR(INDEX(Venues!$F$2:$F$10,MATCH(S11,Venues!$A$2:$A$10,0)),"") | V11: =IFERROR(INDEX(Venues!$H$2:$H$10,MATCH(S11,Venues!$A$2:$A$10,0)),"") | W11: =IF('Pilot offer'!$C$24="Yes",'Pilot offer'!$C$3,S11) | X11: =IF('Pilot offer'!$C$24="Yes",'Pilot offer'!$C$5+'Pilot offer'!$C$6,T11) | Y11: =IF('Pilot offer'!$C$24="Yes",'Pilot offer'!$C$8,U11) | Z11: =IF('Pilot offer'!$C$24="Yes",'Pilot offer'!$C$11,"") | AA11: =IF(X11="","",W11&" · "&TEXT(X11,"ddd d mmm, hh:mm")&" · "&Y11&IF(Z11<>""," · £"&TEXT(Z11,"0.00")&" per player"," · price TBC (cost £"&TEXT(V11,"0.00")&" pp)"))
A12: 10 | B12: 1 · E2 Haggerston | C12: Education | D12: Local businesses | E12: Bangabandhu Primary School | F12: amenity: school | G12: admin@bangabandhu.towerhamlets.sch.uk | H12: general | I12: +44 20 8980 0580 | J12: https://www.bangabandhu.towerhamlets.sch.uk/ | K12: Wessex Street 28, London | L12: E2 0LB | M12: Stepney 3G | N12: 6 | O12: =IFERROR(INDEX(Venues!$C$2:$C$10,MATCH(M12,Venues!$A$2:$A$10,0)),"Not checked") | P12: =IFERROR(INDEX(Venues!$D$2:$D$10,MATCH(M12,Venues!$A$2:$A$10,0)),0) | Q12: =IFERROR(INDEX(Venues!$E$2:$E$10,MATCH(M12,Venues!$A$2:$A$10,0)),"") | R12: =IF(P12>0,"Yes","No") | S12: COLA Shoreditch Park | T12: =IFERROR(INDEX(Venues!$E$2:$E$10,MATCH(S12,Venues!$A$2:$A$10,0)),"") | U12: =IFERROR(INDEX(Venues!$F$2:$F$10,MATCH(S12,Venues!$A$2:$A$10,0)),"") | V12: =IFERROR(INDEX(Venues!$H$2:$H$10,MATCH(S12,Venues!$A$2:$A$10,0)),"") | W12: =IF('Pilot offer'!$C$24="Yes",'Pilot offer'!$C$3,S12) | X12: =IF('Pilot offer'!$C$24="Yes",'Pilot offer'!$C$5+'Pilot offer'!$C$6,T12) | Y12: =IF('Pilot offer'!$C$24="Yes",'Pilot offer'!$C$8,U12) | Z12: =IF('Pilot offer'!$C$24="Yes",'Pilot offer'!$C$11,"") | AA12: =IF(X12="","",W12&" · "&TEXT(X12,"ddd d mmm, hh:mm")&" · "&Y12&IF(Z12<>""," · £"&TEXT(Z12,"0.00")&" per player"," · price TBC (cost £"&TEXT(V12,"0.00")&" pp)"))
A13: 11 | B13: 1 · E2 Haggerston | C13: Education | D13: Local businesses | E13: Bonner Primary School | F13: amenity: school | G13: admin@bonner.towerhamlets.sch.uk | H13: general | I13: +44 20 8980 1004 | J13: https://www.bonner.towerhamlets.sch.uk/ | K13: Stainsbury Street, London | L13: E2 0NF | M13: Stepney 3G | N13: 9 | O13: =IFERROR(INDEX(Venues!$C$2:$C$10,MATCH(M13,Venues!$A$2:$A$10,0)),"Not checked") | P13: =IFERROR(INDEX(Venues!$D$2:$D$10,MATCH(M13,Venues!$A$2:$A$10,0)),0) | Q13: =IFERROR(INDEX(Venues!$E$2:$E$10,MATCH(M13,Venues!$A$2:$A$10,0)),"") | R13: =IF(P13>0,"Yes","No") | S13: COLA Shoreditch Park | T13: =IFERROR(INDEX(Venues!$E$2:$E$10,MATCH(S13,Venues!$A$2:$A$10,0)),"") | U13: =IFERROR(INDEX(Venues!$F$2:$F$10,MATCH(S13,Venues!$A$2:$A$10,0)),"") | V13: =IFERROR(INDEX(Venues!$H$2:$H$10,MATCH(S13,Venues!$A$2:$A$10,0)),"") | W13: =IF('Pilot offer'!$C$24="Yes",'Pilot offer'!$C$3,S13) | X13: =IF('Pilot offer'!$C$24="Yes",'Pilot offer'!$C$5+'Pilot offer'!$C$6,T13) | Y13: =IF('Pilot offer'!$C$24="Yes",'Pilot offer'!$C$8,U13) | Z13: =IF('Pilot offer'!$C$24="Yes",'Pilot offer'!$C$11,"") | AA13: =IF(X13="","",W13&" · "&TEXT(X13,"ddd d mmm, hh:mm")&" · "&Y13&IF(Z13<>""," · £"&TEXT(Z13,"0.00")&" per player"," · price TBC (cost £"&TEXT(V13,"0.00")&" pp)"))
A14: 12 | B14: 1 · E2 Haggerston | C14: Office & professional | D14: Corporate | E14: BRS CONSULTING LTD | F14: finance | G14: info@brsconsulting.co.uk | H14: general | I14: +44 7979 781072 | J14: https://www.brsconsulting.co.uk/ | K14: 125 Roman Rd, Globe Town, London E2 0QN, UK | L14: E2 0QN | M14: Stepney 3G | N14: 9 | O14: =IFERROR(INDEX(Venues!$C$2:$C$10,MATCH(M14,Venues!$A$2:$A$10,0)),"Not checked") | P14: =IFERROR(INDEX(Venues!$D$2:$D$10,MATCH(M14,Venues!$A$2:$A$10,0)),0) | Q14: =IFERROR(INDEX(Venues!$E$2:$E$10,MATCH(M14,Venues!$A$2:$A$10,0)),"") | R14: =IF(P14>0,"Yes","No") | S14: COLA Shoreditch Park | T14: =IFERROR(INDEX(Venues!$E$2:$E$10,MATCH(S14,Venues!$A$2:$A$10,0)),"") | U14: =IFERROR(INDEX(Venues!$F$2:$F$10,MATCH(S14,Venues!$A$2:$A$10,0)),"") | V14: =IFERROR(INDEX(Venues!$H$2:$H$10,MATCH(S14,Venues!$A$2:$A$10,0)),"") | W14: =IF('Pilot offer'!$C$24="Yes",'Pilot offer'!$C$3,S14) | X14: =IF('Pilot offer'!$C$24="Yes",'Pilot offer'!$C$5+'Pilot offer'!$C$6,T14) | Y14: =IF('Pilot offer'!$C$24="Yes",'Pilot offer'!$C$8,U14) | Z14: =IF('Pilot offer'!$C$24="Yes",'Pilot offer'!$C$11,"") | AA14: =IF(X14="","",W14&" · "&TEXT(X14,"ddd d mmm, hh:mm")&" · "&Y14&IF(Z14<>""," · £"&TEXT(Z14,"0.00")&" per player"," · price TBC (cost £"&TEXT(V14,"0.00")&" pp)"))
A15: 13 | B15: 1 · E2 Haggerston | C15: Leisure & culture | D15: Local businesses | E15: Four Corners | F15: tourism: gallery | G15: info@fourcornersfilm.co.uk | H15: general | I15: +44 20 8981 6111 | J15: https://www.fourcornersfilm.co.uk/ | K15: Roman Road 121, London | L15: E2 0QN | M15: Stepney 3G | N15: 9 | O15: =IFERROR(INDEX(Venues!$C$2:$C$10,MATCH(M15,Venues!$A$2:$A$10,0)),"Not checked") | P15: =IFERROR(INDEX(Venues!$D$2:$D$10,MATCH(M15,Venues!$A$2:$A$10,0)),0) | Q15: =IFERROR(INDEX(Venues!$E$2:$E$10,MATCH(M15,Venues!$A$2:$A$10,0)),"") | R15: =IF(P15>0,"Yes","No") | S15: COLA Shoreditch Park | T15: =IFERROR(INDEX(Venues!$E$2:$E$10,MATCH(S15,Venues!$A$2:$A$10,0)),"") | U15: =IFERROR(INDEX(Venues!$F$2:$F$10,MATCH(S15,Venues!$A$2:$A$10,0)),"") | V15: =IFERROR(INDEX(Venues!$H$2:$H$10,MATCH(S15,Venues!$A$2:$A$10,0)),"") | W15: =IF('Pilot offer'!$C$24="Yes",'Pilot offer'!$C$3,S15) | X15: =IF('Pilot offer'!$C$24="Yes",'Pilot offer'!$C$5+'Pilot offer'!$C$6,T15) | Y15: =IF('Pilot offer'!$C$24="Yes",'Pilot offer'!$C$8,U15) | Z15: =IF('Pilot offer'!$C$24="Yes",'Pilot offer'!$C$11,"") | AA15: =IF(X15="","",W15&" · "&TEXT(X15,"ddd d mmm, hh:mm")&" · "&Y15&IF(Z15<>""," · £"&TEXT(Z15,"0.00")&" per player"," · price TBC (cost £"&TEXT(V15,"0.00")&" pp)"))
A16: 14 | B16: 1 · E2 Haggerston | C16: Retail | D16: Local businesses | E16: Paradise Cycles | F16: shop: bicycle | G16: info@paradisecycles.co.uk | H16: general | I16: +44 20 3441 9220 | J16: https://www.paradisecycles.co.uk/ | K16: Roman Road 63, London | L16: E2 0QN | M16: Stepney 3G | N16: 8 | O16: =IFERROR(INDEX(Venues!$C$2:$C$10,MATCH(M16,Venues!$A$2:$A$10,0)),"Not checked") | P16: =IFERROR(INDEX(Venues!$D$2:$D$10,MATCH(M16,Venues!$A$2:$A$10,0)),0) | Q16: =IFERROR(INDEX(Venues!$E$2:$E$10,MATCH(M16,Venues!$A$2:$A$10,0)),"") | R16: =IF(P16>0,"Yes","No") | S16: COLA Shoreditch Park | T16: =IFERROR(INDEX(Venues!$E$2:$E$10,MATCH(S16,Venues!$A$2:$A$10,0)),"") | U16: =IFERROR(INDEX(Venues!$F$2:$F$10,MATCH(S16,Venues!$A$2:$A$10,0)),"") | V16: =IFERROR(INDEX(Venues!$H$2:$H$10,MATCH(S16,Venues!$A$2:$A$10,0)),"") | W16: =IF('Pilot offer'!$C$24="Yes",'Pilot offer'!$C$3,S16) | X16: =IF('Pilot offer'!$C$24="Yes",'Pilot offer'!$C$5+'Pilot offer'!$C$6,T16) | Y16: =IF('Pilot offer'!$C$24="Yes",'Pilot offer'!$C$8,U16) | Z16: =IF('Pilot offer'!$C$24="Yes",'Pilot offer'!$C$11,"") | AA16: =IF(X16="","",W16&" · "&TEXT(X16,"ddd d mmm, hh:mm")&" · "&Y16&IF(Z16<>""," · £"&TEXT(Z16,"0.00")&" per player"," · price TBC (cost £"&TEXT(V16,"0.00")&" pp)"))
A17: 15 | B17: 1 · E2 Haggerston | C17: Office & professional | D17: Corporate | E17: Hamletts.com | F17: estate_agent | G17: info@hamletts.com | H17: openstreetmap_tag | I17: +44 20 8980 3377 | K17: 236 Roman Road, London | L17: E2 0RY | M17: Stepney 3G | N17: 12 | O17: =IFERROR(INDEX(Venues!$C$2:$C$10,MATCH(M17,Venues!$A$2:$A$10,0)),"Not checked") | P17: =IFERROR(INDEX(Venues!$D$2:$D$10,MATCH(M17,Venues!$A$2:$A$10,0)),0) | Q17: =IFERROR(INDEX(Venues!$E$2:$E$10,MATCH(M17,Venues!$A$2:$A$10,0)),"") | R17: =IF(P17>0,"Yes","No") | S17: COLA Shoreditch Park | T17: =IFERROR(INDEX(Venues!$E$2:$E$10,MATCH(S17,Venues!$A$2:$A$10,0)),"") | U17: =IFERROR(INDEX(Venues!$F$2:$F$10,MATCH(S17,Venues!$A$2:$A$10,0)),"") | V17: =IFERROR(INDEX(Venues!$H$2:$H$10,MATCH(S17,Venues!$A$2:$A$10,0)),"") | W17: =IF('Pilot offer'!$C$24="Yes",'Pilot offer'!$C$3,S17) | X17: =IF('Pilot offer'!$C$24="Yes",'Pilot offer'!$C$5+'Pilot offer'!$C$6,T17) | Y17: =IF('Pilot offer'!$C$24="Yes",'Pilot offer'!$C$8,U17) | Z17: =IF('Pilot offer'!$C$24="Yes",'Pilot offer'!$C$11,"") | AA17: =IF(X17="","",W17&" · "&TEXT(X17,"ddd d mmm, hh:mm")&" · "&Y17&IF(Z17<>""," · £"&TEXT(Z17,"0.00")&" per player"," · price TBC (cost £"&TEXT(V17,"0.00")&" pp)"))
A18: 16 | B18: 1 · E2 Haggerston | C18: Office & professional | D18: Corporate | E18: Keystones Properties | F18: estate_agent | G18: info@keystonesltd.co.uk | H18: general | I18: +44 20 8981 9955 | J18: https://www.keystonesltd.co.uk/ | K18: 146 Roman Road, London | L18: E2 0RY | M18: Stepney 3G | N18: 9 | O18: =IFERROR(INDEX(Venues!$C$2:$C$10,MATCH(M18,Venues!$A$2:$A$10,0)),"Not checked") | P18: =IFERROR(INDEX(Venues!$D$2:$D$10,MATCH(M18,Venues!$A$2:$A$10,0)),0) | Q18: =IFERROR(INDEX(Venues!$E$2:$E$10,MATCH(M18,Venues!$A$2:$A$10,0)),"") | R18: =IF(P18>0,"Yes","No") | S18: COLA Shoreditch Park | T18: =IFERROR(INDEX(Venues!$E$2:$E$10,MATCH(S18,Venues!$A$2:$A$10,0)),"") | U18: =IFERROR(INDEX(Venues!$F$2:$F$10,MATCH(S18,Venues!$A$2:$A$10,0)),"") | V18: =IFERROR(INDEX(Venues!$H$2:$H$10,MATCH(S18,Venues!$A$2:$A$10,0)),"") | W18: =IF('Pilot offer'!$C$24="Yes",'Pilot offer'!$C$3,S18) | X18: =IF('Pilot offer'!$C$24="Yes",'Pilot offer'!$C$5+'Pilot offer'!$C$6,T18) | Y18: =IF('Pilot offer'!$C$24="Yes",'Pilot offer'!$C$8,U18) | Z18: =IF('Pilot offer'!$C$24="Yes",'Pilot offer'!$C$11,"") | AA18: =IF(X18="","",W18&" · "&TEXT(X18,"ddd d mmm, hh:mm")&" · "&Y18&IF(Z18<>""," · £"&TEXT(Z18,"0.00")&" per player"," · price TBC (cost £"&TEXT(V18,"0.00")&" pp)"))
A19: 17 | B19: 1 · E2 Haggerston | C19: Education | D19: Local businesses | E19: William Davis Primary School | F19: amenity: school | G19: admin@williamdavis.org.uk | H19: general | I19: +44 20 7739 1511 | J19: https://www.williamdavis.org.uk/ | K19: Wood Close, London | L19: E2 6ET | M19: Whitechapel | N19: 19 | O19: =IFERROR(INDEX(Venues!$C$2:$C$10,MATCH(M19,Venues!$A$2:$A$10,0)),"Not checked") | P19: =IFERROR(INDEX(Venues!$D$2:$D$10,MATCH(M19,Venues!$A$2:$A$10,0)),0) | Q19: =IFERROR(INDEX(Venues!$E$2:$E$10,MATCH(M19,Venues!$A$2:$A$10,0)),"") | R19: =IF(P19>0,"Yes","No") | S19: COLA Shoreditch Park | T19: =IFERROR(INDEX(Venues!$E$2:$E$10,MATCH(S19,Venues!$A$2:$A$10,0)),"") | U19: =IFERROR(INDEX(Venues!$F$2:$F$10,MATCH(S19,Venues!$A$2:$A$10,0)),"") | V19: =IFERROR(INDEX(Venues!$H$2:$H$10,MATCH(S19,Venues!$A$2:$A$10,0)),"") | W19: =IF('Pilot offer'!$C$24="Yes",'Pilot offer'!$C$3,S19) | X19: =IF('Pilot offer'!$C$24="Yes",'Pilot offer'!$C$5+'Pilot offer'!$C$6,T19) | Y19: =IF('Pilot offer'!$C$24="Yes",'Pilot offer'!$C$8,U19) | Z19: =IF('Pilot offer'!$C$24="Yes",'Pilot offer'!$C$11,"") | AA19: =IF(X19="","",W19&" · "&TEXT(X19,"ddd d mmm, hh:mm")&" · "&Y19&IF(Z19<>""," · £"&TEXT(Z19,"0.00")&" per player"," · price TBC (cost £"&TEXT(V19,"0.00")&" pp)"))
A20: 18 | B20: 1 · E2 Haggerston | C20: Office & professional | D20: Corporate | E20: Crafted | F20: company | G20: hello@crafted.co.uk | H20: general | I20: +44 20 3327 9900 | J20: https://www.crafted.co.uk/ | K20: 115 Coventry Road, London | L20: E2 6GG | M20: Stepney 3G | N20: 11 | O20: =IFERROR(INDEX(Venues!$C$2:$C$10,MATCH(M20,Venues!$A$2:$A$10,0)),"Not checked") | P20: =IFERROR(INDEX(Venues!$D$2:$D$10,MATCH(M20,Venues!$A$2:$A$10,0)),0) | Q20: =IFERROR(INDEX(Venues!$E$2:$E$10,MATCH(M20,Venues!$A$2:$A$10,0)),"") | R20: =IF(P20>0,"Yes","No") | S20: COLA Shoreditch Park | T20: =IFERROR(INDEX(Venues!$E$2:$E$10,MATCH(S20,Venues!$A$2:$A$10,0)),"") | U20: =IFERROR(INDEX(Venues!$F$2:$F$10,MATCH(S20,Venues!$A$2:$A$10,0)),"") | V20: =IFERROR(INDEX(Venues!$H$2:$H$10,MATCH(S20,Venues!$A$2:$A$10,0)),"") | W20: =IF('Pilot offer'!$C$24="Yes",'Pilot offer'!$C$3,S20) | X20: =IF('Pilot offer'!$C$24="Yes",'Pilot offer'!$C$5+'Pilot offer'!$C$6,T20) | Y20: =IF('Pilot offer'!$C$24="Yes",'Pilot offer'!$C$8,U20) | Z20: =IF('Pilot offer'!$C$24="Yes",'Pilot offer'!$C$11,"") | AA20: =IF(X20="","",W20&" · "&TEXT(X20,"ddd d mmm, hh:mm")&" · "&Y20&IF(Z20<>""," · £"&TEXT(Z20,"0.00")&" per player"," · price TBC (cost £"&TEXT(V20,"0.00")&" pp)"))
A21: 19 | B21: 1 · E2 Haggerston | C21: Office & professional | D21: Corporate | E21: Transparent Digital Services | F21: advertising_agency | G21: contact@transparentdigitalservices.com | H21: openstreetmap_tag | I21: +44 7540 388706 | J21: https://transparentdigitalservices.com/ | K21: 115 Coventry Road, London | L21: E2 6GH | M21: Stepney 3G | N21: 11 | O21: =IFERROR(INDEX(Venues!$C$2:$C$10,MATCH(M21,Venues!$A$2:$A$10,0)),"Not checked") | P21: =IFERROR(INDEX(Venues!$D$2:$D$10,MATCH(M21,Venues!$A$2:$A$10,0)),0) | Q21: =IFERROR(INDEX(Venues!$E$2:$E$10,MATCH(M21,Venues!$A$2:$A$10,0)),"") | R21: =IF(P21>0,"Yes","No") | S21: COLA Shoreditch Park | T21: =IFERROR(INDEX(Venues!$E$2:$E$10,MATCH(S21,Venues!$A$2:$A$10,0)),"") | U21: =IFERROR(INDEX(Venues!$F$2:$F$10,MATCH(S21,Venues!$A$2:$A$10,0)),"") | V21: =IFERROR(INDEX(Venues!$H$2:$H$10,MATCH(S21,Venues!$A$2:$A$10,0)),"") | W21: =IF('Pilot offer'!$C$24="Yes",'Pilot offer'!$C$3,S21) | X21: =IF('Pilot offer'!$C$24="Yes",'Pilot offer'!$C$5+'Pilot offer'!$C$6,T21) | Y21: =IF('Pilot offer'!$C$24="Yes",'Pilot offer'!$C$8,U21) | Z21: =IF('Pilot offer'!$C$24="Yes",'Pilot offer'!$C$11,"") | AA21: =IF(X21="","",W21&" · "&TEXT(X21,"ddd d mmm, hh:mm")&" · "&Y21&IF(Z21<>""," · £"&TEXT(Z21,"0.00")&" per player"," · price TBC (cost £"&TEXT(V21,"0.00")&" pp)"))
A22: 20 | B22: 1 · E2 Haggerston | C22: Coworking / shared office | D22: Corporate | E22: Oxford House | F22: coworking_space | G22: info@oxfordhouse.org.uk | H22: general | I22: +44 20 7739 9001 | J22: http://www.oxfordhouse.org.uk/ | K22: Oxford House, Derbyshire St, Bethnal Green, London E2 6HG, UK | L22: E2 6HG | M22: Stepney 3G | N22: 15 | O22: =IFERROR(INDEX(Venues!$C$2:$C$10,MATCH(M22,Venues!$A$2:$A$10,0)),"Not checked") | P22: =IFERROR(INDEX(Venues!$D$2:$D$10,MATCH(M22,Venues!$A$2:$A$10,0)),0) | Q22: =IFERROR(INDEX(Venues!$E$2:$E$10,MATCH(M22,Venues!$A$2:$A$10,0)),"") | R22: =IF(P22>0,"Yes","No") | S22: COLA Shoreditch Park | T22: =IFERROR(INDEX(Venues!$E$2:$E$10,MATCH(S22,Venues!$A$2:$A$10,0)),"") | U22: =IFERROR(INDEX(Venues!$F$2:$F$10,MATCH(S22,Venues!$A$2:$A$10,0)),"") | V22: =IFERROR(INDEX(Venues!$H$2:$H$10,MATCH(S22,Venues!$A$2:$A$10,0)),"") | W22: =IF('Pilot offer'!$C$24="Yes",'Pilot offer'!$C$3,S22) | X22: =IF('Pilot offer'!$C$24="Yes",'Pilot offer'!$C$5+'Pilot offer'!$C$6,T22) | Y22: =IF('Pilot offer'!$C$24="Yes",'Pilot offer'!$C$8,U22) | Z22: =IF('Pilot offer'!$C$24="Yes",'Pilot offer'!$C$11,"") | AA22: =IF(X22="","",W22&" · "&TEXT(X22,"ddd d mmm, hh:mm")&" · "&Y22&IF(Z22<>""," · £"&TEXT(Z22,"0.00")&" per player"," · price TBC (cost £"&TEXT(V22,"0.00")&" pp)"))
A23: 21 | B23: 1 · E2 Haggerston | C23: Retail | D23: Local businesses | E23: Eastend Printers | F23: shop: copyshop | G23: info@eastendprinters.co.uk | H23: general | J23: https://eastendprinters.co.uk/ | K23: Dunbridge Street 71, London | L23: E2 6JG | M23: Stepney 3G | N23: 17 | O23: =IFERROR(INDEX(Venues!$C$2:$C$10,MATCH(M23,Venues!$A$2:$A$10,0)),"Not checked") | P23: =IFERROR(INDEX(Venues!$D$2:$D$10,MATCH(M23,Venues!$A$2:$A$10,0)),0) | Q23: =IFERROR(INDEX(Venues!$E$2:$E$10,MATCH(M23,Venues!$A$2:$A$10,0)),"") | R23: =IF(P23>0,"Yes","No") | S23: COLA Shoreditch Park | T23: =IFERROR(INDEX(Venues!$E$2:$E$10,MATCH(S23,Venues!$A$2:$A$10,0)),"") | U23: =IFERROR(INDEX(Venues!$F$2:$F$10,MATCH(S23,Venues!$A$2:$A$10,0)),"") | V23: =IFERROR(INDEX(Venues!$H$2:$H$10,MATCH(S23,Venues!$A$2:$A$10,0)),"") | W23: =IF('Pilot offer'!$C$24="Yes",'Pilot offer'!$C$3,S23) | X23: =IF('Pilot offer'!$C$24="Yes",'Pilot offer'!$C$5+'Pilot offer'!$C$6,T23) | Y23: =IF('Pilot offer'!$C$24="Yes",'Pilot offer'!$C$8,U23) | Z23: =IF('Pilot offer'!$C$24="Yes",'Pilot offer'!$C$11,"") | AA23: =IF(X23="","",W23&" · "&TEXT(X23,"ddd d mmm, hh:mm")&" · "&Y23&IF(Z23<>""," · £"&TEXT(Z23,"0.00")&" per player"," · price TBC (cost £"&TEXT(V23,"0.00")&" pp)"))
A24: 22 | B24: 1 · E2 Haggerston | C24: Leisure & culture | D24: Local businesses | E24: Bethnal Green Working Men's Club | F24: amenity: community centre | G24: info@workersplaytime.net | H24: general | J24: https://workersplaytime.net/ | K24: Pollard Row 42, London | L24: E2 6NB | M24: Stepney 3G | N24: 19 | O24: =IFERROR(INDEX(Venues!$C$2:$C$10,MATCH(M24,Venues!$A$2:$A$10,0)),"Not checked") | P24: =IFERROR(INDEX(Venues!$D$2:$D$10,MATCH(M24,Venues!$A$2:$A$10,0)),0) | Q24: =IFERROR(INDEX(Venues!$E$2:$E$10,MATCH(M24,Venues!$A$2:$A$10,0)),"") | R24: =IF(P24>0,"Yes","No") | S24: COLA Shoreditch Park | T24: =IFERROR(INDEX(Venues!$E$2:$E$10,MATCH(S24,Venues!$A$2:$A$10,0)),"") | U24: =IFERROR(INDEX(Venues!$F$2:$F$10,MATCH(S24,Venues!$A$2:$A$10,0)),"") | V24: =IFERROR(INDEX(Venues!$H$2:$H$10,MATCH(S24,Venues!$A$2:$A$10,0)),"") | W24: =IF('Pilot offer'!$C$24="Yes",'Pilot offer'!$C$3,S24) | X24: =IF('Pilot offer'!$C$24="Yes",'Pilot offer'!$C$5+'Pilot offer'!$C$6,T24) | Y24: =IF('Pilot offer'!$C$24="Yes",'Pilot offer'!$C$8,U24) | Z24: =IF('Pilot offer'!$C$24="Yes",'Pilot offer'!$C$11,"") | AA24: =IF(X24="","",W24&" · "&TEXT(X24,"ddd d mmm, hh:mm")&" · "&Y24&IF(Z24<>""," · £"&TEXT(Z24,"0.00")&" per player"," · price TBC (cost £"&TEXT(V24,"0.00")&" pp)"))
A25: 23 | B25: 1 · E2 Haggerston | C25: Education | D25: Local businesses | E25: Oaklands School | F25: amenity: school | G25: reception@oaklands.towerhamlets.sch.uk | H25: general | J25: https://oaklands.towerhamlets.sch.uk/ | K25: Old Bethnal Green Road, London | L25: E2 6PR | M25: Stepney 3G | N25: 17 | O25: =IFERROR(INDEX(Venues!$C$2:$C$10,MATCH(M25,Venues!$A$2:$A$10,0)),"Not checked") | P25: =IFERROR(INDEX(Venues!$D$2:$D$10,MATCH(M25,Venues!$A$2:$A$10,0)),0) | Q25: =IFERROR(INDEX(Venues!$E$2:$E$10,MATCH(M25,Venues!$A$2:$A$10,0)),"") | R25: =IF(P25>0,"Yes","No") | S25: COLA Shoreditch Park | T25: =IFERROR(INDEX(Venues!$E$2:$E$10,MATCH(S25,Venues!$A$2:$A$10,0)),"") | U25: =IFERROR(INDEX(Venues!$F$2:$F$10,MATCH(S25,Venues!$A$2:$A$10,0)),"") | V25: =IFERROR(INDEX(Venues!$H$2:$H$10,MATCH(S25,Venues!$A$2:$A$10,0)),"") | W25: =IF('Pilot offer'!$C$24="Yes",'Pilot offer'!$C$3,S25) | X25: =IF('Pilot offer'!$C$24="Yes",'Pilot offer'!$C$5+'Pilot offer'!$C$6,T25) | Y25: =IF('Pilot offer'!$C$24="Yes",'Pilot offer'!$C$8,U25) | Z25: =IF('Pilot offer'!$C$24="Yes",'Pilot offer'!$C$11,"") | AA25: =IF(X25="","",W25&" · "&TEXT(X25,"ddd d mmm, hh:mm")&" · "&Y25&IF(Z25<>""," · £"&TEXT(Z25,"0.00")&" per player"," · price TBC (cost £"&TEXT(V25,"0.00")&" pp)"))
A26: 24 | B26: 1 · E2 Haggerston | C26: Hospitality | D26: Local businesses | E26: The Common E2 | F26: amenity: cafe | G26: info@thecommone2.com | H26: general | J26: http://www.thecommone2.com | K26: Old Bethnal Green Road 53, London | L26: E2 6QA | M26: Stepney 3G | N26: 17 | O26: =IFERROR(INDEX(Venues!$C$2:$C$10,MATCH(M26,Venues!$A$2:$A$10,0)),"Not checked") | P26: =IFERROR(INDEX(Venues!$D$2:$D$10,MATCH(M26,Venues!$A$2:$A$10,0)),0) | Q26: =IFERROR(INDEX(Venues!$E$2:$E$10,MATCH(M26,Venues!$A$2:$A$10,0)),"") | R26: =IF(P26>0,"Yes","No") | S26: COLA Shoreditch Park | T26: =IFERROR(INDEX(Venues!$E$2:$E$10,MATCH(S26,Venues!$A$2:$A$10,0)),"") | U26: =IFERROR(INDEX(Venues!$F$2:$F$10,MATCH(S26,Venues!$A$2:$A$10,0)),"") | V26: =IFERROR(INDEX(Venues!$H$2:$H$10,MATCH(S26,Venues!$A$2:$A$10,0)),"") | W26: =IF('Pilot offer'!$C$24="Yes",'Pilot offer'!$C$3,S26) | X26: =IF('Pilot offer'!$C$24="Yes",'Pilot offer'!$C$5+'Pilot offer'!$C$6,T26) | Y26: =IF('Pilot offer'!$C$24="Yes",'Pilot offer'!$C$8,U26) | Z26: =IF('Pilot offer'!$C$24="Yes",'Pilot offer'!$C$11,"") | AA26: =IF(X26="","",W26&" · "&TEXT(X26,"ddd d mmm, hh:mm")&" · "&Y26&IF(Z26<>""," · £"&TEXT(Z26,"0.00")&" per player"," · price TBC (cost £"&TEXT(V26,"0.00")&" pp)"))
A27: 25 | B27: 1 · E2 Haggerston | C27: Hospitality | D27: Local businesses | E27: A Portuguese Love Affair | F27: amenity: cafe | G27: info@aportugueseloveaffair.co.uk | H27: general | I27: +44 20 3490 2662 | J27: https://www.aportugueseloveaffair.co.uk/ | K27: Hackney Road 326, London | L27: E2 7AX | M27: Shoreditch Rooftop | N27: 20 | O27: =IFERROR(INDEX(Venues!$C$2:$C$10,MATCH(M27,Venues!$A$2:$A$10,0)),"Not checked") | P27: =IFERROR(INDEX(Venues!$D$2:$D$10,MATCH(M27,Venues!$A$2:$A$10,0)),0) | Q27: =IFERROR(INDEX(Venues!$E$2:$E$10,MATCH(M27,Venues!$A$2:$A$10,0)),"") | R27: =IF(P27>0,"Yes","No") | S27: Shoreditch Rooftop | T27: =IFERROR(INDEX(Venues!$E$2:$E$10,MATCH(S27,Venues!$A$2:$A$10,0)),"") | U27: =IFERROR(INDEX(Venues!$F$2:$F$10,MATCH(S27,Venues!$A$2:$A$10,0)),"") | V27: =IFERROR(INDEX(Venues!$H$2:$H$10,MATCH(S27,Venues!$A$2:$A$10,0)),"") | W27: =IF('Pilot offer'!$C$24="Yes",'Pilot offer'!$C$3,S27) | X27: =IF('Pilot offer'!$C$24="Yes",'Pilot offer'!$C$5+'Pilot offer'!$C$6,T27) | Y27: =IF('Pilot offer'!$C$24="Yes",'Pilot offer'!$C$8,U27) | Z27: =IF('Pilot offer'!$C$24="Yes",'Pilot offer'!$C$11,"") | AA27: =IF(X27="","",W27&" · "&TEXT(X27,"ddd d mmm, hh:mm")&" · "&Y27&IF(Z27<>""," · £"&TEXT(Z27,"0.00")&" per player"," · price TBC (cost £"&TEXT(V27,"0.00")&" pp)"))
A28: 26 | B28: 1 · E2 Haggerston | C28: Office & professional | D28: Corporate | E28: Small World | F28: consultant | G28: hello@meetsmallworld.com | H28: general | J28: http://www.meetsmallworld.com/ | K28: 10 Redchurch St, London E2 7DD, UK | L28: E2 7DD | M28: Shoreditch Rooftop | N28: 21 | O28: =IFERROR(INDEX(Venues!$C$2:$C$10,MATCH(M28,Venues!$A$2:$A$10,0)),"Not checked") | P28: =IFERROR(INDEX(Venues!$D$2:$D$10,MATCH(M28,Venues!$A$2:$A$10,0)),0) | Q28: =IFERROR(INDEX(Venues!$E$2:$E$10,MATCH(M28,Venues!$A$2:$A$10,0)),"") | R28: =IF(P28>0,"Yes","No") | S28: Shoreditch Rooftop | T28: =IFERROR(INDEX(Venues!$E$2:$E$10,MATCH(S28,Venues!$A$2:$A$10,0)),"") | U28: =IFERROR(INDEX(Venues!$F$2:$F$10,MATCH(S28,Venues!$A$2:$A$10,0)),"") | V28: =IFERROR(INDEX(Venues!$H$2:$H$10,MATCH(S28,Venues!$A$2:$A$10,0)),"") | W28: =IF('Pilot offer'!$C$24="Yes",'Pilot offer'!$C$3,S28) | X28: =IF('Pilot offer'!$C$24="Yes",'Pilot offer'!$C$5+'Pilot offer'!$C$6,T28) | Y28: =IF('Pilot offer'!$C$24="Yes",'Pilot offer'!$C$8,U28) | Z28: =IF('Pilot offer'!$C$24="Yes",'Pilot offer'!$C$11,"") | AA28: =IF(X28="","",W28&" · "&TEXT(X28,"ddd d mmm, hh:mm")&" · "&Y28&IF(Z28<>""," · £"&TEXT(Z28,"0.00")&" per player"," · price TBC (cost £"&TEXT(V28,"0.00")&" pp)"))
A29: 27 | B29: 1 · E2 Haggerston | C29: Hospitality | D29: Local businesses | E29: BAO Noodle Shop | F29: amenity: restaurant | G29: info@baolondon.com | H29: general | J29: https://baolondon.com/ | K29: Redchurch Street 1, London | L29: E2 7DJ | M29: Shoreditch Rooftop | N29: 20 | O29: =IFERROR(INDEX(Venues!$C$2:$C$10,MATCH(M29,Venues!$A$2:$A$10,0)),"Not checked") | P29: =IFERROR(INDEX(Venues!$D$2:$D$10,MATCH(M29,Venues!$A$2:$A$10,0)),0) | Q29: =IFERROR(INDEX(Venues!$E$2:$E$10,MATCH(M29,Venues!$A$2:$A$10,0)),"") | R29: =IF(P29>0,"Yes","No") | S29: Shoreditch Rooftop | T29: =IFERROR(INDEX(Venues!$E$2:$E$10,MATCH(S29,Venues!$A$2:$A$10,0)),"") | U29: =IFERROR(INDEX(Venues!$F$2:$F$10,MATCH(S29,Venues!$A$2:$A$10,0)),"") | V29: =IFERROR(INDEX(Venues!$H$2:$H$10,MATCH(S29,Venues!$A$2:$A$10,0)),"") | W29: =IF('Pilot offer'!$C$24="Yes",'Pilot offer'!$C$3,S29) | X29: =IF('Pilot offer'!$C$24="Yes",'Pilot offer'!$C$5+'Pilot offer'!$C$6,T29) | Y29: =IF('Pilot offer'!$C$24="Yes",'Pilot offer'!$C$8,U29) | Z29: =IF('Pilot offer'!$C$24="Yes",'Pilot offer'!$C$11,"") | AA29: =IF(X29="","",W29&" · "&TEXT(X29,"ddd d mmm, hh:mm")&" · "&Y29&IF(Z29<>""," · £"&TEXT(Z29,"0.00")&" per player"," · price TBC (cost £"&TEXT(V29,"0.00")&" pp)"))
A30: 28 | B30: 1 · E2 Haggerston | C30: Health | D30: Local businesses | E30: Mildmay Mission Hospital | F30: amenity: hospital | G30: info@mildmay.org | H30: general | I30: +44 20 7613 6300 | J30: https://www.mildmay.org/ | K30: Tabernacle Gardens 19, London | L30: E2 7DZ | M30: Shoreditch Rooftop | N30: 15 | O30: =IFERROR(INDEX(Venues!$C$2:$C$10,MATCH(M30,Venues!$A$2:$A$10,0)),"Not checked") | P30: =IFERROR(INDEX(Venues!$D$2:$D$10,MATCH(M30,Venues!$A$2:$A$10,0)),0) | Q30: =IFERROR(INDEX(Venues!$E$2:$E$10,MATCH(M30,Venues!$A$2:$A$10,0)),"") | R30: =IF(P30>0,"Yes","No") | S30: Shoreditch Rooftop | T30: =IFERROR(INDEX(Venues!$E$2:$E$10,MATCH(S30,Venues!$A$2:$A$10,0)),"") | U30: =IFERROR(INDEX(Venues!$F$2:$F$10,MATCH(S30,Venues!$A$2:$A$10,0)),"") | V30: =IFERROR(INDEX(Venues!$H$2:$H$10,MATCH(S30,Venues!$A$2:$A$10,0)),"") | W30: =IF('Pilot offer'!$C$24="Yes",'Pilot offer'!$C$3,S30) | X30: =IF('Pilot offer'!$C$24="Yes",'Pilot offer'!$C$5+'Pilot offer'!$C$6,T30) | Y30: =IF('Pilot offer'!$C$24="Yes",'Pilot offer'!$C$8,U30) | Z30: =IF('Pilot offer'!$C$24="Yes",'Pilot offer'!$C$11,"") | AA30: =IF(X30="","",W30&" · "&TEXT(X30,"ddd d mmm, hh:mm")&" · "&Y30&IF(Z30<>""," · £"&TEXT(Z30,"0.00")&" per player"," · price TBC (cost £"&TEXT(V30,"0.00")&" pp)"))
A31: 29 | B31: 1 · E2 Haggerston | C31: Hospitality | D31: Local businesses | E31: The Umbrella Workshop | F31: amenity: bar | G31: info@theumbrellaproject.co.uk | H31: general | I31: +44 20 7739 4951 | J31: https://theumbrellaproject.co.uk/ | K31: Boundary Street, London | L31: E2 7JD | M31: Shoreditch Rooftop | N31: 17 | O31: =IFERROR(INDEX(Venues!$C$2:$C$10,MATCH(M31,Venues!$A$2:$A$10,0)),"Not checked") | P31: =IFERROR(INDEX(Venues!$D$2:$D$10,MATCH(M31,Venues!$A$2:$A$10,0)),0) | Q31: =IFERROR(INDEX(Venues!$E$2:$E$10,MATCH(M31,Venues!$A$2:$A$10,0)),"") | R31: =IF(P31>0,"Yes","No") | S31: Shoreditch Rooftop | T31: =IFERROR(INDEX(Venues!$E$2:$E$10,MATCH(S31,Venues!$A$2:$A$10,0)),"") | U31: =IFERROR(INDEX(Venues!$F$2:$F$10,MATCH(S31,Venues!$A$2:$A$10,0)),"") | V31: =IFERROR(INDEX(Venues!$H$2:$H$10,MATCH(S31,Venues!$A$2:$A$10,0)),"") | W31: =IF('Pilot offer'!$C$24="Yes",'Pilot offer'!$C$3,S31) | X31: =IF('Pilot offer'!$C$24="Yes",'Pilot offer'!$C$5+'Pilot offer'!$C$6,T31) | Y31: =IF('Pilot offer'!$C$24="Yes",'Pilot offer'!$C$8,U31) | Z31: =IF('Pilot offer'!$C$24="Yes",'Pilot offer'!$C$11,"") | AA31: =IF(X31="","",W31&" · "&TEXT(X31,"ddd d mmm, hh:mm")&" · "&Y31&IF(Z31<>""," · £"&TEXT(Z31,"0.00")&" per player"," · price TBC (cost £"&TEXT(V31,"0.00")&" pp)"))
A32: 30 | B32: 1 · E2 Haggerston | C32: Retail | D32: Local businesses | E32: facebar | F32: shop: beauty | G32: hello@facebarlondon.com | H32: general | I32: +44 7789 618125 | J32: https://facebarlondon.com/ | K32: Boundary Street, London | L32: E2 7JD | M32: Shoreditch Rooftop | N32: 17 | O32: =IFERROR(INDEX(Venues!$C$2:$C$10,MATCH(M32,Venues!$A$2:$A$10,0)),"Not checked") | P32: =IFERROR(INDEX(Venues!$D$2:$D$10,MATCH(M32,Venues!$A$2:$A$10,0)),0) | Q32: =IFERROR(INDEX(Venues!$E$2:$E$10,MATCH(M32,Venues!$A$2:$A$10,0)),"") | R32: =IF(P32>0,"Yes","No") | S32: Shoreditch Rooftop | T32: =IFERROR(INDEX(Venues!$E$2:$E$10,MATCH(S32,Venues!$A$2:$A$10,0)),"") | U32: =IFERROR(INDEX(Venues!$F$2:$F$10,MATCH(S32,Venues!$A$2:$A$10,0)),"") | V32: =IFERROR(INDEX(Venues!$H$2:$H$10,MATCH(S32,Venues!$A$2:$A$10,0)),"") | W32: =IF('Pilot offer'!$C$24="Yes",'Pilot offer'!$C$3,S32) | X32: =IF('Pilot offer'!$C$24="Yes",'Pilot offer'!$C$5+'Pilot offer'!$C$6,T32) | Y32: =IF('Pilot offer'!$C$24="Yes",'Pilot offer'!$C$8,U32) | Z32: =IF('Pilot offer'!$C$24="Yes",'Pilot offer'!$C$11,"") | AA32: =IF(X32="","",W32&" · "&TEXT(X32,"ddd d mmm, hh:mm")&" · "&Y32&IF(Z32<>""," · £"&TEXT(Z32,"0.00")&" per player"," · price TBC (cost £"&TEXT(V32,"0.00")&" pp)"))
A33: 31 | B33: 1 · E2 Haggerston | C33: Hospitality | D33: Local businesses | E33: Paper & Cup | F33: amenity: cafe | G33: paperandcup@sct.org.uk | H33: openstreetmap_tag | I33: +44 7732 691013 | J33: https://sct.org.uk/social-enterprises/paper-cup/ | K33: Calvert Avenue 18, London | L33: E2 7JP | M33: Shoreditch Rooftop | N33: 17 | O33: =IFERROR(INDEX(Venues!$C$2:$C$10,MATCH(M33,Venues!$A$2:$A$10,0)),"Not checked") | P33: =IFERROR(INDEX(Venues!$D$2:$D$10,MATCH(M33,Venues!$A$2:$A$10,0)),0) | Q33: =IFERROR(INDEX(Venues!$E$2:$E$10,MATCH(M33,Venues!$A$2:$A$10,0)),"") | R33: =IF(P33>0,"Yes","No") | S33: Shoreditch Rooftop | T33: =IFERROR(INDEX(Venues!$E$2:$E$10,MATCH(S33,Venues!$A$2:$A$10,0)),"") | U33: =IFERROR(INDEX(Venues!$F$2:$F$10,MATCH(S33,Venues!$A$2:$A$10,0)),"") | V33: =IFERROR(INDEX(Venues!$H$2:$H$10,MATCH(S33,Venues!$A$2:$A$10,0)),"") | W33: =IF('Pilot offer'!$C$24="Yes",'Pilot offer'!$C$3,S33) | X33: =IF('Pilot offer'!$C$24="Yes",'Pilot offer'!$C$5+'Pilot offer'!$C$6,T33) | Y33: =IF('Pilot offer'!$C$24="Yes",'Pilot offer'!$C$8,U33) | Z33: =IF('Pilot offer'!$C$24="Yes",'Pilot offer'!$C$11,"") | AA33: =IF(X33="","",W33&" · "&TEXT(X33,"ddd d mmm, hh:mm")&" · "&Y33&IF(Z33<>""," · £"&TEXT(Z33,"0.00")&" per player"," · price TBC (cost £"&TEXT(V33,"0.00")&" pp)"))
A34: 32 | B34: 1 · E2 Haggerston | C34: Retail | D34: Local businesses | E34: Odyssey Male Grooming | F34: shop: hairdresser | G34: hello@odysseymalegrooming.com | H34: openstreetmap_tag | I34: +44 20 3911 8144 | J34: https://www.odysseymalegrooming.com/ | K34: Hackney Road 63, London | L34: E2 7NX | M34: Shoreditch Rooftop | N34: 14 | O34: =IFERROR(INDEX(Venues!$C$2:$C$10,MATCH(M34,Venues!$A$2:$A$10,0)),"Not checked") | P34: =IFERROR(INDEX(Venues!$D$2:$D$10,MATCH(M34,Venues!$A$2:$A$10,0)),0) | Q34: =IFERROR(INDEX(Venues!$E$2:$E$10,MATCH(M34,Venues!$A$2:$A$10,0)),"") | R34: =IF(P34>0,"Yes","No") | S34: Shoreditch Rooftop | T34: =IFERROR(INDEX(Venues!$E$2:$E$10,MATCH(S34,Venues!$A$2:$A$10,0)),"") | U34: =IFERROR(INDEX(Venues!$F$2:$F$10,MATCH(S34,Venues!$A$2:$A$10,0)),"") | V34: =IFERROR(INDEX(Venues!$H$2:$H$10,MATCH(S34,Venues!$A$2:$A$10,0)),"") | W34: =IF('Pilot offer'!$C$24="Yes",'Pilot offer'!$C$3,S34) | X34: =IF('Pilot offer'!$C$24="Yes",'Pilot offer'!$C$5+'Pilot offer'!$C$6,T34) | Y34: =IF('Pilot offer'!$C$24="Yes",'Pilot offer'!$C$8,U34) | Z34: =IF('Pilot offer'!$C$24="Yes",'Pilot offer'!$C$11,"") | AA34: =IF(X34="","",W34&" · "&TEXT(X34,"ddd d mmm, hh:mm")&" · "&Y34&IF(Z34<>""," · £"&TEXT(Z34,"0.00")&" per player"," · price TBC (cost £"&TEXT(V34,"0.00")&" pp)"))
A35: 33 | B35: 1 · E2 Haggerston | C35: Retail | D35: Local businesses | E35: Idle Moments | F35: shop: wine | G35: info@idle-moments.com | H35: general | I35: +44 20 7646 3762 | J35: https://idle-moments.com/ | K35: Columbia Road 86, London | L35: E2 7QB | M35: Shoreditch Rooftop | N35: 18 | O35: =IFERROR(INDEX(Venues!$C$2:$C$10,MATCH(M35,Venues!$A$2:$A$10,0)),"Not checked") | P35: =IFERROR(INDEX(Venues!$D$2:$D$10,MATCH(M35,Venues!$A$2:$A$10,0)),0) | Q35: =IFERROR(INDEX(Venues!$E$2:$E$10,MATCH(M35,Venues!$A$2:$A$10,0)),"") | R35: =IF(P35>0,"Yes","No") | S35: Shoreditch Rooftop | T35: =IFERROR(INDEX(Venues!$E$2:$E$10,MATCH(S35,Venues!$A$2:$A$10,0)),"") | U35: =IFERROR(INDEX(Venues!$F$2:$F$10,MATCH(S35,Venues!$A$2:$A$10,0)),"") | V35: =IFERROR(INDEX(Venues!$H$2:$H$10,MATCH(S35,Venues!$A$2:$A$10,0)),"") | W35: =IF('Pilot offer'!$C$24="Yes",'Pilot offer'!$C$3,S35) | X35: =IF('Pilot offer'!$C$24="Yes",'Pilot offer'!$C$5+'Pilot offer'!$C$6,T35) | Y35: =IF('Pilot offer'!$C$24="Yes",'Pilot offer'!$C$8,U35) | Z35: =IF('Pilot offer'!$C$24="Yes",'Pilot offer'!$C$11,"") | AA35: =IF(X35="","",W35&" · "&TEXT(X35,"ddd d mmm, hh:mm")&" · "&Y35&IF(Z35<>""," · £"&TEXT(Z35,"0.00")&" per player"," · price TBC (cost £"&TEXT(V35,"0.00")&" pp)"))
A36: 34 | B36: 1 · E2 Haggerston | C36: Hospitality | D36: Local businesses | E36: Brawn | F36: amenity: restaurant | G36: enquiries@brawn.co | H36: general | J36: https://www.brawn.co/ | K36: Columbia Road 49, London | L36: E2 7RG | M36: Shoreditch Rooftop | N36: 18 | O36: =IFERROR(INDEX(Venues!$C$2:$C$10,MATCH(M36,Venues!$A$2:$A$10,0)),"Not checked") | P36: =IFERROR(INDEX(Venues!$D$2:$D$10,MATCH(M36,Venues!$A$2:$A$10,0)),0) | Q36: =IFERROR(INDEX(Venues!$E$2:$E$10,MATCH(M36,Venues!$A$2:$A$10,0)),"") | R36: =IF(P36>0,"Yes","No") | S36: Shoreditch Rooftop | T36: =IFERROR(INDEX(Venues!$E$2:$E$10,MATCH(S36,Venues!$A$2:$A$10,0)),"") | U36: =IFERROR(INDEX(Venues!$F$2:$F$10,MATCH(S36,Venues!$A$2:$A$10,0)),"") | V36: =IFERROR(INDEX(Venues!$H$2:$H$10,MATCH(S36,Venues!$A$2:$A$10,0)),"") | W36: =IF('Pilot offer'!$C$24="Yes",'Pilot offer'!$C$3,S36) | X36: =IF('Pilot offer'!$C$24="Yes",'Pilot offer'!$C$5+'Pilot offer'!$C$6,T36) | Y36: =IF('Pilot offer'!$C$24="Yes",'Pilot offer'!$C$8,U36) | Z36: =IF('Pilot offer'!$C$24="Yes",'Pilot offer'!$C$11,"") | AA36: =IF(X36="","",W36&" · "&TEXT(X36,"ddd d mmm, hh:mm")&" · "&Y36&IF(Z36<>""," · £"&TEXT(Z36,"0.00")&" per player"," · price TBC (cost £"&TEXT(V36,"0.00")&" pp)"))
A37: 35 | B37: 1 · E2 Haggerston | C37: Retail | D37: Local businesses | E37: Mosaic Factory | F37: shop: tiles | G37: info-uk@mosaicdelsur.com | H37: openstreetmap_tag | I37: +44 20 3514 0483 | J37: https://www.cement-tiles.com/ | K37: Columbia Road 106, London | L37: E2 7RG | M37: Shoreditch Rooftop | N37: 18 | O37: =IFERROR(INDEX(Venues!$C$2:$C$10,MATCH(M37,Venues!$A$2:$A$10,0)),"Not checked") | P37: =IFERROR(INDEX(Venues!$D$2:$D$10,MATCH(M37,Venues!$A$2:$A$10,0)),0) | Q37: =IFERROR(INDEX(Venues!$E$2:$E$10,MATCH(M37,Venues!$A$2:$A$10,0)),"") | R37: =IF(P37>0,"Yes","No") | S37: Shoreditch Rooftop | T37: =IFERROR(INDEX(Venues!$E$2:$E$10,MATCH(S37,Venues!$A$2:$A$10,0)),"") | U37: =IFERROR(INDEX(Venues!$F$2:$F$10,MATCH(S37,Venues!$A$2:$A$10,0)),"") | V37: =IFERROR(INDEX(Venues!$H$2:$H$10,MATCH(S37,Venues!$A$2:$A$10,0)),"") | W37: =IF('Pilot offer'!$C$24="Yes",'Pilot offer'!$C$3,S37) | X37: =IF('Pilot offer'!$C$24="Yes",'Pilot offer'!$C$5+'Pilot offer'!$C$6,T37) | Y37: =IF('Pilot offer'!$C$24="Yes",'Pilot offer'!$C$8,U37) | Z37: =IF('Pilot offer'!$C$24="Yes",'Pilot offer'!$C$11,"") | AA37: =IF(X37="","",W37&" · "&TEXT(X37,"ddd d mmm, hh:mm")&" · "&Y37&IF(Z37<>""," · £"&TEXT(Z37,"0.00")&" per player"," · price TBC (cost £"&TEXT(V37,"0.00")&" pp)"))
A38: 36 | B38: 1 · E2 Haggerston | C38: Retail | D38: Local businesses | E38: Play Vinyl | F38: shop: music | G38: info@playvinyl.london | H38: openstreetmap_tag | I38: +44 7480 651744 | J38: https://playvinyl.london/ | K38: Ezra Street 14, London | L38: E2 7RH | M38: Shoreditch Rooftop | N38: 18 | O38: =IFERROR(INDEX(Venues!$C$2:$C$10,MATCH(M38,Venues!$A$2:$A$10,0)),"Not checked") | P38: =IFERROR(INDEX(Venues!$D$2:$D$10,MATCH(M38,Venues!$A$2:$A$10,0)),0) | Q38: =IFERROR(INDEX(Venues!$E$2:$E$10,MATCH(M38,Venues!$A$2:$A$10,0)),"") | R38: =IF(P38>0,"Yes","No") | S38: Shoreditch Rooftop | T38: =IFERROR(INDEX(Venues!$E$2:$E$10,MATCH(S38,Venues!$A$2:$A$10,0)),"") | U38: =IFERROR(INDEX(Venues!$F$2:$F$10,MATCH(S38,Venues!$A$2:$A$10,0)),"") | V38: =IFERROR(INDEX(Venues!$H$2:$H$10,MATCH(S38,Venues!$A$2:$A$10,0)),"") | W38: =IF('Pilot offer'!$C$24="Yes",'Pilot offer'!$C$3,S38) | X38: =IF('Pilot offer'!$C$24="Yes",'Pilot offer'!$C$5+'Pilot offer'!$C$6,T38) | Y38: =IF('Pilot offer'!$C$24="Yes",'Pilot offer'!$C$8,U38) | Z38: =IF('Pilot offer'!$C$24="Yes",'Pilot offer'!$C$11,"") | AA38: =IF(X38="","",W38&" · "&TEXT(X38,"ddd d mmm, hh:mm")&" · "&Y38&IF(Z38<>""," · £"&TEXT(Z38,"0.00")&" per player"," · price TBC (cost £"&TEXT(V38,"0.00")&" pp)"))
A39: 37 | B39: 1 · E2 Haggerston | C39: Hospitality | D39: Local businesses | E39: The Nelson's | F39: amenity: pub | G39: ben@thenelsonspub.com | H39: person_or_other | I39: +44 7427 012091 | J39: https://www.thenelsonspub.com/ | K39: Horatio Street 32, London | L39: E2 7SB | M39: Shoreditch Rooftop | N39: 17 | O39: =IFERROR(INDEX(Venues!$C$2:$C$10,MATCH(M39,Venues!$A$2:$A$10,0)),"Not checked") | P39: =IFERROR(INDEX(Venues!$D$2:$D$10,MATCH(M39,Venues!$A$2:$A$10,0)),0) | Q39: =IFERROR(INDEX(Venues!$E$2:$E$10,MATCH(M39,Venues!$A$2:$A$10,0)),"") | R39: =IF(P39>0,"Yes","No") | S39: Shoreditch Rooftop | T39: =IFERROR(INDEX(Venues!$E$2:$E$10,MATCH(S39,Venues!$A$2:$A$10,0)),"") | U39: =IFERROR(INDEX(Venues!$F$2:$F$10,MATCH(S39,Venues!$A$2:$A$10,0)),"") | V39: =IFERROR(INDEX(Venues!$H$2:$H$10,MATCH(S39,Venues!$A$2:$A$10,0)),"") | W39: =IF('Pilot offer'!$C$24="Yes",'Pilot offer'!$C$3,S39) | X39: =IF('Pilot offer'!$C$24="Yes",'Pilot offer'!$C$5+'Pilot offer'!$C$6,T39) | Y39: =IF('Pilot offer'!$C$24="Yes",'Pilot offer'!$C$8,U39) | Z39: =IF('Pilot offer'!$C$24="Yes",'Pilot offer'!$C$11,"") | AA39: =IF(X39="","",W39&" · "&TEXT(X39,"ddd d mmm, hh:mm")&" · "&Y39&IF(Z39<>""," · £"&TEXT(Z39,"0.00")&" per player"," · price TBC (cost £"&TEXT(V39,"0.00")&" pp)"))
A40: 38 | B40: 1 · E2 Haggerston | C40: Hospitality | D40: Local businesses | E40: Indian Greedy Cow | F40: amenity: fast food | G40: info@indiangreedycow.co.uk | H40: general | I40: +44 20 7739 4884 | J40: https://www.indiangreedycow.co.uk/ | K40: Hackney Road 310, London | L40: E2 7SJ | M40: Shoreditch Rooftop | N40: 19 | O40: =IFERROR(INDEX(Venues!$C$2:$C$10,MATCH(M40,Venues!$A$2:$A$10,0)),"Not checked") | P40: =IFERROR(INDEX(Venues!$D$2:$D$10,MATCH(M40,Venues!$A$2:$A$10,0)),0) | Q40: =IFERROR(INDEX(Venues!$E$2:$E$10,MATCH(M40,Venues!$A$2:$A$10,0)),"") | R40: =IF(P40>0,"Yes","No") | S40: Shoreditch Rooftop | T40: =IFERROR(INDEX(Venues!$E$2:$E$10,MATCH(S40,Venues!$A$2:$A$10,0)),"") | U40: =IFERROR(INDEX(Venues!$F$2:$F$10,MATCH(S40,Venues!$A$2:$A$10,0)),"") | V40: =IFERROR(INDEX(Venues!$H$2:$H$10,MATCH(S40,Venues!$A$2:$A$10,0)),"") | W40: =IF('Pilot offer'!$C$24="Yes",'Pilot offer'!$C$3,S40) | X40: =IF('Pilot offer'!$C$24="Yes",'Pilot offer'!$C$5+'Pilot offer'!$C$6,T40) | Y40: =IF('Pilot offer'!$C$24="Yes",'Pilot offer'!$C$8,U40) | Z40: =IF('Pilot offer'!$C$24="Yes",'Pilot offer'!$C$11,"") | AA40: =IF(X40="","",W40&" · "&TEXT(X40,"ddd d mmm, hh:mm")&" · "&Y40&IF(Z40<>""," · £"&TEXT(Z40,"0.00")&" per player"," · price TBC (cost £"&TEXT(V40,"0.00")&" pp)"))
A41: 39 | B41: 1 · E2 Haggerston | C41: Retail | D41: Local businesses | E41: Provisions | F41: shop: deli | G41: info@provisionslondon.co.uk | H41: general | J41: https://provisionslondon.co.uk/ | K41: Hackney Road 308, London | L41: E2 7SJ | M41: Shoreditch Rooftop | N41: 19 | O41: =IFERROR(INDEX(Venues!$C$2:$C$10,MATCH(M41,Venues!$A$2:$A$10,0)),"Not checked") | P41: =IFERROR(INDEX(Venues!$D$2:$D$10,MATCH(M41,Venues!$A$2:$A$10,0)),0) | Q41: =IFERROR(INDEX(Venues!$E$2:$E$10,MATCH(M41,Venues!$A$2:$A$10,0)),"") | R41: =IF(P41>0,"Yes","No") | S41: Shoreditch Rooftop | T41: =IFERROR(INDEX(Venues!$E$2:$E$10,MATCH(S41,Venues!$A$2:$A$10,0)),"") | U41: =IFERROR(INDEX(Venues!$F$2:$F$10,MATCH(S41,Venues!$A$2:$A$10,0)),"") | V41: =IFERROR(INDEX(Venues!$H$2:$H$10,MATCH(S41,Venues!$A$2:$A$10,0)),"") | W41: =IF('Pilot offer'!$C$24="Yes",'Pilot offer'!$C$3,S41) | X41: =IF('Pilot offer'!$C$24="Yes",'Pilot offer'!$C$5+'Pilot offer'!$C$6,T41) | Y41: =IF('Pilot offer'!$C$24="Yes",'Pilot offer'!$C$8,U41) | Z41: =IF('Pilot offer'!$C$24="Yes",'Pilot offer'!$C$11,"") | AA41: =IF(X41="","",W41&" · "&TEXT(X41,"ddd d mmm, hh:mm")&" · "&Y41&IF(Z41<>""," · £"&TEXT(Z41,"0.00")&" per player"," · price TBC (cost £"&TEXT(V41,"0.00")&" pp)"))
A42: 40 | B42: 1 · E2 Haggerston | C42: Hospitality | D42: Local businesses | E42: Mixology Events | F42: amenity: bar | G42: info@mixologyevents.co.uk | H42: general | I42: +44 333 344 7765 | J42: https://mixologyevents.co.uk/classes/cocktail-making-classes-london/ | K42: Kingsland Road 17B, London | L42: E2 8AA | M42: Shoreditch Rooftop | N42: 12 | O42: =IFERROR(INDEX(Venues!$C$2:$C$10,MATCH(M42,Venues!$A$2:$A$10,0)),"Not checked") | P42: =IFERROR(INDEX(Venues!$D$2:$D$10,MATCH(M42,Venues!$A$2:$A$10,0)),0) | Q42: =IFERROR(INDEX(Venues!$E$2:$E$10,MATCH(M42,Venues!$A$2:$A$10,0)),"") | R42: =IF(P42>0,"Yes","No") | S42: Shoreditch Rooftop | T42: =IFERROR(INDEX(Venues!$E$2:$E$10,MATCH(S42,Venues!$A$2:$A$10,0)),"") | U42: =IFERROR(INDEX(Venues!$F$2:$F$10,MATCH(S42,Venues!$A$2:$A$10,0)),"") | V42: =IFERROR(INDEX(Venues!$H$2:$H$10,MATCH(S42,Venues!$A$2:$A$10,0)),"") | W42: =IF('Pilot offer'!$C$24="Yes",'Pilot offer'!$C$3,S42) | X42: =IF('Pilot offer'!$C$24="Yes",'Pilot offer'!$C$5+'Pilot offer'!$C$6,T42) | Y42: =IF('Pilot offer'!$C$24="Yes",'Pilot offer'!$C$8,U42) | Z42: =IF('Pilot offer'!$C$24="Yes",'Pilot offer'!$C$11,"") | AA42: =IF(X42="","",W42&" · "&TEXT(X42,"ddd d mmm, hh:mm")&" · "&Y42&IF(Z42<>""," · £"&TEXT(Z42,"0.00")&" per player"," · price TBC (cost £"&TEXT(V42,"0.00")&" pp)"))
A43: 41 | B43: 1 · E2 Haggerston | C43: Office & professional | D43: Corporate | E43: Shoreditch Platform | F43: rentable | G43: info@shoreditchplatform.com | H43: openstreetmap_tag | I43: +44 20 3319 9640 | K43: 1 Kingsland Road, London | L43: E2 8AA | M43: Shoreditch Rooftop | N43: 14 | O43: =IFERROR(INDEX(Venues!$C$2:$C$10,MATCH(M43,Venues!$A$2:$A$10,0)),"Not checked") | P43: =IFERROR(INDEX(Venues!$D$2:$D$10,MATCH(M43,Venues!$A$2:$A$10,0)),0) | Q43: =IFERROR(INDEX(Venues!$E$2:$E$10,MATCH(M43,Venues!$A$2:$A$10,0)),"") | R43: =IF(P43>0,"Yes","No") | S43: Shoreditch Rooftop | T43: =IFERROR(INDEX(Venues!$E$2:$E$10,MATCH(S43,Venues!$A$2:$A$10,0)),"") | U43: =IFERROR(INDEX(Venues!$F$2:$F$10,MATCH(S43,Venues!$A$2:$A$10,0)),"") | V43: =IFERROR(INDEX(Venues!$H$2:$H$10,MATCH(S43,Venues!$A$2:$A$10,0)),"") | W43: =IF('Pilot offer'!$C$24="Yes",'Pilot offer'!$C$3,S43) | X43: =IF('Pilot offer'!$C$24="Yes",'Pilot offer'!$C$5+'Pilot offer'!$C$6,T43) | Y43: =IF('Pilot offer'!$C$24="Yes",'Pilot offer'!$C$8,U43) | Z43: =IF('Pilot offer'!$C$24="Yes",'Pilot offer'!$C$11,"") | AA43: =IF(X43="","",W43&" · "&TEXT(X43,"ddd d mmm, hh:mm")&" · "&Y43&IF(Z43<>""," · £"&TEXT(Z43,"0.00")&" per player"," · price TBC (cost £"&TEXT(V43,"0.00")&" pp)"))
A44: 42 | B44: 1 · E2 Haggerston | C44: Hospitality | D44: Local businesses | E44: Gramndegrees | F44: amenity: cafe | G44: hello@gramndegrees.co.uk | H44: general | J44: https://www.gramndegrees.co.uk/ | K44: Kingsland Road 93, London | L44: E2 8AG | M44: Shoreditch Rooftop | N44: 10 | O44: =IFERROR(INDEX(Venues!$C$2:$C$10,MATCH(M44,Venues!$A$2:$A$10,0)),"Not checked") | P44: =IFERROR(INDEX(Venues!$D$2:$D$10,MATCH(M44,Venues!$A$2:$A$10,0)),0) | Q44: =IFERROR(INDEX(Venues!$E$2:$E$10,MATCH(M44,Venues!$A$2:$A$10,0)),"") | R44: =IF(P44>0,"Yes","No") | S44: Shoreditch Rooftop | T44: =IFERROR(INDEX(Venues!$E$2:$E$10,MATCH(S44,Venues!$A$2:$A$10,0)),"") | U44: =IFERROR(INDEX(Venues!$F$2:$F$10,MATCH(S44,Venues!$A$2:$A$10,0)),"") | V44: =IFERROR(INDEX(Venues!$H$2:$H$10,MATCH(S44,Venues!$A$2:$A$10,0)),"") | W44: =IF('Pilot offer'!$C$24="Yes",'Pilot offer'!$C$3,S44) | X44: =IF('Pilot offer'!$C$24="Yes",'Pilot offer'!$C$5+'Pilot offer'!$C$6,T44) | Y44: =IF('Pilot offer'!$C$24="Yes",'Pilot offer'!$C$8,U44) | Z44: =IF('Pilot offer'!$C$24="Yes",'Pilot offer'!$C$11,"") | AA44: =IF(X44="","",W44&" · "&TEXT(X44,"ddd d mmm, hh:mm")&" · "&Y44&IF(Z44<>""," · £"&TEXT(Z44,"0.00")&" per player"," · price TBC (cost £"&TEXT(V44,"0.00")&" pp)"))
A45: 43 | B45: 1 · E2 Haggerston | C45: Retail | D45: Local businesses | E45: Longdan | F45: shop: supermarket | G45: longdan@longdan.co.uk | H45: person_or_other | I45: +44 20 7739 3968 | J45: https://longdan.co.uk/ | K45: Kingsland Road 57-59, London | L45: E2 8AG | M45: Shoreditch Rooftop | N45: 11 | O45: =IFERROR(INDEX(Venues!$C$2:$C$10,MATCH(M45,Venues!$A$2:$A$10,0)),"Not checked") | P45: =IFERROR(INDEX(Venues!$D$2:$D$10,MATCH(M45,Venues!$A$2:$A$10,0)),0) | Q45: =IFERROR(INDEX(Venues!$E$2:$E$10,MATCH(M45,Venues!$A$2:$A$10,0)),"") | R45: =IF(P45>0,"Yes","No") | S45: Shoreditch Rooftop | T45: =IFERROR(INDEX(Venues!$E$2:$E$10,MATCH(S45,Venues!$A$2:$A$10,0)),"") | U45: =IFERROR(INDEX(Venues!$F$2:$F$10,MATCH(S45,Venues!$A$2:$A$10,0)),"") | V45: =IFERROR(INDEX(Venues!$H$2:$H$10,MATCH(S45,Venues!$A$2:$A$10,0)),"") | W45: =IF('Pilot offer'!$C$24="Yes",'Pilot offer'!$C$3,S45) | X45: =IF('Pilot offer'!$C$24="Yes",'Pilot offer'!$C$5+'Pilot offer'!$C$6,T45) | Y45: =IF('Pilot offer'!$C$24="Yes",'Pilot offer'!$C$8,U45) | Z45: =IF('Pilot offer'!$C$24="Yes",'Pilot offer'!$C$11,"") | AA45: =IF(X45="","",W45&" · "&TEXT(X45,"ddd d mmm, hh:mm")&" · "&Y45&IF(Z45<>""," · £"&TEXT(Z45,"0.00")&" per player"," · price TBC (cost £"&TEXT(V45,"0.00")&" pp)"))
A46: 44 | B46: 1 · E2 Haggerston | C46: Coworking / shared office | D46: Corporate | E46: UMA Workspace | F46: coworking_space | G46: info@umaworkspace.co.uk | H46: general | J46: http://www.umaworkspace.co.uk/ | K46: Unit 1, 83-85 Kingsland Rd, London E2 8AG, UK | L46: E2 8AG | M46: Shoreditch Rooftop | N46: 11 | O46: =IFERROR(INDEX(Venues!$C$2:$C$10,MATCH(M46,Venues!$A$2:$A$10,0)),"Not checked") | P46: =IFERROR(INDEX(Venues!$D$2:$D$10,MATCH(M46,Venues!$A$2:$A$10,0)),0) | Q46: =IFERROR(INDEX(Venues!$E$2:$E$10,MATCH(M46,Venues!$A$2:$A$10,0)),"") | R46: =IF(P46>0,"Yes","No") | S46: Shoreditch Rooftop | T46: =IFERROR(INDEX(Venues!$E$2:$E$10,MATCH(S46,Venues!$A$2:$A$10,0)),"") | U46: =IFERROR(INDEX(Venues!$F$2:$F$10,MATCH(S46,Venues!$A$2:$A$10,0)),"") | V46: =IFERROR(INDEX(Venues!$H$2:$H$10,MATCH(S46,Venues!$A$2:$A$10,0)),"") | W46: =IF('Pilot offer'!$C$24="Yes",'Pilot offer'!$C$3,S46) | X46: =IF('Pilot offer'!$C$24="Yes",'Pilot offer'!$C$5+'Pilot offer'!$C$6,T46) | Y46: =IF('Pilot offer'!$C$24="Yes",'Pilot offer'!$C$8,U46) | Z46: =IF('Pilot offer'!$C$24="Yes",'Pilot offer'!$C$11,"") | AA46: =IF(X46="","",W46&" · "&TEXT(X46,"ddd d mmm, hh:mm")&" · "&Y46&IF(Z46<>""," · £"&TEXT(Z46,"0.00")&" per player"," · price TBC (cost £"&TEXT(V46,"0.00")&" pp)"))
A47: 45 | B47: 1 · E2 Haggerston | C47: Retail | D47: Local businesses | E47: The Steam Room | F47: shop: dry cleaning | G47: hello@thesteamroom.cleaning | H47: general | J47: https://www.thesteamroom.cleaning/our-story | K47: Kingsland Road 230, London | L47: E2 8AX | M47: COLA Shoreditch Park | N47: 8 | O47: =IFERROR(INDEX(Venues!$C$2:$C$10,MATCH(M47,Venues!$A$2:$A$10,0)),"Not checked") | P47: =IFERROR(INDEX(Venues!$D$2:$D$10,MATCH(M47,Venues!$A$2:$A$10,0)),0) | Q47: =IFERROR(INDEX(Venues!$E$2:$E$10,MATCH(M47,Venues!$A$2:$A$10,0)),"") | R47: =IF(P47>0,"Yes","No") | S47: COLA Shoreditch Park | T47: =IFERROR(INDEX(Venues!$E$2:$E$10,MATCH(S47,Venues!$A$2:$A$10,0)),"") | U47: =IFERROR(INDEX(Venues!$F$2:$F$10,MATCH(S47,Venues!$A$2:$A$10,0)),"") | V47: =IFERROR(INDEX(Venues!$H$2:$H$10,MATCH(S47,Venues!$A$2:$A$10,0)),"") | W47: =IF('Pilot offer'!$C$24="Yes",'Pilot offer'!$C$3,S47) | X47: =IF('Pilot offer'!$C$24="Yes",'Pilot offer'!$C$5+'Pilot offer'!$C$6,T47) | Y47: =IF('Pilot offer'!$C$24="Yes",'Pilot offer'!$C$8,U47) | Z47: =IF('Pilot offer'!$C$24="Yes",'Pilot offer'!$C$11,"") | AA47: =IF(X47="","",W47&" · "&TEXT(X47,"ddd d mmm, hh:mm")&" · "&Y47&IF(Z47<>""," · £"&TEXT(Z47,"0.00")&" per player"," · price TBC (cost £"&TEXT(V47,"0.00")&" pp)"))
A48: 46 | B48: 1 · E2 Haggerston | C48: Education | D48: Local businesses | E48: The Bridge Academy | F48: amenity: school | G48: wgourley@tbah.uk | H48: person_or_other | I48: +44 20 7749 5240 | J48: https://www.tbah.uk/ | K48: Laburnum Street, London | L48: E2 8BA | M48: COLA Shoreditch Park | N48: 12 | O48: =IFERROR(INDEX(Venues!$C$2:$C$10,MATCH(M48,Venues!$A$2:$A$10,0)),"Not checked") | P48: =IFERROR(INDEX(Venues!$D$2:$D$10,MATCH(M48,Venues!$A$2:$A$10,0)),0) | Q48: =IFERROR(INDEX(Venues!$E$2:$E$10,MATCH(M48,Venues!$A$2:$A$10,0)),"") | R48: =IF(P48>0,"Yes","No") | S48: COLA Shoreditch Park | T48: =IFERROR(INDEX(Venues!$E$2:$E$10,MATCH(S48,Venues!$A$2:$A$10,0)),"") | U48: =IFERROR(INDEX(Venues!$F$2:$F$10,MATCH(S48,Venues!$A$2:$A$10,0)),"") | V48: =IFERROR(INDEX(Venues!$H$2:$H$10,MATCH(S48,Venues!$A$2:$A$10,0)),"") | W48: =IF('Pilot offer'!$C$24="Yes",'Pilot offer'!$C$3,S48) | X48: =IF('Pilot offer'!$C$24="Yes",'Pilot offer'!$C$5+'Pilot offer'!$C$6,T48) | Y48: =IF('Pilot offer'!$C$24="Yes",'Pilot offer'!$C$8,U48) | Z48: =IF('Pilot offer'!$C$24="Yes",'Pilot offer'!$C$11,"") | AA48: =IF(X48="","",W48&" · "&TEXT(X48,"ddd d mmm, hh:mm")&" · "&Y48&IF(Z48<>""," · £"&TEXT(Z48,"0.00")&" per player"," · price TBC (cost £"&TEXT(V48,"0.00")&" pp)"))
A49: 47 | B49: 1 · E2 Haggerston | C49: Leisure & culture | D49: Local businesses | E49: Laburnum Boat Club | F49: club: sport | G49: info@laburnumboatclub.com | H49: openstreetmap_tag | I49: +44 20 7729 2915 | J49: https://www.laburnumboatclub.com/ | K49: Laburnum Street, London | L49: E2 8BH | M49: COLA Shoreditch Park | N49: 11 | O49: =IFERROR(INDEX(Venues!$C$2:$C$10,MATCH(M49,Venues!$A$2:$A$10,0)),"Not checked") | P49: =IFERROR(INDEX(Venues!$D$2:$D$10,MATCH(M49,Venues!$A$2:$A$10,0)),0) | Q49: =IFERROR(INDEX(Venues!$E$2:$E$10,MATCH(M49,Venues!$A$2:$A$10,0)),"") | R49: =IF(P49>0,"Yes","No") | S49: COLA Shoreditch Park | T49: =IFERROR(INDEX(Venues!$E$2:$E$10,MATCH(S49,Venues!$A$2:$A$10,0)),"") | U49: =IFERROR(INDEX(Venues!$F$2:$F$10,MATCH(S49,Venues!$A$2:$A$10,0)),"") | V49: =IFERROR(INDEX(Venues!$H$2:$H$10,MATCH(S49,Venues!$A$2:$A$10,0)),"") | W49: =IF('Pilot offer'!$C$24="Yes",'Pilot offer'!$C$3,S49) | X49: =IF('Pilot offer'!$C$24="Yes",'Pilot offer'!$C$5+'Pilot offer'!$C$6,T49) | Y49: =IF('Pilot offer'!$C$24="Yes",'Pilot offer'!$C$8,U49) | Z49: =IF('Pilot offer'!$C$24="Yes",'Pilot offer'!$C$11,"") | AA49: =IF(X49="","",W49&" · "&TEXT(X49,"ddd d mmm, hh:mm")&" · "&Y49&IF(Z49<>""," · £"&TEXT(Z49,"0.00")&" per player"," · price TBC (cost £"&TEXT(V49,"0.00")&" pp)"))
A50: 48 | B50: 1 · E2 Haggerston | C50: Hospitality | D50: Local businesses | E50: East West Pizza | F50: amenity: restaurant | G50: hello@eastwestlondon.com | H50: general | I50: +44 20 7916 6698 | J50: https://www.eastwestlondon.com | K50: Kingsland Road 42-44, London | L50: E2 8DA | M50: Shoreditch Rooftop | N50: 13 | O50: =IFERROR(INDEX(Venues!$C$2:$C$10,MATCH(M50,Venues!$A$2:$A$10,0)),"Not checked") | P50: =IFERROR(INDEX(Venues!$D$2:$D$10,MATCH(M50,Venues!$A$2:$A$10,0)),0) | Q50: =IFERROR(INDEX(Venues!$E$2:$E$10,MATCH(M50,Venues!$A$2:$A$10,0)),"") | R50: =IF(P50>0,"Yes","No") | S50: Shoreditch Rooftop | T50: =IFERROR(INDEX(Venues!$E$2:$E$10,MATCH(S50,Venues!$A$2:$A$10,0)),"") | U50: =IFERROR(INDEX(Venues!$F$2:$F$10,MATCH(S50,Venues!$A$2:$A$10,0)),"") | V50: =IFERROR(INDEX(Venues!$H$2:$H$10,MATCH(S50,Venues!$A$2:$A$10,0)),"") | W50: =IF('Pilot offer'!$C$24="Yes",'Pilot offer'!$C$3,S50) | X50: =IF('Pilot offer'!$C$24="Yes",'Pilot offer'!$C$5+'Pilot offer'!$C$6,T50) | Y50: =IF('Pilot offer'!$C$24="Yes",'Pilot offer'!$C$8,U50) | Z50: =IF('Pilot offer'!$C$24="Yes",'Pilot offer'!$C$11,"") | AA50: =IF(X50="","",W50&" · "&TEXT(X50,"ddd d mmm, hh:mm")&" · "&Y50&IF(Z50<>""," · £"&TEXT(Z50,"0.00")&" per player"," · price TBC (cost £"&TEXT(V50,"0.00")&" pp)"))
A51: 49 | B51: 1 · E2 Haggerston | C51: Hospitality | D51: Local businesses | E51: Gyros Lab | F51: amenity: fast food | G51: info@gyroslab.com | H51: general | I51: +44 20 3337 5856 | J51: https://www.gyroslab.com/ | K51: Kingsland Road 2, London | L51: E2 8DA | M51: Shoreditch Rooftop | N51: 15 | O51: =IFERROR(INDEX(Venues!$C$2:$C$10,MATCH(M51,Venues!$A$2:$A$10,0)),"Not checked") | P51: =IFERROR(INDEX(Venues!$D$2:$D$10,MATCH(M51,Venues!$A$2:$A$10,0)),0) | Q51: =IFERROR(INDEX(Venues!$E$2:$E$10,MATCH(M51,Venues!$A$2:$A$10,0)),"") | R51: =IF(P51>0,"Yes","No") | S51: Shoreditch Rooftop | T51: =IFERROR(INDEX(Venues!$E$2:$E$10,MATCH(S51,Venues!$A$2:$A$10,0)),"") | U51: =IFERROR(INDEX(Venues!$F$2:$F$10,MATCH(S51,Venues!$A$2:$A$10,0)),"") | V51: =IFERROR(INDEX(Venues!$H$2:$H$10,MATCH(S51,Venues!$A$2:$A$10,0)),"") | W51: =IF('Pilot offer'!$C$24="Yes",'Pilot offer'!$C$3,S51) | X51: =IF('Pilot offer'!$C$24="Yes",'Pilot offer'!$C$5+'Pilot offer'!$C$6,T51) | Y51: =IF('Pilot offer'!$C$24="Yes",'Pilot offer'!$C$8,U51) | Z51: =IF('Pilot offer'!$C$24="Yes",'Pilot offer'!$C$11,"") | AA51: =IF(X51="","",W51&" · "&TEXT(X51,"ddd d mmm, hh:mm")&" · "&Y51&IF(Z51<>""," · £"&TEXT(Z51,"0.00")&" per player"," · price TBC (cost £"&TEXT(V51,"0.00")&" pp)"))
A52: 50 | B52: 1 · E2 Haggerston | C52: Office & professional | D52: Corporate | E52: TOWER London - Head Office | F52: corporate_office | G52: customer-services@tower-london.com | H52: person_or_other | I52: +44 20 7781 8500 | J52: https://www.tower-london.com/ | K52: 16g, Hope House, 38 Kingsland Rd, London E2 8DD, UK | L52: E2 8DD | M52: Shoreditch Rooftop | N52: 14 | O52: =IFERROR(INDEX(Venues!$C$2:$C$10,MATCH(M52,Venues!$A$2:$A$10,0)),"Not checked") | P52: =IFERROR(INDEX(Venues!$D$2:$D$10,MATCH(M52,Venues!$A$2:$A$10,0)),0) | Q52: =IFERROR(INDEX(Venues!$E$2:$E$10,MATCH(M52,Venues!$A$2:$A$10,0)),"") | R52: =IF(P52>0,"Yes","No") | S52: Shoreditch Rooftop | T52: =IFERROR(INDEX(Venues!$E$2:$E$10,MATCH(S52,Venues!$A$2:$A$10,0)),"") | U52: =IFERROR(INDEX(Venues!$F$2:$F$10,MATCH(S52,Venues!$A$2:$A$10,0)),"") | V52: =IFERROR(INDEX(Venues!$H$2:$H$10,MATCH(S52,Venues!$A$2:$A$10,0)),"") | W52: =IF('Pilot offer'!$C$24="Yes",'Pilot offer'!$C$3,S52) | X52: =IF('Pilot offer'!$C$24="Yes",'Pilot offer'!$C$5+'Pilot offer'!$C$6,T52) | Y52: =IF('Pilot offer'!$C$24="Yes",'Pilot offer'!$C$8,U52) | Z52: =IF('Pilot offer'!$C$24="Yes",'Pilot offer'!$C$11,"") | AA52: =IF(X52="","",W52&" · "&TEXT(X52,"ddd d mmm, hh:mm")&" · "&Y52&IF(Z52<>""," · £"&TEXT(Z52,"0.00")&" per player"," · price TBC (cost £"&TEXT(V52,"0.00")&" pp)"))
A53: 51 | B53: 1 · E2 Haggerston | C53: Hospitality | D53: Local businesses | E53: Central Hoxton | F53: tourism: hotel | G53: hello@centralhoxton.com | H53: openstreetmap_tag | I53: +44 20 7739 0846 | J53: https://www.centralhoxton.com/ | K53: Kingsland Road 100, London | L53: E2 8DP | M53: Shoreditch Rooftop | N53: 11 | O53: =IFERROR(INDEX(Venues!$C$2:$C$10,MATCH(M53,Venues!$A$2:$A$10,0)),"Not checked") | P53: =IFERROR(INDEX(Venues!$D$2:$D$10,MATCH(M53,Venues!$A$2:$A$10,0)),0) | Q53: =IFERROR(INDEX(Venues!$E$2:$E$10,MATCH(M53,Venues!$A$2:$A$10,0)),"") | R53: =IF(P53>0,"Yes","No") | S53: Shoreditch Rooftop | T53: =IFERROR(INDEX(Venues!$E$2:$E$10,MATCH(S53,Venues!$A$2:$A$10,0)),"") | U53: =IFERROR(INDEX(Venues!$F$2:$F$10,MATCH(S53,Venues!$A$2:$A$10,0)),"") | V53: =IFERROR(INDEX(Venues!$H$2:$H$10,MATCH(S53,Venues!$A$2:$A$10,0)),"") | W53: =IF('Pilot offer'!$C$24="Yes",'Pilot offer'!$C$3,S53) | X53: =IF('Pilot offer'!$C$24="Yes",'Pilot offer'!$C$5+'Pilot offer'!$C$6,T53) | Y53: =IF('Pilot offer'!$C$24="Yes",'Pilot offer'!$C$8,U53) | Z53: =IF('Pilot offer'!$C$24="Yes",'Pilot offer'!$C$11,"") | AA53: =IF(X53="","",W53&" · "&TEXT(X53,"ddd d mmm, hh:mm")&" · "&Y53&IF(Z53<>""," · £"&TEXT(Z53,"0.00")&" per player"," · price TBC (cost £"&TEXT(V53,"0.00")&" pp)"))
A54: 52 | B54: 1 · E2 Haggerston | C54: Retail | D54: Local businesses | E54: The Grocery | F54: shop: supermarket | G54: info@thegroceryshop.co.uk | H54: openstreetmap_tag | I54: +44 20 7729 6855 | J54: https://www.thegroceryshop.co.uk/ | K54: Kingsland Road 52-56, London | L54: E2 8DP | M54: Shoreditch Rooftop | N54: 12 | O54: =IFERROR(INDEX(Venues!$C$2:$C$10,MATCH(M54,Venues!$A$2:$A$10,0)),"Not checked") | P54: =IFERROR(INDEX(Venues!$D$2:$D$10,MATCH(M54,Venues!$A$2:$A$10,0)),0) | Q54: =IFERROR(INDEX(Venues!$E$2:$E$10,MATCH(M54,Venues!$A$2:$A$10,0)),"") | R54: =IF(P54>0,"Yes","No") | S54: Shoreditch Rooftop | T54: =IFERROR(INDEX(Venues!$E$2:$E$10,MATCH(S54,Venues!$A$2:$A$10,0)),"") | U54: =IFERROR(INDEX(Venues!$F$2:$F$10,MATCH(S54,Venues!$A$2:$A$10,0)),"") | V54: =IFERROR(INDEX(Venues!$H$2:$H$10,MATCH(S54,Venues!$A$2:$A$10,0)),"") | W54: =IF('Pilot offer'!$C$24="Yes",'Pilot offer'!$C$3,S54) | X54: =IF('Pilot offer'!$C$24="Yes",'Pilot offer'!$C$5+'Pilot offer'!$C$6,T54) | Y54: =IF('Pilot offer'!$C$24="Yes",'Pilot offer'!$C$8,U54) | Z54: =IF('Pilot offer'!$C$24="Yes",'Pilot offer'!$C$11,"") | AA54: =IF(X54="","",W54&" · "&TEXT(X54,"ddd d mmm, hh:mm")&" · "&Y54&IF(Z54<>""," · £"&TEXT(Z54,"0.00")&" per player"," · price TBC (cost £"&TEXT(V54,"0.00")&" pp)"))
A55: 53 | B55: 1 · E2 Haggerston | C55: Office & professional | D55: Corporate | E55: Aazz Ai Seo Agency London | F55: service | G55: sales@aazzagency.co.uk | H55: commercial | I55: +44 7988 595628 | J55: https://aazzagency.co.uk/ | K55: studio 6, Shoreditch Stables, 138 Kingsland Rd, London E2 8DY, UK | L55: E2 8DY | M55: Shoreditch Rooftop | N55: 9 | O55: =IFERROR(INDEX(Venues!$C$2:$C$10,MATCH(M55,Venues!$A$2:$A$10,0)),"Not checked") | P55: =IFERROR(INDEX(Venues!$D$2:$D$10,MATCH(M55,Venues!$A$2:$A$10,0)),0) | Q55: =IFERROR(INDEX(Venues!$E$2:$E$10,MATCH(M55,Venues!$A$2:$A$10,0)),"") | R55: =IF(P55>0,"Yes","No") | S55: Shoreditch Rooftop | T55: =IFERROR(INDEX(Venues!$E$2:$E$10,MATCH(S55,Venues!$A$2:$A$10,0)),"") | U55: =IFERROR(INDEX(Venues!$F$2:$F$10,MATCH(S55,Venues!$A$2:$A$10,0)),"") | V55: =IFERROR(INDEX(Venues!$H$2:$H$10,MATCH(S55,Venues!$A$2:$A$10,0)),"") | W55: =IF('Pilot offer'!$C$24="Yes",'Pilot offer'!$C$3,S55) | X55: =IF('Pilot offer'!$C$24="Yes",'Pilot offer'!$C$5+'Pilot offer'!$C$6,T55) | Y55: =IF('Pilot offer'!$C$24="Yes",'Pilot offer'!$C$8,U55) | Z55: =IF('Pilot offer'!$C$24="Yes",'Pilot offer'!$C$11,"") | AA55: =IF(X55="","",W55&" · "&TEXT(X55,"ddd d mmm, hh:mm")&" · "&Y55&IF(Z55<>""," · £"&TEXT(Z55,"0.00")&" per player"," · price TBC (cost £"&TEXT(V55,"0.00")&" pp)"))
A56: 54 | B56: 1 · E2 Haggerston | C56: Office & professional | D56: Corporate | E56: Charles Luf & Co | F56: lawyer | G56: enquiries@charlesluf.com | H56: general | J56: https://charlesluf.com/ | K56: 134D Kingsland Road, London | L56: E2 8DY | M56: Shoreditch Rooftop | N56: 10 | O56: =IFERROR(INDEX(Venues!$C$2:$C$10,MATCH(M56,Venues!$A$2:$A$10,0)),"Not checked") | P56: =IFERROR(INDEX(Venues!$D$2:$D$10,MATCH(M56,Venues!$A$2:$A$10,0)),0) | Q56: =IFERROR(INDEX(Venues!$E$2:$E$10,MATCH(M56,Venues!$A$2:$A$10,0)),"") | R56: =IF(P56>0,"Yes","No") | S56: Shoreditch Rooftop | T56: =IFERROR(INDEX(Venues!$E$2:$E$10,MATCH(S56,Venues!$A$2:$A$10,0)),"") | U56: =IFERROR(INDEX(Venues!$F$2:$F$10,MATCH(S56,Venues!$A$2:$A$10,0)),"") | V56: =IFERROR(INDEX(Venues!$H$2:$H$10,MATCH(S56,Venues!$A$2:$A$10,0)),"") | W56: =IF('Pilot offer'!$C$24="Yes",'Pilot offer'!$C$3,S56) | X56: =IF('Pilot offer'!$C$24="Yes",'Pilot offer'!$C$5+'Pilot offer'!$C$6,T56) | Y56: =IF('Pilot offer'!$C$24="Yes",'Pilot offer'!$C$8,U56) | Z56: =IF('Pilot offer'!$C$24="Yes",'Pilot offer'!$C$11,"") | AA56: =IF(X56="","",W56&" · "&TEXT(X56,"ddd d mmm, hh:mm")&" · "&Y56&IF(Z56<>""," · £"&TEXT(Z56,"0.00")&" per player"," · price TBC (cost £"&TEXT(V56,"0.00")&" pp)"))
A57: 55 | B57: 1 · E2 Haggerston | C57: Leisure & culture | D57: Local businesses | E57: Museum of the Home | F57: tourism: museum | G57: bookings@museumofthehome.org.uk | H57: openstreetmap_tag | I57: +44 20 7739 9893 | J57: https://www.museumofthehome.org.uk/ | K57: Kingsland Road 136, London | L57: E2 8EA | M57: Shoreditch Rooftop | N57: 10 | O57: =IFERROR(INDEX(Venues!$C$2:$C$10,MATCH(M57,Venues!$A$2:$A$10,0)),"Not checked") | P57: =IFERROR(INDEX(Venues!$D$2:$D$10,MATCH(M57,Venues!$A$2:$A$10,0)),0) | Q57: =IFERROR(INDEX(Venues!$E$2:$E$10,MATCH(M57,Venues!$A$2:$A$10,0)),"") | R57: =IF(P57>0,"Yes","No") | S57: Shoreditch Rooftop | T57: =IFERROR(INDEX(Venues!$E$2:$E$10,MATCH(S57,Venues!$A$2:$A$10,0)),"") | U57: =IFERROR(INDEX(Venues!$F$2:$F$10,MATCH(S57,Venues!$A$2:$A$10,0)),"") | V57: =IFERROR(INDEX(Venues!$H$2:$H$10,MATCH(S57,Venues!$A$2:$A$10,0)),"") | W57: =IF('Pilot offer'!$C$24="Yes",'Pilot offer'!$C$3,S57) | X57: =IF('Pilot offer'!$C$24="Yes",'Pilot offer'!$C$5+'Pilot offer'!$C$6,T57) | Y57: =IF('Pilot offer'!$C$24="Yes",'Pilot offer'!$C$8,U57) | Z57: =IF('Pilot offer'!$C$24="Yes",'Pilot offer'!$C$11,"") | AA57: =IF(X57="","",W57&" · "&TEXT(X57,"ddd d mmm, hh:mm")&" · "&Y57&IF(Z57<>""," · £"&TEXT(Z57,"0.00")&" per player"," · price TBC (cost £"&TEXT(V57,"0.00")&" pp)"))
A58: 56 | B58: 1 · E2 Haggerston | C58: Hospitality | D58: Local businesses | E58: The Arcanist's Tavern | F58: amenity: bar | G58: inquiries@alchemygames.uk | H58: openstreetmap_tag | I58: +44 20 8191 2983 | J58: https://arcaniststavern.uk/ | K58: Hackney Road 87-91, London | L58: E2 8FE | M58: Shoreditch Rooftop | N58: 13 | O58: =IFERROR(INDEX(Venues!$C$2:$C$10,MATCH(M58,Venues!$A$2:$A$10,0)),"Not checked") | P58: =IFERROR(INDEX(Venues!$D$2:$D$10,MATCH(M58,Venues!$A$2:$A$10,0)),0) | Q58: =IFERROR(INDEX(Venues!$E$2:$E$10,MATCH(M58,Venues!$A$2:$A$10,0)),"") | R58: =IF(P58>0,"Yes","No") | S58: Shoreditch Rooftop | T58: =IFERROR(INDEX(Venues!$E$2:$E$10,MATCH(S58,Venues!$A$2:$A$10,0)),"") | U58: =IFERROR(INDEX(Venues!$F$2:$F$10,MATCH(S58,Venues!$A$2:$A$10,0)),"") | V58: =IFERROR(INDEX(Venues!$H$2:$H$10,MATCH(S58,Venues!$A$2:$A$10,0)),"") | W58: =IF('Pilot offer'!$C$24="Yes",'Pilot offer'!$C$3,S58) | X58: =IF('Pilot offer'!$C$24="Yes",'Pilot offer'!$C$5+'Pilot offer'!$C$6,T58) | Y58: =IF('Pilot offer'!$C$24="Yes",'Pilot offer'!$C$8,U58) | Z58: =IF('Pilot offer'!$C$24="Yes",'Pilot offer'!$C$11,"") | AA58: =IF(X58="","",W58&" · "&TEXT(X58,"ddd d mmm, hh:mm")&" · "&Y58&IF(Z58<>""," · £"&TEXT(Z58,"0.00")&" per player"," · price TBC (cost £"&TEXT(V58,"0.00")&" pp)"))
A59: 57 | B59: 1 · E2 Haggerston | C59: Leisure & culture | D59: Local businesses | E59: Centre 151 | F59: amenity: community centre | G59: info@centre151.com | H59: general | I59: +44 20 7739 3650 | J59: https://www.centre151.com/ | K59: Whiston Road 151, London | L59: E2 8GU | M59: COLA Shoreditch Park | N59: 14 | O59: =IFERROR(INDEX(Venues!$C$2:$C$10,MATCH(M59,Venues!$A$2:$A$10,0)),"Not checked") | P59: =IFERROR(INDEX(Venues!$D$2:$D$10,MATCH(M59,Venues!$A$2:$A$10,0)),0) | Q59: =IFERROR(INDEX(Venues!$E$2:$E$10,MATCH(M59,Venues!$A$2:$A$10,0)),"") | R59: =IF(P59>0,"Yes","No") | S59: COLA Shoreditch Park | T59: =IFERROR(INDEX(Venues!$E$2:$E$10,MATCH(S59,Venues!$A$2:$A$10,0)),"") | U59: =IFERROR(INDEX(Venues!$F$2:$F$10,MATCH(S59,Venues!$A$2:$A$10,0)),"") | V59: =IFERROR(INDEX(Venues!$H$2:$H$10,MATCH(S59,Venues!$A$2:$A$10,0)),"") | W59: =IF('Pilot offer'!$C$24="Yes",'Pilot offer'!$C$3,S59) | X59: =IF('Pilot offer'!$C$24="Yes",'Pilot offer'!$C$5+'Pilot offer'!$C$6,T59) | Y59: =IF('Pilot offer'!$C$24="Yes",'Pilot offer'!$C$8,U59) | Z59: =IF('Pilot offer'!$C$24="Yes",'Pilot offer'!$C$11,"") | AA59: =IF(X59="","",W59&" · "&TEXT(X59,"ddd d mmm, hh:mm")&" · "&Y59&IF(Z59<>""," · £"&TEXT(Z59,"0.00")&" per player"," · price TBC (cost £"&TEXT(V59,"0.00")&" pp)"))
A60: 58 | B60: 1 · E2 Haggerston | C60: Retail | D60: Local businesses | E60: Butchers Salon | F60: shop: hairdresser | G60: hoxton@butcherssalon.com | H60: person_or_other | I60: +44 20 7613 4313 | J60: https://www.butcherssalon.com | K60: Cremer Street, London | L60: E2 8GX | M60: Shoreditch Rooftop | N60: 13 | O60: =IFERROR(INDEX(Venues!$C$2:$C$10,MATCH(M60,Venues!$A$2:$A$10,0)),"Not checked") | P60: =IFERROR(INDEX(Venues!$D$2:$D$10,MATCH(M60,Venues!$A$2:$A$10,0)),0) | Q60: =IFERROR(INDEX(Venues!$E$2:$E$10,MATCH(M60,Venues!$A$2:$A$10,0)),"") | R60: =IF(P60>0,"Yes","No") | S60: Shoreditch Rooftop | T60: =IFERROR(INDEX(Venues!$E$2:$E$10,MATCH(S60,Venues!$A$2:$A$10,0)),"") | U60: =IFERROR(INDEX(Venues!$F$2:$F$10,MATCH(S60,Venues!$A$2:$A$10,0)),"") | V60: =IFERROR(INDEX(Venues!$H$2:$H$10,MATCH(S60,Venues!$A$2:$A$10,0)),"") | W60: =IF('Pilot offer'!$C$24="Yes",'Pilot offer'!$C$3,S60) | X60: =IF('Pilot offer'!$C$24="Yes",'Pilot offer'!$C$5+'Pilot offer'!$C$6,T60) | Y60: =IF('Pilot offer'!$C$24="Yes",'Pilot offer'!$C$8,U60) | Z60: =IF('Pilot offer'!$C$24="Yes",'Pilot offer'!$C$11,"") | AA60: =IF(X60="","",W60&" · "&TEXT(X60,"ddd d mmm, hh:mm")&" · "&Y60&IF(Z60<>""," · £"&TEXT(Z60,"0.00")&" per player"," · price TBC (cost £"&TEXT(V60,"0.00")&" pp)"))
A61: 59 | B61: 1 · E2 Haggerston | C61: Hospitality | D61: Local businesses | E61: Gaia Bistro | F61: amenity: restaurant | G61: marketing@gaiabistro.co.uk | H61: openstreetmap_tag | I61: +44 20 4547 2760 | J61: https://gaiabistro.co.uk/ | K61: Hackney Road, London | L61: E2 8GY | M61: Shoreditch Rooftop | N61: 13 | O61: =IFERROR(INDEX(Venues!$C$2:$C$10,MATCH(M61,Venues!$A$2:$A$10,0)),"Not checked") | P61: =IFERROR(INDEX(Venues!$D$2:$D$10,MATCH(M61,Venues!$A$2:$A$10,0)),0) | Q61: =IFERROR(INDEX(Venues!$E$2:$E$10,MATCH(M61,Venues!$A$2:$A$10,0)),"") | R61: =IF(P61>0,"Yes","No") | S61: Shoreditch Rooftop | T61: =IFERROR(INDEX(Venues!$E$2:$E$10,MATCH(S61,Venues!$A$2:$A$10,0)),"") | U61: =IFERROR(INDEX(Venues!$F$2:$F$10,MATCH(S61,Venues!$A$2:$A$10,0)),"") | V61: =IFERROR(INDEX(Venues!$H$2:$H$10,MATCH(S61,Venues!$A$2:$A$10,0)),"") | W61: =IF('Pilot offer'!$C$24="Yes",'Pilot offer'!$C$3,S61) | X61: =IF('Pilot offer'!$C$24="Yes",'Pilot offer'!$C$5+'Pilot offer'!$C$6,T61) | Y61: =IF('Pilot offer'!$C$24="Yes",'Pilot offer'!$C$8,U61) | Z61: =IF('Pilot offer'!$C$24="Yes",'Pilot offer'!$C$11,"") | AA61: =IF(X61="","",W61&" · "&TEXT(X61,"ddd d mmm, hh:mm")&" · "&Y61&IF(Z61<>""," · £"&TEXT(Z61,"0.00")&" per player"," · price TBC (cost £"&TEXT(V61,"0.00")&" pp)"))
A62: 60 | B62: 1 · E2 Haggerston | C62: Leisure & culture | D62: Local businesses | E62: Legacy Martial Arts | F62: amenity: dojo | G62: info@legacymartialartslondon.co.uk | H62: openstreetmap_tag | J62: https://www.legacymartialartslondon.co.uk/ | K62: Cremer Street 403, London | L62: E2 8HB | M62: Shoreditch Rooftop | N62: 11 | O62: =IFERROR(INDEX(Venues!$C$2:$C$10,MATCH(M62,Venues!$A$2:$A$10,0)),"Not checked") | P62: =IFERROR(INDEX(Venues!$D$2:$D$10,MATCH(M62,Venues!$A$2:$A$10,0)),0) | Q62: =IFERROR(INDEX(Venues!$E$2:$E$10,MATCH(M62,Venues!$A$2:$A$10,0)),"") | R62: =IF(P62>0,"Yes","No") | S62: Shoreditch Rooftop | T62: =IFERROR(INDEX(Venues!$E$2:$E$10,MATCH(S62,Venues!$A$2:$A$10,0)),"") | U62: =IFERROR(INDEX(Venues!$F$2:$F$10,MATCH(S62,Venues!$A$2:$A$10,0)),"") | V62: =IFERROR(INDEX(Venues!$H$2:$H$10,MATCH(S62,Venues!$A$2:$A$10,0)),"") | W62: =IF('Pilot offer'!$C$24="Yes",'Pilot offer'!$C$3,S62) | X62: =IF('Pilot offer'!$C$24="Yes",'Pilot offer'!$C$5+'Pilot offer'!$C$6,T62) | Y62: =IF('Pilot offer'!$C$24="Yes",'Pilot offer'!$C$8,U62) | Z62: =IF('Pilot offer'!$C$24="Yes",'Pilot offer'!$C$11,"") | AA62: =IF(X62="","",W62&" · "&TEXT(X62,"ddd d mmm, hh:mm")&" · "&Y62&IF(Z62<>""," · £"&TEXT(Z62,"0.00")&" per player"," · price TBC (cost £"&TEXT(V62,"0.00")&" pp)"))
A63: 61 | B63: 1 · E2 Haggerston | C63: Office & professional | D63: Corporate | E63: BioPak Head Office | F63: manufacturer | G63: sales@biopak.com | H63: commercial | I63: +44 1386 555777 | J63: https://www.biopak.com/uk | K63: Room G01, Brickfields Business Centre, 37 Cremer St, London E2 8HD, UK | L63: E2 8HD | M63: Shoreditch Rooftop | N63: 11 | O63: =IFERROR(INDEX(Venues!$C$2:$C$10,MATCH(M63,Venues!$A$2:$A$10,0)),"Not checked") | P63: =IFERROR(INDEX(Venues!$D$2:$D$10,MATCH(M63,Venues!$A$2:$A$10,0)),0) | Q63: =IFERROR(INDEX(Venues!$E$2:$E$10,MATCH(M63,Venues!$A$2:$A$10,0)),"") | R63: =IF(P63>0,"Yes","No") | S63: Shoreditch Rooftop | T63: =IFERROR(INDEX(Venues!$E$2:$E$10,MATCH(S63,Venues!$A$2:$A$10,0)),"") | U63: =IFERROR(INDEX(Venues!$F$2:$F$10,MATCH(S63,Venues!$A$2:$A$10,0)),"") | V63: =IFERROR(INDEX(Venues!$H$2:$H$10,MATCH(S63,Venues!$A$2:$A$10,0)),"") | W63: =IF('Pilot offer'!$C$24="Yes",'Pilot offer'!$C$3,S63) | X63: =IF('Pilot offer'!$C$24="Yes",'Pilot offer'!$C$5+'Pilot offer'!$C$6,T63) | Y63: =IF('Pilot offer'!$C$24="Yes",'Pilot offer'!$C$8,U63) | Z63: =IF('Pilot offer'!$C$24="Yes",'Pilot offer'!$C$11,"") | AA63: =IF(X63="","",W63&" · "&TEXT(X63,"ddd d mmm, hh:mm")&" · "&Y63&IF(Z63<>""," · £"&TEXT(Z63,"0.00")&" per player"," · price TBC (cost £"&TEXT(V63,"0.00")&" pp)"))
A64: 62 | B64: 1 · E2 Haggerston | C64: Office & professional | D64: Corporate | E64: Magnetic London | F64: service | G64: hello@magnetic-london.co.uk | H64: general | I64: +44 20 7193 3747 | J64: https://www.magnetic-london.co.uk/?utm_source=google&utm_medium=wix_google_business_profile&utm_campaign=13745144260154332613 | K64: Studio 123, Brickfield Business Centre, 37 Cremer St, London E2 8HD, UK | L64: E2 8HD | M64: Shoreditch Rooftop | N64: 11 | O64: =IFERROR(INDEX(Venues!$C$2:$C$10,MATCH(M64,Venues!$A$2:$A$10,0)),"Not checked") | P64: =IFERROR(INDEX(Venues!$D$2:$D$10,MATCH(M64,Venues!$A$2:$A$10,0)),0) | Q64: =IFERROR(INDEX(Venues!$E$2:$E$10,MATCH(M64,Venues!$A$2:$A$10,0)),"") | R64: =IF(P64>0,"Yes","No") | S64: Shoreditch Rooftop | T64: =IFERROR(INDEX(Venues!$E$2:$E$10,MATCH(S64,Venues!$A$2:$A$10,0)),"") | U64: =IFERROR(INDEX(Venues!$F$2:$F$10,MATCH(S64,Venues!$A$2:$A$10,0)),"") | V64: =IFERROR(INDEX(Venues!$H$2:$H$10,MATCH(S64,Venues!$A$2:$A$10,0)),"") | W64: =IF('Pilot offer'!$C$24="Yes",'Pilot offer'!$C$3,S64) | X64: =IF('Pilot offer'!$C$24="Yes",'Pilot offer'!$C$5+'Pilot offer'!$C$6,T64) | Y64: =IF('Pilot offer'!$C$24="Yes",'Pilot offer'!$C$8,U64) | Z64: =IF('Pilot offer'!$C$24="Yes",'Pilot offer'!$C$11,"") | AA64: =IF(X64="","",W64&" · "&TEXT(X64,"ddd d mmm, hh:mm")&" · "&Y64&IF(Z64<>""," · £"&TEXT(Z64,"0.00")&" per player"," · price TBC (cost £"&TEXT(V64,"0.00")&" pp)"))
A65: 63 | B65: 1 · E2 Haggerston | C65: Leisure & culture | D65: Local businesses | E65: Outset Studio - Hoxton | F65: amenity: studio | G65: hello@outsetstudio.com | H65: openstreetmap_tag | I65: +44 20 3151 3242 | J65: https://outsetstudio.com/ | K65: Cremer Street 37, London | L65: E2 8HD | M65: Shoreditch Rooftop | N65: 11 | O65: =IFERROR(INDEX(Venues!$C$2:$C$10,MATCH(M65,Venues!$A$2:$A$10,0)),"Not checked") | P65: =IFERROR(INDEX(Venues!$D$2:$D$10,MATCH(M65,Venues!$A$2:$A$10,0)),0) | Q65: =IFERROR(INDEX(Venues!$E$2:$E$10,MATCH(M65,Venues!$A$2:$A$10,0)),"") | R65: =IF(P65>0,"Yes","No") | S65: Shoreditch Rooftop | T65: =IFERROR(INDEX(Venues!$E$2:$E$10,MATCH(S65,Venues!$A$2:$A$10,0)),"") | U65: =IFERROR(INDEX(Venues!$F$2:$F$10,MATCH(S65,Venues!$A$2:$A$10,0)),"") | V65: =IFERROR(INDEX(Venues!$H$2:$H$10,MATCH(S65,Venues!$A$2:$A$10,0)),"") | W65: =IF('Pilot offer'!$C$24="Yes",'Pilot offer'!$C$3,S65) | X65: =IF('Pilot offer'!$C$24="Yes",'Pilot offer'!$C$5+'Pilot offer'!$C$6,T65) | Y65: =IF('Pilot offer'!$C$24="Yes",'Pilot offer'!$C$8,U65) | Z65: =IF('Pilot offer'!$C$24="Yes",'Pilot offer'!$C$11,"") | AA65: =IF(X65="","",W65&" · "&TEXT(X65,"ddd d mmm, hh:mm")&" · "&Y65&IF(Z65<>""," · £"&TEXT(Z65,"0.00")&" per player"," · price TBC (cost £"&TEXT(V65,"0.00")&" pp)"))
A66: 64 | B66: 1 · E2 Haggerston | C66: Office & professional | D66: Corporate | E66: Docklands Accountancy | F66: finance | G66: info@docklandsacc.com | H66: general | I66: +44 20 7033 9123 | J66: https://docklandsacc.com/ | K66: 10 Waterson St, London E2 8HE, UK | L66: E2 8HE | M66: Shoreditch Rooftop | N66: 13 | O66: =IFERROR(INDEX(Venues!$C$2:$C$10,MATCH(M66,Venues!$A$2:$A$10,0)),"Not checked") | P66: =IFERROR(INDEX(Venues!$D$2:$D$10,MATCH(M66,Venues!$A$2:$A$10,0)),0) | Q66: =IFERROR(INDEX(Venues!$E$2:$E$10,MATCH(M66,Venues!$A$2:$A$10,0)),"") | R66: =IF(P66>0,"Yes","No") | S66: Shoreditch Rooftop | T66: =IFERROR(INDEX(Venues!$E$2:$E$10,MATCH(S66,Venues!$A$2:$A$10,0)),"") | U66: =IFERROR(INDEX(Venues!$F$2:$F$10,MATCH(S66,Venues!$A$2:$A$10,0)),"") | V66: =IFERROR(INDEX(Venues!$H$2:$H$10,MATCH(S66,Venues!$A$2:$A$10,0)),"") | W66: =IF('Pilot offer'!$C$24="Yes",'Pilot offer'!$C$3,S66) | X66: =IF('Pilot offer'!$C$24="Yes",'Pilot offer'!$C$5+'Pilot offer'!$C$6,T66) | Y66: =IF('Pilot offer'!$C$24="Yes",'Pilot offer'!$C$8,U66) | Z66: =IF('Pilot offer'!$C$24="Yes",'Pilot offer'!$C$11,"") | AA66: =IF(X66="","",W66&" · "&TEXT(X66,"ddd d mmm, hh:mm")&" · "&Y66&IF(Z66<>""," · £"&TEXT(Z66,"0.00")&" per player"," · price TBC (cost £"&TEXT(V66,"0.00")&" pp)"))
A67: 65 | B67: 1 · E2 Haggerston | C67: Retail | D67: Local businesses | E67: Jackson's Framing | F67: shop: frame | G67: sales@jacksonsframing.co.uk | H67: openstreetmap_tag | J67: jacksonsframing.co.uk | K67: Long Street 18 B, London | L67: E2 8HQ | M67: Shoreditch Rooftop | N67: 13 | O67: =IFERROR(INDEX(Venues!$C$2:$C$10,MATCH(M67,Venues!$A$2:$A$10,0)),"Not checked") | P67: =IFERROR(INDEX(Venues!$D$2:$D$10,MATCH(M67,Venues!$A$2:$A$10,0)),0) | Q67: =IFERROR(INDEX(Venues!$E$2:$E$10,MATCH(M67,Venues!$A$2:$A$10,0)),"") | R67: =IF(P67>0,"Yes","No") | S67: Shoreditch Rooftop | T67: =IFERROR(INDEX(Venues!$E$2:$E$10,MATCH(S67,Venues!$A$2:$A$10,0)),"") | U67: =IFERROR(INDEX(Venues!$F$2:$F$10,MATCH(S67,Venues!$A$2:$A$10,0)),"") | V67: =IFERROR(INDEX(Venues!$H$2:$H$10,MATCH(S67,Venues!$A$2:$A$10,0)),"") | W67: =IF('Pilot offer'!$C$24="Yes",'Pilot offer'!$C$3,S67) | X67: =IF('Pilot offer'!$C$24="Yes",'Pilot offer'!$C$5+'Pilot offer'!$C$6,T67) | Y67: =IF('Pilot offer'!$C$24="Yes",'Pilot offer'!$C$8,U67) | Z67: =IF('Pilot offer'!$C$24="Yes",'Pilot offer'!$C$11,"") | AA67: =IF(X67="","",W67&" · "&TEXT(X67,"ddd d mmm, hh:mm")&" · "&Y67&IF(Z67<>""," · £"&TEXT(Z67,"0.00")&" per player"," · price TBC (cost £"&TEXT(V67,"0.00")&" pp)"))
A68: 66 | B68: 1 · E2 Haggerston | C68: Leisure & culture | D68: Local businesses | E68: Hundred Years Gallery | F68: tourism: gallery | G68: info@hundredyearsgallery.com | H68: openstreetmap_tag | I68: +44 20 3602 7973 | J68: http://hundredyearsgallery.co.uk/ | K68: Pearson Street 13, London | L68: E2 8JD | M68: Shoreditch Rooftop | N68: 9 | O68: =IFERROR(INDEX(Venues!$C$2:$C$10,MATCH(M68,Venues!$A$2:$A$10,0)),"Not checked") | P68: =IFERROR(INDEX(Venues!$D$2:$D$10,MATCH(M68,Venues!$A$2:$A$10,0)),0) | Q68: =IFERROR(INDEX(Venues!$E$2:$E$10,MATCH(M68,Venues!$A$2:$A$10,0)),"") | R68: =IF(P68>0,"Yes","No") | S68: Shoreditch Rooftop | T68: =IFERROR(INDEX(Venues!$E$2:$E$10,MATCH(S68,Venues!$A$2:$A$10,0)),"") | U68: =IFERROR(INDEX(Venues!$F$2:$F$10,MATCH(S68,Venues!$A$2:$A$10,0)),"") | V68: =IFERROR(INDEX(Venues!$H$2:$H$10,MATCH(S68,Venues!$A$2:$A$10,0)),"") | W68: =IF('Pilot offer'!$C$24="Yes",'Pilot offer'!$C$3,S68) | X68: =IF('Pilot offer'!$C$24="Yes",'Pilot offer'!$C$5+'Pilot offer'!$C$6,T68) | Y68: =IF('Pilot offer'!$C$24="Yes",'Pilot offer'!$C$8,U68) | Z68: =IF('Pilot offer'!$C$24="Yes",'Pilot offer'!$C$11,"") | AA68: =IF(X68="","",W68&" · "&TEXT(X68,"ddd d mmm, hh:mm")&" · "&Y68&IF(Z68<>""," · £"&TEXT(Z68,"0.00")&" per player"," · price TBC (cost £"&TEXT(V68,"0.00")&" pp)"))
A69: 67 | B69: 1 · E2 Haggerston | C69: Retail | D69: Local businesses | E69: Love Vinyl | F69: shop: music | G69: lovevinylldn@gmail.com | H69: openstreetmap_tag | I69: +44 20 7729 8978 | J69: https://lovevinyl.net/ | K69: Pearson Street 5, London | L69: E2 8JD | M69: Shoreditch Rooftop | N69: 9 | O69: =IFERROR(INDEX(Venues!$C$2:$C$10,MATCH(M69,Venues!$A$2:$A$10,0)),"Not checked") | P69: =IFERROR(INDEX(Venues!$D$2:$D$10,MATCH(M69,Venues!$A$2:$A$10,0)),0) | Q69: =IFERROR(INDEX(Venues!$E$2:$E$10,MATCH(M69,Venues!$A$2:$A$10,0)),"") | R69: =IF(P69>0,"Yes","No") | S69: Shoreditch Rooftop | T69: =IFERROR(INDEX(Venues!$E$2:$E$10,MATCH(S69,Venues!$A$2:$A$10,0)),"") | U69: =IFERROR(INDEX(Venues!$F$2:$F$10,MATCH(S69,Venues!$A$2:$A$10,0)),"") | V69: =IFERROR(INDEX(Venues!$H$2:$H$10,MATCH(S69,Venues!$A$2:$A$10,0)),"") | W69: =IF('Pilot offer'!$C$24="Yes",'Pilot offer'!$C$3,S69) | X69: =IF('Pilot offer'!$C$24="Yes",'Pilot offer'!$C$5+'Pilot offer'!$C$6,T69) | Y69: =IF('Pilot offer'!$C$24="Yes",'Pilot offer'!$C$8,U69) | Z69: =IF('Pilot offer'!$C$24="Yes",'Pilot offer'!$C$11,"") | AA69: =IF(X69="","",W69&" · "&TEXT(X69,"ddd d mmm, hh:mm")&" · "&Y69&IF(Z69<>""," · £"&TEXT(Z69,"0.00")&" per player"," · price TBC (cost £"&TEXT(V69,"0.00")&" pp)"))
A70: 68 | B70: 1 · E2 Haggerston | C70: Office & professional | D70: Corporate | E70: Chilled Consulting | F70: finance | G70: chilledconsulting@outlook.com | H70: freemail | J70: https://www.chilledconsulting.com/ | K70: Shoreditch Exchange, Gorsuch Pl, London E2 8JF, UK | L70: E2 8JF | M70: Shoreditch Rooftop | N70: 12 | O70: =IFERROR(INDEX(Venues!$C$2:$C$10,MATCH(M70,Venues!$A$2:$A$10,0)),"Not checked") | P70: =IFERROR(INDEX(Venues!$D$2:$D$10,MATCH(M70,Venues!$A$2:$A$10,0)),0) | Q70: =IFERROR(INDEX(Venues!$E$2:$E$10,MATCH(M70,Venues!$A$2:$A$10,0)),"") | R70: =IF(P70>0,"Yes","No") | S70: Shoreditch Rooftop | T70: =IFERROR(INDEX(Venues!$E$2:$E$10,MATCH(S70,Venues!$A$2:$A$10,0)),"") | U70: =IFERROR(INDEX(Venues!$F$2:$F$10,MATCH(S70,Venues!$A$2:$A$10,0)),"") | V70: =IFERROR(INDEX(Venues!$H$2:$H$10,MATCH(S70,Venues!$A$2:$A$10,0)),"") | W70: =IF('Pilot offer'!$C$24="Yes",'Pilot offer'!$C$3,S70) | X70: =IF('Pilot offer'!$C$24="Yes",'Pilot offer'!$C$5+'Pilot offer'!$C$6,T70) | Y70: =IF('Pilot offer'!$C$24="Yes",'Pilot offer'!$C$8,U70) | Z70: =IF('Pilot offer'!$C$24="Yes",'Pilot offer'!$C$11,"") | AA70: =IF(X70="","",W70&" · "&TEXT(X70,"ddd d mmm, hh:mm")&" · "&Y70&IF(Z70<>""," · £"&TEXT(Z70,"0.00")&" per player"," · price TBC (cost £"&TEXT(V70,"0.00")&" pp)"))
A71: 69 | B71: 1 · E2 Haggerston | C71: Office & professional | D71: Corporate | E71: Grammatik Agency | F71: consultant | G71: contact@grammatikagency.com | H71: general | I71: +44 20 3950 7057 | J71: http://grammatikagency.com/ | K71: Shoreditch Exchange, Senna Building, Gorsuch Pl, London E2 8JF, UK | L71: E2 8JF | M71: Shoreditch Rooftop | N71: 12 | O71: =IFERROR(INDEX(Venues!$C$2:$C$10,MATCH(M71,Venues!$A$2:$A$10,0)),"Not checked") | P71: =IFERROR(INDEX(Venues!$D$2:$D$10,MATCH(M71,Venues!$A$2:$A$10,0)),0) | Q71: =IFERROR(INDEX(Venues!$E$2:$E$10,MATCH(M71,Venues!$A$2:$A$10,0)),"") | R71: =IF(P71>0,"Yes","No") | S71: Shoreditch Rooftop | T71: =IFERROR(INDEX(Venues!$E$2:$E$10,MATCH(S71,Venues!$A$2:$A$10,0)),"") | U71: =IFERROR(INDEX(Venues!$F$2:$F$10,MATCH(S71,Venues!$A$2:$A$10,0)),"") | V71: =IFERROR(INDEX(Venues!$H$2:$H$10,MATCH(S71,Venues!$A$2:$A$10,0)),"") | W71: =IF('Pilot offer'!$C$24="Yes",'Pilot offer'!$C$3,S71) | X71: =IF('Pilot offer'!$C$24="Yes",'Pilot offer'!$C$5+'Pilot offer'!$C$6,T71) | Y71: =IF('Pilot offer'!$C$24="Yes",'Pilot offer'!$C$8,U71) | Z71: =IF('Pilot offer'!$C$24="Yes",'Pilot offer'!$C$11,"") | AA71: =IF(X71="","",W71&" · "&TEXT(X71,"ddd d mmm, hh:mm")&" · "&Y71&IF(Z71<>""," · £"&TEXT(Z71,"0.00")&" per player"," · price TBC (cost £"&TEXT(V71,"0.00")&" pp)"))
A72: 70 | B72: 1 · E2 Haggerston | C72: Coworking / shared office | D72: Corporate | E72: Shoreditch Exchange | F72: coworking | G72: marketing@withoneder.com | H72: people_team | I72: +44 20 8050 3325 | J72: https://shoreditch-exchange.com/ | K72: Gorsuch Place, London | L72: E2 8JF | M72: Shoreditch Rooftop | N72: 12 | O72: =IFERROR(INDEX(Venues!$C$2:$C$10,MATCH(M72,Venues!$A$2:$A$10,0)),"Not checked") | P72: =IFERROR(INDEX(Venues!$D$2:$D$10,MATCH(M72,Venues!$A$2:$A$10,0)),0) | Q72: =IFERROR(INDEX(Venues!$E$2:$E$10,MATCH(M72,Venues!$A$2:$A$10,0)),"") | R72: =IF(P72>0,"Yes","No") | S72: Shoreditch Rooftop | T72: =IFERROR(INDEX(Venues!$E$2:$E$10,MATCH(S72,Venues!$A$2:$A$10,0)),"") | U72: =IFERROR(INDEX(Venues!$F$2:$F$10,MATCH(S72,Venues!$A$2:$A$10,0)),"") | V72: =IFERROR(INDEX(Venues!$H$2:$H$10,MATCH(S72,Venues!$A$2:$A$10,0)),"") | W72: =IF('Pilot offer'!$C$24="Yes",'Pilot offer'!$C$3,S72) | X72: =IF('Pilot offer'!$C$24="Yes",'Pilot offer'!$C$5+'Pilot offer'!$C$6,T72) | Y72: =IF('Pilot offer'!$C$24="Yes",'Pilot offer'!$C$8,U72) | Z72: =IF('Pilot offer'!$C$24="Yes",'Pilot offer'!$C$11,"") | AA72: =IF(X72="","",W72&" · "&TEXT(X72,"ddd d mmm, hh:mm")&" · "&Y72&IF(Z72<>""," · £"&TEXT(Z72,"0.00")&" per player"," · price TBC (cost £"&TEXT(V72,"0.00")&" pp)"))
A73: 71 | B73: 1 · E2 Haggerston | C73: Hospitality | D73: Local businesses | E73: Sager + Wilde | F73: amenity: bar | G73: hello@sagerandwilde.com | H73: general | I73: +44 7761 168529 | J73: https://www.sagerandwilde.com/ | K73: Hackney Road 193, London | L73: E2 8JL | M73: Shoreditch Rooftop | N73: 14 | O73: =IFERROR(INDEX(Venues!$C$2:$C$10,MATCH(M73,Venues!$A$2:$A$10,0)),"Not checked") | P73: =IFERROR(INDEX(Venues!$D$2:$D$10,MATCH(M73,Venues!$A$2:$A$10,0)),0) | Q73: =IFERROR(INDEX(Venues!$E$2:$E$10,MATCH(M73,Venues!$A$2:$A$10,0)),"") | R73: =IF(P73>0,"Yes","No") | S73: Shoreditch Rooftop | T73: =IFERROR(INDEX(Venues!$E$2:$E$10,MATCH(S73,Venues!$A$2:$A$10,0)),"") | U73: =IFERROR(INDEX(Venues!$F$2:$F$10,MATCH(S73,Venues!$A$2:$A$10,0)),"") | V73: =IFERROR(INDEX(Venues!$H$2:$H$10,MATCH(S73,Venues!$A$2:$A$10,0)),"") | W73: =IF('Pilot offer'!$C$24="Yes",'Pilot offer'!$C$3,S73) | X73: =IF('Pilot offer'!$C$24="Yes",'Pilot offer'!$C$5+'Pilot offer'!$C$6,T73) | Y73: =IF('Pilot offer'!$C$24="Yes",'Pilot offer'!$C$8,U73) | Z73: =IF('Pilot offer'!$C$24="Yes",'Pilot offer'!$C$11,"") | AA73: =IF(X73="","",W73&" · "&TEXT(X73,"ddd d mmm, hh:mm")&" · "&Y73&IF(Z73<>""," · £"&TEXT(Z73,"0.00")&" per player"," · price TBC (cost £"&TEXT(V73,"0.00")&" pp)"))
A74: 72 | B74: 1 · E2 Haggerston | C74: Hospitality | D74: Local businesses | E74: The Premises Cafe | F74: amenity: restaurant | G74: bookings@premisesstudios.com | H74: commercial | I74: +44 20 7684 2230 | J74: https://www.premisesstudios.com/cafe/ | K74: Hackney Road 209, London | L74: E2 8JL | M74: Shoreditch Rooftop | N74: 15 | O74: =IFERROR(INDEX(Venues!$C$2:$C$10,MATCH(M74,Venues!$A$2:$A$10,0)),"Not checked") | P74: =IFERROR(INDEX(Venues!$D$2:$D$10,MATCH(M74,Venues!$A$2:$A$10,0)),0) | Q74: =IFERROR(INDEX(Venues!$E$2:$E$10,MATCH(M74,Venues!$A$2:$A$10,0)),"") | R74: =IF(P74>0,"Yes","No") | S74: Shoreditch Rooftop | T74: =IFERROR(INDEX(Venues!$E$2:$E$10,MATCH(S74,Venues!$A$2:$A$10,0)),"") | U74: =IFERROR(INDEX(Venues!$F$2:$F$10,MATCH(S74,Venues!$A$2:$A$10,0)),"") | V74: =IFERROR(INDEX(Venues!$H$2:$H$10,MATCH(S74,Venues!$A$2:$A$10,0)),"") | W74: =IF('Pilot offer'!$C$24="Yes",'Pilot offer'!$C$3,S74) | X74: =IF('Pilot offer'!$C$24="Yes",'Pilot offer'!$C$5+'Pilot offer'!$C$6,T74) | Y74: =IF('Pilot offer'!$C$24="Yes",'Pilot offer'!$C$8,U74) | Z74: =IF('Pilot offer'!$C$24="Yes",'Pilot offer'!$C$11,"") | AA74: =IF(X74="","",W74&" · "&TEXT(X74,"ddd d mmm, hh:mm")&" · "&Y74&IF(Z74<>""," · £"&TEXT(Z74,"0.00")&" per player"," · price TBC (cost £"&TEXT(V74,"0.00")&" pp)"))
A75: 73 | B75: 1 · E2 Haggerston | C75: Education | D75: Local businesses | E75: Haggerston School | F75: amenity: school | G75: haggerstonschool@haggerstoncst.org | H75: person_or_other | I75: +44 20 7739 7324 | J75: https://www.haggerstoncst.org/ | K75: Weymouth Terrace, London | L75: E2 8LS | M75: Shoreditch Rooftop | N75: 15 | O75: =IFERROR(INDEX(Venues!$C$2:$C$10,MATCH(M75,Venues!$A$2:$A$10,0)),"Not checked") | P75: =IFERROR(INDEX(Venues!$D$2:$D$10,MATCH(M75,Venues!$A$2:$A$10,0)),0) | Q75: =IFERROR(INDEX(Venues!$E$2:$E$10,MATCH(M75,Venues!$A$2:$A$10,0)),"") | R75: =IF(P75>0,"Yes","No") | S75: Shoreditch Rooftop | T75: =IFERROR(INDEX(Venues!$E$2:$E$10,MATCH(S75,Venues!$A$2:$A$10,0)),"") | U75: =IFERROR(INDEX(Venues!$F$2:$F$10,MATCH(S75,Venues!$A$2:$A$10,0)),"") | V75: =IFERROR(INDEX(Venues!$H$2:$H$10,MATCH(S75,Venues!$A$2:$A$10,0)),"") | W75: =IF('Pilot offer'!$C$24="Yes",'Pilot offer'!$C$3,S75) | X75: =IF('Pilot offer'!$C$24="Yes",'Pilot offer'!$C$5+'Pilot offer'!$C$6,T75) | Y75: =IF('Pilot offer'!$C$24="Yes",'Pilot offer'!$C$8,U75) | Z75: =IF('Pilot offer'!$C$24="Yes",'Pilot offer'!$C$11,"") | AA75: =IF(X75="","",W75&" · "&TEXT(X75,"ddd d mmm, hh:mm")&" · "&Y75&IF(Z75<>""," · £"&TEXT(Z75,"0.00")&" per player"," · price TBC (cost £"&TEXT(V75,"0.00")&" pp)"))
A76: 74 | B76: 1 · E2 Haggerston | C76: Hospitality | D76: Local businesses | E76: Equal Parts | F76: amenity: bar | G76: hello@equalpartslondon.com | H76: openstreetmap_tag | J76: https://www.equalpartslondon.com/ | K76: Hackney Road 245, London | L76: E2 8NA | M76: Shoreditch Rooftop | N76: 17 | O76: =IFERROR(INDEX(Venues!$C$2:$C$10,MATCH(M76,Venues!$A$2:$A$10,0)),"Not checked") | P76: =IFERROR(INDEX(Venues!$D$2:$D$10,MATCH(M76,Venues!$A$2:$A$10,0)),0) | Q76: =IFERROR(INDEX(Venues!$E$2:$E$10,MATCH(M76,Venues!$A$2:$A$10,0)),"") | R76: =IF(P76>0,"Yes","No") | S76: Shoreditch Rooftop | T76: =IFERROR(INDEX(Venues!$E$2:$E$10,MATCH(S76,Venues!$A$2:$A$10,0)),"") | U76: =IFERROR(INDEX(Venues!$F$2:$F$10,MATCH(S76,Venues!$A$2:$A$10,0)),"") | V76: =IFERROR(INDEX(Venues!$H$2:$H$10,MATCH(S76,Venues!$A$2:$A$10,0)),"") | W76: =IF('Pilot offer'!$C$24="Yes",'Pilot offer'!$C$3,S76) | X76: =IF('Pilot offer'!$C$24="Yes",'Pilot offer'!$C$5+'Pilot offer'!$C$6,T76) | Y76: =IF('Pilot offer'!$C$24="Yes",'Pilot offer'!$C$8,U76) | Z76: =IF('Pilot offer'!$C$24="Yes",'Pilot offer'!$C$11,"") | AA76: =IF(X76="","",W76&" · "&TEXT(X76,"ddd d mmm, hh:mm")&" · "&Y76&IF(Z76<>""," · £"&TEXT(Z76,"0.00")&" per player"," · price TBC (cost £"&TEXT(V76,"0.00")&" pp)"))
A77: 75 | B77: 1 · E2 Haggerston | C77: Retail | D77: Local businesses | E77: Fish Planet London | F77: shop: pet | G77: fishplanetlondon@gmail.com | H77: freemail | I77: +44 20 4625 9881 | J77: https://fishplanetlondon.co.uk/ | K77: Scawfell Street 6, London | L77: E2 8NG | M77: Shoreditch Rooftop | N77: 16 | O77: =IFERROR(INDEX(Venues!$C$2:$C$10,MATCH(M77,Venues!$A$2:$A$10,0)),"Not checked") | P77: =IFERROR(INDEX(Venues!$D$2:$D$10,MATCH(M77,Venues!$A$2:$A$10,0)),0) | Q77: =IFERROR(INDEX(Venues!$E$2:$E$10,MATCH(M77,Venues!$A$2:$A$10,0)),"") | R77: =IF(P77>0,"Yes","No") | S77: Shoreditch Rooftop | T77: =IFERROR(INDEX(Venues!$E$2:$E$10,MATCH(S77,Venues!$A$2:$A$10,0)),"") | U77: =IFERROR(INDEX(Venues!$F$2:$F$10,MATCH(S77,Venues!$A$2:$A$10,0)),"") | V77: =IFERROR(INDEX(Venues!$H$2:$H$10,MATCH(S77,Venues!$A$2:$A$10,0)),"") | W77: =IF('Pilot offer'!$C$24="Yes",'Pilot offer'!$C$3,S77) | X77: =IF('Pilot offer'!$C$24="Yes",'Pilot offer'!$C$5+'Pilot offer'!$C$6,T77) | Y77: =IF('Pilot offer'!$C$24="Yes",'Pilot offer'!$C$8,U77) | Z77: =IF('Pilot offer'!$C$24="Yes",'Pilot offer'!$C$11,"") | AA77: =IF(X77="","",W77&" · "&TEXT(X77,"ddd d mmm, hh:mm")&" · "&Y77&IF(Z77<>""," · £"&TEXT(Z77,"0.00")&" per player"," · price TBC (cost £"&TEXT(V77,"0.00")&" pp)"))
A78: 76 | B78: 1 · E2 Haggerston | C78: Hospitality | D78: Local businesses | E78: Frizzante | F78: amenity: restaurant | G78: info@frizzanterestaurant.com | H78: general | J78: https://frizzanterestaurant.com/ | K78: Goldsmiths' Row 1, London | L78: E2 8QA | M78: Shoreditch Rooftop | N78: 20 | O78: =IFERROR(INDEX(Venues!$C$2:$C$10,MATCH(M78,Venues!$A$2:$A$10,0)),"Not checked") | P78: =IFERROR(INDEX(Venues!$D$2:$D$10,MATCH(M78,Venues!$A$2:$A$10,0)),0) | Q78: =IFERROR(INDEX(Venues!$E$2:$E$10,MATCH(M78,Venues!$A$2:$A$10,0)),"") | R78: =IF(P78>0,"Yes","No") | S78: Shoreditch Rooftop | T78: =IFERROR(INDEX(Venues!$E$2:$E$10,MATCH(S78,Venues!$A$2:$A$10,0)),"") | U78: =IFERROR(INDEX(Venues!$F$2:$F$10,MATCH(S78,Venues!$A$2:$A$10,0)),"") | V78: =IFERROR(INDEX(Venues!$H$2:$H$10,MATCH(S78,Venues!$A$2:$A$10,0)),"") | W78: =IF('Pilot offer'!$C$24="Yes",'Pilot offer'!$C$3,S78) | X78: =IF('Pilot offer'!$C$24="Yes",'Pilot offer'!$C$5+'Pilot offer'!$C$6,T78) | Y78: =IF('Pilot offer'!$C$24="Yes",'Pilot offer'!$C$8,U78) | Z78: =IF('Pilot offer'!$C$24="Yes",'Pilot offer'!$C$11,"") | AA78: =IF(X78="","",W78&" · "&TEXT(X78,"ddd d mmm, hh:mm")&" · "&Y78&IF(Z78<>""," · £"&TEXT(Z78,"0.00")&" per player"," · price TBC (cost £"&TEXT(V78,"0.00")&" pp)"))
A79: 77 | B79: 1 · E2 Haggerston | C79: Education | D79: Local businesses | E79: Sebright School | F79: amenity: school | G79: admin@sebright.hackney.sch.uk | H79: general | I79: +44 20 7739 6531 | J79: https://www.sebright.hackney.sch.uk/ | K79: Audrey Street, London | L79: E2 8QH | M79: COLA Shoreditch Park | N79: 20 | O79: =IFERROR(INDEX(Venues!$C$2:$C$10,MATCH(M79,Venues!$A$2:$A$10,0)),"Not checked") | P79: =IFERROR(INDEX(Venues!$D$2:$D$10,MATCH(M79,Venues!$A$2:$A$10,0)),0) | Q79: =IFERROR(INDEX(Venues!$E$2:$E$10,MATCH(M79,Venues!$A$2:$A$10,0)),"") | R79: =IF(P79>0,"Yes","No") | S79: COLA Shoreditch Park | T79: =IFERROR(INDEX(Venues!$E$2:$E$10,MATCH(S79,Venues!$A$2:$A$10,0)),"") | U79: =IFERROR(INDEX(Venues!$F$2:$F$10,MATCH(S79,Venues!$A$2:$A$10,0)),"") | V79: =IFERROR(INDEX(Venues!$H$2:$H$10,MATCH(S79,Venues!$A$2:$A$10,0)),"") | W79: =IF('Pilot offer'!$C$24="Yes",'Pilot offer'!$C$3,S79) | X79: =IF('Pilot offer'!$C$24="Yes",'Pilot offer'!$C$5+'Pilot offer'!$C$6,T79) | Y79: =IF('Pilot offer'!$C$24="Yes",'Pilot offer'!$C$8,U79) | Z79: =IF('Pilot offer'!$C$24="Yes",'Pilot offer'!$C$11,"") | AA79: =IF(X79="","",W79&" · "&TEXT(X79,"ddd d mmm, hh:mm")&" · "&Y79&IF(Z79<>""," · £"&TEXT(Z79,"0.00")&" per player"," · price TBC (cost £"&TEXT(V79,"0.00")&" pp)"))
A80: 78 | B80: 1 · E2 Haggerston | C80: Coworking / shared office | D80: Corporate | E80: Gauchoworld SPACE | F80: coworking_space | G80: contact@gauchoworld.com | H80: general | J80: https://www.gauchoworld.com/ | K80: 145 Goldsmiths Row, London E2 8QR, UK | L80: E2 8QR | M80: COLA Shoreditch Park | N80: 22 | O80: =IFERROR(INDEX(Venues!$C$2:$C$10,MATCH(M80,Venues!$A$2:$A$10,0)),"Not checked") | P80: =IFERROR(INDEX(Venues!$D$2:$D$10,MATCH(M80,Venues!$A$2:$A$10,0)),0) | Q80: =IFERROR(INDEX(Venues!$E$2:$E$10,MATCH(M80,Venues!$A$2:$A$10,0)),"") | R80: =IF(P80>0,"Yes","No") | S80: COLA Shoreditch Park | T80: =IFERROR(INDEX(Venues!$E$2:$E$10,MATCH(S80,Venues!$A$2:$A$10,0)),"") | U80: =IFERROR(INDEX(Venues!$F$2:$F$10,MATCH(S80,Venues!$A$2:$A$10,0)),"") | V80: =IFERROR(INDEX(Venues!$H$2:$H$10,MATCH(S80,Venues!$A$2:$A$10,0)),"") | W80: =IF('Pilot offer'!$C$24="Yes",'Pilot offer'!$C$3,S80) | X80: =IF('Pilot offer'!$C$24="Yes",'Pilot offer'!$C$5+'Pilot offer'!$C$6,T80) | Y80: =IF('Pilot offer'!$C$24="Yes",'Pilot offer'!$C$8,U80) | Z80: =IF('Pilot offer'!$C$24="Yes",'Pilot offer'!$C$11,"") | AA80: =IF(X80="","",W80&" · "&TEXT(X80,"ddd d mmm, hh:mm")&" · "&Y80&IF(Z80<>""," · £"&TEXT(Z80,"0.00")&" per player"," · price TBC (cost £"&TEXT(V80,"0.00")&" pp)"))
A81: 79 | B81: 1 · E2 Haggerston | C81: Health | D81: Local businesses | E81: Chrysanth Dental Care | F81: amenity: dentist | G81: info@chrysanth.london | H81: general | I81: +44 20 3620 1113 | J81: https://www.chrysanth.london/ | K81: Cambridge Heath Road 493, London | L81: E2 9BU | M81: Stepney 3G | N81: 19 | O81: =IFERROR(INDEX(Venues!$C$2:$C$10,MATCH(M81,Venues!$A$2:$A$10,0)),"Not checked") | P81: =IFERROR(INDEX(Venues!$D$2:$D$10,MATCH(M81,Venues!$A$2:$A$10,0)),0) | Q81: =IFERROR(INDEX(Venues!$E$2:$E$10,MATCH(M81,Venues!$A$2:$A$10,0)),"") | R81: =IF(P81>0,"Yes","No") | S81: COLA Shoreditch Park | T81: =IFERROR(INDEX(Venues!$E$2:$E$10,MATCH(S81,Venues!$A$2:$A$10,0)),"") | U81: =IFERROR(INDEX(Venues!$F$2:$F$10,MATCH(S81,Venues!$A$2:$A$10,0)),"") | V81: =IFERROR(INDEX(Venues!$H$2:$H$10,MATCH(S81,Venues!$A$2:$A$10,0)),"") | W81: =IF('Pilot offer'!$C$24="Yes",'Pilot offer'!$C$3,S81) | X81: =IF('Pilot offer'!$C$24="Yes",'Pilot offer'!$C$5+'Pilot offer'!$C$6,T81) | Y81: =IF('Pilot offer'!$C$24="Yes",'Pilot offer'!$C$8,U81) | Z81: =IF('Pilot offer'!$C$24="Yes",'Pilot offer'!$C$11,"") | AA81: =IF(X81="","",W81&" · "&TEXT(X81,"ddd d mmm, hh:mm")&" · "&Y81&IF(Z81<>""," · £"&TEXT(Z81,"0.00")&" per player"," · price TBC (cost £"&TEXT(V81,"0.00")&" pp)"))
A82: 80 | B82: 1 · E2 Haggerston | C82: Retail | D82: Local businesses | E82: Yo Yo Records London | F82: shop: music | G82: yoyorecordslondon@gmail.com | H82: freemail | I82: +44 20 7033 8777 | J82: https://www.yoyorecordslondon.com/ | K82: Cambridge Heath Road 501, London | L82: E2 9BU | M82: Stepney 3G | N82: 20 | O82: =IFERROR(INDEX(Venues!$C$2:$C$10,MATCH(M82,Venues!$A$2:$A$10,0)),"Not checked") | P82: =IFERROR(INDEX(Venues!$D$2:$D$10,MATCH(M82,Venues!$A$2:$A$10,0)),0) | Q82: =IFERROR(INDEX(Venues!$E$2:$E$10,MATCH(M82,Venues!$A$2:$A$10,0)),"") | R82: =IF(P82>0,"Yes","No") | S82: COLA Shoreditch Park | T82: =IFERROR(INDEX(Venues!$E$2:$E$10,MATCH(S82,Venues!$A$2:$A$10,0)),"") | U82: =IFERROR(INDEX(Venues!$F$2:$F$10,MATCH(S82,Venues!$A$2:$A$10,0)),"") | V82: =IFERROR(INDEX(Venues!$H$2:$H$10,MATCH(S82,Venues!$A$2:$A$10,0)),"") | W82: =IF('Pilot offer'!$C$24="Yes",'Pilot offer'!$C$3,S82) | X82: =IF('Pilot offer'!$C$24="Yes",'Pilot offer'!$C$5+'Pilot offer'!$C$6,T82) | Y82: =IF('Pilot offer'!$C$24="Yes",'Pilot offer'!$C$8,U82) | Z82: =IF('Pilot offer'!$C$24="Yes",'Pilot offer'!$C$11,"") | AA82: =IF(X82="","",W82&" · "&TEXT(X82,"ddd d mmm, hh:mm")&" · "&Y82&IF(Z82<>""," · £"&TEXT(Z82,"0.00")&" per player"," · price TBC (cost £"&TEXT(V82,"0.00")&" pp)"))
A83: 81 | B83: 1 · E2 Haggerston | C83: Leisure & culture | D83: Local businesses | E83: Fitness4Less | F83: leisure: sports centre | G83: info@fitness4less.co.uk | H83: general | J83: https://www.fitness4less.co.uk/location/cambridge/ | K83: Cambridge Heath Road, London | L83: E2 9BY | M83: Stepney 3G | N83: 19 | O83: =IFERROR(INDEX(Venues!$C$2:$C$10,MATCH(M83,Venues!$A$2:$A$10,0)),"Not checked") | P83: =IFERROR(INDEX(Venues!$D$2:$D$10,MATCH(M83,Venues!$A$2:$A$10,0)),0) | Q83: =IFERROR(INDEX(Venues!$E$2:$E$10,MATCH(M83,Venues!$A$2:$A$10,0)),"") | R83: =IF(P83>0,"Yes","No") | S83: COLA Shoreditch Park | T83: =IFERROR(INDEX(Venues!$E$2:$E$10,MATCH(S83,Venues!$A$2:$A$10,0)),"") | U83: =IFERROR(INDEX(Venues!$F$2:$F$10,MATCH(S83,Venues!$A$2:$A$10,0)),"") | V83: =IFERROR(INDEX(Venues!$H$2:$H$10,MATCH(S83,Venues!$A$2:$A$10,0)),"") | W83: =IF('Pilot offer'!$C$24="Yes",'Pilot offer'!$C$3,S83) | X83: =IF('Pilot offer'!$C$24="Yes",'Pilot offer'!$C$5+'Pilot offer'!$C$6,T83) | Y83: =IF('Pilot offer'!$C$24="Yes",'Pilot offer'!$C$8,U83) | Z83: =IF('Pilot offer'!$C$24="Yes",'Pilot offer'!$C$11,"") | AA83: =IF(X83="","",W83&" · "&TEXT(X83,"ddd d mmm, hh:mm")&" · "&Y83&IF(Z83<>""," · £"&TEXT(Z83,"0.00")&" per player"," · price TBC (cost £"&TEXT(V83,"0.00")&" pp)"))
A84: 82 | B84: 1 · E2 Haggerston | C84: Office & professional | D84: Corporate | E84: Eye Present | F84: company | G84: genevieve.dexter@eyepresent.co.uk | H84: person_or_other | J84: https://www.eyepresent.co.uk/ | K84: 1-5 Vyner Street, London | L84: E2 9DG | M84: Stepney 3G | N84: 21 | O84: =IFERROR(INDEX(Venues!$C$2:$C$10,MATCH(M84,Venues!$A$2:$A$10,0)),"Not checked") | P84: =IFERROR(INDEX(Venues!$D$2:$D$10,MATCH(M84,Venues!$A$2:$A$10,0)),0) | Q84: =IFERROR(INDEX(Venues!$E$2:$E$10,MATCH(M84,Venues!$A$2:$A$10,0)),"") | R84: =IF(P84>0,"Yes","No") | S84: COLA Shoreditch Park | T84: =IFERROR(INDEX(Venues!$E$2:$E$10,MATCH(S84,Venues!$A$2:$A$10,0)),"") | U84: =IFERROR(INDEX(Venues!$F$2:$F$10,MATCH(S84,Venues!$A$2:$A$10,0)),"") | V84: =IFERROR(INDEX(Venues!$H$2:$H$10,MATCH(S84,Venues!$A$2:$A$10,0)),"") | W84: =IF('Pilot offer'!$C$24="Yes",'Pilot offer'!$C$3,S84) | X84: =IF('Pilot offer'!$C$24="Yes",'Pilot offer'!$C$5+'Pilot offer'!$C$6,T84) | Y84: =IF('Pilot offer'!$C$24="Yes",'Pilot offer'!$C$8,U84) | Z84: =IF('Pilot offer'!$C$24="Yes",'Pilot offer'!$C$11,"") | AA84: =IF(X84="","",W84&" · "&TEXT(X84,"ddd d mmm, hh:mm")&" · "&Y84&IF(Z84<>""," · £"&TEXT(Z84,"0.00")&" per player"," · price TBC (cost £"&TEXT(V84,"0.00")&" pp)"))
A85: 83 | B85: 1 · E2 Haggerston | C85: Office & professional | D85: Corporate | E85: Holland Harvey Architects | F85: architect | G85: hello@hollandharvey.com | H85: general | J85: https://www.hollandharvey.com/ | K85: 1-5 Vyner Street, London | L85: E2 9DG | M85: Stepney 3G | N85: 21 | O85: =IFERROR(INDEX(Venues!$C$2:$C$10,MATCH(M85,Venues!$A$2:$A$10,0)),"Not checked") | P85: =IFERROR(INDEX(Venues!$D$2:$D$10,MATCH(M85,Venues!$A$2:$A$10,0)),0) | Q85: =IFERROR(INDEX(Venues!$E$2:$E$10,MATCH(M85,Venues!$A$2:$A$10,0)),"") | R85: =IF(P85>0,"Yes","No") | S85: COLA Shoreditch Park | T85: =IFERROR(INDEX(Venues!$E$2:$E$10,MATCH(S85,Venues!$A$2:$A$10,0)),"") | U85: =IFERROR(INDEX(Venues!$F$2:$F$10,MATCH(S85,Venues!$A$2:$A$10,0)),"") | V85: =IFERROR(INDEX(Venues!$H$2:$H$10,MATCH(S85,Venues!$A$2:$A$10,0)),"") | W85: =IF('Pilot offer'!$C$24="Yes",'Pilot offer'!$C$3,S85) | X85: =IF('Pilot offer'!$C$24="Yes",'Pilot offer'!$C$5+'Pilot offer'!$C$6,T85) | Y85: =IF('Pilot offer'!$C$24="Yes",'Pilot offer'!$C$8,U85) | Z85: =IF('Pilot offer'!$C$24="Yes",'Pilot offer'!$C$11,"") | AA85: =IF(X85="","",W85&" · "&TEXT(X85,"ddd d mmm, hh:mm")&" · "&Y85&IF(Z85<>""," · £"&TEXT(Z85,"0.00")&" per player"," · price TBC (cost £"&TEXT(V85,"0.00")&" pp)"))
A86: 84 | B86: 1 · E2 Haggerston | C86: Office & professional | D86: Corporate | E86: Squint/Opera | F86: company | G86: hello@squintopera.com | H86: general | I86: +44 20 7978 7788 | J86: https://www.squintopera.com/ | K86: 1-5 Vyner Street, London | L86: E2 9DG | M86: Stepney 3G | N86: 21 | O86: =IFERROR(INDEX(Venues!$C$2:$C$10,MATCH(M86,Venues!$A$2:$A$10,0)),"Not checked") | P86: =IFERROR(INDEX(Venues!$D$2:$D$10,MATCH(M86,Venues!$A$2:$A$10,0)),0) | Q86: =IFERROR(INDEX(Venues!$E$2:$E$10,MATCH(M86,Venues!$A$2:$A$10,0)),"") | R86: =IF(P86>0,"Yes","No") | S86: COLA Shoreditch Park | T86: =IFERROR(INDEX(Venues!$E$2:$E$10,MATCH(S86,Venues!$A$2:$A$10,0)),"") | U86: =IFERROR(INDEX(Venues!$F$2:$F$10,MATCH(S86,Venues!$A$2:$A$10,0)),"") | V86: =IFERROR(INDEX(Venues!$H$2:$H$10,MATCH(S86,Venues!$A$2:$A$10,0)),"") | W86: =IF('Pilot offer'!$C$24="Yes",'Pilot offer'!$C$3,S86) | X86: =IF('Pilot offer'!$C$24="Yes",'Pilot offer'!$C$5+'Pilot offer'!$C$6,T86) | Y86: =IF('Pilot offer'!$C$24="Yes",'Pilot offer'!$C$8,U86) | Z86: =IF('Pilot offer'!$C$24="Yes",'Pilot offer'!$C$11,"") | AA86: =IF(X86="","",W86&" · "&TEXT(X86,"ddd d mmm, hh:mm")&" · "&Y86&IF(Z86<>""," · £"&TEXT(Z86,"0.00")&" per player"," · price TBC (cost £"&TEXT(V86,"0.00")&" pp)"))
A87: 85 | B87: 1 · E2 Haggerston | C87: Retail | D87: Local businesses | E87: Hackney Cycles | F87: shop: bicycle | G87: contacts@hackney-cycles.co.uk | H87: person_or_other | J87: https://www.hackney-cycles.co.uk/ | K87: Hackney Road 507, London | L87: E2 9ED | M87: Stepney 3G | N87: 19 | O87: =IFERROR(INDEX(Venues!$C$2:$C$10,MATCH(M87,Venues!$A$2:$A$10,0)),"Not checked") | P87: =IFERROR(INDEX(Venues!$D$2:$D$10,MATCH(M87,Venues!$A$2:$A$10,0)),0) | Q87: =IFERROR(INDEX(Venues!$E$2:$E$10,MATCH(M87,Venues!$A$2:$A$10,0)),"") | R87: =IF(P87>0,"Yes","No") | S87: COLA Shoreditch Park | T87: =IFERROR(INDEX(Venues!$E$2:$E$10,MATCH(S87,Venues!$A$2:$A$10,0)),"") | U87: =IFERROR(INDEX(Venues!$F$2:$F$10,MATCH(S87,Venues!$A$2:$A$10,0)),"") | V87: =IFERROR(INDEX(Venues!$H$2:$H$10,MATCH(S87,Venues!$A$2:$A$10,0)),"") | W87: =IF('Pilot offer'!$C$24="Yes",'Pilot offer'!$C$3,S87) | X87: =IF('Pilot offer'!$C$24="Yes",'Pilot offer'!$C$5+'Pilot offer'!$C$6,T87) | Y87: =IF('Pilot offer'!$C$24="Yes",'Pilot offer'!$C$8,U87) | Z87: =IF('Pilot offer'!$C$24="Yes",'Pilot offer'!$C$11,"") | AA87: =IF(X87="","",W87&" · "&TEXT(X87,"ddd d mmm, hh:mm")&" · "&Y87&IF(Z87<>""," · £"&TEXT(Z87,"0.00")&" per player"," · price TBC (cost £"&TEXT(V87,"0.00")&" pp)"))
A88: 86 | B88: 1 · E2 Haggerston | C88: Hospitality | D88: Local businesses | E88: The Queen Adelaide | F88: amenity: pub | G88: richard@thequeenadelaide.com | H88: person_or_other | J88: https://www.thequeenadelaide.com/ | K88: Hackney Road 483, London | L88: E2 9ED | M88: Stepney 3G | N88: 19 | O88: =IFERROR(INDEX(Venues!$C$2:$C$10,MATCH(M88,Venues!$A$2:$A$10,0)),"Not checked") | P88: =IFERROR(INDEX(Venues!$D$2:$D$10,MATCH(M88,Venues!$A$2:$A$10,0)),0) | Q88: =IFERROR(INDEX(Venues!$E$2:$E$10,MATCH(M88,Venues!$A$2:$A$10,0)),"") | R88: =IF(P88>0,"Yes","No") | S88: COLA Shoreditch Park | T88: =IFERROR(INDEX(Venues!$E$2:$E$10,MATCH(S88,Venues!$A$2:$A$10,0)),"") | U88: =IFERROR(INDEX(Venues!$F$2:$F$10,MATCH(S88,Venues!$A$2:$A$10,0)),"") | V88: =IFERROR(INDEX(Venues!$H$2:$H$10,MATCH(S88,Venues!$A$2:$A$10,0)),"") | W88: =IF('Pilot offer'!$C$24="Yes",'Pilot offer'!$C$3,S88) | X88: =IF('Pilot offer'!$C$24="Yes",'Pilot offer'!$C$5+'Pilot offer'!$C$6,T88) | Y88: =IF('Pilot offer'!$C$24="Yes",'Pilot offer'!$C$8,U88) | Z88: =IF('Pilot offer'!$C$24="Yes",'Pilot offer'!$C$11,"") | AA88: =IF(X88="","",W88&" · "&TEXT(X88,"ddd d mmm, hh:mm")&" · "&Y88&IF(Z88<>""," · £"&TEXT(Z88,"0.00")&" per player"," · price TBC (cost £"&TEXT(V88,"0.00")&" pp)"))
A89: 87 | B89: 1 · E2 Haggerston | C89: Office & professional | D89: Corporate | E89: Celeste - social media marketing | F89: service | G89: hello@iamwithceleste.com | H89: general | I89: +44 7830 729708 | J89: https://www.iamwithceleste.com/ | K89: 1 Emma St, London E2 9FP, UK | L89: E2 9FP | M89: Stepney 3G | N89: 20 | O89: =IFERROR(INDEX(Venues!$C$2:$C$10,MATCH(M89,Venues!$A$2:$A$10,0)),"Not checked") | P89: =IFERROR(INDEX(Venues!$D$2:$D$10,MATCH(M89,Venues!$A$2:$A$10,0)),0) | Q89: =IFERROR(INDEX(Venues!$E$2:$E$10,MATCH(M89,Venues!$A$2:$A$10,0)),"") | R89: =IF(P89>0,"Yes","No") | S89: COLA Shoreditch Park | T89: =IFERROR(INDEX(Venues!$E$2:$E$10,MATCH(S89,Venues!$A$2:$A$10,0)),"") | U89: =IFERROR(INDEX(Venues!$F$2:$F$10,MATCH(S89,Venues!$A$2:$A$10,0)),"") | V89: =IFERROR(INDEX(Venues!$H$2:$H$10,MATCH(S89,Venues!$A$2:$A$10,0)),"") | W89: =IF('Pilot offer'!$C$24="Yes",'Pilot offer'!$C$3,S89) | X89: =IF('Pilot offer'!$C$24="Yes",'Pilot offer'!$C$5+'Pilot offer'!$C$6,T89) | Y89: =IF('Pilot offer'!$C$24="Yes",'Pilot offer'!$C$8,U89) | Z89: =IF('Pilot offer'!$C$24="Yes",'Pilot offer'!$C$11,"") | AA89: =IF(X89="","",W89&" · "&TEXT(X89,"ddd d mmm, hh:mm")&" · "&Y89&IF(Z89<>""," · £"&TEXT(Z89,"0.00")&" per player"," · price TBC (cost £"&TEXT(V89,"0.00")&" pp)"))
A90: 88 | B90: 1 · E2 Haggerston | C90: Office & professional | D90: Corporate | E90: Containerville | F90: corporate_office | G90: hello@containerville.co.uk | H90: general | I90: +44 7469 149024 | J90: http://www.containerville.co.uk/ | K90: 1 Emma St, London E2 9FP, UK | L90: E2 9FP | M90: Stepney 3G | N90: 20 | O90: =IFERROR(INDEX(Venues!$C$2:$C$10,MATCH(M90,Venues!$A$2:$A$10,0)),"Not checked") | P90: =IFERROR(INDEX(Venues!$D$2:$D$10,MATCH(M90,Venues!$A$2:$A$10,0)),0) | Q90: =IFERROR(INDEX(Venues!$E$2:$E$10,MATCH(M90,Venues!$A$2:$A$10,0)),"") | R90: =IF(P90>0,"Yes","No") | S90: COLA Shoreditch Park | T90: =IFERROR(INDEX(Venues!$E$2:$E$10,MATCH(S90,Venues!$A$2:$A$10,0)),"") | U90: =IFERROR(INDEX(Venues!$F$2:$F$10,MATCH(S90,Venues!$A$2:$A$10,0)),"") | V90: =IFERROR(INDEX(Venues!$H$2:$H$10,MATCH(S90,Venues!$A$2:$A$10,0)),"") | W90: =IF('Pilot offer'!$C$24="Yes",'Pilot offer'!$C$3,S90) | X90: =IF('Pilot offer'!$C$24="Yes",'Pilot offer'!$C$5+'Pilot offer'!$C$6,T90) | Y90: =IF('Pilot offer'!$C$24="Yes",'Pilot offer'!$C$8,U90) | Z90: =IF('Pilot offer'!$C$24="Yes",'Pilot offer'!$C$11,"") | AA90: =IF(X90="","",W90&" · "&TEXT(X90,"ddd d mmm, hh:mm")&" · "&Y90&IF(Z90<>""," · £"&TEXT(Z90,"0.00")&" per player"," · price TBC (cost £"&TEXT(V90,"0.00")&" pp)"))
A91: 89 | B91: 1 · E2 Haggerston | C91: Hospitality | D91: Local businesses | E91: Love Shack | F91: amenity: restaurant | G91: hi@loveshackldn.com | H91: general | J91: https://www.loveshackldn.com/ | K91: Cambridge Heath Road 298-299, London | L91: E2 9HA | M91: Stepney 3G | N91: 18 | O91: =IFERROR(INDEX(Venues!$C$2:$C$10,MATCH(M91,Venues!$A$2:$A$10,0)),"Not checked") | P91: =IFERROR(INDEX(Venues!$D$2:$D$10,MATCH(M91,Venues!$A$2:$A$10,0)),0) | Q91: =IFERROR(INDEX(Venues!$E$2:$E$10,MATCH(M91,Venues!$A$2:$A$10,0)),"") | R91: =IF(P91>0,"Yes","No") | S91: COLA Shoreditch Park | T91: =IFERROR(INDEX(Venues!$E$2:$E$10,MATCH(S91,Venues!$A$2:$A$10,0)),"") | U91: =IFERROR(INDEX(Venues!$F$2:$F$10,MATCH(S91,Venues!$A$2:$A$10,0)),"") | V91: =IFERROR(INDEX(Venues!$H$2:$H$10,MATCH(S91,Venues!$A$2:$A$10,0)),"") | W91: =IF('Pilot offer'!$C$24="Yes",'Pilot offer'!$C$3,S91) | X91: =IF('Pilot offer'!$C$24="Yes",'Pilot offer'!$C$5+'Pilot offer'!$C$6,T91) | Y91: =IF('Pilot offer'!$C$24="Yes",'Pilot offer'!$C$8,U91) | Z91: =IF('Pilot offer'!$C$24="Yes",'Pilot offer'!$C$11,"") | AA91: =IF(X91="","",W91&" · "&TEXT(X91,"ddd d mmm, hh:mm")&" · "&Y91&IF(Z91<>""," · £"&TEXT(Z91,"0.00")&" per player"," · price TBC (cost £"&TEXT(V91,"0.00")&" pp)"))
A92: 90 | B92: 1 · E2 Haggerston | C92: Education | D92: Local businesses | E92: Mowlem Primary School | F92: amenity: school | G92: admin@mowlem.towerhamlets.sch.uk | H92: general | I92: +44 20 8249 6880 | J92: https://www.mowlem.towerhamlets.sch.uk/ | K92: Mowlem Street, London | L92: E2 9HE | M92: Stepney 3G | N92: 19 | O92: =IFERROR(INDEX(Venues!$C$2:$C$10,MATCH(M92,Venues!$A$2:$A$10,0)),"Not checked") | P92: =IFERROR(INDEX(Venues!$D$2:$D$10,MATCH(M92,Venues!$A$2:$A$10,0)),0) | Q92: =IFERROR(INDEX(Venues!$E$2:$E$10,MATCH(M92,Venues!$A$2:$A$10,0)),"") | R92: =IF(P92>0,"Yes","No") | S92: COLA Shoreditch Park | T92: =IFERROR(INDEX(Venues!$E$2:$E$10,MATCH(S92,Venues!$A$2:$A$10,0)),"") | U92: =IFERROR(INDEX(Venues!$F$2:$F$10,MATCH(S92,Venues!$A$2:$A$10,0)),"") | V92: =IFERROR(INDEX(Venues!$H$2:$H$10,MATCH(S92,Venues!$A$2:$A$10,0)),"") | W92: =IF('Pilot offer'!$C$24="Yes",'Pilot offer'!$C$3,S92) | X92: =IF('Pilot offer'!$C$24="Yes",'Pilot offer'!$C$5+'Pilot offer'!$C$6,T92) | Y92: =IF('Pilot offer'!$C$24="Yes",'Pilot offer'!$C$8,U92) | Z92: =IF('Pilot offer'!$C$24="Yes",'Pilot offer'!$C$11,"") | AA92: =IF(X92="","",W92&" · "&TEXT(X92,"ddd d mmm, hh:mm")&" · "&Y92&IF(Z92<>""," · £"&TEXT(Z92,"0.00")&" per player"," · price TBC (cost £"&TEXT(V92,"0.00")&" pp)"))
A93: 91 | B93: 1 · E2 Haggerston | C93: Education | D93: Local businesses | E93: Gatehouse School | F93: amenity: school | G93: admin@gatehouseschool.co.uk | H93: general | I93: +44 20 8980 2978 | J93: https://www.gatehouseschool.co.uk/ | K93: Sewardstone Road, London | L93: E2 9JG | M93: Stepney 3G | N93: 14 | O93: =IFERROR(INDEX(Venues!$C$2:$C$10,MATCH(M93,Venues!$A$2:$A$10,0)),"Not checked") | P93: =IFERROR(INDEX(Venues!$D$2:$D$10,MATCH(M93,Venues!$A$2:$A$10,0)),0) | Q93: =IFERROR(INDEX(Venues!$E$2:$E$10,MATCH(M93,Venues!$A$2:$A$10,0)),"") | R93: =IF(P93>0,"Yes","No") | S93: COLA Shoreditch Park | T93: =IFERROR(INDEX(Venues!$E$2:$E$10,MATCH(S93,Venues!$A$2:$A$10,0)),"") | U93: =IFERROR(INDEX(Venues!$F$2:$F$10,MATCH(S93,Venues!$A$2:$A$10,0)),"") | V93: =IFERROR(INDEX(Venues!$H$2:$H$10,MATCH(S93,Venues!$A$2:$A$10,0)),"") | W93: =IF('Pilot offer'!$C$24="Yes",'Pilot offer'!$C$3,S93) | X93: =IF('Pilot offer'!$C$24="Yes",'Pilot offer'!$C$5+'Pilot offer'!$C$6,T93) | Y93: =IF('Pilot offer'!$C$24="Yes",'Pilot offer'!$C$8,U93) | Z93: =IF('Pilot offer'!$C$24="Yes",'Pilot offer'!$C$11,"") | AA93: =IF(X93="","",W93&" · "&TEXT(X93,"ddd d mmm, hh:mm")&" · "&Y93&IF(Z93<>""," · £"&TEXT(Z93,"0.00")&" per player"," · price TBC (cost £"&TEXT(V93,"0.00")&" pp)"))
A94: 92 | B94: 1 · E2 Haggerston | C94: Hospitality | D94: Local businesses | E94: The Dundee Arms | F94: amenity: pub | G94: info@thedundeearms.com | H94: openstreetmap_tag | I94: +44 20 7729 6903 | J94: http://www.thedundeearms.com/ | K94: Cambridge Heath Road 339, London | L94: E2 9LH | M94: Stepney 3G | N94: 13 | O94: =IFERROR(INDEX(Venues!$C$2:$C$10,MATCH(M94,Venues!$A$2:$A$10,0)),"Not checked") | P94: =IFERROR(INDEX(Venues!$D$2:$D$10,MATCH(M94,Venues!$A$2:$A$10,0)),0) | Q94: =IFERROR(INDEX(Venues!$E$2:$E$10,MATCH(M94,Venues!$A$2:$A$10,0)),"") | R94: =IF(P94>0,"Yes","No") | S94: COLA Shoreditch Park | T94: =IFERROR(INDEX(Venues!$E$2:$E$10,MATCH(S94,Venues!$A$2:$A$10,0)),"") | U94: =IFERROR(INDEX(Venues!$F$2:$F$10,MATCH(S94,Venues!$A$2:$A$10,0)),"") | V94: =IFERROR(INDEX(Venues!$H$2:$H$10,MATCH(S94,Venues!$A$2:$A$10,0)),"") | W94: =IF('Pilot offer'!$C$24="Yes",'Pilot offer'!$C$3,S94) | X94: =IF('Pilot offer'!$C$24="Yes",'Pilot offer'!$C$5+'Pilot offer'!$C$6,T94) | Y94: =IF('Pilot offer'!$C$24="Yes",'Pilot offer'!$C$8,U94) | Z94: =IF('Pilot offer'!$C$24="Yes",'Pilot offer'!$C$11,"") | AA94: =IF(X94="","",W94&" · "&TEXT(X94,"ddd d mmm, hh:mm")&" · "&Y94&IF(Z94<>""," · £"&TEXT(Z94,"0.00")&" per player"," · price TBC (cost £"&TEXT(V94,"0.00")&" pp)"))
A95: 93 | B95: 1 · E2 Haggerston | C95: Education | D95: Local businesses | E95: St John's Church of England Primary School | F95: amenity: school | G95: admin@st-johns.towerhamlets.sch.uk | H95: general | I95: +44 20 8980 1142 | J95: https://www.st-johns.towerhamlets.sch.uk/ | K95: Peel Grove, London | L95: E2 9LR | M95: Stepney 3G | N95: 14 | O95: =IFERROR(INDEX(Venues!$C$2:$C$10,MATCH(M95,Venues!$A$2:$A$10,0)),"Not checked") | P95: =IFERROR(INDEX(Venues!$D$2:$D$10,MATCH(M95,Venues!$A$2:$A$10,0)),0) | Q95: =IFERROR(INDEX(Venues!$E$2:$E$10,MATCH(M95,Venues!$A$2:$A$10,0)),"") | R95: =IF(P95>0,"Yes","No") | S95: COLA Shoreditch Park | T95: =IFERROR(INDEX(Venues!$E$2:$E$10,MATCH(S95,Venues!$A$2:$A$10,0)),"") | U95: =IFERROR(INDEX(Venues!$F$2:$F$10,MATCH(S95,Venues!$A$2:$A$10,0)),"") | V95: =IFERROR(INDEX(Venues!$H$2:$H$10,MATCH(S95,Venues!$A$2:$A$10,0)),"") | W95: =IF('Pilot offer'!$C$24="Yes",'Pilot offer'!$C$3,S95) | X95: =IF('Pilot offer'!$C$24="Yes",'Pilot offer'!$C$5+'Pilot offer'!$C$6,T95) | Y95: =IF('Pilot offer'!$C$24="Yes",'Pilot offer'!$C$8,U95) | Z95: =IF('Pilot offer'!$C$24="Yes",'Pilot offer'!$C$11,"") | AA95: =IF(X95="","",W95&" · "&TEXT(X95,"ddd d mmm, hh:mm")&" · "&Y95&IF(Z95<>""," · £"&TEXT(Z95,"0.00")&" per player"," · price TBC (cost £"&TEXT(V95,"0.00")&" pp)"))
A96: 94 | B96: 1 · E2 Haggerston | C96: Hospitality | D96: Local businesses | E96: The Approach Tavern | F96: amenity: pub | G96: approachtavern@remarkablepubs.co.uk | H96: openstreetmap_tag | I96: +44 20 8980 2321 | J96: https://theapproachtavern.co.uk/ | K96: Approach Road 47, London | L96: E2 9LY | M96: Stepney 3G | N96: 14 | O96: =IFERROR(INDEX(Venues!$C$2:$C$10,MATCH(M96,Venues!$A$2:$A$10,0)),"Not checked") | P96: =IFERROR(INDEX(Venues!$D$2:$D$10,MATCH(M96,Venues!$A$2:$A$10,0)),0) | Q96: =IFERROR(INDEX(Venues!$E$2:$E$10,MATCH(M96,Venues!$A$2:$A$10,0)),"") | R96: =IF(P96>0,"Yes","No") | S96: COLA Shoreditch Park | T96: =IFERROR(INDEX(Venues!$E$2:$E$10,MATCH(S96,Venues!$A$2:$A$10,0)),"") | U96: =IFERROR(INDEX(Venues!$F$2:$F$10,MATCH(S96,Venues!$A$2:$A$10,0)),"") | V96: =IFERROR(INDEX(Venues!$H$2:$H$10,MATCH(S96,Venues!$A$2:$A$10,0)),"") | W96: =IF('Pilot offer'!$C$24="Yes",'Pilot offer'!$C$3,S96) | X96: =IF('Pilot offer'!$C$24="Yes",'Pilot offer'!$C$5+'Pilot offer'!$C$6,T96) | Y96: =IF('Pilot offer'!$C$24="Yes",'Pilot offer'!$C$8,U96) | Z96: =IF('Pilot offer'!$C$24="Yes",'Pilot offer'!$C$11,"") | AA96: =IF(X96="","",W96&" · "&TEXT(X96,"ddd d mmm, hh:mm")&" · "&Y96&IF(Z96<>""," · £"&TEXT(Z96,"0.00")&" per player"," · price TBC (cost £"&TEXT(V96,"0.00")&" pp)"))
A97: 95 | B97: 1 · E2 Haggerston | C97: Hospitality | D97: Local businesses | E97: The Solo Kitchen & Bar | F97: amenity: restaurant | G97: info@thesolo.co.uk | H97: general | I97: +44 20 8014 2656 | J97: https://www.thesolo.co.uk/ | K97: Cambridge Heath Road, London | L97: E2 9PA | M97: Stepney 3G | N97: 11 | O97: =IFERROR(INDEX(Venues!$C$2:$C$10,MATCH(M97,Venues!$A$2:$A$10,0)),"Not checked") | P97: =IFERROR(INDEX(Venues!$D$2:$D$10,MATCH(M97,Venues!$A$2:$A$10,0)),0) | Q97: =IFERROR(INDEX(Venues!$E$2:$E$10,MATCH(M97,Venues!$A$2:$A$10,0)),"") | R97: =IF(P97>0,"Yes","No") | S97: COLA Shoreditch Park | T97: =IFERROR(INDEX(Venues!$E$2:$E$10,MATCH(S97,Venues!$A$2:$A$10,0)),"") | U97: =IFERROR(INDEX(Venues!$F$2:$F$10,MATCH(S97,Venues!$A$2:$A$10,0)),"") | V97: =IFERROR(INDEX(Venues!$H$2:$H$10,MATCH(S97,Venues!$A$2:$A$10,0)),"") | W97: =IF('Pilot offer'!$C$24="Yes",'Pilot offer'!$C$3,S97) | X97: =IF('Pilot offer'!$C$24="Yes",'Pilot offer'!$C$5+'Pilot offer'!$C$6,T97) | Y97: =IF('Pilot offer'!$C$24="Yes",'Pilot offer'!$C$8,U97) | Z97: =IF('Pilot offer'!$C$24="Yes",'Pilot offer'!$C$11,"") | AA97: =IF(X97="","",W97&" · "&TEXT(X97,"ddd d mmm, hh:mm")&" · "&Y97&IF(Z97<>""," · £"&TEXT(Z97,"0.00")&" per player"," · price TBC (cost £"&TEXT(V97,"0.00")&" pp)"))
A98: 96 | B98: 1 · E2 Haggerston | C98: Leisure & culture | D98: Local businesses | E98: Young V&A | F98: tourism: museum | G98: hello@vam.ac.uk | H98: general | I98: +44 20 7942 2000 | J98: https://www.vam.ac.uk/young | K98: Cambridge Heath Road, London | L98: E2 9PA | M98: Stepney 3G | N98: 12 | O98: =IFERROR(INDEX(Venues!$C$2:$C$10,MATCH(M98,Venues!$A$2:$A$10,0)),"Not checked") | P98: =IFERROR(INDEX(Venues!$D$2:$D$10,MATCH(M98,Venues!$A$2:$A$10,0)),0) | Q98: =IFERROR(INDEX(Venues!$E$2:$E$10,MATCH(M98,Venues!$A$2:$A$10,0)),"") | R98: =IF(P98>0,"Yes","No") | S98: COLA Shoreditch Park | T98: =IFERROR(INDEX(Venues!$E$2:$E$10,MATCH(S98,Venues!$A$2:$A$10,0)),"") | U98: =IFERROR(INDEX(Venues!$F$2:$F$10,MATCH(S98,Venues!$A$2:$A$10,0)),"") | V98: =IFERROR(INDEX(Venues!$H$2:$H$10,MATCH(S98,Venues!$A$2:$A$10,0)),"") | W98: =IF('Pilot offer'!$C$24="Yes",'Pilot offer'!$C$3,S98) | X98: =IF('Pilot offer'!$C$24="Yes",'Pilot offer'!$C$5+'Pilot offer'!$C$6,T98) | Y98: =IF('Pilot offer'!$C$24="Yes",'Pilot offer'!$C$8,U98) | Z98: =IF('Pilot offer'!$C$24="Yes",'Pilot offer'!$C$11,"") | AA98: =IF(X98="","",W98&" · "&TEXT(X98,"ddd d mmm, hh:mm")&" · "&Y98&IF(Z98<>""," · £"&TEXT(Z98,"0.00")&" per player"," · price TBC (cost £"&TEXT(V98,"0.00")&" pp)"))
A99: 97 | B99: 1 · E2 Haggerston | C99: Hospitality | D99: Local businesses | E99: Gallery Café | F99: amenity: cafe | G99: office@stmargaretshouse.org.uk | H99: general | J99: https://www.stmargaretshouse.org.uk/the-gallery-cafe | K99: Old Ford Road 15-23, London | L99: E2 9PJ | M99: Stepney 3G | N99: 13 | O99: =IFERROR(INDEX(Venues!$C$2:$C$10,MATCH(M99,Venues!$A$2:$A$10,0)),"Not checked") | P99: =IFERROR(INDEX(Venues!$D$2:$D$10,MATCH(M99,Venues!$A$2:$A$10,0)),0) | Q99: =IFERROR(INDEX(Venues!$E$2:$E$10,MATCH(M99,Venues!$A$2:$A$10,0)),"") | R99: =IF(P99>0,"Yes","No") | S99: COLA Shoreditch Park | T99: =IFERROR(INDEX(Venues!$E$2:$E$10,MATCH(S99,Venues!$A$2:$A$10,0)),"") | U99: =IFERROR(INDEX(Venues!$F$2:$F$10,MATCH(S99,Venues!$A$2:$A$10,0)),"") | V99: =IFERROR(INDEX(Venues!$H$2:$H$10,MATCH(S99,Venues!$A$2:$A$10,0)),"") | W99: =IF('Pilot offer'!$C$24="Yes",'Pilot offer'!$C$3,S99) | X99: =IF('Pilot offer'!$C$24="Yes",'Pilot offer'!$C$5+'Pilot offer'!$C$6,T99) | Y99: =IF('Pilot offer'!$C$24="Yes",'Pilot offer'!$C$8,U99) | Z99: =IF('Pilot offer'!$C$24="Yes",'Pilot offer'!$C$11,"") | AA99: =IF(X99="","",W99&" · "&TEXT(X99,"ddd d mmm, hh:mm")&" · "&Y99&IF(Z99<>""," · £"&TEXT(Z99,"0.00")&" per player"," · price TBC (cost £"&TEXT(V99,"0.00")&" pp)"))
A100: 98 | B100: 1 · E2 Haggerston | C100: Retail | D100: Local businesses | E100: The People's Letters Bookshop | F100: shop: books | G100: info@peoplesletters.org | H100: general | J100: https://peoplesletters.org/ | K100: Cambridge Heath Road 395, London | L100: E2 9RA | M100: Stepney 3G | N100: 15 | O100: =IFERROR(INDEX(Venues!$C$2:$C$10,MATCH(M100,Venues!$A$2:$A$10,0)),"Not checked") | P100: =IFERROR(INDEX(Venues!$D$2:$D$10,MATCH(M100,Venues!$A$2:$A$10,0)),0) | Q100: =IFERROR(INDEX(Venues!$E$2:$E$10,MATCH(M100,Venues!$A$2:$A$10,0)),"") | R100: =IF(P100>0,"Yes","No") | S100: COLA Shoreditch Park | T100: =IFERROR(INDEX(Venues!$E$2:$E$10,MATCH(S100,Venues!$A$2:$A$10,0)),"") | U100: =IFERROR(INDEX(Venues!$F$2:$F$10,MATCH(S100,Venues!$A$2:$A$10,0)),"") | V100: =IFERROR(INDEX(Venues!$H$2:$H$10,MATCH(S100,Venues!$A$2:$A$10,0)),"") | W100: =IF('Pilot offer'!$C$24="Yes",'Pilot offer'!$C$3,S100) | X100: =IF('Pilot offer'!$C$24="Yes",'Pilot offer'!$C$5+'Pilot offer'!$C$6,T100) | Y100: =IF('Pilot offer'!$C$24="Yes",'Pilot offer'!$C$8,U100) | Z100: =IF('Pilot offer'!$C$24="Yes",'Pilot offer'!$C$11,"") | AA100: =IF(X100="","",W100&" · "&TEXT(X100,"ddd d mmm, hh:mm")&" · "&Y100&IF(Z100<>""," · £"&TEXT(Z100,"0.00")&" per player"," · price TBC (cost £"&TEXT(V100,"0.00")&" pp)"))
...

Sheet Pilot offer
B1: Pilot offer · Haggerston Park
B2: Yellow cells are inputs. Once date, kick-off, format and price are filled, every Outreach row leads with this slot.
B3: Pitch | C3: Haggerston Park | D3: Luuk
B4: Address | C4: Yorkton St, E2 8NH | D4: Luuk
B5: Date | D5: Luuk
B6: Kick-off | D6: Luuk
B7: Duration (min) | C7: 60 | D7: Luuk
B8: Format | D8: Luuk
B9: Players on the pitch | C9: =IFERROR(VALUE(LEFT(C8,FIND("-",C8)-1))*2,"")
B10: Hire cost (£) | D10: Luuk
B11: Price per player (£) | D11: Joep
B12: Minimum paying players to cover hire | C12: =IF(OR(C10="",C11="",C11=0),"",ROUNDUP(C10/C11,0))
B13: Revenue if full (£) | C13: =IF(OR(C9="",C11=""),"",C9*C11)
B14: Margin if full (£) | C14: =IF(OR(C13="",C10=""),"",C13-C10)
B15: Margin if full (%) | C15: =IF(OR(C14="",C13="",C13=0),"",C14/C13)
B16: Booking deadline (venue) | D16: Luuk
B17: Cancellation terms (venue) | D17: Luuk
B18: We commit to the venue when… | D18: Joep
B19: Joining link (app)
B20: Deadline for players to commit
B21: Who confirms the booking | C21: Hackney Parks bookings (GLL) · 020 8986 7955 (Mon–Fri 09:00–15:30) · hackney.marshes@gll.org | D21: Luuk
B22: Floodlit | C22: Yes per Playfinder / Hackney Council (18:00–22:00 in term time); fcurban.com page says no — confirm on the call | D22: Luuk
B24: Pilot ready to lead outreach? | C24: =IF(AND(C5<>"",C6<>"",C8<>"",C11<>""),"Yes","No — fill Date, Kick-off, Format and Price")
B26: Cost floor for comparison: see Venues › Cost per player at earliest. Old St – Moreland 6-a-side works out at £7.50 per player at cost; COLA 5-a-side £9.10.

Sheet Venues
A1: Venue | B1: Address | C1: Status | D1: Open after-work slots | E1: Earliest slot | F1: Earliest format | G1: Earliest hire (£) | H1: Cost per player at earliest (£) | I1: Floodlit | J1: Booking source | K1: Booking link | L1: Booking contact | M1: Phone | N1: Email | O1: How to book / notes | P1: Leads tagged here | Q1: Leads using as fallback
A2: Haggerston Park | B2: Yorkton St, E2 8NH | C2: Contact required | D2: =COUNTIFS(Slots!$A$2:$A$90,A2,Slots!$I$2:$I$90,"Available") | E2: =IF(D2=0,"",_xlfn.MINIFS(Slots!$F$2:$F$90,Slots!$A$2:$A$90,A2,Slots!$I$2:$I$90,"Available")) | F2: =IFERROR(INDEX(Slots!$G$2:$G$90,MATCH(A2&"#1",Slots!$R$2:$R$90,0)),"") | G2: =IFERROR(INDEX(Slots!$J$2:$J$90,MATCH(A2&"#1",Slots!$R$2:$R$90,0)),"") | H2: =IFERROR(INDEX(Slots!$L$2:$L$90,MATCH(A2&"#1",Slots!$R$2:$R$90,0)),"") | I2: yes | J2: Hackney Council (GLL) | K2: https://www.hackney.gov.uk/courts-and-pitches | L2: Hackney Parks bookings (GLL) | M2: 020 8986 7955 | N2: hackney.marshes@gll.org | O2: Phone line Mon-Fri 09:00-15:30. Pitch bookable 18:00-22:00 in term time per Hackney Council | P2: =COUNTIF(Outreach!$M$3:$M$2000,A2) | Q2: =COUNTIF(Outreach!$S$3:$S$2000,A2)
A3: Whitechapel | B3: Mulberry Sports & Leisure Centre, Richard St, E1 2JP | C3: Contact required | D3: =COUNTIFS(Slots!$A$2:$A$90,A3,Slots!$I$2:$I$90,"Available") | E3: =IF(D3=0,"",_xlfn.MINIFS(Slots!$F$2:$F$90,Slots!$A$2:$A$90,A3,Slots!$I$2:$I$90,"Available")) | F3: =IFERROR(INDEX(Slots!$G$2:$G$90,MATCH(A3&"#1",Slots!$R$2:$R$90,0)),"") | G3: =IFERROR(INDEX(Slots!$J$2:$J$90,MATCH(A3&"#1",Slots!$R$2:$R$90,0)),"") | H3: =IFERROR(INDEX(Slots!$L$2:$L$90,MATCH(A3&"#1",Slots!$R$2:$R$90,0)),"") | I3: yes | J3: Mulberry Sports & Leisure Centre (Parkwood Leisure) | K3: https://pitchbooking.com/partners/MULBERRYSPORTSLEISURECENTRE | L3: Mulberry Sports & Leisure Centre reception (Parkwood Leisure) | M3: 020 7790 3854 | O3: Powerleague partner venue for leagues only: Natasha Gouveia (club manager) 0800 567 0757 partnervenues@powerleague.com | P3: =COUNTIF(Outreach!$M$3:$M$2000,A3) | Q3: =COUNTIF(Outreach!$S$3:$S$2000,A3)
A4: Shoreditch Rooftop | B4: Britannia Leisure Centre, Pitfield St, N1 5FT | C4: Available | D4: =COUNTIFS(Slots!$A$2:$A$90,A4,Slots!$I$2:$I$90,"Available") | E4: =IF(D4=0,"",_xlfn.MINIFS(Slots!$F$2:$F$90,Slots!$A$2:$A$90,A4,Slots!$I$2:$I$90,"Available")) | F4: =IFERROR(INDEX(Slots!$G$2:$G$90,MATCH(A4&"#1",Slots!$R$2:$R$90,0)),"") | G4: =IFERROR(INDEX(Slots!$J$2:$J$90,MATCH(A4&"#1",Slots!$R$2:$R$90,0)),"") | H4: =IFERROR(INDEX(Slots!$L$2:$L$90,MATCH(A4&"#1",Slots!$R$2:$R$90,0)),"") | I4: yes | J4: Better (GLL) | K4: https://bookings.better.org.uk/location/britannia-leisure-centre/3g-cage/2026-09-28/by-time | L4: Better - Britannia Leisure Centre | O4: Online at bookings.better.org.uk with a Better account. Slots released 6 days ahead. Ask Better about a block booking for later dates | P4: =COUNTIF(Outreach!$M$3:$M$2000,A4) | Q4: =COUNTIF(Outreach!$S$3:$S$2000,A4)
A5: Rosemary Gardens 3G - Islington | B5: Southgate Rd, N1 3JP | C5: No availability | D5: =COUNTIFS(Slots!$A$2:$A$90,A5,Slots!$I$2:$I$90,"Available") | E5: =IF(D5=0,"",_xlfn.MINIFS(Slots!$F$2:$F$90,Slots!$A$2:$A$90,A5,Slots!$I$2:$I$90,"Available")) | F5: =IFERROR(INDEX(Slots!$G$2:$G$90,MATCH(A5&"#1",Slots!$R$2:$R$90,0)),"") | G5: =IFERROR(INDEX(Slots!$J$2:$J$90,MATCH(A5&"#1",Slots!$R$2:$R$90,0)),"") | H5: =IFERROR(INDEX(Slots!$L$2:$L$90,MATCH(A5&"#1",Slots!$R$2:$R$90,0)),"") | I5: yes | J5: Better (GLL) - Islington | K5: https://bookings.better.org.uk/location/islington-tennis-centre/rosemary-gardens-activities | L5: Better - Islington Tennis Centre (Islington parks pitches) | O5: Online at bookings.better.org.uk with a Better account. Slots released 6 days ahead | P5: =COUNTIF(Outreach!$M$3:$M$2000,A5) | Q5: =COUNTIF(Outreach!$S$3:$S$2000,A5)
A6: Stepney 3G | B6: Globe Football Pitch, 110 Globe Rd, E1 4DZ | C6: Available | D6: =COUNTIFS(Slots!$A$2:$A$90,A6,Slots!$I$2:$I$90,"Available") | E6: =IF(D6=0,"",_xlfn.MINIFS(Slots!$F$2:$F$90,Slots!$A$2:$A$90,A6,Slots!$I$2:$I$90,"Available")) | F6: =IFERROR(INDEX(Slots!$G$2:$G$90,MATCH(A6&"#1",Slots!$R$2:$R$90,0)),"") | G6: =IFERROR(INDEX(Slots!$J$2:$J$90,MATCH(A6&"#1",Slots!$R$2:$R$90,0)),"") | H6: =IFERROR(INDEX(Slots!$L$2:$L$90,MATCH(A6&"#1",Slots!$R$2:$R$90,0)),"") | I6: unknown | J6: BookMyPitch | K6: https://bookmypitch.uk/slots/c5d1422b-8c1e-4497-b8a4-13cd96677bdc | L6: BookMyPitch (Globe Football Pitch) | O6: Venue is Globe Football Pitch 110 Globe Rd E1 4DZ. This is not the Tower Hamlets Stepney Green Park astroturf, which needs a council account. BookMyPitch venue contact for listings: masud@bookmypitch.uk | P6: =COUNTIF(Outreach!$M$3:$M$2000,A6) | Q6: =COUNTIF(Outreach!$S$3:$S$2000,A6)
A7: Old St - Moreland Primary School | B7: Gard St, EC1V 8DW | C7: Available | D7: =COUNTIFS(Slots!$A$2:$A$90,A7,Slots!$I$2:$I$90,"Available") | E7: =IF(D7=0,"",_xlfn.MINIFS(Slots!$F$2:$F$90,Slots!$A$2:$A$90,A7,Slots!$I$2:$I$90,"Available")) | F7: =IFERROR(INDEX(Slots!$G$2:$G$90,MATCH(A7&"#1",Slots!$R$2:$R$90,0)),"") | G7: =IFERROR(INDEX(Slots!$J$2:$J$90,MATCH(A7&"#1",Slots!$R$2:$R$90,0)),"") | H7: =IFERROR(INDEX(Slots!$L$2:$L$90,MATCH(A7&"#1",Slots!$R$2:$R$90,0)),"") | I7: yes | J7: PlayFootball | K7: https://www.playfootball.net/venues/old-street-moreland-school/book-a-pitch/87/6-a-side3gpitchhire | L7: PlayFootball | O7: Regular weekly bookings by enquiry via https://www.playfootball.net/contact-us (reply within 48h). One-off bookings online up to 30 days ahead | P7: =COUNTIF(Outreach!$M$3:$M$2000,A7) | Q7: =COUNTIF(Outreach!$S$3:$S$2000,A7)
A8: Hackney | B8: The City Academy Hackney, Homerton High St, E9 6JQ | C8: Available | D8: =COUNTIFS(Slots!$A$2:$A$90,A8,Slots!$I$2:$I$90,"Available") | E8: =IF(D8=0,"",_xlfn.MINIFS(Slots!$F$2:$F$90,Slots!$A$2:$A$90,A8,Slots!$I$2:$I$90,"Available")) | F8: =IFERROR(INDEX(Slots!$G$2:$G$90,MATCH(A8&"#1",Slots!$R$2:$R$90,0)),"") | G8: =IFERROR(INDEX(Slots!$J$2:$J$90,MATCH(A8&"#1",Slots!$R$2:$R$90,0)),"") | H8: =IFERROR(INDEX(Slots!$L$2:$L$90,MATCH(A8&"#1",Slots!$R$2:$R$90,0)),"") | I8: yes | J8: enni.space (The City Academy Hackney) | K8: https://enni.space/search/2872-city-academy-hackney-3g-pitch | L8: The City Academy Hackney lettings (via enni.space) | O8: Booking request on enni.space. Not instant book | P8: =COUNTIF(Outreach!$M$3:$M$2000,A8) | Q8: =COUNTIF(Outreach!$S$3:$S$2000,A8)
A9: COLA Shoreditch Park | B9: Hyde Rd, N1 5JU | C9: Available | D9: =COUNTIFS(Slots!$A$2:$A$90,A9,Slots!$I$2:$I$90,"Available") | E9: =IF(D9=0,"",_xlfn.MINIFS(Slots!$F$2:$F$90,Slots!$A$2:$A$90,A9,Slots!$I$2:$I$90,"Available")) | F9: =IFERROR(INDEX(Slots!$G$2:$G$90,MATCH(A9&"#1",Slots!$R$2:$R$90,0)),"") | G9: =IFERROR(INDEX(Slots!$J$2:$J$90,MATCH(A9&"#1",Slots!$R$2:$R$90,0)),"") | H9: =IFERROR(INDEX(Slots!$L$2:$L$90,MATCH(A9&"#1",Slots!$R$2:$R$90,0)),"") | I9: unknown | J9: enni.space (City of London Academy Shoreditch Park) | K9: https://enni.space/search/21782-cola-shoreditch-park-3g-5-a-side-pitch | L9: City of London Academy Shoreditch Park lettings (via enni.space) | O9: Pitch free 17:30-19:00. Rooftop 3G. Price-from per hour | P9: =COUNTIF(Outreach!$M$3:$M$2000,A9) | Q9: =COUNTIF(Outreach!$S$3:$S$2000,A9)
A10: Market Road | B10: Market Rd, N7 9PL | C10: Available | D10: =COUNTIFS(Slots!$A$2:$A$90,A10,Slots!$I$2:$I$90,"Available") | E10: =IF(D10=0,"",_xlfn.MINIFS(Slots!$F$2:$F$90,Slots!$A$2:$A$90,A10,Slots!$I$2:$I$90,"Available")) | F10: =IFERROR(INDEX(Slots!$G$2:$G$90,MATCH(A10&"#1",Slots!$R$2:$R$90,0)),"") | G10: =IFERROR(INDEX(Slots!$J$2:$J$90,MATCH(A10&"#1",Slots!$R$2:$R$90,0)),"") | H10: =IFERROR(INDEX(Slots!$L$2:$L$90,MATCH(A10&"#1",Slots!$R$2:$R$90,0)),"") | I10: yes | J10: Better (GLL) - Islington Tennis Centre | K10: https://bookings.better.org.uk/location/islington-tennis-centre/market-road | L10: Better - Islington Tennis Centre / PlayFootball Islington Market Road | O10: Better 5-a-side slots online 6 days ahead. PlayFootball 7-a-side pitch is online. Regular bookings by enquiry via https://www.playfootball.net/contact-us | P10: =COUNTIF(Outreach!$M$3:$M$2000,A10) | Q10: =COUNTIF(Outreach!$S$3:$S$2000,A10)

Sheet Slots
A1: Venue | B1: Date | C1: Day | D1: Start | E1: End | F1: Slot start | G1: Format | H1: Players (full pitch) | I1: Status | J1: Hire (£ per slot) | K1: Venue charges per player (£) | L1: Cost per player (£) | M1: Floodlit | N1: Booking source | O1: Booking link | P1: Notes | Q1: Rank in venue | R1: Key
A2: Haggerston Park | F2: =IF(B2="","",B2+D2) | G2: 5/7/11-a-side | H2: =IFERROR(VALUE(LEFT(G2,FIND("-",G2)-1))*2,"") | I2: Contact required | L2: =IF(J2<>"",IF(H2="","",J2/H2),IF(K2<>"",K2,"")) | M2: yes | N2: Hackney Council (GLL) | O2: https://www.hackney.gov.uk/courts-and-pitches | P2: No online calendar. Book by phone 020 8986 7955 (Mon-Fri 09:00-15:30) or hackney.marshes@gll.org. Floodlit per Playfinder listing. Playfinder also shows the venue as fully booked | Q2: =IF(I2="Available",COUNTIFS($A$2:$A$90,A2,$I$2:$I$90,"Available",$F$2:$F$90,"<"&F2)+1,"") | R2: =IF(Q2="","",A2&"#"&Q2)
A3: Whitechapel | F3: =IF(B3="","",B3+D3) | G3: 5-a-side | H3: =IFERROR(VALUE(LEFT(G3,FIND("-",G3)-1))*2,"") | I3: Contact required | L3: =IF(J3<>"",IF(H3="","",J3/H3),IF(K3<>"",K3,"")) | M3: yes | N3: Mulberry Sports & Leisure Centre (Parkwood Leisure) | O3: https://pitchbooking.com/partners/MULBERRYSPORTSLEISURECENTRE | P3: Enquiry only. Call 020 7790 3854. Centre is at Richard St E1 2JP (brief says E1 2JR). Weekday hours 18:00-22:00. Powerleague runs Mon and Tue 19:30 leagues here. Floodlit per Powerleague | Q3: =IF(I3="Available",COUNTIFS($A$2:$A$90,A3,$I$2:$I$90,"Available",$F$2:$F$90,"<"&F3)+1,"") | R3: =IF(Q3="","",A3&"#"&Q3)
A4: Shoreditch Rooftop | B4: 46293 | C4: Mon | D4: 0.75 | E4: 0.79166667 | F4: =IF(B4="","",B4+D4) | G4: 5-a-side | H4: =IFERROR(VALUE(LEFT(G4,FIND("-",G4)-1))*2,"") | I4: Available | J4: 72.2 | L4: =IF(J4<>"",IF(H4="","",J4/H4),IF(K4<>"",K4,"")) | M4: yes | N4: Better (GLL) | O4: https://bookings.better.org.uk/location/britannia-leisure-centre/3g-cage/2026-09-28/by-time | P4: Football Pitch 2. Better account needed to book. 29 Sep 18:00-21:00 full. Better only releases slots 6 days ahead so 30 Sep onwards not visible yet | Q4: =IF(I4="Available",COUNTIFS($A$2:$A$90,A4,$I$2:$I$90,"Available",$F$2:$F$90,"<"&F4)+1,"") | R4: =IF(Q4="","",A4&"#"&Q4)
A5: Rosemary Gardens 3G - Islington | F5: =IF(B5="","",B5+D5) | G5: 7-a-side (full) / half pitch | H5: =IFERROR(VALUE(LEFT(G5,FIND("-",G5)-1))*2,"") | I5: No availability | L5: =IF(J5<>"",IF(H5="","",J5/H5),IF(K5<>"",K5,"")) | M5: yes | N5: Better (GLL) - Islington | O5: https://bookings.better.org.uk/location/islington-tennis-centre/rosemary-gardens-activities | P5: No evening slots listed for full or half pitch on 28-29 Sep. 30 Sep onwards not released yet (6-day window). Daytime prices shown: full pitch 108.90/hr and half pitch 54.45/hr. Floodlit per Islington Council | Q5: =IF(I5="Available",COUNTIFS($A$2:$A$90,A5,$I$2:$I$90,"Available",$F$2:$F$90,"<"&F5)+1,"") | R5: =IF(Q5="","",A5&"#"&Q5)
A6: Stepney 3G | B6: 46293 | C6: Mon | D6: 0.72916667 | E6: 0.77083333 | F6: =IF(B6="","",B6+D6) | G6: 5-a-side | H6: =IFERROR(VALUE(LEFT(G6,FIND("-",G6)-1))*2,"") | I6: Available | K6: 3 | L6: =IF(J6<>"",IF(H6="","",J6/H6),IF(K6<>"",K6,"")) | M6: unknown | N6: BookMyPitch | O6: https://bookmypitch.uk/slots/c5d1422b-8c1e-4497-b8a4-13cd96677bdc | P6: Off-peak 3/player. Priced per player, not per pitch (game is created and charged once full). 4G surface. Calendar only shows up to 7 Oct | Q6: =IF(I6="Available",COUNTIFS($A$2:$A$90,A6,$I$2:$I$90,"Available",$F$2:$F$90,"<"&F6)+1,"") | R6: =IF(Q6="","",A6&"#"&Q6)
A7: Stepney 3G | B7: 46293 | C7: Mon | D7: 0.77083333 | E7: 0.8125 | F7: =IF(B7="","",B7+D7) | G7: 5-a-side | H7: =IFERROR(VALUE(LEFT(G7,FIND("-",G7)-1))*2,"") | I7: Available | K7: 5 | L7: =IF(J7<>"",IF(H7="","",J7/H7),IF(K7<>"",K7,"")) | M7: unknown | N7: BookMyPitch | O7: https://bookmypitch.uk/slots/c5d1422b-8c1e-4497-b8a4-13cd96677bdc | P7: Peak 5/player. Priced per player, not per pitch (game is created and charged once full). 4G surface. Calendar only shows up to 7 Oct | Q7: =IF(I7="Available",COUNTIFS($A$2:$A$90,A7,$I$2:$I$90,"Available",$F$2:$F$90,"<"&F7)+1,"") | R7: =IF(Q7="","",A7&"#"&Q7)
A8: Stepney 3G | B8: 46293 | C8: Mon | D8: 0.8125 | E8: 0.85416667 | F8: =IF(B8="","",B8+D8) | G8: 5-a-side | H8: =IFERROR(VALUE(LEFT(G8,FIND("-",G8)-1))*2,"") | I8: Available | K8: 5 | L8: =IF(J8<>"",IF(H8="","",J8/H8),IF(K8<>"",K8,"")) | M8: unknown | N8: BookMyPitch | O8: https://bookmypitch.uk/slots/c5d1422b-8c1e-4497-b8a4-13cd96677bdc | P8: Peak 5/player. Priced per player, not per pitch (game is created and charged once full). 4G surface. Calendar only shows up to 7 Oct | Q8: =IF(I8="Available",COUNTIFS($A$2:$A$90,A8,$I$2:$I$90,"Available",$F$2:$F$90,"<"&F8)+1,"") | R8: =IF(Q8="","",A8&"#"&Q8)
A9: Stepney 3G | B9: 46293 | C9: Mon | D9: 0.85416667 | E9: 0.89583333 | F9: =IF(B9="","",B9+D9) | G9: 5-a-side | H9: =IFERROR(VALUE(LEFT(G9,FIND("-",G9)-1))*2,"") | I9: Available | K9: 5 | L9: =IF(J9<>"",IF(H9="","",J9/H9),IF(K9<>"",K9,"")) | M9: unknown | N9: BookMyPitch | O9: https://bookmypitch.uk/slots/c5d1422b-8c1e-4497-b8a4-13cd96677bdc | P9: Peak 5/player. Priced per player, not per pitch (game is created and charged once full). 4G surface. Calendar only shows up to 7 Oct | Q9: =IF(I9="Available",COUNTIFS($A$2:$A$90,A9,$I$2:$I$90,"Available",$F$2:$F$90,"<"&F9)+1,"") | R9: =IF(Q9="","",A9&"#"&Q9)
A10: Stepney 3G | B10: 46294 | C10: Tue | D10: 0.72916667 | E10: 0.77083333 | F10: =IF(B10="","",B10+D10) | G10: 5-a-side | H10: =IFERROR(VALUE(LEFT(G10,FIND("-",G10)-1))*2,"") | I10: Available | K10: 3 | L10: =IF(J10<>"",IF(H10="","",J10/H10),IF(K10<>"",K10,"")) | M10: unknown | N10: BookMyPitch | O10: https://bookmypitch.uk/slots/c5d1422b-8c1e-4497-b8a4-13cd96677bdc | P10: Off-peak 3/player. Priced per player, not per pitch (game is created and charged once full). 4G surface. Calendar only shows up to 7 Oct | Q10: =IF(I10="Available",COUNTIFS($A$2:$A$90,A10,$I$2:$I$90,"Available",$F$2:$F$90,"<"&F10)+1,"") | R10: =IF(Q10="","",A10&"#"&Q10)
A11: Stepney 3G | B11: 46294 | C11: Tue | D11: 0.77083333 | E11: 0.8125 | F11: =IF(B11="","",B11+D11) | G11: 5-a-side | H11: =IFERROR(VALUE(LEFT(G11,FIND("-",G11)-1))*2,"") | I11: Available | K11: 5 | L11: =IF(J11<>"",IF(H11="","",J11/H11),IF(K11<>"",K11,"")) | M11: unknown | N11: BookMyPitch | O11: https://bookmypitch.uk/slots/c5d1422b-8c1e-4497-b8a4-13cd96677bdc | P11: Peak 5/player. Priced per player, not per pitch (game is created and charged once full). 4G surface. Calendar only shows up to 7 Oct | Q11: =IF(I11="Available",COUNTIFS($A$2:$A$90,A11,$I$2:$I$90,"Available",$F$2:$F$90,"<"&F11)+1,"") | R11: =IF(Q11="","",A11&"#"&Q11)
A12: Stepney 3G | B12: 46294 | C12: Tue | D12: 0.8125 | E12: 0.85416667 | F12: =IF(B12="","",B12+D12) | G12: 5-a-side | H12: =IFERROR(VALUE(LEFT(G12,FIND("-",G12)-1))*2,"") | I12: Available | K12: 5 | L12: =IF(J12<>"",IF(H12="","",J12/H12),IF(K12<>"",K12,"")) | M12: unknown | N12: BookMyPitch | O12: https://bookmypitch.uk/slots/c5d1422b-8c1e-4497-b8a4-13cd96677bdc | P12: Peak 5/player. Priced per player, not per pitch (game is created and charged once full). 4G surface. Calendar only shows up to 7 Oct | Q12: =IF(I12="Available",COUNTIFS($A$2:$A$90,A12,$I$2:$I$90,"Available",$F$2:$F$90,"<"&F12)+1,"") | R12: =IF(Q12="","",A12&"#"&Q12)
A13: Stepney 3G | B13: 46294 | C13: Tue | D13: 0.85416667 | E13: 0.89583333 | F13: =IF(B13="","",B13+D13) | G13: 5-a-side | H13: =IFERROR(VALUE(LEFT(G13,FIND("-",G13)-1))*2,"") | I13: Available | K13: 5 | L13: =IF(J13<>"",IF(H13="","",J13/H13),IF(K13<>"",K13,"")) | M13: unknown | N13: BookMyPitch | O13: https://bookmypitch.uk/slots/c5d1422b-8c1e-4497-b8a4-13cd96677bdc | P13: Peak 5/player. Priced per player, not per pitch (game is created and charged once full). 4G surface. Calendar only shows up to 7 Oct | Q13: =IF(I13="Available",COUNTIFS($A$2:$A$90,A13,$I$2:$I$90,"Available",$F$2:$F$90,"<"&F13)+1,"") | R13: =IF(Q13="","",A13&"#"&Q13)
A14: Stepney 3G | B14: 46295 | C14: Wed | D14: 0.72916667 | E14: 0.77083333 | F14: =IF(B14="","",B14+D14) | G14: 5-a-side | H14: =IFERROR(VALUE(LEFT(G14,FIND("-",G14)-1))*2,"") | I14: Available | K14: 3 | L14: =IF(J14<>"",IF(H14="","",J14/H14),IF(K14<>"",K14,"")) | M14: unknown | N14: BookMyPitch | O14: https://bookmypitch.uk/slots/c5d1422b-8c1e-4497-b8a4-13cd96677bdc | P14: Off-peak 3/player. Priced per player, not per pitch (game is created and charged once full). 4G surface. Calendar only shows up to 7 Oct | Q14: =IF(I14="Available",COUNTIFS($A$2:$A$90,A14,$I$2:$I$90,"Available",$F$2:$F$90,"<"&F14)+1,"") | R14: =IF(Q14="","",A14&"#"&Q14)
A15: Stepney 3G | B15: 46295 | C15: Wed | D15: 0.77083333 | E15: 0.8125 | F15: =IF(B15="","",B15+D15) | G15: 5-a-side | H15: =IFERROR(VALUE(LEFT(G15,FIND("-",G15)-1))*2,"") | I15: Available | K15: 5 | L15: =IF(J15<>"",IF(H15="","",J15/H15),IF(K15<>"",K15,"")) | M15: unknown | N15: BookMyPitch | O15: https://bookmypitch.uk/slots/c5d1422b-8c1e-4497-b8a4-13cd96677bdc | P15: Peak 5/player. Priced per player, not per pitch (game is created and charged once full). 4G surface. Calendar only shows up to 7 Oct | Q15: =IF(I15="Available",COUNTIFS($A$2:$A$90,A15,$I$2:$I$90,"Available",$F$2:$F$90,"<"&F15)+1,"") | R15: =IF(Q15="","",A15&"#"&Q15)
A16: Stepney 3G | B16: 46295 | C16: Wed | D16: 0.8125 | E16: 0.85416667 | F16: =IF(B16="","",B16+D16) | G16: 5-a-side | H16: =IFERROR(VALUE(LEFT(G16,FIND("-",G16)-1))*2,"") | I16: Available | K16: 5 | L16: =IF(J16<>"",IF(H16="","",J16/H16),IF(K16<>"",K16,"")) | M16: unknown | N16: BookMyPitch | O16: https://bookmypitch.uk/slots/c5d1422b-8c1e-4497-b8a4-13cd96677bdc | P16: Peak 5/player. Priced per player, not per pitch (game is created and charged once full). 4G surface. Calendar only shows up to 7 Oct | Q16: =IF(I16="Available",COUNTIFS($A$2:$A$90,A16,$I$2:$I$90,"Available",$F$2:$F$90,"<"&F16)+1,"") | R16: =IF(Q16="","",A16&"#"&Q16)
A17: Stepney 3G | B17: 46295 | C17: Wed | D17: 0.85416667 | E17: 0.89583333 | F17: =IF(B17="","",B17+D17) | G17: 5-a-side | H17: =IFERROR(VALUE(LEFT(G17,FIND("-",G17)-1))*2,"") | I17: Available | K17: 5 | L17: =IF(J17<>"",IF(H17="","",J17/H17),IF(K17<>"",K17,"")) | M17: unknown | N17: BookMyPitch | O17: https://bookmypitch.uk/slots/c5d1422b-8c1e-4497-b8a4-13cd96677bdc | P17: Peak 5/player. Priced per player, not per pitch (game is created and charged once full). 4G surface. Calendar only shows up to 7 Oct | Q17: =IF(I17="Available",COUNTIFS($A$2:$A$90,A17,$I$2:$I$90,"Available",$F$2:$F$90,"<"&F17)+1,"") | R17: =IF(Q17="","",A17&"#"&Q17)
... A37: Stepney 3G | B37: 46302 | C37: Wed | D37: 0.85416667 | E37: 0.89583333 | F37: =IF(B37="","",B37+D37) | G37: 5-a-side | H37: =IFERROR(VALUE(LEFT(G37,FIND("-",G37)-1))*2,"") | I37: Available | K37: 5 | L37: =IF(J37<>"",IF(H37="","",J37/H37),IF(K37<>"",K37,"")) | M37: unknown | N37: BookMyPitch | O37: https://bookmypitch.uk/slots/c5d1422b-8c1e-4497-b8a4-13cd96677bdc | P37: Peak 5/player. Priced per player, not per pitch (game is created and charged once full). 4G surface. Calendar only shows up to 7 Oct | Q37: =IF(I37="Available",COUNTIFS($A$2:$A$90,A37,$I$2:$I$90,"Available",$F$2:$F$90,"<"&F37)+1,"") | R37: =IF(Q37="","",A37&"#"&Q37)
A38: Old St - Moreland Primary School | B38: 46297 | C38: Fri | D38: 0.83333333 | E38: 0.875 | F38: =IF(B38="","",B38+D38) | G38: 6-a-side | H38: =IFERROR(VALUE(LEFT(G38,FIND("-",G38)-1))*2,"") | I38: Available | J38: 90 | L38: =IF(J38<>"",IF(H38="","",J38/H38),IF(K38<>"",K38,"")) | M38: yes | N38: PlayFootball | O38: https://www.playfootball.net/venues/old-street-moreland-school/book-a-pitch/87/6-a-side3gpitchhire | Q38: =IF(I38="Available",COUNTIFS($A$2:$A$90,A38,$I$2:$I$90,"Available",$F$2:$F$90,"<"&F38)+1,"") | R38: =IF(Q38="","",A38&"#"&Q38)
A39: Old St - Moreland Primary School | B39: 46304 | C39: Fri | D39: 0.83333333 | E39: 0.875 | F39: =IF(B39="","",B39+D39) | G39: 6-a-side | H39: =IFERROR(VALUE(LEFT(G39,FIND("-",G39)-1))*2,"") | I39: Available | J39: 90 | L39: =IF(J39<>"",IF(H39="","",J39/H39),IF(K39<>"",K39,"")) | M39: yes | N39: PlayFootball | O39: https://www.playfootball.net/venues/old-street-moreland-school/book-a-pitch/87/6-a-side3gpitchhire | Q39: =IF(I39="Available",COUNTIFS($A$2:$A$90,A39,$I$2:$I$90,"Available",$F$2:$F$90,"<"&F39)+1,"") | R39: =IF(Q39="","",A39&"#"&Q39)
A40: Old St - Moreland Primary School | B40: 46307 | C40: Mon | D40: 0.75 | E40: 0.79166667 | F40: =IF(B40="","",B40+D40) | G40: 6-a-side | H40: =IFERROR(VALUE(LEFT(G40,FIND("-",G40)-1))*2,"") | I40: Available | J40: 90 | L40: =IF(J40<>"",IF(H40="","",J40/H40),IF(K40<>"",K40,"")) | M40: yes | N40: PlayFootball | O40: https://www.playfootball.net/venues/old-street-moreland-school/book-a-pitch/87/6-a-side3gpitchhire | Q40: =IF(I40="Available",COUNTIFS($A$2:$A$90,A40,$I$2:$I$90,"Available",$F$2:$F$90,"<"&F40)+1,"") | R40: =IF(Q40="","",A40&"#"&Q40)
A41: Old St - Moreland Primary School | B41: 46307 | C41: Mon | D41: 0.79166667 | E41: 0.83333333 | F41: =IF(B41="","",B41+D41) | G41: 6-a-side | H41: =IFERROR(VALUE(LEFT(G41,FIND("-",G41)-1))*2,"") | I41: Available | J41: 90 | L41: =IF(J41<>"",IF(H41="","",J41/H41),IF(K41<>"",K41,"")) | M41: yes | N41: PlayFootball | O41: https://www.playfootball.net/venues/old-street-moreland-school/book-a-pitch/87/6-a-side3gpitchhire | Q41: =IF(I41="Available",COUNTIFS($A$2:$A$90,A41,$I$2:$I$90,"Available",$F$2:$F$90,"<"&F41)+1,"") | R41: =IF(Q41="","",A41&"#"&Q41)
A42: Old St - Moreland Primary School | B42: 46307 | C42: Mon | D42: 0.83333333 | E42: 0.875 | F42: =IF(B42="","",B42+D42) | G42: 6-a-side | H42: =IFERROR(VALUE(LEFT(G42,FIND("-",G42)-1))*2,"") | I42: Available | J42: 90 | L42: =IF(J42<>"",IF(H42="","",J42/H42),IF(K42<>"",K42,"")) | M42: yes | N42: PlayFootball | O42: https://www.playfootball.net/venues/old-street-moreland-school/book-a-pitch/87/6-a-side3gpitchhire | Q42: =IF(I42="Available",COUNTIFS($A$2:$A$90,A42,$I$2:$I$90,"Available",$F$2:$F$90,"<"&F42)+1,"") | R42: =IF(Q42="","",A42&"#"&Q42)
A43: Old St - Moreland Primary School | B43: 46311 | C43: Fri | D43: 0.83333333 | E43: 0.875 | F43: =IF(B43="","",B43+D43) | G43: 6-a-side | H43: =IFERROR(VALUE(LEFT(G43,FIND("-",G43)-1))*2,"") | I43: Available | J43: 90 | L43: =IF(J43<>"",IF(H43="","",J43/H43),IF(K43<>"",K43,"")) | M43: yes | N43: PlayFootball | O43: https://www.playfootball.net/venues/old-street-moreland-school/book-a-pitch/87/6-a-side3gpitchhire | Q43: =IF(I43="Available",COUNTIFS($A$2:$A$90,A43,$I$2:$I$90,"Available",$F$2:$F$90,"<"&F43)+1,"") | R43: =IF(Q43="","",A43&"#"&Q43)
A44: Old St - Moreland Primary School | B44: 46314 | C44: Mon | D44: 0.75 | E44: 0.79166667 | F44: =IF(B44="","",B44+D44) | G44: 6-a-side | H44: =IFERROR(VALUE(LEFT(G44,FIND("-",G44)-1))*2,"") | I44: Available | J44: 90 | L44: =IF(J44<>"",IF(H44="","",J44/H44),IF(K44<>"",K44,"")) | M44: yes | N44: PlayFootball | O44: https://www.playfootball.net/venues/old-street-moreland-school/book-a-pitch/87/6-a-side3gpitchhire | P44: Bookable 30 days ahead so 21-23 Oct not open yet | Q44: =IF(I44="Available",COUNTIFS($A$2:$A$90,A44,$I$2:$I$90,"Available",$F$2:$F$90,"<"&F44)+1,"") | R44: =IF(Q44="","",A44&"#"&Q44)
A45: Old St - Moreland Primary School | B45: 46314 | C45: Mon | D45: 0.79166667 | E45: 0.83333333 | F45: =IF(B45="","",B45+D45) | G45: 6-a-side | H45: =IFERROR(VALUE(LEFT(G45,FIND("-",G45)-1))*2,"") | I45: Available | J45: 90 | L45: =IF(J45<>"",IF(H45="","",J45/H45),IF(K45<>"",K45,"")) | M45: yes | N45: PlayFootball | O45: https://www.playfootball.net/venues/old-street-moreland-school/book-a-pitch/87/6-a-side3gpitchhire | P45: Bookable 30 days ahead so 21-23 Oct not open yet | Q45: =IF(I45="Available",COUNTIFS($A$2:$A$90,A45,$I$2:$I$90,"Available",$F$2:$F$90,"<"&F45)+1,"") | R45: =IF(Q45="","",A45&"#"&Q45)
A46: Old St - Moreland Primary School | B46: 46314 | C46: Mon | D46: 0.83333333 | E46: 0.875 | F46: =IF(B46="","",B46+D46) | G46: 6-a-side | H46: =IFERROR(VALUE(LEFT(G46,FIND("-",G46)-1))*2,"") | I46: Available | J46: 90 | L46: =IF(J46<>"",IF(H46="","",J46/H46),IF(K46<>"",K46,"")) | M46: yes | N46: PlayFootball | O46: https://www.playfootball.net/venues/old-street-moreland-school/book-a-pitch/87/6-a-side3gpitchhire | P46: Bookable 30 days ahead so 21-23 Oct not open yet | Q46: =IF(I46="Available",COUNTIFS($A$2:$A$90,A46,$I$2:$I$90,"Available",$F$2:$F$90,"<"&F46)+1,"") | R46: =IF(Q46="","",A46&"#"&Q46)
A47: Old St - Moreland Primary School | B47: 46315 | C47: Tue | D47: 0.75 | E47: 0.79166667 | F47: =IF(B47="","",B47+D47) | G47: 6-a-side | H47: =IFERROR(VALUE(LEFT(G47,FIND("-",G47)-1))*2,"") | I47: Available | J47: 90 | L47: =IF(J47<>"",IF(H47="","",J47/H47),IF(K47<>"",K47,"")) | M47: yes | N47: PlayFootball | O47: https://www.playfootball.net/venues/old-street-moreland-school/book-a-pitch/87/6-a-side3gpitchhire | P47: Bookable 30 days ahead so 21-23 Oct not open yet | Q47: =IF(I47="Available",COUNTIFS($A$2:$A$90,A47,$I$2:$I$90,"Available",$F$2:$F$90,"<"&F47)+1,"") | R47: =IF(Q47="","",A47&"#"&Q47)
A48: Old St - Moreland Primary School | B48: 46315 | C48: Tue | D48: 0.79166667 | E48: 0.83333333 | F48: =IF(B48="","",B48+D48) | G48: 6-a-side | H48: =IFERROR(VALUE(LEFT(G48,FIND("-",G48)-1))*2,"") | I48: Available | J48: 90 | L48: =IF(J48<>"",IF(H48="","",J48/H48),IF(K48<>"",K48,"")) | M48: yes | N48: PlayFootball | O48: https://www.playfootball.net/venues/old-street-moreland-school/book-a-pitch/87/6-a-side3gpitchhire | P48: Bookable 30 days ahead so 21-23 Oct not open yet | Q48: =IF(I48="Available",COUNTIFS($A$2:$A$90,A48,$I$2:$I$90,"Available",$F$2:$F$90,"<"&F48)+1,"") | R48: =IF(Q48="","",A48&"#"&Q48)
A49: Old St - Moreland Primary School | B49: 46315 | C49: Tue | D49: 0.83333333 | E49: 0.875 | F49: =IF(B49="","",B49+D49) | G49: 6-a-side | H49: =IFERROR(VALUE(LEFT(G49,FIND("-",G49)-1))*2,"") | I49: Available | J49: 90 | L49: =IF(J49<>"",IF(H49="","",J49/H49),IF(K49<>"",K49,"")) | M49: yes | N49: PlayFootball | O49: https://www.playfootball.net/venues/old-street-moreland-school/book-a-pitch/87/6-a-side3gpitchhire | P49: Bookable 30 days ahead so 21-23 Oct not open yet | Q49: =IF(I49="Available",COUNTIFS($A$2:$A$90,A49,$I$2:$I$90,"Available",$F$2:$F$90,"<"&F49)+1,"") | R49: =IF(Q49="","",A49&"#"&Q49)
A50: Hackney | B50: 46297 | C50: Fri | D50: 0.83333333 | E50: 0.875 | F50: =IF(B50="","",B50+D50) | G50: 7-a-side | H50: =IFERROR(VALUE(LEFT(G50,FIND("-",G50)-1))*2,"") | I50: Available | J50: 97.54 | L50: =IF(J50<>"",IF(H50="","",J50/H50),IF(K50<>"",K50,"")) | M50: yes | N50: enni.space (The City Academy Hackney) | O50: https://enni.space/search/2872-city-academy-hackney-3g-pitch | P50: Pitch free 20:00-22:00. Listed as price-from per hour. Booked by request, not instant. Floodlit per school site | Q50: =IF(I50="Available",COUNTIFS($A$2:$A$90,A50,$I$2:$I$90,"Available",$F$2:$F$90,"<"&F50)+1,"") | R50: =IF(Q50="","",A50&"#"&Q50)
A51: Hackney | B51: 46304 | C51: Fri | D51: 0.83333333 | E51: 0.875 | F51: =IF(B51="","",B51+D51) | G51: 7-a-side | H51: =IFERROR(VALUE(LEFT(G51,FIND("-",G51)-1))*2,"") | I51: Available | J51: 97.54 | L51: =IF(J51<>"",IF(H51="","",J51/H51),IF(K51<>"",K51,"")) | M51: yes | N51: enni.space (The City Academy Hackney) | O51: https://enni.space/search/2872-city-academy-hackney-3g-pitch | P51: Pitch free 20:00-22:00. Listed as price-from per hour. Booked by request, not instant. Floodlit per school site | Q51: =IF(I51="Available",COUNTIFS($A$2:$A$90,A51,$I$2:$I$90,"Available",$F$2:$F$90,"<"&F51)+1,"") | R51: =IF(Q51="","",A51&"#"&Q51)
A52: Hackney | B52: 46311 | C52: Fri | D52: 0.83333333 | E52: 0.875 | F52: =IF(B52="","",B52+D52) | G52: 7-a-side | H52: =IFERROR(VALUE(LEFT(G52,FIND("-",G52)-1))*2,"") | I52: Available | J52: 97.54 | L52: =IF(J52<>"",IF(H52="","",J52/H52),IF(K52<>"",K52,"")) | M52: yes | N52: enni.space (The City Academy Hackney) | O52: https://enni.space/search/2872-city-academy-hackney-3g-pitch | P52: Pitch free 20:00-22:00. Listed as price-from per hour. Booked by request, not instant. Floodlit per school site | Q52: =IF(I52="Available",COUNTIFS($A$2:$A$90,A52,$I$2:$I$90,"Available",$F$2:$F$90,"<"&F52)+1,"") | R52: =IF(Q52="","",A52&"#"&Q52)
A53: Hackney | B53: 46318 | C53: Fri | D53: 0.83333333 | E53: 0.875 | F53: =IF(B53="","",B53+D53) | G53: 7-a-side | H53: =IFERROR(VALUE(LEFT(G53,FIND("-",G53)-1))*2,"") | I53: Available | J53: 97.54 | L53: =IF(J53<>"",IF(H53="","",J53/H53),IF(K53<>"",K53,"")) | M53: yes | N53: enni.space (The City Academy Hackney) | O53: https://enni.space/search/2872-city-academy-hackney-3g-pitch | P53: Pitch free 20:00-22:00. Listed as price-from per hour. Booked by request, not instant. Floodlit per school site | Q53: =IF(I53="Available",COUNTIFS($A$2:$A$90,A53,$I$2:$I$90,"Available",$F$2:$F$90,"<"&F53)+1,"") | R53: =IF(Q53="","",A53&"#"&Q53)
A54: COLA Shoreditch Park | B54: 46294 | C54: Tue | D54: 0.72916667 | E54: 0.77083333 | F54: =IF(B54="","",B54+D54) | G54: 5-a-side | H54: =IFERROR(VALUE(LEFT(G54,FIND("-",G54)-1))*2,"") | I54: Available | J54: 90.97 | L54: =IF(J54<>"",IF(H54="","",J54/H54),IF(K54<>"",K54,"")) | M54: unknown | N54: enni.space (City of London Academy Shoreditch Park) | O54: https://enni.space/search/21782-cola-shoreditch-park-3g-5-a-side-pitch | P54: Pitch free 17:30-19:00. Rooftop 3G. Price-from per hour | Q54: =IF(I54="Available",COUNTIFS($A$2:$A$90,A54,$I$2:$I$90,"Available",$F$2:$F$90,"<"&F54)+1,"") | R54: =IF(Q54="","",A54&"#"&Q54)
A55: COLA Shoreditch Park | B55: 46301 | C55: Tue | D55: 0.72916667 | E55: 0.77083333 | F55: =IF(B55="","",B55+D55) | G55: 5-a-side | H55: =IFERROR(VALUE(LEFT(G55,FIND("-",G55)-1))*2,"") | I55: Available | J55: 90.97 | L55: =IF(J55<>"",IF(H55="","",J55/H55),IF(K55<>"",K55,"")) | M55: unknown | N55: enni.space (City of London Academy Shoreditch Park) | O55: https://enni.space/search/21782-cola-shoreditch-park-3g-5-a-side-pitch | P55: Pitch free 17:30-19:00. Rooftop 3G. Price-from per hour | Q55: =IF(I55="Available",COUNTIFS($A$2:$A$90,A55,$I$2:$I$90,"Available",$F$2:$F$90,"<"&F55)+1,"") | R55: =IF(Q55="","",A55&"#"&Q55)
... A90: Market Road | B90: 46293 | C90: Mon | D90: 0.75 | E90: 0.79166667 | F90: =IF(B90="","",B90+D90) | G90: 5-a-side | H90: =IFERROR(VALUE(LEFT(G90,FIND("-",G90)-1))*2,"") | I90: Available | J90: 110.3 | L90: =IF(J90<>"",IF(H90="","",J90/H90),IF(K90<>"",K90,"")) | M90: yes | N90: Better (GLL) - Islington Tennis Centre | O90: https://bookings.better.org.uk/location/islington-tennis-centre/market-road | P90: 1 of 3 pitches left. 29 Sep 18:00 full. 30 Sep onwards not released yet (6-day window). PlayFootball 7-a-side is fully booked 17:00-21:00 on 28 Sep and later dates are not open online | Q90: =IF(I90="Available",COUNTIFS($A$2:$A$90,A90,$I$2:$I$90,"Available",$F$2:$F$90,"<"&F90)+1,"") | R90: =IF(Q90="","",A90&"#"&Q90)

Sheet Totals
A1: Totals
A3: Leads by tier
B4: Count
A5: 1 · E2 Haggerston | B5: =COUNTIF(Outreach!$B$3:$B$2000,A5)
A6: 1 · E8 London Fields | B6: =COUNTIF(Outreach!$B$3:$B$2000,A6)
A7: 2 · EC2A Shoreditch | B7: =COUNTIF(Outreach!$B$3:$B$2000,A7)
A8: 2 · N1 Hoxton | B8: =COUNTIF(Outreach!$B$3:$B$2000,A8)
A9: 3 · E1 Whitechapel | B9: =COUNTIF(Outreach!$B$3:$B$2000,A9)
A10: Total | B10: =SUM(B5:B9)
A12: Leads by segment
B13: Count
A14: Office & professional | B14: =COUNTIF(Outreach!$C$3:$C$2000,A14)
A15: Coworking / shared office | B15: =COUNTIF(Outreach!$C$3:$C$2000,A15)
A16: Hospitality | B16: =COUNTIF(Outreach!$C$3:$C$2000,A16)
A17: Education | B17: =COUNTIF(Outreach!$C$3:$C$2000,A17)
A18: Retail | B18: =COUNTIF(Outreach!$C$3:$C$2000,A18)
A19: Leisure & culture | B19: =COUNTIF(Outreach!$C$3:$C$2000,A19)
A20: Health | B20: =COUNTIF(Outreach!$C$3:$C$2000,A20)
A21: Other | B21: =COUNTIF(Outreach!$C$3:$C$2000,A21)
A22: Total | B22: =SUM(B14:B21)
A24: Leads by tagged-venue status
B25: Count
A26: Available | B26: =COUNTIF(Outreach!$O$3:$O$2000,A26)
A27: Contact required | B27: =COUNTIF(Outreach!$O$3:$O$2000,A27)
A28: No availability | B28: =COUNTIF(Outreach!$O$3:$O$2000,A28)
A29: Total | B29: =SUM(B26:B28)
A31: Funnel (from the Tracking columns on Outreach)
A32: Stage | B32: Leads | C32: % of previous stage
A33: Contacted | B33: =COUNTIF(Outreach!$AD$3:$AD$2000,">0")
A34: Replied | B34: =COUNTIF(Outreach!$AE$3:$AE$2000,"Yes") | C34: =IF(B33=0,"",B34/B33)
A35: Call booked | B35: =COUNTIF(Outreach!$AF$3:$AF$2000,"Yes") | C35: =IF(B34=0,"",B35/B34)
A36: Group created | B36: =COUNTIF(Outreach!$AG$3:$AG$2000,"Yes") | C36: =IF(B35=0,"",B36/B35)
A37: First game booked | B37: =COUNTIF(Outreach!$AH$3:$AH$2000,"Yes") | C37: =IF(B36=0,"",B37/B36)
A38: Second game booked | B38: =COUNTIF(Outreach!$AI$3:$AI$2000,"Yes") | C38: =IF(B37=0,"",B38/B37)
A39: Saw FC Urban as a competitor | B39: =COUNTIF(Outreach!$AJ$3:$AJ$2000,"Yes")
A42: Funnel by channel
A43: Channel | B43: Contacted | C43: Replied | D43: Call booked | E43: Group created | F43: First game booked | G43: Second game booked
A44: Email | B44: =COUNTIFS(Outreach!$AC$3:$AC$2000,$A44,Outreach!$AD$3:$AD$2000,">0") | C44: =COUNTIFS(Outreach!$AC$3:$AC$2000,$A44,Outreach!$AE$3:$AE$2000,"Yes") | D44: =COUNTIFS(Outreach!$AC$3:$AC$2000,$A44,Outreach!$AF$3:$AF$2000,"Yes") | E44: =COUNTIFS(Outreach!$AC$3:$AC$2000,$A44,Outreach!$AG$3:$AG$2000,"Yes") | F44: =COUNTIFS(Outreach!$AC$3:$AC$2000,$A44,Outreach!$AH$3:$AH$2000,"Yes") | G44: =COUNTIFS(Outreach!$AC$3:$AC$2000,$A44,Outreach!$AI$3:$AI$2000,"Yes")
A45: LinkedIn | B45: =COUNTIFS(Outreach!$AC$3:$AC$2000,$A45,Outreach!$AD$3:$AD$2000,">0") | C45: =COUNTIFS(Outreach!$AC$3:$AC$2000,$A45,Outreach!$AE$3:$AE$2000,"Yes") | D45: =COUNTIFS(Outreach!$AC$3:$AC$2000,$A45,Outreach!$AF$3:$AF$2000,"Yes") | E45: =COUNTIFS(Outreach!$AC$3:$AC$2000,$A45,Outreach!$AG$3:$AG$2000,"Yes") | F45: =COUNTIFS(Outreach!$AC$3:$AC$2000,$A45,Outreach!$AH$3:$AH$2000,"Yes") | G45: =COUNTIFS(Outreach!$AC$3:$AC$2000,$A45,Outreach!$AI$3:$AI$2000,"Yes")
A46: Phone | B46: =COUNTIFS(Outreach!$AC$3:$AC$2000,$A46,Outreach!$AD$3:$AD$2000,">0") | C46: =COUNTIFS(Outreach!$AC$3:$AC$2000,$A46,Outreach!$AE$3:$AE$2000,"Yes") | D46: =COUNTIFS(Outreach!$AC$3:$AC$2000,$A46,Outreach!$AF$3:$AF$2000,"Yes") | E46: =COUNTIFS(Outreach!$AC$3:$AC$2000,$A46,Outreach!$AG$3:$AG$2000,"Yes") | F46: =COUNTIFS(Outreach!$AC$3:$AC$2000,$A46,Outreach!$AH$3:$AH$2000,"Yes") | G46: =COUNTIFS(Outreach!$AC$3:$AC$2000,$A46,Outreach!$AI$3:$AI$2000,"Yes")
A47: Instagram | B47: =COUNTIFS(Outreach!$AC$3:$AC$2000,$A47,Outreach!$AD$3:$AD$2000,">0") | C47: =COUNTIFS(Outreach!$AC$3:$AC$2000,$A47,Outreach!$AE$3:$AE$2000,"Yes") | D47: =COUNTIFS(Outreach!$AC$3:$AC$2000,$A47,Outreach!$AF$3:$AF$2000,"Yes") | E47: =COUNTIFS(Outreach!$AC$3:$AC$2000,$A47,Outreach!$AG$3:$AG$2000,"Yes") | F47: =COUNTIFS(Outreach!$AC$3:$AC$2000,$A47,Outreach!$AH$3:$AH$2000,"Yes") | G47: =COUNTIFS(Outreach!$AC$3:$AC$2000,$A47,Outreach!$AI$3:$AI$2000,"Yes")
A48: WhatsApp | B48: =COUNTIFS(Outreach!$AC$3:$AC$2000,$A48,Outreach!$AD$3:$AD$2000,">0") | C48: =COUNTIFS(Outreach!$AC$3:$AC$2000,$A48,Outreach!$AE$3:$AE$2000,"Yes") | D48: =COUNTIFS(Outreach!$AC$3:$AC$2000,$A48,Outreach!$AF$3:$AF$2000,"Yes") | E48: =COUNTIFS(Outreach!$AC$3:$AC$2000,$A48,Outreach!$AG$3:$AG$2000,"Yes") | F48: =COUNTIFS(Outreach!$AC$3:$AC$2000,$A48,Outreach!$AH$3:$AH$2000,"Yes") | G48: =COUNTIFS(Outreach!$AC$3:$AC$2000,$A48,Outreach!$AI$3:$AI$2000,"Yes")
A49: Walk-in | B49: =COUNTIFS(Outreach!$AC$3:$AC$2000,$A49,Outreach!$AD$3:$AD$2000,">0") | C49: =COUNTIFS(Outreach!$AC$3:$AC$2000,$A49,Outreach!$AE$3:$AE$2000,"Yes") | D49: =COUNTIFS(Outreach!$AC$3:$AC$2000,$A49,Outreach!$AF$3:$AF$2000,"Yes") | E49: =COUNTIFS(Outreach!$AC$3:$AC$2000,$A49,Outreach!$AG$3:$AG$2000,"Yes") | F49: =COUNTIFS(Outreach!$AC$3:$AC$2000,$A49,Outreach!$AH$3:$AH$2000,"Yes") | G49: =COUNTIFS(Outreach!$AC$3:$AC$2000,$A49,Outreach!$AI$3:$AI$2000,"Yes")
A50: Other | B50: =COUNTIFS(Outreach!$AC$3:$AC$2000,$A50,Outreach!$AD$3:$AD$2000,">0") | C50: =COUNTIFS(Outreach!$AC$3:$AC$2000,$A50,Outreach!$AE$3:$AE$2000,"Yes") | D50: =COUNTIFS(Outreach!$AC$3:$AC$2000,$A50,Outreach!$AF$3:$AF$2000,"Yes") | E50: =COUNTIFS(Outreach!$AC$3:$AC$2000,$A50,Outreach!$AG$3:$AG$2000,"Yes") | F50: =COUNTIFS(Outreach!$AC$3:$AC$2000,$A50,Outreach!$AH$3:$AH$2000,"Yes") | G50: =COUNTIFS(Outreach!$AC$3:$AC$2000,$A50,Outreach!$AI$3:$AI$2000,"Yes")
A53: Funnel by segment
A54: Segment | B54: Contacted | C54: Replied | D54: Call booked | E54: Group created | F54: First game booked | G54: Second game booked
A55: Office & professional | B55: =COUNTIFS(Outreach!$C$3:$C$2000,$A55,Outreach!$AD$3:$AD$2000,">0") | C55: =COUNTIFS(Outreach!$C$3:$C$2000,$A55,Outreach!$AE$3:$AE$2000,"Yes") | D55: =COUNTIFS(Outreach!$C$3:$C$2000,$A55,Outreach!$AF$3:$AF$2000,"Yes") | E55: =COUNTIFS(Outreach!$C$3:$C$2000,$A55,Outreach!$AG$3:$AG$2000,"Yes") | F55: =COUNTIFS(Outreach!$C$3:$C$2000,$A55,Outreach!$AH$3:$AH$2000,"Yes") | G55: =COUNTIFS(Outreach!$C$3:$C$2000,$A55,Outreach!$AI$3:$AI$2000,"Yes")
A56: Coworking / shared office | B56: =COUNTIFS(Outreach!$C$3:$C$2000,$A56,Outreach!$AD$3:$AD$2000,">0") | C56: =COUNTIFS(Outreach!$C$3:$C$2000,$A56,Outreach!$AE$3:$AE$2000,"Yes") | D56: =COUNTIFS(Outreach!$C$3:$C$2000,$A56,Outreach!$AF$3:$AF$2000,"Yes") | E56: =COUNTIFS(Outreach!$C$3:$C$2000,$A56,Outreach!$AG$3:$AG$2000,"Yes") | F56: =COUNTIFS(Outreach!$C$3:$C$2000,$A56,Outreach!$AH$3:$AH$2000,"Yes") | G56: =COUNTIFS(Outreach!$C$3:$C$2000,$A56,Outreach!$AI$3:$AI$2000,"Yes")
A57: Hospitality | B57: =COUNTIFS(Outreach!$C$3:$C$2000,$A57,Outreach!$AD$3:$AD$2000,">0") | C57: =COUNTIFS(Outreach!$C$3:$C$2000,$A57,Outreach!$AE$3:$AE$2000,"Yes") | D57: =COUNTIFS(Outreach!$C$3:$C$2000,$A57,Outreach!$AF$3:$AF$2000,"Yes") | E57: =COUNTIFS(Outreach!$C$3:$C$2000,$A57,Outreach!$AG$3:$AG$2000,"Yes") | F57: =COUNTIFS(Outreach!$C$3:$C$2000,$A57,Outreach!$AH$3:$AH$2000,"Yes") | G57: =COUNTIFS(Outreach!$C$3:$C$2000,$A57,Outreach!$AI$3:$AI$2000,"Yes")
A58: Education | B58: =COUNTIFS(Outreach!$C$3:$C$2000,$A58,Outreach!$AD$3:$AD$2000,">0") | C58: =COUNTIFS(Outreach!$C$3:$C$2000,$A58,Outreach!$AE$3:$AE$2000,"Yes") | D58: =COUNTIFS(Outreach!$C$3:$C$2000,$A58,Outreach!$AF$3:$AF$2000,"Yes") | E58: =COUNTIFS(Outreach!$C$3:$C$2000,$A58,Outreach!$AG$3:$AG$2000,"Yes") | F58: =COUNTIFS(Outreach!$C$3:$C$2000,$A58,Outreach!$AH$3:$AH$2000,"Yes") | G58: =COUNTIFS(Outreach!$C$3:$C$2000,$A58,Outreach!$AI$3:$AI$2000,"Yes")
A59: Retail | B59: =COUNTIFS(Outreach!$C$3:$C$2000,$A59,Outreach!$AD$3:$AD$2000,">0") | C59: =COUNTIFS(Outreach!$C$3:$C$2000,$A59,Outreach!$AE$3:$AE$2000,"Yes") | D59: =COUNTIFS(Outreach!$C$3:$C$2000,$A59,Outreach!$AF$3:$AF$2000,"Yes") | E59: =COUNTIFS(Outreach!$C$3:$C$2000,$A59,Outreach!$AG$3:$AG$2000,"Yes") | F59: =COUNTIFS(Outreach!$C$3:$C$2000,$A59,Outreach!$AH$3:$AH$2000,"Yes") | G59: =COUNTIFS(Outreach!$C$3:$C$2000,$A59,Outreach!$AI$3:$AI$2000,"Yes")
A60: Leisure & culture | B60: =COUNTIFS(Outreach!$C$3:$C$2000,$A60,Outreach!$AD$3:$AD$2000,">0") | C60: =COUNTIFS(Outreach!$C$3:$C$2000,$A60,Outreach!$AE$3:$AE$2000,"Yes") | D60: =COUNTIFS(Outreach!$C$3:$C$2000,$A60,Outreach!$AF$3:$AF$2000,"Yes") | E60: =COUNTIFS(Outreach!$C$3:$C$2000,$A60,Outreach!$AG$3:$AG$2000,"Yes") | F60: =COUNTIFS(Outreach!$C$3:$C$2000,$A60,Outreach!$AH$3:$AH$2000,"Yes") | G60: =COUNTIFS(Outreach!$C$3:$C$2000,$A60,Outreach!$AI$3:$AI$2000,"Yes")
A61: Health | B61: =COUNTIFS(Outreach!$C$3:$C$2000,$A61,Outreach!$AD$3:$AD$2000,">0") | C61: =COUNTIFS(Outreach!$C$3:$C$2000,$A61,Outreach!$AE$3:$AE$2000,"Yes") | D61: =COUNTIFS(Outreach!$C$3:$C$2000,$A61,Outreach!$AF$3:$AF$2000,"Yes") | E61: =COUNTIFS(Outreach!$C$3:$C$2000,$A61,Outreach!$AG$3:$AG$2000,"Yes") | F61: =COUNTIFS(Outreach!$C$3:$C$2000,$A61,Outreach!$AH$3:$AH$2000,"Yes") | G61: =COUNTIFS(Outreach!$C$3:$C$2000,$A61,Outreach!$AI$3:$AI$2000,"Yes")
A62: Other | B62: =COUNTIFS(Outreach!$C$3:$C$2000,$A62,Outreach!$AD$3:$AD$2000,">0") | C62: =COUNTIFS(Outreach!$C$3:$C$2000,$A62,Outreach!$AE$3:$AE$2000,"Yes") | D62: =COUNTIFS(Outreach!$C$3:$C$2000,$A62,Outreach!$AF$3:$AF$2000,"Yes") | E62: =COUNTIFS(Outreach!$C$3:$C$2000,$A62,Outreach!$AG$3:$AG$2000,"Yes") | F62: =COUNTIFS(Outreach!$C$3:$C$2000,$A62,Outreach!$AH$3:$AH$2000,"Yes") | G62: =COUNTIFS(Outreach!$C$3:$C$2000,$A62,Outreach!$AI$3:$AI$2000,"Yes")
A65: Open after-work slots by venue and weekday (28 Sep – 23 Oct)
A66: Venue | B66: Mon | C66: Tue | D66: Wed | E66: Thu | F66: Fri | G66: Total
A67: Haggerston Park | B67: =COUNTIFS(Slots!$A$2:$A$90,$A67,Slots!$C$2:$C$90,"Mon",Slots!$I$2:$I$90,"Available") | C67: =COUNTIFS(Slots!$A$2:$A$90,$A67,Slots!$C$2:$C$90,"Tue",Slots!$I$2:$I$90,"Available") | D67: =COUNTIFS(Slots!$A$2:$A$90,$A67,Slots!$C$2:$C$90,"Wed",Slots!$I$2:$I$90,"Available") | E67: =COUNTIFS(Slots!$A$2:$A$90,$A67,Slots!$C$2:$C$90,"Thu",Slots!$I$2:$I$90,"Available") | F67: =COUNTIFS(Slots!$A$2:$A$90,$A67,Slots!$C$2:$C$90,"Fri",Slots!$I$2:$I$90,"Available") | G67: =SUM(B67:F67)
A68: Whitechapel | B68: =COUNTIFS(Slots!$A$2:$A$90,$A68,Slots!$C$2:$C$90,"Mon",Slots!$I$2:$I$90,"Available") | C68: =COUNTIFS(Slots!$A$2:$A$90,$A68,Slots!$C$2:$C$90,"Tue",Slots!$I$2:$I$90,"Available") | D68: =COUNTIFS(Slots!$A$2:$A$90,$A68,Slots!$C$2:$C$90,"Wed",Slots!$I$2:$I$90,"Available") | E68: =COUNTIFS(Slots!$A$2:$A$90,$A68,Slots!$C$2:$C$90,"Thu",Slots!$I$2:$I$90,"Available") | F68: =COUNTIFS(Slots!$A$2:$A$90,$A68,Slots!$C$2:$C$90,"Fri",Slots!$I$2:$I$90,"Available") | G68: =SUM(B68:F68)
A69: Shoreditch Rooftop | B69: =COUNTIFS(Slots!$A$2:$A$90,$A69,Slots!$C$2:$C$90,"Mon",Slots!$I$2:$I$90,"Available") | C69: =COUNTIFS(Slots!$A$2:$A$90,$A69,Slots!$C$2:$C$90,"Tue",Slots!$I$2:$I$90,"Available") | D69: =COUNTIFS(Slots!$A$2:$A$90,$A69,Slots!$C$2:$C$90,"Wed",Slots!$I$2:$I$90,"Available") | E69: =COUNTIFS(Slots!$A$2:$A$90,$A69,Slots!$C$2:$C$90,"Thu",Slots!$I$2:$I$90,"Available") | F69: =COUNTIFS(Slots!$A$2:$A$90,$A69,Slots!$C$2:$C$90,"Fri",Slots!$I$2:$I$90,"Available") | G69: =SUM(B69:F69)
A70: Rosemary Gardens 3G - Islington | B70: =COUNTIFS(Slots!$A$2:$A$90,$A70,Slots!$C$2:$C$90,"Mon",Slots!$I$2:$I$90,"Available") | C70: =COUNTIFS(Slots!$A$2:$A$90,$A70,Slots!$C$2:$C$90,"Tue",Slots!$I$2:$I$90,"Available") | D70: =COUNTIFS(Slots!$A$2:$A$90,$A70,Slots!$C$2:$C$90,"Wed",Slots!$I$2:$I$90,"Available") | E70: =COUNTIFS(Slots!$A$2:$A$90,$A70,Slots!$C$2:$C$90,"Thu",Slots!$I$2:$I$90,"Available") | F70: =COUNTIFS(Slots!$A$2:$A$90,$A70,Slots!$C$2:$C$90,"Fri",Slots!$I$2:$I$90,"Available") | G70: =SUM(B70:F70)
A71: Stepney 3G | B71: =COUNTIFS(Slots!$A$2:$A$90,$A71,Slots!$C$2:$C$90,"Mon",Slots!$I$2:$I$90,"Available") | C71: =COUNTIFS(Slots!$A$2:$A$90,$A71,Slots!$C$2:$C$90,"Tue",Slots!$I$2:$I$90,"Available") | D71: =COUNTIFS(Slots!$A$2:$A$90,$A71,Slots!$C$2:$C$90,"Wed",Slots!$I$2:$I$90,"Available") | E71: =COUNTIFS(Slots!$A$2:$A$90,$A71,Slots!$C$2:$C$90,"Thu",Slots!$I$2:$I$90,"Available") | F71: =COUNTIFS(Slots!$A$2:$A$90,$A71,Slots!$C$2:$C$90,"Fri",Slots!$I$2:$I$90,"Available") | G71: =SUM(B71:F71)
A72: Old St - Moreland Primary School | B72: =COUNTIFS(Slots!$A$2:$A$90,$A72,Slots!$C$2:$C$90,"Mon",Slots!$I$2:$I$90,"Available") | C72: =COUNTIFS(Slots!$A$2:$A$90,$A72,Slots!$C$2:$C$90,"Tue",Slots!$I$2:$I$90,"Available") | D72: =COUNTIFS(Slots!$A$2:$A$90,$A72,Slots!$C$2:$C$90,"Wed",Slots!$I$2:$I$90,"Available") | E72: =COUNTIFS(Slots!$A$2:$A$90,$A72,Slots!$C$2:$C$90,"Thu",Slots!$I$2:$I$90,"Available") | F72: =COUNTIFS(Slots!$A$2:$A$90,$A72,Slots!$C$2:$C$90,"Fri",Slots!$I$2:$I$90,"Available") | G72: =SUM(B72:F72)
A73: Hackney | B73: =COUNTIFS(Slots!$A$2:$A$90,$A73,Slots!$C$2:$C$90,"Mon",Slots!$I$2:$I$90,"Available") | C73: =COUNTIFS(Slots!$A$2:$A$90,$A73,Slots!$C$2:$C$90,"Tue",Slots!$I$2:$I$90,"Available") | D73: =COUNTIFS(Slots!$A$2:$A$90,$A73,Slots!$C$2:$C$90,"Wed",Slots!$I$2:$I$90,"Available") | E73: =COUNTIFS(Slots!$A$2:$A$90,$A73,Slots!$C$2:$C$90,"Thu",Slots!$I$2:$I$90,"Available") | F73: =COUNTIFS(Slots!$A$2:$A$90,$A73,Slots!$C$2:$C$90,"Fri",Slots!$I$2:$I$90,"Available") | G73: =SUM(B73:F73)
A74: COLA Shoreditch Park | B74: =COUNTIFS(Slots!$A$2:$A$90,$A74,Slots!$C$2:$C$90,"Mon",Slots!$I$2:$I$90,"Available") | C74: =COUNTIFS(Slots!$A$2:$A$90,$A74,Slots!$C$2:$C$90,"Tue",Slots!$I$2:$I$90,"Available") | D74: =COUNTIFS(Slots!$A$2:$A$90,$A74,Slots!$C$2:$C$90,"Wed",Slots!$I$2:$I$90,"Available") | E74: =COUNTIFS(Slots!$A$2:$A$90,$A74,Slots!$C$2:$C$90,"Thu",Slots!$I$2:$I$90,"Available") | F74: =COUNTIFS(Slots!$A$2:$A$90,$A74,Slots!$C$2:$C$90,"Fri",Slots!$I$2:$I$90,"Available") | G74: =SUM(B74:F74)
A75: Market Road | B75: =COUNTIFS(Slots!$A$2:$A$90,$A75,Slots!$C$2:$C$90,"Mon",Slots!$I$2:$I$90,"Available") | C75: =COUNTIFS(Slots!$A$2:$A$90,$A75,Slots!$C$2:$C$90,"Tue",Slots!$I$2:$I$90,"Available") | D75: =COUNTIFS(Slots!$A$2:$A$90,$A75,Slots!$C$2:$C$90,"Wed",Slots!$I$2:$I$90,"Available") | E75: =COUNTIFS(Slots!$A$2:$A$90,$A75,Slots!$C$2:$C$90,"Thu",Slots!$I$2:$I$90,"Available") | F75: =COUNTIFS(Slots!$A$2:$A$90,$A75,Slots!$C$2:$C$90,"Fri",Slots!$I$2:$I$90,"Available") | G75: =SUM(B75:F75)
A76: Total | B76: =SUM(B67:B75) | C76: =SUM(C67:C75) | D76: =SUM(D67:D75) | E76: =SUM(E67:E75) | F76: =SUM(F67:F75) | G76: =SUM(G67:G75)

Sheet Read me
A1: FC Urban · London pilot · Haggerston Park
A2: Goal: book a first game by leading with a specific pitch, time and price per player, and learn what makes organisers commit or hold back.
A4: Tabs
A5: Outreach — one row per organiser to contact (696). Everything needed to draft and log a message is on the row.
A6: Pilot offer — the Haggerston Park slot and price. Fill the yellow cells; Outreach then leads with this slot on every row.
A7: Venues — one row per nearby venue: open slots, earliest slot, cost per player, floodlights, who to call.
A8: Slots — every open after-work slot found (weekdays 17:30–20:30 kick-off, 28 Sep – 23 Oct 2026).
A9: Totals — leads by tier/segment, the outreach funnel (overall, by channel, by segment) and slots by weekday.
A11: What to fill in (yellow)
A12: Pilot offer: Date, Kick-off, Format, Hire cost (Luuk); Price per player and the commit point (Joep); booking deadline, cancellation terms, joining link.
A13: Outreach › Tracking columns: Owner, Channel, Contacted on, then Yes/No per funnel stage. Objection only when they see us as a competitor — exact words.
A14: Blue text = values typed in from a source. Green text = formulas; leave those alone.
A16: Example of a logged row (Tracking columns only)
A17: Owner | B17: Channel | C17: Contacted on | D17: Replied | E17: Call booked | F17: Group created | G17: First game booked | H17: Second game booked | I17: Sees us as competitor? | J17: Objection (exact words) | K17: Next step
A18: Luuk | B18: Email | C18: 46294 | D18: Yes | E18: Yes | F18: No | G18: No | H18: No | I18: Yes | J18: "We already have a Thursday kickabout, I don't want players moving to your app" | K18: Call Tue 6 Oct 12:30, send pitch link
A20: Rules used
A21: Tier: 1 = E2 and E8 (closest to Yorkton St); 2 = N1 and EC2A; 3 = E1.
A22: Segment: grouped from the Industry column — Office & professional, Coworking / shared office, Hospitality, Education, Retail, Leisure & culture, Health, Other.
A23: Fallback venue: the lead’s tagged venue if it has bookable after-work slots; otherwise COLA Shoreditch Park (closest to Haggerston, most open slots).
A24: Cost per player at cost: whole-pitch hire ÷ players on a full pitch (5-a-side = 10, 6 = 12, 7 = 14). This is the floor, not the price to charge.
A26: Sources and caveats
A27: Slots and contacts: Claude in Chrome check of each venue’s booking system, 24 Sep 2026. Leads: FC Urban London lead list, postcodes E1, E2, E8, N1, EC2A.
A28: Better (GLL) venues release slots only 6 days ahead — Shoreditch Rooftop, Market Road and Rosemary Gardens will show more availability closer to the date.
A29: Stepney 3G is run by BookMyPitch as pay-per-player games (£3–£5), not a pitch we hire — it does not fit the “our pitch, our price” offer.
A30: Haggerston Park: no online calendar; Playfinder shows it fully booked. Floodlit per Playfinder and Hackney Council, but the fcurban.com page says no — confirm on the call.
A31: Cancellation terms and booking deadlines were not published by any venue — ask on the call.
